Workbook

Sheet 1. Instructions
A1: NRM1 COST ESTIMATE TOOL — v5.19 (October 2026)
A2: Prices and scope of works for Projento, in four sheets. Prepared by Nabil Kayali.
A4: THE FOUR SHEETS
A5: 2. Rates | B5: Every price. One row per item or option, the rates side by side. The sheet you maintain.
A6: 3. Settings | B6: Project types (and which rate column each reads), building uses, specification and intervention levels, location factors, benchmarks, quantity ratios, factors and percentages.
A7: 4. Scope rules | B7: How the app uses each item: when it shows, what starts ticked, how the quantity is estimated, BCIS split and old codes. Rarely needs changing.
A8: 1. Instructions | B8: This page: how to read and change the workbook, the self-checks and the update log.
A10: READING '2. RATES'
A11: Rates | B11: Mid-point UK rates before the location factor, preliminaries and overheads & profit — the app adds those from '3. Settings'.
A12: Which column | B12: Refurbishment, Fit-out and Demolition only read the Refurb & Fit-out columns (the same price for both). New build, Extension and External works only read the New build & Extension columns. Other or mixed reads Refurb & Fit-out, then New build where that is 0.
A13: Blank Basic or High | B13: Same as Standard.
A14: Dash (–) = no price | B14: No price for that project type, so the item (or option) cannot be selected in Q2.3 Scope of works for it. The cell holds 0.
A15: Building use | B15: ALL = any building use. A code (e.g. HOS, HEA, RES STU) = a rate for that use only; the app uses it for that use and the ALL row otherwise.
A16: What's included / Not included | B16: What the rate covers, and what is priced elsewhere (with the code of the row that prices it) or not at all. Size bands (Small / Medium / Large) say what each lump sum assumes.
A17: Units | B17: m² GIFA = gross internal floor area of the building worked on (Q1.5). m² footprint = ground-floor area (GIFA ÷ storeys). m² upper floors = GIFA − footprint. m² roof = roof on plan (= footprint). m² external = the external works area. nr … = a count (WCs, lifts, spaces). band = one lump sum.
A18: Formula cells | B18: A few options are priced as a multiple of another row (e.g. air source heat pump = gas boiler × 1.3). The Source column shows the row and factor; change the factor in the cell formula.
A19: Code and Rate key | B19: Code (0.1, 4.2a) is for reading. Rate key (last column, grey) is permanent: saved projects store it. Never change or reuse a Rate key.
A20: Spon's check | B20: Spon's Architects' & Builders' Price Book 2024 figure converted to this workbook's basis (Q3 2026, UK mid-point, excluding prelims and OH&P), with the PDF page.
A21: Tender check | B21: Lakeside Staff & Family Flats tender returns (29 Sept 2026) converted to this workbook's basis: the median of the four credible bids (BSN, Chiel, Harrabin, William Gough with its kitchen error corrected; Watkin Jones excluded at twice the field) ÷ 0.94 West Midlands factor, per this row's unit, on 3,306 m² measured floor area (49 flats, the Warden's house and nine stair cores). Excludes the contractors' preliminaries and OH&P. Lines starting 'CS:' are the Computer Science Building decarbonisation tender returns (Harrabin and Chiel, March 2024; two bids, so the mean): tender × 1.07 (to Q3 2026) ÷ 0.94, on 3,495 m² GIA (UoW Estates CAD outlines) and 699 m² of roof. Evidence only: no rate was changed for them in v5.8. Final out-turn (financial statement, July 2026): construction £2.73m, +3.4% on a £2.64m contract; total project £3.13m excl. VAT. WF lines: Whitefields demolition (17 blocks, UoW main campus), the Total Reclaims contract (tendered Feb 2026, Option 2) — the figure is also in column R, Whitefields rate. CC lines: the Claycroft student residences refurbishment (679 beds, three occupied blocks, UoW main campus), Morgan Sindall G4 contract (May 2025, SCAPE) — the figure is also in column S, Claycroft rate.
A22: Whitefields rate | B22: Column R on '2. Rates': the Whitefields demolition contract figure for that row (Total Reclaims, £525,676; AFC £532,445 at FS 16, Jul 2026), in the row's unit and on this workbook's basis — line items without the contractor's prelims and OH&P, ÷ 0.94 West Midlands factor, × 1.014 to Q3 2026. Quantities from the owner: 17 blocks, 3,740 m² GIA (about 220 m² each over ground and first floors), 2,210 m² footprint (about 130 m² each), 8,000 m² site. Evidence only: the app does not read this column and no rate changed.
... A24: Project rate columns (T–Z) | B24: Columns T–Y on '2. Rates' hold the other real projects' figures in the row's unit and on this workbook's basis, beside Whitefields (R) and Claycroft (S): T Lakeside S&F (tender Sep 2026, median of 4 bids); U Computer Science decarbonisation (tender Mar 2024, mean of 2 bids); V Scarman Public Toilets Phase 2 (HIGH spec, tender Apr 2026, median of 6 bids; per m² over the 71 m² toilet area); W Co-op grocery store fit-out (Kingfisher contract Aug 2025, 885 m²); X IBRB café servery (Senevo winning bid 2025, 72 m² café, 28 m² servery); Y Riley Court Psychology full refurbishment (Maris signed contract £9.15m, GMP Nov 2024, GIFA 3,850 m²). Each excludes the contractor's prelims, OH&P and design, rebased to Q3 2026 and ÷ 0.94 West Midlands. Column Z is the average of R–Y for the row. Projects differ in scope and specification, so expect spread. Not on '2. Rates': scaffold for envelope works £42 (CS) and £33 (Claycroft) per m² GIFA; retail refrigeration £379 and retailer equipment £373 per m² (Co-op); preliminaries Lakeside ~9%, Whitefields 16.8%, Claycroft 11.3%, Scarman 14%, Co-op 7.2%, IBRB 17.7%, Riley Court 5.5% (+4% contractor PM and design). Evidence only: the app does not read these columns and no rate changed. Column AA is Claude's suggested Refurb & Fit-out Standard rate for each row with evidence, and AB the reason (Raise / Lower / Keep). They are suggestions for the owner only: the app does not read them, and a rate changes only when the owner edits the rate columns.
A25: PRICE SOURCE (column 'Source' on '2. Rates')
A26: Your figure | B26: Set by the owner.
A27: Spon's-based (approved) | B27: Suggested from Spon's 2024 and approved by the owner.
A28: Kept after Spon's check | B28: Compared with Spon's 2024; the owner kept the existing rate.
A29: Older workbook (v4.5) | B29: Carried from v4.5, not yet checked.
A30: Unverified † | B30: Estimated, not yet checked. Lines using it are marked † on reports until the source changes.
A31: Tender – Lakeside S&F (Sep 2026) | B31: From the Lakeside Staff & Family Flats tender returns (29 Sept 2026); the figure and bid range are in the 'Tender check' column.
A33: HOW TO CHANGE THINGS
A34: Change a price | B34: Edit the cell on '2. Rates' and update its Source. Save in Excel.
A35: Add an option | B35: Insert a row on '2. Rates' under the item with the next Rate key (e.g. S-0039-16), and a row for that key on '4. Scope rules' ▶ options.
A36: Add an item | B36: Insert its rows on '2. Rates', a row on ▶ items (next unused Scope ID — never reuse one) and a row per option on ▶ options.
A37: When an item shows, or its quantity | B37: 4. Scope rules'.
A38: A percentage, ratio or factor | B38: 3. Settings'.
A39: After any change | B39: Check the self-checks below all read 0, bump the Version on '3. Settings', add a line to the update log, save in Excel.
A40: Needs a code change | B40: A new column, pricing type, input name or 'When selected' effect type; renamed sheets, ▶ markers or column headers.
A42: SCOPE RULES SHEET — WHAT THE COLUMNS MEAN
A43: Project type codes | B43: NB New build · EX Extension · RF Refurbishment · FO Fit-out · EW External works only · DM Demolition only · OM Other or mixed. Several codes separated by spaces, e.g. "NB EX RF". "—" means none.
A44: Building use codes | B44: RES Residential · STU Student · OFF Commercial offices · EDU Education · HEA Healthcare · RET Retail · IND Industrial / warehouse · HOS Hospitality / leisure · MIX Mixed use · OTH Other · ALL any building use.
A45: Shown on / Pre-ticked on | B45: The project types an item is offered on, and the ones where "Use typical scope" ticks it.
A46: Relevant building uses | B46: Uses for which the item is listed first and can start ticked. It never hides an item — the rest sit under "More items".
A47: Options: pick | B47: One = the user picks one option (drop-down). Several = more than one option, each with its own quantity (e.g. standard + accessible toilets).
A48: Default option | B48: Yes = the option chosen unless the user picks another. Building-use codes (e.g. RES STU) = the default for those uses only, ahead of Yes — Kitchens defaults to a domestic kitchen on residential and student buildings and a staff kitchenette everywhere else.
A49: Quantity rule | B49: How the app estimates the quantity when the user has not entered one (their figure always wins). On ▶ options, blank = the item's rule.
A50: names | B50: GIFA · STOREYS · FOOTPRINT · UPPER · EXT_AREA · DEMOLISHED · PT · USE · AGE · LEVEL — defined, with defaults, on '3. Settings' ▶ inputs.
A51: ratios | B51: r.name reads ▶ quantity_ratios on '3. Settings': the row for the building use, else ALL (e.g. r.m2_per_bed is 25 for student, 70 for healthcare).
A52: functions | B52: IF(test, then, else) · ROUND(x, 0) · MAX(a, b) · MIN(a, b) · SQRT(x) · Q(S-0000) = another item's quantity · + − * / and = <> < > <= >=.
A53: keywords | B53: ENTER = not priced until the user enters a quantity. 1 = one item.
A54: Other conditions | B54: Tests joined by "&", then "→ tick" or "→ untick", e.g. "PT=NB & USE=RES → tick". "=" followed by several codes means any of them.
... A59: Replaces old codes | B59: v4.5 codes this item replaces, so older saved projects still open. Never delete.
A61: SELF-CHECKS (each should be 0)
A62: Duplicate rate keys on '2. Rates' | C62: =SUMPRODUCT(('2. Rates'!O6:O159<>"")*(COUNTIF('2. Rates'!O6:O159,'2. Rates'!O6:O159)>1)) -> 0
A63: Rows on '2. Rates' with no ▶ options row | C63: =SUMPRODUCT(('2. Rates'!O6:O159<>"")*(COUNTIF('4. Scope rules'!A91:A236,'2. Rates'!O6:O159)=0)) -> 0
A64: ▶ options rows with no '2. Rates' row | C64: =SUMPRODUCT(('4. Scope rules'!A91:A236<>"")*(COUNTIF('2. Rates'!O6:O159,'4. Scope rules'!A91:A236)=0)) -> 0
A65: ▶ options rows whose Scope ID is not on ▶ items | C65: =SUMPRODUCT(('4. Scope rules'!A91:A236<>"")*(COUNTIF('4. Scope rules'!A6:A87,'4. Scope rules'!B91:B236)=0)) -> 0
A66: Rows with no Source | C66: =SUMPRODUCT(('2. Rates'!O6:O159<>"")*('2. Rates'!M6:M159="")) -> 0
A67: Items whose BCIS shares don't total 100% | C67: =SUMPRODUCT(('4. Scope rules'!A6:A87<>"")*(ROUND('4. Scope rules'!M6:M87+'4. Scope rules'!O6:O87,4)<>1)) -> 0
A68: Items with no default option | C68: =SUMPRODUCT(('4. Scope rules'!A6:A87<>"")*(COUNTIFS('4. Scope rules'!B91:B236,'4. Scope rules'!A6:A87,'4. Scope rules'!E91:E236,"Yes")=0)) -> 0
A69: Pick-one items with more than one default | C69: =SUMPRODUCT(('4. Scope rules'!A6:A87<>"")*('4. Scope rules'!F6:F87="One")*(COUNTIFS('4. Scope rules'!B91:B236,'4. Scope rules'!A6:A87,'4. Scope rules'!E91:E236,"Yes")>1)) -> 0
A70: Items with no quantity rule | C70: =SUMPRODUCT(('4. Scope rules'!A6:A87<>"")*('4. Scope rules'!G6:G87="")) -> 0
A71: Unknown project type codes | C71: =SUMPRODUCT(--(LEN(TRIM(SUBSTITUTE(SUBSTITUTE(SUBSTITUTE(SUBSTITUTE(SUBSTITUTE(SUBSTITUTE(SUBSTITUTE(SUBSTITUTE('4. Scope rules'!H6:H87,"NB",""),"EX",""),"RF",""),"FO",""),"EW",""),"DM",""),"OM",""),"—","")))>0))+SUMPRODUCT(--(LEN(TRIM(SUBSTITUTE(SUBSTITUTE(SUBSTITUTE(SUBSTITUTE(SUBSTITUTE(SUBSTITUTE(SUBSTITUTE(SUBSTITUTE('4. Scope rules'!I6:I87,"NB",""),"EX",""),"RF",""),"FO",""),"EW",""),"DM",""),"OM",""),"—","")))>0)) -> 0
A72: Unknown building use codes | C72: =SUMPRODUCT(--(LEN(TRIM(SUBSTITUTE(SUBSTITUTE(SUBSTITUTE(SUBSTITUTE(SUBSTITUTE(SUBSTITUTE(SUBSTITUTE(SUBSTITUTE(SUBSTITUTE(SUBSTITUTE(SUBSTITUTE('4. Scope rules'!J6:J87,"RES",""),"STU",""),"OFF",""),"EDU",""),"HEA",""),"RET",""),"IND",""),"HOS",""),"MIX",""),"OTH",""),"ALL","")))>0))+SUMPRODUCT(--(LEN(TRIM(SUBSTITUTE(SUBSTITUTE(SUBSTITUTE(SUBSTITUTE(SUBSTITUTE(SUBSTITUTE(SUBSTITUTE(SUBSTITUTE(SUBSTITUTE(SUBSTITUTE(SUBSTITUTE('2. Rates'!D6:D159,"RES",""),"STU",""),"OFF",""),"EDU",""),"HEA",""),"RET",""),"IND",""),"HOS",""),"MIX",""),"OTH",""),"ALL","")))>0)) -> 0
A73: Ratio keys with no ALL row | C73: =SUMPRODUCT(('3. Settings'!A98:A125<>"")*(COUNTIFS('3. Settings'!A98:A125,'3. Settings'!A98:A125,'3. Settings'!B98:B125,"ALL")=0)) -> 0
A74: Ratios with no value | C74: =SUMPRODUCT(('3. Settings'!A98:A125<>"")*('3. Settings'!C98:C125="")) -> 0
A76: COUNTS
A77: Scope items | C77: =COUNTA('4. Scope rules'!A6:A87) -> 82
A78: Priced rows | C78: =COUNTA('2. Rates'!O6:O159) -> 146
A80: UPDATE LOG
A81: v5.27 — 12 Oct 2026 | B81: New build roof and external walls (owner, 12 Oct 2026). v5.12 moved each changed row's New build columns by the refurbishment evidence ratio, with no new-build evidence; roof and external walls ended up above Spon's new-build range and go back to their v5.11 rates: roof 2.5a 380/518 → 220/300 (Spon's £181–£258), external walls 2.6a 367/567 → 220/340 (Spon's £75–£338). Tested on the 30 batch-4 scenarios: residential, office and mixed-use new build come back into their expected ranges. Ceilings, lighting and fire alarm were also above Spon's but were kept: lowering them pushed healthcare, hotel, student and education projects below range. Refurb & Fit-out columns unchanged; industrial has its own roof and wall rows (v5.25).
A82: v5.26 — 12 Oct 2026 | B82: Two quantity rules on '4. Scope rules' ▶ items (owner, 12 Oct 2026; no rate changed). Soft landscaping (8.10) = the smaller of external area × pct_soft and what is left after paving (8.7), car parking (8.8, × m2_per_car_space) and HGV yard (8.9) — it was 40% of the site on top of them, so a site came to more than 100%. Foul drainage (8.3) on Industrial / warehouse New build and Extension = OFFICES + PRODUCTION, like heating and water — the storage floor has no drainage points; every other building use stays on GIFA.
A83: v5.25 — 12 Oct 2026 | B83: Industrial / warehouse rates (owner, 12 Oct 2026: industrial may have its own rates). IND rows beside the ALL rows on '2. Rates' and '4. Scope rules' for foundations (1.1d, 1.1e), ground floor slab (1.2b), frame (2.1b), roof (2.5c), external walls (2.6b) and windows and external doors (2.7b): New build & Extension columns from the Spon's 2024 Retail Distribution Unit cost model × 1.30 (a steel portal-frame shed); Refurb & Fit-out columns are the ALL row's, so industrial refurbishment is unchanged. Codes 1.2, 2.1, 2.6, 2.7 became 1.2a, 2.1a, 2.6a, 2.7a. ▶ benchmarks NB IND low 900 → 650 (a shed's works now come out at about £800 per m²). Every other building use prices as before.
A84: v5.24 — 11 Oct 2026 | B84: No figure changed. The route names in ▶ route_fees follow the RIBA Plan of Work 2020, as the Procurement Reference v2.3 now does: 'Design and build (single stage)' is 'Design & Build 1 Stage', 'Two-stage (PCSA)' is 'Design & Build 2 Stage', 'Construction management' is 'Management Contract / Construction Management'. The fee adjustments are unchanged.
A85: v5.23 — 11 Oct 2026 | B85: No figure the estimate uses changed. The last number the app held in its code now lives here: ▶ factors gains risk_level_low_max (11) and risk_level_medium_max (13) — the risk + contingency % at or below which the report's risk level reads Low or Medium (above: High). The app now also refuses this workbook if a prelims (A) or risk (E) BASE row loses its cap, the OH&P (B) rows leave a works value uncovered, or the fee (C) BASE rows leave a design stage 0–4 uncovered — it no longer has backup percentages to fall back on.
A86: v5.22 — 10 Oct 2026 | B86: No rate changed. Industrial / warehouse new build and extensions are split into offices and the main space (owner, 10 Oct 2026): new inputs OFFICES (Q1.3a share × GIFA; default GIFA × r.office_share) and PRODUCTION (Q1.3b Factory / production → the rest of the floor, Storage / warehouse → 0); new ratio office_share 0.10 (suggestion, AI estimate – verify). On those projects internal walls, internal doors, wall / floor / ceiling finishes, signage and data are measured on OFFICES, and heating, water, ventilation, power and builder's work on OFFICES + PRODUCTION. Every other building use and project type is measured on GIFA as before.
A87: v5.21 — 10 Oct 2026 | B87: No figure the estimate uses changed. Numbers the app used to hold in its code now live here, so nothing is ever assumed: ▶ factors gains vat_partly_share (0.5 — half the VAT counted when Q4.3a = Partly) and the eight what-if steps of the cost-drivers list (sens_*); ▶ range_widths gains DEFAULT (0.89 / 1.11, used only before the grade is known); ▶ confidence gains BENCHMARK_BREACH (estimate more than 30% outside its ▶ benchmarks band caps the grade at D). The app now refuses a workbook missing any of these rows, a range-width grade, an F row without a cap, or a G row of 0.
A88: v5.20 — 10 Oct 2026 | B88: Pre-launch fixes from test batch 3. ▶ percentage_rules: Q3.5 reworded (shared access) and three new Prelims ADD rows of 0.5 (restricted deliveries, tight site, public road), same 11% cap. ▶ quantity_ratios: m2_per_car_space 25 (AI estimate); Roads, paths and paving now deducts the car parking and HGV yard the client entered. ▶ inputs DEMOLISHED: ENTER on New Build and Extension (it was the new floor area); Asbestos removal follows it on Extension too. ▶ location_factors Scotland mid 0.90 → 0.965 (it sat below its own low). Heating: gas boiler is the default; the air source heat pump options carry NETZERO, the default when Q2.5 includes Net zero (owner, 10 Oct 2026).
A89: v5.19 — 9 Oct 2026 | B89: Wording only, no figure changed: ▶ risk_allowance label 'ageing M&E, being replaced' → 'ageing M&E being replaced' (it read as two items in the report).
A90: v5.18 — 8 Oct 2026 | B90: Professional fees by procurement route: new ▶ route_fees on '3. Settings'. Design and build: client fees −3 points and contractor's design 2% of construction (Claycroft D&B 2.1%); two-stage (PCSA): −1.5 and 1%; traditional and construction management unchanged. Only while Stage 4 is still to do. The preferred route comes from the Procurement Reference.
A91: v5.17 — 8 Oct 2026 | B91: Inflation from the rate base date: new ▶ inflation on '3. Settings'. Rates are at Q3 2026 (15 Aug 2026); 3.5% a year compounded to the programme's construction mid-point, capped at 12%. Replaces the banded F rows of ▶ percentage_rules.
A92: v5.16 — 8 Oct 2026 | B92: Risk allowance in the four NRM1 categories: new ▶ risk_allowance on '3. Settings' (design development by design stage, construction, employer change, employer other; cap 25%). Replaces E and the fixed 5% contingency H. Items already priced in the scope reduce or remove their risk row; occupation, deadline and phasing stay in prelims and programme only.
... A110: v4.5 — June 2026 | B110: Q2.2 trigger column removed from the Master Cost Table (see v4.5 file for earlier logs).

Sheet 2. Rates
A1: RATES — mid-point UK rates, before the location factor, preliminaries and OH&P
A2: Two price families: Refurb & Fit-out (Refurbishment, Fit-out, Demolition only) and New build & Extension (New build, Extension, External works only). A blank Basic or High = same as Standard. A dash (–) = no price, so the item cannot be selected in Q2.3 for that project type.
A3: Units: m² GIFA = gross internal floor area; m² footprint = ground-floor area. When an item shows and how its quantity is estimated are on '4. Scope rules'. Rate key (grey, last column) is permanent — never change it.
A5: Code | B5: Item | C5: Option | D5: Building use | E5: What's included | F5: Not included (priced elsewhere, or not at all) | G5: Unit | H5: Refurb & Fit-out Basic | I5: Refurb & Fit-out Std | J5: Refurb & Fit-out High | K5: New build & Extension Std | L5: New build & Extension High | M5: Source | N5: Spon's check (converted, PDF page) | O5: Rate key | P5: NK Comment | Q5: Tender check (this row's unit, on this workbook's basis. Unlabelled = Lakeside S&F, Sep 2026: median of 4 bids ÷ 0.94. CS = Computer Science decarbonisation, Mar 2024: 2 bids × 1.07 ÷ 0.94. WF = Whitefields demolition, Total Reclaims contract 2026: line items × 1.014 ÷ 0.94 — the figure is also in column R. CC = Claycroft refurbishment, Morgan Sindall G4 contract May 2025: packages × 1.034 ÷ 0.94 — the figure is also in column S) | R5: Whitefields rate (£ per this row's unit, this workbook's basis: Total Reclaims contract 2026, excl. the contractor's prelims and OH&P, ÷ 0.94 × 1.014. Evidence only — the app does not read it) | S5: Claycroft rate (£ per this row's unit, this workbook's basis: Morgan Sindall G4 contract, May 2025 — sub-contract packages excl. Morgan Sindall's prelims, risk, fee and design, × 1.034 ÷ 0.94, on 17,172 m² GIA measured. 2.10 fire stopping is the forecast out-turn (Mace Val 16, Sep 2026). Evidence only — the app does not read it) | T5: Lakeside rate (£ per this row's unit, this workbook's basis: Lakeside Staff & Family Flats refurbishment, tender Sep 2026, median of 4 bids ÷ 0.94. Evidence only — the app does not read it) | U5: Computer Science rate (£ per this row's unit, this workbook's basis: CS Building decarbonisation, tender Mar 2024, mean of 2 bids × 1.07 ÷ 0.94; roof per m² footprint; 5.1b is the whole M&E package. Evidence only) | V5: Scarman rate (£ per this row's unit, this workbook's basis: Scarman Public Toilets Phase 2, HIGH specification, tender Apr 2026, median of 6 bids × 1.007 ÷ 0.94; per m² figures over the 71 m² toilet area only. Evidence only) | W5: Co-op rate (£ per this row's unit, this workbook's basis: Co-op grocery store fit-out, Kingfisher CSA, contract Aug 2025 × 1.03 ÷ 0.94, over 885 m². Evidence only) | X5: IBRB café rate (£ per this row's unit, this workbook's basis: IBRB café servery fit-out, Senevo winning bid 2025 × 1.035 ÷ 0.94, over 72 m² (catering kitchen per 28 m² servery). Evidence only) | Y5: Riley Court rate (£ per this row's unit, this workbook's basis: Psychology building full refurbishment, Maris signed contract CSA £9.15m, GMP Nov 2024 × 1.05 ÷ 0.94, GIFA 3,850 m². Evidence only) | Z5: Average of project rates (mean of columns R–Y that hold a figure for this row. Projects differ in scope and specification, so read it with the column notes. Evidence only — the app does not read it) | AA5: Suggested Refurb & Fit-out Std rate (Claude's suggestion from the project columns R–Y, 4 Oct 2026, for the owner to accept, change or ignore. Evidence only — the app does not read it) | AB5: Reason for the suggestion
A6: GROUP 0 — FACILITATING WORKS
A7: 0.1 | B7: Asbestos removal | D7: ALL | E7: Survey-led removal and disposal of asbestos and other hazardous materials from the building worked on (on New build: the building being demolished), incl. enclosures, air testing and licensed disposal | F7: The asbestos refurbishment & demolition survey itself (a fee) | G7: m² GIFA | I7: 25 | K7: 25 | M7: Your figure | N7: £13 (p.248) | O7: S-0001-01 | Q7: WF: £8.1 on the contract (Total Reclaims, £28,050 to the asbestos BoQ) over 3,740 m² GIA (17 blocks × about 220 m², owner's figures). Five bids on the same BoQ: £8.1–£42.5, median £12.7. Mace's pre-tender allowance was £85,000 (£24.5). The R&D survey (£9,400) was a fee. | R7: 8.1 | Z7: =AVERAGE(R7:Y7) -> 8.1 | AA7: 25 | AB7: Keep. Matches Mace pre-tender allowance (£24.5); one low tender (£8) is not enough to cut it.
A8: 0.2 | B8: Demolition of existing building | D8: ALL | E8: Demolition of the whole existing building to ground level: soft strip, disconnection of services, breaking out ground slab and shallow foundations, removal and disposal of arisings | F8: Asbestos removal (0.1); basements and deep foundations; contaminated ground (0.4) | G8: m² demolished | I8: 100 | K8: 100 | M8: Your figure | N8: £131–£397 (p.413) | O8: S-0002-01 | Q8: WF: £73 per m² demolished on the contract, 3,740 m² GIA (17 blocks × about 220 m², owner's figures): soft strip, demolish, slabs and foundations £34; disconnecting and cutting back drainage, water, gas, electrical and telecoms, plus Trinity / Honeywell fire alarm, security and metering removal, £39. Core demolition across five bids £34–£70 (median £46). About £15k per block. Excludes the water-main replacement (0.7) and the contractor's own £15k provisional sums for the Trinity / Honeywell work, which those quotes replace. | R8: 73.3 | Z8: =AVERAGE(R8:Y8) -> 73.3 | AA8: 100 | AB8: Lower. Whitefields £73 on simple 2-storey masonry; £100 leaves room for framed or taller buildings.
A9: 0.3 | B9: Strip-out | D9: ALL | E9: Removal of existing finishes, ceilings, non-structural partitions, fittings and redundant services back to shell, incl. disposal | F9: Structural alterations (7.2); asbestos (0.1) | G9: m² GIFA | I9: 55 | K9: 0 | M9: Tender – Lakeside S&F (Sep 2026) | N9: £35–£99 (p.242, 246) | O9: S-0003-01 | Q9: £54 (bids £36–£56) for a partial strip-out: finishes, fittings, redundant electrics and protection CC: £51.4 on the Claycroft G4 contract (Cawarden, £801,990): full strip-out of three occupied student blocks, 17,172 m² GIA. Three bids £802k–£928k. | S9: 51.4 | T9: 54 | V9: 217 | W9: 48.8 | X9: 11.5 | Y9: 54.9 | Z9: =AVERAGE(R9:Y9) -> 72.933333 | AA9: 55 | AB9: Keep. Lakeside, Claycroft, Co-op and Riley Court all £49–55. Scarman and IBRB are tiny jobs.
A10: 0.4 | B10: Contaminated land | D10: ALL | E10: Treatment or removal and disposal of contaminated ground under the building (on External works only: the site area), incl. capping layer and verification | F10: Site investigation (a fee). Not offered on refurbishment, fit-out or demolition only | G10: m² GIFA | I10: 0 | K10: 60 | M10: Your figure | N10: £47–£164 (p.112) | O10: S-0004-01
A11: 0.5 | B11: Ground improvement | D11: ALL | E11: Ground stabilisation under the building footprint: mine-working grouting, vibro-compaction or soil improvement | F11: Piling (in 1.1b Foundations) | G11: m² footprint | I11: 0 | K11: 35 | M11: Your figure | O11: S-0005-01
A12: 0.6 | B12: Tree removal | D12: ALL | E12: Per tree: felling, stump grinding or removal, and disposal | F12: Replacement planting (8.10); tree surveys and protection orders | G12: nr trees | I12: 750 | K12: 750 | M12: Your figure | N12: £340–£833 (p.452) | O12: S-0006-01
A13: 0.7 | B13: Service diversions | D13: ALL | E13: Diverting or protecting existing underground services (drains, cables, pipes) that cross the building footprint, incl. utility company charges for the diversion | F13: New connections for the building (8.4 External utilities) | G13: m² footprint | I13: 100 | K13: 100 | M13: Your figure | O13: S-0007-01 | Q13: WF: £36 per m² footprint on the contract (17 × about 130 m² = 2,210 m² footprint): replacing 254 m of ductile iron water main across the site in MDPE, with temporary water, trenching, stone surround and tarmac reinstatement (£74k; about £315/m of main). £44 with the changes pending at FS 16, Jul 2026 (trial pits on the district heating and water mains, out-of-hours water works: £16.7k). | R13: 36.3 | Z13: =AVERAGE(R13:Y13) -> 36.3 | AA13: 100 | AB13: Keep. One water-main job (£36); diversions are too site-specific to move the rate.
A14: GROUP 1 — SUBSTRUCTURE
A15: 1.1a | B15: Foundations | C15: Standard | D15: ALL | E15: Excavation, disposal, concrete strip or pad foundations and ground beams up to ground-floor slab level | F15: Ground floor slab (1.2); basement (1.3); ground improvement (0.5) | G15: m² footprint | I15: 0 | K15: 115 | L15: 140 | M15: Spon's-based (approved) | N15: £114–£158 (p.292) | O15: S-0008-01
A16: 1.1d | B16: Foundations | C16: Standard | D16: IND | E16: Industrial / warehouse: pad foundations to the portal-frame columns, column casings below slab and a perimeter ground beam under the cladding | F16: Ground floor slab (1.2); basement (1.3); ground improvement (0.5) | G16: m² footprint | I16: 0 | K16: 22 | L16: 30 | M16: Spon's-based (approved) | N16: Shed model: pads, casings, perimeter beam and dock foundations £8.80 per m² GIFA at 29,640 m²; about £13.60 at 4,000 m² (more perimeter per m²) × 1.30 = £18 (p.221) | O16: S-0008-04
A17: 1.1b | B17: Foundations | C17: Piled | D17: ALL | E17: Piled foundations (CFA or mini-piles) with pile caps and ground beams, for poor ground | F17: Ground floor slab (1.2); basement (1.3); ground improvement (0.5) | G17: m² footprint | I17: 0 | K17: 260 | L17: 320 | M17: Spon's-based (approved) | N17: £250–£335 (p.292) | O17: S-0008-02
A18: 1.1c | B18: Foundations | C18: Not sure | D18: ALL | E18: Priced as standard foundations and adds a piling risk to the report until ground conditions are known | F18: Ground floor slab (1.2); basement (1.3); ground improvement (0.5) | G18: m² footprint | I18: =I15*1 -> 0 | K18: =K15*1 -> 115 | L18: =L15*1 -> 140 | M18: Older workbook (v4.5) (= 1.1a × 1) | O18: S-0008-03
A19: 1.1e | B19: Foundations | C19: Not sure | D19: IND | E19: Industrial / warehouse: foundation type not yet known — priced as standard pad foundations (1.1d) and raises a piling risk | F19: Ground floor slab (1.2); basement (1.3); ground improvement (0.5) | G19: m² footprint | I19: =I16*1 -> 0 | K19: =K16*1 -> 22 | L19: =L16*1 -> 30 | M19: Spon's-based (approved) (= 1.1d × 1) | O19: S-0008-05
A20: 1.2a | B20: Ground floor slab | D20: ALL | E20: Excavation to formation, hardcore sub-base, blinding, DPM, insulation and reinforced concrete ground-bearing slab | F20: Floor finishes and screed (3.2) | G20: m² footprint | I20: 0 | K20: 160 | L20: 195 | M20: Spon's-based (approved) | N20: £131–£196 (p.299, 300, 301) | O20: S-0009-01
A21: 1.2b | B21: Ground floor slab | D21: IND | E21: Industrial / warehouse: 200 mm reinforced ground-bearing slab to FM2 flatness with surface hardener and sealed joints, type 1 sub-base, fill to make up levels and a floor survey | F21: Floor finishes and screed (3.2) | G21: m² footprint | I21: 0 | K21: 100 | L21: 125 | M21: Spon's-based (approved) | N21: Shed model: slab £61 + fill £8.75 + type 1 £8.10 + survey £0.60 = £78.50 per m² × 1.30 = £102 (p.221) | O21: S-0009-02
A22: 1.3 | B22: Basement | D22: ALL | E22: Bulk excavation and disposal, temporary works, reinforced concrete basement walls and floor, and waterproofing (tanking) | F22: Finishes and services inside the basement | G22: m² basement | I22: 0 | K22: 600 | L22: 1000 | M22: Your figure | N22: £438–£533 (p.302) | O22: S-0010-01
A23: GROUP 2 — SUPERSTRUCTURE AND ENVELOPE
A24: 2.1a | B24: Frame | D24: ALL | E24: New build: steel or concrete frame (columns, beams, bracing) incl. fire protection. Refurbishment: strengthening or adapting the existing frame | F24: Floor slabs (1.2, 2.2); roof structure (2.5) | G24: m² GIFA | H24: - | I24: - | J24: - | K24: 350 | L24: 550 | M24: Kept after Spon's check | N24: Refurb £118 (p.242) · New build £103–£201 (p.265, 302) | O24: S-0011-01
A25: 2.1b | B25: Frame | D25: IND | E25: Industrial / warehouse: steel portal frame with cold-rolled roof purlins and wall rails, painted, incl. the frame of an office block inside the shed | F25: Floor slabs (1.2, 2.2); roof structure (2.5) | G25: m² GIFA | H25: - | I25: - | J25: - | K25: 90 | L25: 120 | M25: Spon's-based (approved) | N25: Shed model: portal frame £70.60 per m² GIFA × 1.30 = £92 (p.221) | O25: S-0011-02
A26: 2.2 | B26: Upper floors | D26: ALL | E26: Upper floor slabs or decks (composite steel deck, precast or timber) incl. balconies. Refurbishment: repairing or strengthening existing floors | F26: Floor finishes (3.2); frame (2.1) | G26: m² upper floors | H26: - | I26: - | J26: - | K26: 110 | L26: 135 | M26: Spon's-based (approved) | N26: Refurb £25 (p.242) · New build £93–£136 (p.308) | O26: S-0012-01
A27: 2.3 | B27: Stairs and ramps | D27: ALL | E27: Staircases and ramps with finishes, handrails and balustrades | F27: Lifts (5.16) | G27: m² GIFA | H27: - | I27: - | J27: - | K27: 20 | L27: 35 | M27: Spon's-based (approved) | N27: Refurb £43 (p.242) · New build £6–£35 (p.266, 260) | O27: S-0013-01
A28: 2.4 | B28: Mezzanine floor | D28: ALL | E28: Free-standing steel mezzanine floor with deck, access stair, balustrade and fire protection | F28: Finishes and services on the mezzanine | G28: m² mezzanine | H28: 180 | I28: 250 | J28: 350 | K28: 250 | L28: 350 | M28: Kept after Spon's check | N28: £187–£234 (p.302) | O28: S-0014-01
A29: 2.5a | B29: Roof | C29: Full roof | D29: ALL | E29: Roof structure, covering, insulation, rainwater goods, roof access and edge protection (measured on plan, = footprint). Refurbishment: re-covering and insulating the existing roof | F29: Rooflights over standard provision; green roof (8.11); solar PV (5.17) | G29: m² roof | H29: 155 | I29: 190 | J29: 345 | K29: 220 | L29: 300 | M29: Your figure | N29: Refurb £94–£220 (p.246, 313) · New build £181–£258 (p.310, 313) | O29: S-0015-01 | Q29: Loft insulation only: £32 — see 2.5b. CS: £313 (bids £288–£338) per m² of roof re-covered (699 m², less than the footprint) for a flat warm-roof overlay on the kept asphalt: AVCL, 120 mm PIR, two-layer felt, insulated upstands, new copings, ballast relaid. Scaffold extra (see 2.7). Claycroft pitched re-roof £627–£704. CC: £517 per m² of roof plan (5,747 m² footprint) on the G4 contract: strip concrete tiles, top-hat spacers, Euroclad secret-fix metal over-roof, hips and verges, new eaves, gutters and soffits (£596 per m of eaves), incl. Metclad's design and prelims; excl. the bay-window cladding and scaffold (scaffold £99 per m² of plan). Forecast out-turn with roof timber remedials £601. Tiled like-for-like alternative about £460 (Stage 3). | S29: 516.9 | U29: 182 | Z29: =AVERAGE(R29:Y29) -> 349.45 | AA29: 190 | AB29: Raise. Computer Science £182 per m² footprint. Claycroft metal over-roof £517 is a High case.
A30: 2.5c | B30: Roof | C30: Full roof | D30: IND | E30: Industrial / warehouse: insulated trapezoidal composite roof panels with rooflights (about 15%), valley and eaves gutters, syphonic rainwater drainage, roof access and fall-arrest system (measured on plan, = footprint) | F30: Rooflights over standard provision; green roof (8.11); solar PV (5.17) | G30: m² roof | H30: 155 | I30: 190 | J30: 345 | K30: 115 | L30: 150 | M30: Spon's-based (approved) | N30: Shed model: roof £90.24 per m² × 1.30 = £117 (p.222) | O30: S-0015-03
A31: 2.5b | B31: Roof | C31: Loft insulation only | D31: ALL | E31: Loft insulation top-up only, roof kept: remove and dispose of old quilt, lay 300 mm mineral wool quilt at ceiling level between and over joists (measured on plan, = footprint) | F31: Roof covering, structure and repairs (2.5a); fire barriers in the roof void (2.10). Not offered on new build | G31: m² roof | I31: 32 | K31: 0 | M31: Tender – Lakeside S&F (Sep 2026) | O31: S-0015-02 | Q31: £32 (bids £29–£39) on 1,099 m², incl. removing the old insulation | T31: 32 | Z31: =AVERAGE(R31:Y31) -> 32 | AA31: 32 | AB31: Keep. Lakeside tender.
A32: 2.6a | B32: External walls | D32: ALL | E32: External walls and facade: masonry, cladding or curtain wall (solid parts), insulation and internal lining. Refurbishment: repairs, re-rendering or over-cladding | F32: Windows and external doors (2.7) | G32: m² GIFA | H32: 50 | I32: 100 | J32: 183 | K32: 220 | L32: 340 | M32: Your figure | N32: Refurb £18–£61 (p.242, 246) · New build £75–£338 (p.266, 324) | O32: S-0016-01 | Q32: CS: £48 (bids £45–£51) for insulated render to part of the façade of an occupied 4-storey building. With the brick remedials under it (see 7.1a): £97 (bids £70–£122). Scaffold extra (see 2.7). | U32: 48 | Y32: 170.5 | Z32: =AVERAGE(R32:Y32) -> 109.25 | AA32: 100 | AB32: Raise. CS part render £48; Riley Court full envelope upgrade £171 (cladding, insulated linings).
A33: 2.6b | B33: External walls | D33: IND | E33: Industrial / warehouse: insulated composite wall cladding (micro-rib and trapezoidal panels), parapet cladding, flashings and access equipment. Priced for a unit of about 2,000–5,000 m² with 8–10 m eaves; smaller units have more wall per m² GIFA | F33: Windows and external doors (2.7) | G33: m² GIFA | H33: 50 | I33: 100 | J33: 183 | K33: 100 | L33: 140 | M33: Spon's-based (approved) | N33: Shed model: cladding about £115 per m² of wall × 1.30 = £150; a 4,000 m² unit has about 0.67 m² of wall per m² GIFA = £100 (p.222) | O33: S-0016-02
A34: 2.7a | B34: Windows and external doors | D34: ALL | E34: Windows, external doors, entrance screens and glazing, with ironmongery | F34: Curtain walling solid panels (2.6) | G34: m² GIFA | H34: 105 | I34: 140 | J34: 210 | K34: 210 | L34: 303 | M34: Your figure | N34: Refurb £107 (p.246) · New build £122–£226 (p.266, 333) | O34: S-0017-01 | Q34: CS: £210 (bids £192–£228) for triple-glazed windows, curtain walling and doors on a whole 4-storey building (openings ≈ 16% of GIFA, ≈ £1,330/m² of opening), incl. take-out, closers, fire barriers, reveals, boards and decs (≈ 30% on top of supply and fit). 17% above High. The low bid left out the curtain walling. Scaffold for envelope works (in the bids' prelims): £42 (bids £35–£49) per m² GIFA, extra to 2.5a, 2.6 and 2.7. Out-turn: window design development added £86k (3.3% of the contract sum) after award. | U34: 210 | W34: 24.4 | Y34: 146.7 | Z34: =AVERAGE(R34:Y34) -> 127.03333 | AA34: 140 | AB34: Raise. Riley Court new windows £147; CS triple glazing £210 (High). Co-op was refinish only.
A35: 2.7b | B35: Windows and external doors | D35: IND | E35: Industrial / warehouse: office windows, curtain walling and entrance doors, personnel escape doors and plant-room louvres. Loading and dock doors are in 4.13 Warehouse | F35: Curtain walling solid panels (2.6) | G35: m² GIFA | H35: 105 | I35: 140 | J35: 210 | K35: 25 | L35: 40 | M35: Spon's-based (approved) | N35: Shed model: office glazing £119 per m² of office (about £14 per m² GIFA at 10% offices) + escape doors and louvres £3.60 = £17.50 × 1.30 = £23 (p.222) | O35: S-0017-02
A36: 2.8 | B36: Internal walls | D36: ALL | E36: Internal walls and partitions (stud or block), incl. acoustic and fire-rated partitions, and toilet IPS panels | F36: Wall finishes (3.1); doors (2.9) | G36: m² GIFA | H36: 68 | I36: 150 | J36: 218 | K36: 150 | L36: 218 | M36: Your figure | N36: £115–£167 (p.275, 243) | O36: S-0018-01 | W36: 26.4 | Y36: 246.9 | Z36: =AVERAGE(R36:Y36) -> 136.65 | AA36: 150 | AB36: Raise. Riley Court £247 (acoustic academic partitions); Co-op £26 was a light shop fit-out.
A37: 2.9 | B37: Internal doors | D37: ALL | E37: Internal doorsets (frame, leaf, ironmongery, decoration), incl. fire doors | F37: External doors (2.7) | G37: m² GIFA | H37: 50 | I37: 100 | J37: 200 | K37: 100 | L37: 200 | M37: Your figure | N37: Refurb £62–£147 (p.247, 255) · New build £38–£163 (p.275, 251) | O37: S-0019-01 | V37: 99 | W37: 9.1 | Y37: 163.7 | Z37: =AVERAGE(R37:Y37) -> 90.6 | AA37: 100 | AB37: Raise. Riley Court £164, Scarman £99; Co-op £9 reused most doors.
A38: 2.10 | B38: Fire stopping | D38: ALL | E38: Upgrading fire stopping and compartmentation in an existing building: sealing service penetrations, fire barriers in voids and cavities | F38: Fire doors (2.9); fire alarm (5.11) | G38: m² GIFA | H38: 15 | I38: 30 | J38: 60 | K38: 15 | L38: 30 | M38: Kept after Spon's check | O38: S-0020-01 | Q38: £13.5 (bids £7–£32) for local fire stopping only — in line with Basic £15 CC: £96 forecast out-turn (Mace Val 16, Sep 2026; £88 if the Claycroft 2 CE replaces its provisional sum), against £22 for the £350k provisional sum in the G4 contract. By block: Claycroft 1 £53 (final); Claycroft 3 £76 (measured: about 18 seals per bed at about £42 each; access 22% of the cost); Claycroft 2 £135–£155 (under review). Excludes £1.30m of compartment-wall head remediation on Claycroft 3, which included a 16-week delay. | S38: 95.8 | T38: 13.5 | V38: 24 | W38: 3.4 | Y38: 15.6 | Z38: =AVERAGE(R38:Y38) -> 30.46 | AA38: 30 | AB38: Keep. Most projects £3–24; Claycroft £96 out-turn (surveyed occupied residential) is a High case.
A39: GROUP 3 — INTERNAL FINISHES
A40: 3.1 | B40: Wall finishes | D40: ALL | E40: Plaster or dry lining, decoration and wall tiling, incl. tanking in wet areas | F40: Wall panelling as joinery (4.5) | G40: m² GIFA | H40: 30 | I40: 75 | J40: 140 | K40: 55 | L40: 140 | M40: Your figure | N40: Refurb £89–£119 (p.247, 255) · New build £56–£134 (p.251, 267) | O40: S-0021-01 | Q40: £72 (bids £60–£84) incl. bathroom wall cladding, kitchen tiling and full redecoration — confirms £75 CC: £99 on the G4 contract: decoration (RE Martin, £1.02m; three bids £1.02m–£1.16m), making good (£274k) and PVC hygienic wall cladding (£251k). Includes painting ceilings and doors. | S40: 99.3 | T40: 72 | V40: 304 | W40: 26.6 | X40: 49 | Y40: 39.4 | Z40: =AVERAGE(R40:Y40) -> 98.383333 | AA40: 75 | AB40: Keep. Lakeside £72, Claycroft £99, Riley Court £39 (decoration only). Scarman is toilet-area only.
A41: 3.2a | B41: Floor finishes | C41: Raised access floor: No | D41: ALL | E41: Screed and floor coverings (carpet, vinyl, tiles, timber), skirtings and entrance matting, incl. tanking in wet areas | F41: Structural slabs (1.2, 2.2) | G41: m² GIFA | H41: 51 | I41: 85 | J41: 227 | K41: 85 | L41: 227 | M41: Your figure | N41: Refurb £72–£215 (p.247, 256) · New build £75–£110 (p.251, 261) | O41: S-0022-01 | Q41: Residential: £51 — see 3.2c | V41: 177 | W41: 21.5 | Y41: 95.3 | Z41: =AVERAGE(R41:Y41) -> 97.933333 | AA41: 85 | AB41: Raise slightly. Riley Court £95 full replacement; Co-op £22 kept its floor. Scarman is toilet-area only.
A42: 3.2b | B42: Floor finishes | C42: Raised access floor: Yes | D42: ALL | E42: As 3.2a plus a raised access floor (steel-encased panels on pedestals) for offices and data rooms | F42: Structural slabs (1.2, 2.2) | G42: m² GIFA | H42: 90 | I42: 120 | J42: 245 | K42: 120 | L42: 245 | M42: Kept after Spon's check | N42: Refurb £127–£142 (p.353) · New build £142–£190 (p.353) | O42: S-0022-02
A43: 3.2c | B43: Floor finishes | C43: Raised access floor: No | D43: RES STU | E43: As 3.2a for flats and student rooms: latex levelling screed, sheet vinyl (slip-resistant in wet areas), skirtings and threshold strips | F43: Structural slabs (1.2, 2.2) | G43: m² GIFA | H43: 30 | I43: 50 | J43: 135 | K43: 75 | L43: 200 | M43: Tender – Lakeside S&F (Sep 2026) | O43: S-0022-03 | Q43: £51 (bids £48–£59). New build columns copied from 3.2a CC: £38 on the G4 contract: carpet and vinyl (Active, £506k; three bids £506k–£660k), Claycroft 2 corridor and lobby floors (£88k) and screed (£4.5k). | S43: 38.4 | T43: 51 | Z43: =AVERAGE(R43:Y43) -> 44.7 | AA43: 50 | AB43: Keep. Lakeside £51, Claycroft £38.
A44: 3.3a | B44: Ceiling finishes | D44: ALL | E44: Suspended or plasterboard ceilings with decoration, incl. access panels and bulkheads | F44: Light fittings (5.8) | G44: m² GIFA | H44: 48 | I44: 80 | J44: 224 | K44: 112 | L44: 224 | M44: Your figure | N44: Refurb £42–£106 (p.247, 256) · New build £71–£104 (p.252, 267) | O44: S-0023-01 | Q44: Residential: £30 — see 3.3b | V44: 129 | W44: 21 | Y44: 109.6 | Z44: =AVERAGE(R44:Y44) -> 86.533333 | AA44: 80 | AB44: Raise. Riley Court £110 new suspended ceilings; Co-op £21 painted soffits only.
A45: 3.3b | B45: Ceiling finishes | D45: RES STU | E45: As 3.3a for flats and student rooms: overboarding or making good existing plasterboard ceilings, mist coat and two coats emulsion (anti-fungal in kitchens and bathrooms) | F45: Light fittings (5.8); loft insulation (2.5b) | G45: m² GIFA | H45: 18 | I45: 30 | J45: 85 | K45: 70 | L45: 140 | M45: Tender – Lakeside S&F (Sep 2026) | O45: S-0023-02 | Q45: £30 (bids £21–£36). New build columns copied from 3.3a CC: £70 on the G4 contract: ceilings and partitions package (Ace, £1.10m; three bids £1.10m–£1.23m) — replacement plasterboard ceilings (two layers of fire-line board on top floors), stair soffits and some partitions, not split. Claycroft replaced its ceilings, so compare with 3.3a. | S45: 70.4 | T45: 30 | Z45: =AVERAGE(R45:Y45) -> 50.2 | AA45: 30 | AB45: Keep. Lakeside £30; Claycroft £70 was full replacement (High case).
A46: GROUP 4 — TOILETS, KITCHENS AND FITTINGS
A47: 4.1a | B47: Toilets | C47: Standard | D47: ALL | E47: Per WC: WC pan, wash basin and taps, cubicle, hand dryer and a share of vanity units and accessories, fitted | F47: Wall and floor tiling (3.1, 3.2); water pipework and drainage (5.2); lighting and ventilation | G47: nr WCs | H47: 1800 | I47: 3950 | J47: 6400 | K47: 3950 | L47: 6400 | M47: Kept after Spon's check | N47: £1,710–£2,137 (p.361) | O47: S-0024-01 | V47: 7653 | Y47: 14573 | Z47: =AVERAGE(R47:Y47) -> 11113 | AA47: 7000 | AB47: Keep as is (owner, 4 Oct 2026).
A48: 4.1b | B48: Toilets | C48: Accessible | D48: ALL | E48: Per accessible WC (Approved Document M): larger cubicle, Doc M pack, grab rails, alarm and accessories | F48: Wall and floor tiling (3.1, 3.2); water pipework and drainage (5.2); lighting and ventilation | G48: nr WCs | H48: 3500 | I48: 5500 | J48: 9000 | K48: 5500 | L48: 9000 | M48: Kept after Spon's check | O48: S-0024-04 | Y48: 16025 | Z48: =AVERAGE(R48:Y48) -> 16025 | AA48: 9000 | AB48: Keep as is (owner, 4 Oct 2026).
A49: 4.1c | B49: Toilets | C49: Changing Places (hoist, adult changing bench) | D49: ALL | E49: Per Changing Places toilet: ceiling hoist, height-adjustable adult changing bench, peninsular WC, privacy screen and alarm. Needed in some large new public buildings. Priced only when you enter how many | F49: Wall and floor tiling (3.1, 3.2); water pipework and drainage (5.2); lighting and ventilation | G49: nr | I49: 45000 | J49: 80000 | K49: 45000 | L49: 80000 | M49: Your figure | O49: S-0024-05
A50: 4.2a | B50: Bathrooms and en-suites | C50: Standard | D50: ALL | E50: Per bathroom: bath or shower tray and screen, WC, basin, taps, mirror and accessories, fitted | F50: Tiling (3.1, 3.2); pipework (5.2); extract fan (5.3) | G50: nr bathrooms | H50: 1150 | I50: 2500 | J50: 4400 | K50: 2000 | L50: 3500 | M50: Tender – Lakeside S&F (Sep 2026) | N50: £1,916–£2,558 (p.362) | O50: S-0025-01 | Q50: £2,563 per bathroom (bids £2,322–£4,440); standard suite alone £2,460. New build columns not changed CC: £3,869 per bathroom on the G4 contract, Claycroft 1 (135 bathroom units): IPS and vanity (Inscape) plus WC, basin and bath with taps, incl. assisted-bathroom changes. Water and drainage connections are in 5.2a; PVC wall cladding is in 3.1. | S50: 3869 | T50: 2563 | Z50: =AVERAGE(R50:Y50) -> 3216 | AA50: 2500 | AB50: Keep. Lakeside £2,563; Claycroft £3,869 sits between Std and High.
A51: 4.2b | B51: Bathrooms and en-suites | C51: Standard | D51: HOS | E51: As 4.2a with hotel-grade fittings and finishes | F51: Tiling (3.1, 3.2); pipework (5.2); extract fan (5.3) | G51: nr bathrooms | H51: 3500 | I51: 5500 | J51: 8500 | K51: 5500 | L51: 8500 | M51: Older workbook (v4.5) | N51: £6,560–£8,247 (p.359) | O51: S-0025-02
A52: 4.3 | B52: Showers | D52: ALL | E52: Per shower: tray, screen or curtain, thermostatic valve and head, fitted | F52: Tiling (3.1, 3.2); pipework (5.2); benches and lockers (4.14) | G52: nr showers | H52: 900 | I52: 1400 | J52: 2500 | K52: 1400 | L52: 2500 | M52: Spon's-based (approved) | N52: £890–£1,148 (p.362) | O52: S-0026-01
A53: 4.4a | B53: Kitchens | C53: Domestic kitchen | D53: ALL | E53: Per kitchen: base and wall units, worktop, sink and taps, fitted | F53: White goods (4.8); pipework (5.2); electrics (5.7) | G53: nr kitchens | H53: 3100 | I53: 5300 | J53: 8850 | K53: 6000 | L53: 10000 | M53: Tender – Lakeside S&F (Sep 2026) | N53: £2,975–£11,245 (p.358) | O53: S-0027-01 | Q53: £5,296 per kitchen (bids £4,538–£5,890): units supplied and fitted, sink and taps connected. New build columns not changed | T53: 5296 | Z53: =AVERAGE(R53:Y53) -> 5296 | AA53: 5300 | AB53: Keep. Lakeside tender £5,296.
A54: 4.4b | B54: Kitchens | C54: Staff kitchenette (non-domestic) | D54: ALL | E54: Per staff kitchenette in a non-domestic building (offices, schools, healthcare): base and wall units, worktop, sink and hot-water tap, fitted | F54: White goods (4.8); pipework (5.2); electrics (5.7) | G54: nr kitchenettes | H54: 3750 | I54: 6000 | J54: 10500 | K54: 6000 | L54: 10500 | M54: Your figure | N54: £2,975–£3,702 (p.358) | O54: S-0027-02 | Y54: 10276 | Z54: =AVERAGE(R54:Y54) -> 10276 | AA54: 6000 | AB54: Raise. Riley Court about £10,300 per tea point (8 assumed); your own review said £5,500.
A55: 4.5 | B55: Fixed joinery | D55: ALL | E55: Built-in, made-to-fit items: reception desks, fitted storage and shelving, lockers, fitted benches, wall panelling | F55: Loose furniture (4.8); kitchens (4.4); toilet vanity units (4.1) | G55: m² GIFA | H55: 15 | I55: 45 | J55: 100 | K55: 45 | L55: 100 | M55: Older workbook (v4.5) | N55: Refurb £72–£257 (p.248, 243) · New build £32–£102 (p.276, 252) | O55: S-0028-01 | Q55: CC: £64 on the G4 contract: joinery package (Mansard, £994k; two bids £994k–£1.04m) — bathroom joinery (boxings, bath panels, shelves) 67%, bedroom joinery (wardrobe alterations, shelving) 21%, other incl. signage 12%. | S55: 63.7 | W55: 7 | Y55: 41.8 | Z55: =AVERAGE(R55:Y55) -> 37.5 | AA55: 45 | AB55: Keep. Riley Court £42, Claycroft £64, Co-op £7.
A56: 4.6 | B56: Signage | D56: ALL | E56: Statutory safety signs (fire exits, fire equipment, accessible WCs, room signs) and internal wayfinding | F56: External building name signs and branding | G56: m² GIFA | H56: 6 | I56: 12 | J56: 18 | K56: 12 | L56: 18 | M56: Your figure | N56: £3–£4 (p.248, 276) | O56: S-0029-01 | W56: 16.4 | Y56: 12.2 | Z56: =AVERAGE(R56:Y56) -> 14.3 | AA56: 12 | AB56: Raise slightly. Riley Court £12, Co-op £16 (incl. graphics).
A57: 4.7 | B57: AV equipment | D57: ALL | E57: Screens, projectors, audio, and room booking panels in meeting and teaching rooms, installed | F57: Data cabling (5.14) | G57: m² GIFA | H57: - | I57: 25 | J57: 60 | K57: 25 | L57: 60 | M57: Older workbook (v4.5) | O57: S-0030-01
A58: 4.8a | B58: Loose furniture | C58: Standard | D58: ALL | E58: Loose furniture and equipment: desks, chairs, tables, beds, white goods | F58: Built-in joinery (4.5) | G58: m² GIFA | H58: 55 | I58: 110 | J58: 240 | K58: 110 | L58: 240 | M58: Older workbook (v4.5) | N58: £103–£131 (p.358) | O58: S-0031-01
A59: 4.8b | B59: Loose furniture | C59: Standard | D59: RES | E59: Residential: sofas, beds, tables, chairs and white goods per flat, spread over the floor area | F59: Built-in joinery (4.5) | G59: m² GIFA | H59: 28 | I59: 50 | J59: 120 | K59: 50 | L59: 120 | M59: Older workbook (v4.5) | O59: S-0031-02
A60: 4.8c | B60: Loose furniture | C60: Standard | D60: STU | E60: Student rooms: bed, desk, chair, storage per room, spread over the floor area | F60: Built-in joinery (4.5) | G60: m² GIFA | H60: 48 | I60: 88 | J60: 180 | K60: 88 | L60: 180 | M60: Older workbook (v4.5) | O60: S-0031-03
A61: 4.8d | B61: Loose furniture | C61: Standard | D61: HOS | E61: Hotel rooms: beds, case goods, seating and public-area furniture, spread over the floor area | F61: Built-in joinery (4.5) | G61: m² GIFA | H61: 62 | I61: 138 | J61: 350 | K61: 138 | L61: 350 | M61: Older workbook (v4.5) | O61: S-0031-04
A62: 4.9 | B62: Catering kitchen | D62: ALL | E62: Commercial kitchen: cooking equipment, stainless steel benching, servery and bar counters, extract canopy and grease trap | F62: Kitchen room finishes (Group 3); general ventilation (5.3) | G62: m² kitchen | H62: 541 | I62: 1000 | J62: 2100 | K62: 1000 | L62: 2100 | M62: Your figure | O62: S-0032-01 | X62: 1438 | Z62: =AVERAGE(R62:Y62) -> 1438 | AA62: 1000 | AB62: Raise. IBRB café servery £1,438 (bespoke stainless) = High; your own review said Std £1,000.
A63: 4.10 | B63: Laboratory | D63: ALL | E63: Laboratory benching, sinks, storage and fume cupboards | F63: Fume extract ductwork and fans (5.21); lab gases | G63: m² lab | I63: 310 | J63: 600 | K63: 310 | L63: 600 | M63: Older workbook (v4.5) | O63: S-0033-01
A64: 4.11 | B64: Clinical | D64: ALL | E64: Clinical fittings and fixed equipment: couches, clinical sinks, pendants, clinical storage | F64: Medical gas pipework (5.23); nurse call (5.24) | G64: m² clinical | I64: 65 | J64: 130 | K64: 65 | L64: 130 | M64: Older workbook (v4.5) | O64: S-0034-01
A65: 4.12 | B65: Retail | D65: ALL | E65: Shop fit-out fixtures: display units, counters and tills, fitting rooms, security tags | F65: Shopfront (2.7); floor and ceiling finishes (Group 3) | G65: m² sales area | I65: 163 | J65: 305 | K65: 163 | L65: 305 | M65: Older workbook (v4.5) | O65: S-0035-01
A66: 4.13 | B66: Warehouse | D66: ALL | E66: Pallet racking, dock levellers and loading doors | F66: Overhead cranes (use Other / specialist scope) | G66: m² warehouse | H66: 22 | I66: 24 | J66: 51 | K66: 24 | L66: 51 | M66: Older workbook (v4.5) | O66: S-0036-01
A67: 4.14 | B67: Sports | D67: ALL | E67: Gym and fitness equipment, changing room lockers and benches | F67: Sports floor finishes (3.2); spectator seating (use Other / specialist scope) | G67: m² sports area | I67: 152 | J67: 352 | K67: 152 | L67: 352 | M67: Older workbook (v4.5) | O67: S-0037-01
A68: 4.15 | B68: Cleanroom | D68: ALL | E68: Cleanroom enclosure, ceiling, filtered air supply and validation | F68: Process equipment | G68: m² cleanroom | I68: 380 | J68: 860 | K68: 380 | L68: 860 | M68: Older workbook (v4.5) | O68: S-0038-01
A69: GROUP 5 — SERVICES
A70: 5.1a | B70: Heating and hot water | C70: Gas boiler, full system | D70: ALL | E70: Full system: heat source, pipework, radiators or underfloor heating, controls, and hot water generation | F70: Cooling (5.4); ventilation (5.3); gas supply to the site (8.4) | G70: m² GIFA | H70: 30 | I70: 60 | J70: 135 | K70: 60 | L70: 105 | M70: Older workbook (v4.5) | N70: Refurb £92–£137 (p.243, 248) · New build £50–£112 (p.364, 363) | O70: S-0039-01
A71: 5.1b | B71: Heating and hot water | C71: Air source heat pump, full system | D71: ALL | E71: Full system with an air source heat pump as the heat source (incl. hot water cylinder and buffer) | F71: Cooling (5.4); ventilation (5.3); gas supply to the site (8.4) | G71: m² GIFA | H71: 95 | I71: 190 | J71: 427 | K71: 190 | L71: 332 | M71: Your figure | O71: S-0039-02 | Q71: CS: £224 (bids £210–£238) for the whole M&E package of an air source heat pump conversion of an occupied academic building: heat pumps replacing gas boilers, LTHW alterations, coils to 6 AHUs, about 160 radiators, BMS and ventilation (no breakdown). Std 5.1b + 5.5 = £93. Heat pumps: 3 × 118 kW (N+1, about 240 kW duty, about 69 W/m² after the fabric works), so about £1,800–2,100 per kW installed for the whole M&E package. | U71: 224 | Z71: =AVERAGE(R71:Y71) -> 224 | AA71: 190 | AB71: Raise. CS whole heat pump M&E package £224; enter as a figure, not = 5.1a × factor.
A72: 5.1c | B72: Heating and hot water | C72: Ground source heat pump, full system | D72: ALL | E72: Full system with a ground source heat pump incl. boreholes or ground loops | F72: Cooling (5.4); ventilation (5.3); gas supply to the site (8.4) | G72: m² GIFA | H72: =H70*1.8 -> 54 | I72: =I70*1.8 -> 108 | J72: =J70*1.8 -> 243 | K72: =K70*1.8 -> 108 | L72: =L70*1.8 -> 189 | M72: Unverified † (= 5.1a × 1.8) | O72: S-0039-03
A73: 5.1d | B73: Heating and hot water | C73: District heating, full system | D73: ALL | E73: Full system fed from a district heating network: heat interface units, pipework and emitters | F73: Cooling (5.4); ventilation (5.3); gas supply to the site (8.4) | G73: m² GIFA | H73: 60 | I73: 120 | J73: 270 | K73: 120 | L73: 210 | M73: Your figure | O73: S-0039-04 | Y73: 134.7 | Z73: =AVERAGE(R73:Y73) -> 134.7 | AA73: 120 | AB73: Raise. Riley Court £135 incl. new LTHW pipework, radiators and pumps off district heating.
A74: 5.1e | B74: Heating and hot water | C74: Electric, full system | D74: ALL | E74: Electric heating throughout: panel heaters or electric boilers and direct hot water heaters | F74: Cooling (5.4); ventilation (5.3); gas supply to the site (8.4) | G74: m² GIFA | H74: =H70*0.6 -> 18 | I74: =I70*0.6 -> 36 | J74: =J70*0.6 -> 81 | K74: =K70*0.6 -> 36 | L74: =L70*0.6 -> 63 | M74: Unverified † (= 5.1a × 0.6) | O74: S-0039-05
A75: 5.1f | B75: Heating and hot water | C75: Gas boiler, plant only | D75: ALL | E75: Plant only: new gas boiler(s), flue, pumps and plant-room pipework; existing pipework and radiators kept | F75: Cooling (5.4); ventilation (5.3); gas supply to the site (8.4) | G75: m² GIFA | H75: =H70*0.35 -> 10.5 | I75: =I70*0.35 -> 21 | J75: =J70*0.35 -> 47.25 | K75: =K70*0.35 -> 21 | L75: =L70*0.35 -> 36.75 | M75: Unverified † (= 5.1a × 0.35) | O75: S-0039-06
A76: 5.1g | B76: Heating and hot water | C76: Gas boiler, radiators and controls only | D76: ALL | E76: Radiators and controls only: new emitters, TRVs, local pipework and controls; existing heat source kept | F76: Cooling (5.4); ventilation (5.3); gas supply to the site (8.4) | G76: m² GIFA | H76: =H70*0.3 -> 9 | I76: =I70*0.3 -> 18 | J76: =J70*0.3 -> 40.5 | K76: =K70*0.3 -> 18 | L76: =L70*0.3 -> 31.5 | M76: Unverified † (= 5.1a × 0.3) | O76: S-0039-07
A77: 5.1h | B77: Heating and hot water | C77: Air source heat pump, plant only | D77: ALL | E77: Plant only: new air source heat pump(s), cylinder and plant pipework; existing pipework and radiators kept | F77: Cooling (5.4); ventilation (5.3); gas supply to the site (8.4) | G77: m² GIFA | H77: =H71*0.45 -> 42.75 | I77: =I71*0.45 -> 85.5 | J77: =J71*0.45 -> 192.15 | K77: =K71*0.45 -> 85.5 | L77: =L71*0.45 -> 149.4 | M77: Unverified † (= 5.1b × 0.45) | O77: S-0039-08
A78: 5.1i | B78: Heating and hot water | C78: Air source heat pump, radiators and controls only | D78: ALL | E78: Radiators and controls only (sized for a heat pump); existing heat pump kept | F78: Cooling (5.4); ventilation (5.3); gas supply to the site (8.4) | G78: m² GIFA | H78: =H71*0.3 -> 28.5 | I78: =I71*0.3 -> 57 | J78: =J71*0.3 -> 128.1 | K78: =K71*0.3 -> 57 | L78: =L71*0.3 -> 99.6 | M78: Unverified † (= 5.1b × 0.3) | O78: S-0039-09
A79: 5.1j | B79: Heating and hot water | C79: Ground source heat pump, plant only | D79: ALL | E79: Plant only: ground source heat pump, boreholes or ground loops; existing pipework and radiators kept | F79: Cooling (5.4); ventilation (5.3); gas supply to the site (8.4) | G79: m² GIFA | H79: =H72*0.45 -> 24.3 | I79: =I72*0.45 -> 48.6 | J79: =J72*0.45 -> 109.35 | K79: =K72*0.45 -> 48.6 | L79: =L72*0.45 -> 85.05 | M79: Unverified † (= 5.1c × 0.45) | O79: S-0039-10
A80: 5.1k | B80: Heating and hot water | C80: Ground source heat pump, radiators and controls only | D80: ALL | E80: Radiators and controls only (sized for a ground source heat pump); existing heat source kept | F80: Cooling (5.4); ventilation (5.3); gas supply to the site (8.4) | G80: m² GIFA | H80: =H72*0.3 -> 16.2 | I80: =I72*0.3 -> 32.4 | J80: =J72*0.3 -> 72.9 | K80: =K72*0.3 -> 32.4 | L80: =L72*0.3 -> 56.7 | M80: Unverified † (= 5.1c × 0.3) | O80: S-0039-11
A81: 5.1l | B81: Heating and hot water | C81: District heating, plant only | D81: ALL | E81: Plant only: heat interface unit and connection to the network; existing pipework and radiators kept | F81: Cooling (5.4); ventilation (5.3); gas supply to the site (8.4) | G81: m² GIFA | H81: =H73*0.3 -> 18 | I81: =I73*0.3 -> 36 | J81: =J73*0.3 -> 81 | K81: =K73*0.3 -> 36 | L81: =L73*0.3 -> 63 | M81: Unverified † (= 5.1d × 0.3) | O81: S-0039-12
A82: 5.1m | B82: Heating and hot water | C82: District heating, radiators and controls only | D82: ALL | E82: Radiators and controls only on a district heating system; existing connection kept | F82: Cooling (5.4); ventilation (5.3); gas supply to the site (8.4) | G82: m² GIFA | H82: =H73*0.3 -> 18 | I82: =I73*0.3 -> 36 | J82: =J73*0.3 -> 81 | K82: =K73*0.3 -> 36 | L82: =L73*0.3 -> 63 | M82: Unverified † (= 5.1d × 0.3) | O82: S-0039-13
A83: 5.1n | B83: Heating and hot water | C83: Electric, plant only | D83: ALL | E83: Plant only: electric boiler or water heaters; existing emitters kept | F83: Cooling (5.4); ventilation (5.3); gas supply to the site (8.4) | G83: m² GIFA | H83: =H74*0.5 -> 9 | I83: =I74*0.5 -> 18 | J83: =J74*0.5 -> 40.5 | K83: =K74*0.5 -> 18 | L83: =L74*0.5 -> 31.5 | M83: Unverified † (= 5.1e × 0.5) | O83: S-0039-14
A84: 5.1o | B84: Heating and hot water | C84: Electric, radiators and controls only | D84: ALL | E84: New electric panel heaters and controls only | F84: Cooling (5.4); ventilation (5.3); gas supply to the site (8.4) | G84: m² GIFA | H84: =H74*0.3 -> 5.4 | I84: =I74*0.3 -> 10.8 | J84: =J74*0.3 -> 24.3 | K84: =K74*0.3 -> 10.8 | L84: =L74*0.3 -> 18.9 | M84: Unverified † (= 5.1e × 0.3) | O84: S-0039-15
A85: 5.2a | B85: Water and drainage | C85: Full installation | D85: ALL | E85: Full installation: cold and hot water distribution pipework, above-ground soil, waste and rainwater pipework, and the connections to sanitary fittings | F85: Sanitaryware (4.1–4.3); below-ground drainage (8.3) | G85: m² GIFA | H85: 37 | I85: 80 | J85: 222 | K85: 37 | L85: 111 | M85: Your figure | N85: Refurb £68–£180 (p.248, 257) · New build £22–£89 (p.362, 363) | O85: S-0040-01 | Q85: CC: £39 on the G4 contract: domestic hot and cold water (riser pipework and valves, bathroom connections, DHW plate heat exchangers and pumps) and drainage (bathroom connections to stacks, SVP terminations). A partial replacement, not a full installation. Sanitaryware is in 4.2a. | S85: 38.9 | V85: 209 | W85: 18.2 | X85: 124 | Y85: 104.5 | Z85: =AVERAGE(R85:Y85) -> 98.92 | AA85: 80 | AB85: Raise. Riley Court £105, IBRB £124 (small café); Claycroft £39 and Co-op £18 were partial.
A86: 5.2b | B86: Water and drainage | C86: Visible fittings only | D86: ALL | E86: Visible fittings only: taps, valves and short connections to sanitaryware; existing pipework kept | F86: Sanitaryware (4.1–4.3); below-ground drainage (8.3) | G86: m² GIFA | H86: 9 | I86: 19.5 | J86: 54 | K86: 9 | L86: 27 | M86: Tender – Lakeside S&F (Sep 2026) | O86: S-0040-02 | Q86: £20 (bids £15–£26) for local pipework changes to new kitchens and bathrooms — confirms £19.5 | T86: 20 | Z86: =AVERAGE(R86:Y86) -> 20 | AA86: 19.5 | AB86: Keep. Lakeside £20.
A87: 5.3a | B87: Ventilation | C87: Full system | D87: ALL | E87: Mechanical ventilation and extract: fans, AHUs or MVHR units, ductwork, grilles and controls | F87: Cooling (5.4); smoke ventilation (5.13); fume extraction (5.21) | G87: m² GIFA | H87: 33 | I87: 75 | J87: 150 | K87: 67 | L87: 117 | M87: Your figure | N87: Refurb £13–£29 (p.248, 258) · New build £8–£66 (p.364) | O87: S-0041-01 | Q87: Residential extract-only scope: £18.5 — see 5.3b CC: forecast out-turn £92 (Mace Val 16) for bathroom extract incl. new ductwork and roof-mounted fans added by CE in Claycroft 1 (£182k) and Claycroft 2 (£865k). The contract figure is on 5.3b. | W87: 73.1 | Y87: 172.4 | Z87: =AVERAGE(R87:Y87) -> 122.75 | AA87: 75 | AB87: Raise. Riley Court MVHR £172, Co-op £73, Claycroft out-turn £92.
A88: 5.3b | B88: Ventilation | C88: Extract fans only | D88: ALL | E88: Extract fans only: bathroom and WC extract fans, kitchen cooker-hood extract, ducting to outside, fire collars and electrical connection; no central plant | F88: Full ventilation systems (5.3a); cooling (5.4). Not offered on new build | G88: m² GIFA | H88: 9 | I88: 22 | J88: 44 | K88: 0 | M88: Your figure | O88: S-0041-02 | Q88: £18.5 (bids £13–£23), incl. the electrical connection to each fan CC: £28 on the G4 contract: new branch connections, dampers and grilles to the existing bathroom extract, duct cleaning and flow checks, plus fire dampers (£124k). Forecast out-turn £92 once new ductwork and roof fans were added — see 5.3a. | S88: 28.2 | T88: 18.5 | V88: 62 | Z88: =AVERAGE(R88:Y88) -> 36.233333 | AA88: 22 | AB88: Raise slightly. Lakeside £18.5, Claycroft £28; Scarman £62 is toilet-area only.
A89: 5.4 | B89: Cooling | D89: ALL | E89: Air conditioning or comfort cooling: VRF / split units or chilled water, pipework and controls | F89: Server room cooling (5.25) | G89: m² GIFA | H89: 30 | I89: 75 | J89: 150 | K89: 75 | L89: 150 | M89: Older workbook (v4.5) | N89: £84–£149 (p.363) | O89: S-0042-01 | W89: 39.5 | Y89: 34.1 | Z89: =AVERAGE(R89:Y89) -> 36.8 | AA89: 75 | AB89: Keep. Riley Court £34 and Co-op £40 cooled only some rooms; no whole-building evidence.
A90: 5.5 | B90: Controls and BMS | D90: ALL | E90: Building management system: controllers, sensors, meters and software for heating, cooling and ventilation | F90: Local controls supplied with each system | G90: m² GIFA | H90: 13 | I90: 25 | J90: 37 | K90: 25 | L90: 37 | M90: Your figure | N90: £22 (p.244) | O90: S-0043-01 | Q90: CC: £4.3 on the G4 contract: interfaces from the existing BEMS to the new fire alarm and DHW controls only. | S90: 4.3 | W90: 11.5 | Y90: 59.1 | Z90: =AVERAGE(R90:Y90) -> 24.966667 | AA90: 25 | AB90: Raise. Riley Court £59 (full BMS budget); Co-op £11.5; Claycroft £4 interfaces only.
A91: 5.6a | B91: Electricity supply upgrade | C91: Small | D91: ALL | E91: New or upgraded electricity supply from the network, priced as a lump sum by size. Small: capacity increase on the existing supply — new meter, cut-out and incoming cable, no DNO network works | F91: Internal distribution (5.7) | G91: band | I91: 10000 | K91: 10000 | M91: Older workbook (v4.5) | O91: S-0044-01
A92: 5.6b | B92: Electricity supply upgrade | C92: Medium | D92: ALL | E92: Medium: new larger low-voltage supply from the network with DNO reinforcement, no new substation | F92: Internal distribution (5.7) | G92: band | I92: 40000 | K92: 40000 | M92: Older workbook (v4.5) | N92: £40,764–£48,729 (p.393) | O92: S-0044-02
A93: 5.6c | B93: Electricity supply upgrade | C93: Large | D93: ALL | E93: Large: new high-voltage supply with an on-site substation and DNO works | F93: Internal distribution (5.7) | G93: band | I93: 250000 | K93: 250000 | M93: Older workbook (v4.5) | N93: £40,764–£48,729 (p.393) | O93: S-0044-03
A94: 5.7a | B94: Power | C94: Full installation | D94: ALL | E94: Full installation: main switchgear, distribution boards, containment, all wiring for power and lighting circuits, sockets and switches | F94: Light fittings (5.8); new supply from the network (5.6) | G94: m² GIFA | H94: 80 | I94: 126 | J94: 215 | K94: 109 | L94: 174 | M94: Older workbook (v4.5) | N94: Refurb £186–£217 (p.248, 244) · New build £53–£137 (p.365) | O94: S-0045-01 | V94: 97 | W94: 88.5 | X94: 218 | Y94: 130.6 | Z94: =AVERAGE(R94:Y94) -> 133.525 | AA94: 126 | AB94: Keep. Riley Court £131, Scarman £97, Co-op £89. IBRB £218 is one supply on a small room.
A95: 5.7b | B95: Power | C95: Full installation | D95: RES STU | E95: As 5.7a for flats and student rooms: consumer units per dwelling, wiring and sockets (no sub-distribution boards) | F95: Light fittings (5.8); new supply from the network (5.6) | G95: m² GIFA | H95: 95 | I95: 150 | J95: 255 | K95: 93 | L95: 148 | M95: Tender – Lakeside S&F (Sep 2026) | N95: £84–£119 (p.366) | O95: S-0045-02 | Q95: Power + lighting £186 (bids £157–£253) less lighting 5.8a £33 = £153; incl. landlord panels and sub-mains per block. New build columns not changed CC: £158 on the G4 contract: full rewire — LV switch panels and distribution boards (£1.10m), containment (£366k), small power (£669k), isolation and strip-out of the old installation (£158k) and earthing. Electrical total with lighting, fire alarm and data: £355. | S95: 157.7 | T95: 153 | Z95: =AVERAGE(R95:Y95) -> 155.35 | AA95: 150 | AB95: Keep. Lakeside £153, Claycroft £158.
A96: 5.7c | B96: Power | C96: Second fix only | D96: ALL | E96: Second fix only: new sockets, switches and accessories on existing wiring | F96: Light fittings (5.8); new supply from the network (5.6) | G96: m² GIFA | H96: 13 | I96: 15 | J96: 30 | K96: 0 | M96: Older workbook (v4.5) | O96: S-0045-03
A97: 5.8a | B97: Lighting | C97: Full installation | D97: ALL | E97: Full installation: light fittings (LED), lighting controls and external lights fixed to the building | F97: Wiring (in 5.7 Power); emergency lighting (5.9); site lighting (8.14) | G97: m² GIFA | H97: 48 | I97: 80 | J97: 126 | K97: 80 | L97: 126 | M97: Your figure | N97: Refurb £62 (p.248) · New build £34–£46 (p.365) | O97: S-0046-01 | Q97: Not separable in the tender — checked together with 5.7b CC: £113 on the G4 contract for general, emergency and external lighting together (£1.66m, not split) — compare with 5.8a + 5.9 (£33 + £10). | S97: 113.2 | V97: 84 | W97: 80.6 | X97: 51 | Y97: 198 | Z97: =AVERAGE(R97:Y97) -> 105.36 | AA97: 80 | AB97: Raise. Five projects £51–198 (median £84); £33 is far too low.
A98: 5.8b | B98: Lighting | C98: Replace fittings only | D98: ALL | E98: Replace light fittings only: like-for-like LED fittings on existing wiring and layout, no new controls | F98: Wiring (in 5.7 Power); emergency lighting (5.9); site lighting (8.14) | G98: m² GIFA | H98: =H97*0.75 -> 36 | I98: =I97*0.75 -> 60 | J98: =J97*0.75 -> 94.5 | K98: =K97*0.75 -> 60 | L98: =L97*0.75 -> 94.5 | M98: Unverified † (= 5.8a × 0.75) | O98: S-0046-02
A99: 5.9 | B99: Emergency lighting | D99: ALL | E99: Emergency and exit lighting with testing system | F99: General lighting (5.8) | G99: m² GIFA | H99: 5 | I99: 10 | J99: 18 | K99: 8 | L99: 12 | M99: Older workbook (v4.5) | O99: S-0047-01 | Q99: Not comparable: the tender only covered works to the existing central battery system
A100: 5.10a | B100: Standby power | C100: Generator, small | D100: ALL | E100: Standby power (generator or UPS), priced as a lump sum by type and size. Standby generator up to 50 kVA with enclosure, fuel tank and changeover switch | F100: Distribution to the protected circuits (5.7) | G100: band | I100: 25000 | K100: 25000 | M100: Unverified † | O100: S-0048-01
A101: 5.10b | B101: Standby power | C101: UPS, small | D101: ALL | E101: UPS 10–20 kVA with batteries, for comms or critical circuits | F101: Distribution to the protected circuits (5.7) | G101: band | I101: 17000 | K101: 17000 | M101: Older workbook (v4.5) | O101: S-0048-02
...

Sheet 3. Settings
A1: SETTINGS — every other number the app reads
A2: Each table starts at its ▶ marker and ends at the first blank row. To add a row, insert it inside the table (above the blank row). Don't rename markers or headers: the app finds tables by them.
A4: ▶ workbook_info | B4: Version stamped on every report the app produces. Update on every change
A5: Field | B5: Value | C5: Notes
A6: Version | B6: 5.27 | C6: Bump on every published change (5.3, 5.4 …) and add a line to the update log
A7: Date | B7: 46307
A8: Owner | B8: Nabil Kayali
A10: ▶ building_uses | B10: Q1.3 options. The Code is what '2. Rates' and '4. Scope rules' uses
A11: Code | B11: Building use (label on screen) | C11: Treated as residential | D11: Notes
A12: RES | B12: Residential | C12: Yes
A13: STU | B13: Student accommodation (PBSA / halls) | C13: Yes
A14: OFF | B14: Commercial offices | C14: No
A15: EDU | B15: Education | C15: No
A16: HEA | B16: Healthcare | C16: No
A17: RET | B17: Retail | C17: No
A18: IND | B18: Industrial / warehouse | C18: No
A19: HOS | B19: Hospitality / leisure | C19: No
A20: MIX | B20: Mixed use | C20: No | D20: Every item listed; nothing hidden under More items
A21: OTH | B21: Other | C21: No | D21: Every item listed; nothing hidden under More items
A22: ALL | B22: (any building use) | D22: Used on '2. Rates' and '4. Scope rules' only: the item or rate applies to every building use
A24: ▶ project_types | B24: Q1.2 options. The rate column read for each specification level. The Code is what '2. Rates' and '4. Scope rules' uses
A25: Code | B25: Project type (label on screen) | C25: Basic column | D25: Standard column | E25: High column | F25: Uses level of intervention | G25: Notes
A26: NB | B26: New Build | C26: New build & Extension Std | D26: New build & Extension Std | E26: New build & Extension High | F26: No | G26: There is no Basic new-build rate, so Basic reads Standard
A27: EX | B27: Extension | C27: New build & Extension Std | D27: New build & Extension Std | E27: New build & Extension High | F27: No | G27: Same rates as New build (owner, 27 Sept 2026)
A28: RF | B28: Refurbishment | C28: Refurb & Fit-out Basic | D28: Refurb & Fit-out Std | E28: Refurb & Fit-out High | F28: Yes
A29: FO | B29: Fit-out | C29: Refurb & Fit-out Basic | D29: Refurb & Fit-out Std | E29: Refurb & Fit-out High | F29: Yes | G29: Same rates as Refurbishment
A30: EW | B30: External works only | C30: New build & Extension Std | D30: New build & Extension Std | E30: New build & Extension Std | F30: No | G30: Reads the New build Standard rates; quantities from the external works area
A31: DM | B31: Demolition only | C31: Refurb & Fit-out Basic | D31: Refurb & Fit-out Std | E31: Refurb & Fit-out High | F31: No
A32: OM | B32: Other or mixed | C32: Per component | D32: Per component | E32: Per component | F32: No | G32: From v4.5: split GIFA by use/type, price each block on its own project type's columns, and sum
A34: ▶ spec_levels | B34: Q2.4 options. The level picks the Basic / Standard / High column on project_types
A35: Level | B35: Description
A36: Basic | B36: Minimum compliance; budget materials; functional finish. Student accommodation, back-of-house, warehouses.
A37: Standard | B37: Good commercial standard; durable mid-range materials. Typical offices, education, general academic space.
A38: High | B38: Flagship/premium; high-end finishes, bespoke joinery, enhanced M&E. Boardrooms, reception, executive, prestige.
A40: ▶ intervention_levels | B40: Level of intervention (Refurbishment and Fit-out only) → band multiplier and design duration (from v4.5)
A41: Level | B41: Name | C41: Band multiplier (m² rates) | D41: Description | E41: Design duration multiplier
A42: 1 | B42: Fabric and finishes only | C42: 0.8 | D42: Decoration, floor/wall finishes, ceilings, fixtures replaced in-place. No M&E work. No walls moved. Lowest cost and shortest programme. | E42: 0.5
A43: 2 | B43: Finishes with minor services | C43: 0.9 | D43: Finishes as above plus light-touch M&E: 2nd fix fixtures, replacement light fittings, sockets and switches. Existing wiring and pipework retained. No new systems. | E43: 0.7
A44: 3 | B44: Full systems replacement | C44: 1 | D44: Complete replacement of heating, plumbing and electrical systems throughout. Same layout, same positions, no structural changes. Building rewired and re-plumbed. Typical full flat or office refurbishment. | E44: 1
A45: 4 | B45: Reconfiguration or full redesign | C45: 1.15 | D45: Layout changes, walls moved or removed, or building stripped to structure and redesigned. Requires architect, structural engineer, building control, possibly planning. Highest cost and longest programme. | E45: 1.3
A47: ▶ location_factors | B47: Regional location factor by postcode area, or by district where an area is split (e.g. SY10). West Midlands is the default. South West added in v5.4 — its factors are an AI estimate, verify against BCIS
A48: Region | B48: Postcode areas | C48: Low | D48: High | E48: Mid (use)
A49: Inner London | B49: EC,WC,E1W,SW1,SE1 | C49: 1.2 | D49: 1.3 | E49: 1.25
A50: Outer London | B50: E,N,NW,SE,SW,W,BR,CR,DA,EN,HA,IG,KT,RM,SM,TW,UB,WD | C50: 1.1 | D50: 1.2 | E50: 1.15
A51: South East | B51: GU,RH,TN,ME,CT,BN,PO,SO,RG,SL,OX,HP,MK | C51: 1.05 | D51: 1.12 | E51: 1.08
A52: East of England | B52: CM,CB,IP,NR,LU,AL,SG,PE,SS,CO | C52: 1 | D52: 1.05 | E52: 1.03
A53: West Midlands ★ DEFAULT | B53: B,CV,WV,WS,DY,ST,WR,HR,TF,SY1,SY2,SY3,SY4,SY5,SY6,SY7,SY8,SY9,SY10,SY11,SY12,SY13 | C53: 0.92 | D53: 0.97 | E53: 0.94
A54: East Midlands | B54: LE,NG,DE,LN,NN | C54: 0.91 | D54: 0.96 | E54: 0.93
A55: Yorkshire & Humberside | B55: LS,BD,HX,HD,HG,YO,HU,S,DN,WF | C55: 0.88 | D55: 0.93 | E55: 0.9
A56: North West | B56: M,SK,WN,WA,BL,OL,PR,BB,LA,FY,CW,CH,L,CA,SY14 | C56: 0.9 | D56: 0.95 | E56: 0.92
A57: North East | B57: NE,SR,DH,TS,DL | C57: 0.87 | D57: 0.92 | E57: 0.88
A58: Wales | B58: CF,SA,NP,LD,SY,LL | C58: 0.87 | D58: 0.93 | E58: 0.89
A59: Scotland | B59: EH,G,FK,KY,DD,PH,AB,IV,KW,PA,KA,ML,TD,DG,HS,ZE | C59: 0.93 | D59: 1 | E59: 0.965
A60: Northern Ireland | B60: BT | C60: 0.82 | D60: 0.88 | E60: 0.85
A61: South West | B61: BS,BA,BH,DT,EX,GL,PL,SN,SP,TA,TQ,TR | C61: 0.94 | D61: 1 | E61: 0.97
A62: ▶ benchmarks | B62: Expected works £/m² by project type and building use (from v4.5, now in codes). Outside the range = review flag
A63: Project type | B63: Building use | C63: Expected low £/m² | D63: Expected high £/m²
A64: RF | B64: OFF | C64: 600 | D64: 1200
A65: RF | B65: RES | C65: 700 | D65: 1500
A66: RF | B66: EDU | C66: 800 | D66: 1800
A67: RF | B67: HOS | C67: 1000 | D67: 2200
A68: RF | B68: HEA | C68: 1500 | D68: 3000
A69: RF | B69: RET | C69: 500 | D69: 1300
A70: RF | B70: IND | C70: 400 | D70: 1100
A71: FO | B71: OFF | C71: 500 | D71: 1200
A72: FO | B72: HOS | C72: 900 | D72: 2000
A73: FO | B73: RET | C73: 500 | D73: 1400
A74: NB | B74: OFF | C74: 1800 | D74: 2800
A75: NB | B75: RES | C75: 1600 | D75: 2600
... A79: NB | B79: IND | C79: 650 | D79: 1800
A81: ▶ inputs | B81: Names used in 'Quantity rule' and 'Other conditions'. Default = what the app uses if the answer is blank
A82: Name | B82: Comes from | C82: Default (quantity rule) | D82: Notes
A83: GIFA | B83: Q1.5 Approximate size (GIFA) | C83: IF(PT=EW, 0, ENTER) | D83: On Refurbishment and Fit-out this is the area of works
A84: STOREYS | B84: Number of storeys (existing question) | C84: 1 | D84: Default used only if the answer is blank
A85: FOOTPRINT | B85: Worked out | C85: GIFA / STOREYS | D85: Ground floor area
A86: UPPER | B86: Worked out | C86: GIFA - FOOTPRINT | D86: Upper floor area
A87: EXT_AREA | B87: External works area, asked on the Group 8 header | C87: IF(PT=EW, ENTER, FOOTPRINT * r.site_ratio) | D87: Must be entered on External works only
A88: DEMOLISHED | B88: Demolition item, 'I know this' | C88: IF(PT=NB EX, ENTER, GIFA) | D88: Area of building to demolish
A89: PT | B89: Q1.2 Project type | D89: A code from project_types
A90: USE | B90: Q1.3 Building use | D90: A code from building_uses
A91: AGE | B91: Q1.4 Building age | D91: End year of the chosen band (e.g. 1980–1999 → 1999); post-2000 → current year
A92: LEVEL | B92: Level of intervention | D92: 1–4; Refurbishment and Fit-out only
A93: OFFICES | B93: Q1.3a share of the floor that is offices, welfare and staff areas (%) × GIFA | C93: GIFA * r.office_share | D93: Industrial / warehouse, New build and Extension (where Q1.3a is asked). Fit-out items are measured on it
A94: PRODUCTION | B94: Q1.3b: Factory / production → GIFA − OFFICES; Storage / warehouse → 0 | C94: 0 | D94: Production floor that also gets the building services
A96: ▶ quantity_ratios | B96: Named ratios used as r.name in quantity rules. The row for the building use is used, else ALL
A97: Key | B97: Building use | C97: Value | D97: Used for | E97: Source
A98: m2_per_person | B98: ALL | C98: 10 | D98: Toilets: people = GIFA ÷ this | E98: AI estimate – verify
A99: m2_per_person | B99: EDU | C99: 5 | D99: Toilets (education) | E99: AI estimate – verify
A100: m2_per_person | B100: HEA | C100: 15 | D100: Toilets (healthcare) | E100: AI estimate – verify
A101: m2_per_person | B101: RET | C101: 7 | D101: Toilets (retail) | E101: AI estimate – verify
A102: m2_per_person | B102: IND | C102: 40 | D102: Toilets (industrial) | E102: AI estimate – verify
A103: m2_per_person | B103: HOS | C103: 5 | D103: Toilets (hospitality) | E103: AI estimate – verify
A104: persons_per_wc | B104: ALL | C104: 20 | D104: Toilets: WCs = people ÷ this (simplified BS 6465-1 / Workplace Regs) | E104: AI estimate – verify
A105: accessible_wc_per_floor | B105: ALL | C105: 1 | D105: Toilets: accessible option | E105: AI estimate – verify
A106: m2_per_dwelling | B106: ALL | C106: 66 | D106: Bathrooms, kitchens, EV charging (residential) | E106: Lakeside S&F tender, Sep 2026: 50 dwellings on 3,306 m², one bathroom each
A107: bathrooms_per_dwelling | B107: ALL | C107: 1 | D107: Bathrooms (residential) | E107: Lakeside S&F tender, Sep 2026: 50 dwellings on 3,306 m², one bathroom each
A108: m2_per_bed | B108: ALL | C108: 25 | D108: Student beds or hospital beds, by building use | E108: AI estimate – verify
A109: m2_per_bed | B109: STU | C109: 25 | D109: Bathrooms and kitchens (student en-suite beds) | E109: AI estimate – verify
... A127: office_share | B127: ALL | C127: 0.1 | D127: Industrial / warehouse (New build, Extension): share of the floor priced as offices, welfare and staff areas, the suggestion shown at Q1.3a | E127: AI estimate – verify
A129: ▶ factors | B129: Multipliers applied to rates
...

Sheet 4. Scope rules
A1: SCOPE RULES — how the app uses each item (rarely needs changing)
A2: Two tables, each starting at its ▶ marker and ending at the first blank row — to add a row, insert it inside the table. ▶ items: one row per Scope ID. ▶ options: one row per Rate key on '2. Rates'. What each column means is on '1. Instructions'.
A4: ▶ items
A5: Scope ID | B5: Code | C5: Item (for reading) | D5: Group | E5: Section | F5: Options: pick | G5: Quantity rule | H5: Shown on (project type codes) | I5: Pre-ticked on (project type codes) | J5: Relevant building uses (codes) | K5: Other conditions | L5: BCIS element 1 | M5: Share 1 | N5: BCIS element 2 | O5: Share 2 | P5: Replaces old codes
A6: S-0001 | B6: 0.1 | C6: Asbestos removal | D6: 0 Facilitating works | E6: — | F6: One | G6: IF(PT=NB EX, DEMOLISHED, GIFA) | H6: NB EX RF FO EW DM OM | I6: — | J6: ALL | K6: AGE<2000 & PT=RF FO DM → tick | L6: 0.1 | M6: 1 | P6: 0.1
A7: S-0002 | B7: 0.2 | C7: Demolition of existing building | D7: 0 Facilitating works | E7: — | F7: One | G7: DEMOLISHED | H7: NB EX EW DM OM | I7: DM | J7: ALL | L7: 0.2 | M7: 1 | P7: 0.2
A8: S-0003 | B8: 0.3 | C8: Strip-out | D8: 0 Facilitating works | E8: — | F8: One | G8: GIFA | H8: RF FO OM | I8: — | J8: ALL | L8: 0.2 | M8: 1 | P8: 0.5
A9: S-0004 | B9: 0.4 | C9: Contaminated land | D9: 0 Facilitating works | E9: — | F9: One | G9: IF(PT=EW, EXT_AREA, GIFA) | H9: NB EX EW OM | I9: — | J9: ALL | L9: 0.1 | M9: 1 | P9: 0.3
A10: S-0005 | B10: 0.5 | C10: Ground improvement | D10: 0 Facilitating works | E10: — | F10: One | G10: FOOTPRINT | H10: NB EX EW OM | I10: — | J10: ALL | L10: 0.4 | M10: 1 | P10: 0.4
A11: S-0006 | B11: 0.6 | C11: Tree removal | D11: 0 Facilitating works | E11: — | F11: One | G11: ENTER | H11: NB EX EW DM OM | I11: — | J11: ALL | L11: 8.1 | M11: 1 | P11: 0.6
A12: S-0007 | B12: 0.7 | C12: Service diversions | D12: 0 Facilitating works | E12: — | F12: One | G12: IF(PT=EW, EXT_AREA, FOOTPRINT) | H12: NB EX EW DM OM | I12: — | J12: ALL | L12: 0.5 | M12: 1 | P12: 0.7
A13: S-0008 | B13: 1.1 | C13: Foundations | D13: 1 Substructure | E13: — | F13: One | G13: FOOTPRINT | H13: NB EX OM | I13: NB EX | J13: ALL | L13: 1.1 | M13: 1 | P13: 1.1, 1.2
A14: S-0009 | B14: 1.2 | C14: Ground floor slab | D14: 1 Substructure | E14: — | F14: One | G14: FOOTPRINT | H14: NB EX OM | I14: NB EX | J14: ALL | L14: 1.1 | M14: 1 | P14: 1.3
A15: S-0010 | B15: 1.3 | C15: Basement | D15: 1 Substructure | E15: — | F15: One | G15: FOOTPRINT | H15: NB EX OM | I15: — | J15: ALL | L15: 1.1 | M15: 1 | P15: 1.4, 2.9, 2.10
A16: S-0011 | B16: 2.1 | C16: Frame | D16: 2 Superstructure and envelope | E16: Structure | F16: One | G16: GIFA | H16: NB EX OM | I16: NB EX | J16: ALL | L16: 2.1 | M16: 1 | P16: 2.1
A17: S-0012 | B17: 2.2 | C17: Upper floors | D17: 2 Superstructure and envelope | E17: Structure | F17: One | G17: UPPER | H17: NB EX OM | I17: NB EX | J17: ALL | K17: STOREYS<2 → untick | L17: 2.2 | M17: 1 | P17: 2.2
A18: S-0013 | B18: 2.3 | C18: Stairs and ramps | D18: 2 Superstructure and envelope | E18: Structure | F18: One | G18: GIFA | H18: NB EX RF OM | I18: NB EX | J18: ALL | K18: STOREYS<2 → untick | L18: 2.4 | M18: 1 | P18: 2.4
A19: S-0014 | B19: 2.4 | C19: Mezzanine floor | D19: 2 Superstructure and envelope | E19: Structure | F19: One | G19: ENTER | H19: NB EX FO OM | I19: — | J19: OFF EDU RET IND | L19: 2.2 | M19: 1 | P19: 2.12, 6.2
A20: S-0015 | B20: 2.5 | C20: Roof | D20: 2 Superstructure and envelope | E20: Roof and walls | F20: One | G20: FOOTPRINT | H20: NB EX RF OM | I20: NB EX | J20: ALL | L20: 2.3 | M20: 1 | P20: 2.3
A21: S-0016 | B21: 2.6 | C21: External walls | D21: 2 Superstructure and envelope | E21: Roof and walls | F21: One | G21: GIFA | H21: NB EX RF OM | I21: NB EX | J21: ALL | L21: 2.5 | M21: 1 | P21: 2.5
A22: S-0017 | B22: 2.7 | C22: Windows and external doors | D22: 2 Superstructure and envelope | E22: Roof and walls | F22: One | G22: GIFA | H22: NB EX RF OM | I22: NB EX | J22: ALL | L22: 2.6 | M22: 1 | P22: 2.6
A23: S-0018 | B23: 2.8 | C23: Internal walls | D23: 2 Superstructure and envelope | E23: Internal walls and doors | F23: One | G23: IF(USE=IND, IF(PT=NB EX, OFFICES, GIFA), GIFA) | H23: NB EX RF FO OM | I23: NB EX | J23: ALL | L23: 2.7 | M23: 1 | P23: 2.7
A24: S-0019 | B24: 2.9 | C24: Internal doors | D24: 2 Superstructure and envelope | E24: Internal walls and doors | F24: One | G24: IF(USE=IND, IF(PT=NB EX, OFFICES, GIFA), GIFA) | H24: NB EX RF FO OM | I24: NB EX | J24: ALL | L24: 2.8 | M24: 1 | P24: 2.8
A25: S-0020 | B25: 2.10 | C25: Fire stopping | D25: 2 Superstructure and envelope | E25: Internal walls and doors | F25: One | G25: GIFA | H25: EX RF FO OM | I25: — | J25: ALL | L25: 2.7 | M25: 1 | P25: 2.11
A26: S-0021 | B26: 3.1 | C26: Wall finishes | D26: 3 Internal finishes | E26: — | F26: One | G26: IF(USE=IND, IF(PT=NB EX, OFFICES, GIFA), GIFA) | H26: NB EX RF FO OM | I26: NB EX | J26: ALL | L26: 3.1 | M26: 1 | P26: 2.9, 3.1
A27: S-0022 | B27: 3.2 | C27: Floor finishes | D27: 3 Internal finishes | E27: — | F27: One | G27: IF(USE=IND, IF(PT=NB EX, OFFICES, GIFA), GIFA) | H27: NB EX RF FO OM | I27: NB EX | J27: ALL | L27: 3.2 | M27: 1 | P27: 2.9, 3.2
A28: S-0023 | B28: 3.3 | C28: Ceiling finishes | D28: 3 Internal finishes | E28: — | F28: One | G28: IF(USE=IND, IF(PT=NB EX, OFFICES, GIFA), GIFA) | H28: NB EX RF FO OM | I28: NB EX | J28: ALL | L28: 3.3 | M28: 1 | P28: 3.3
A29: S-0024 | B29: 4.1 | C29: Toilets | D29: 4 Toilets, kitchens and fittings | E29: Toilets, bathrooms and kitchens | F29: Several | G29: ROUND(GIFA / r.m2_per_person / r.persons_per_wc, 0) | H29: NB EX RF FO OM | I29: NB EX | J29: OFF EDU HEA RET IND HOS | L29: 5.1 | M29: 0.8 | N29: 2.7 | O29: 0.2 | P29: 4.2-COM, 4.2-HC, 4.2-HP, 4.31-NR, 4.32-HOH, 5.30-NR
A30: S-0025 | B30: 4.2 | C30: Bathrooms and en-suites | D30: 4 Toilets, kitchens and fittings | E30: Toilets, bathrooms and kitchens | F30: One | G30: ROUND(IF(USE=STU, GIFA / r.m2_per_bed, IF(USE=HOS, GIFA / r.m2_per_key, GIFA / r.m2_per_dwelling * r.bathrooms_per_dwelling)), 0) | H30: NB EX RF FO OM | I30: NB EX | J30: RES STU HOS | L30: 5.1 | M30: 1 | P30: 4.2-HG, 4.2-RES, 6.3
A31: S-0026 | B31: 4.3 | C31: Showers | D31: 4 Toilets, kitchens and fittings | E31: Toilets, bathrooms and kitchens | F31: One | G31: ENTER | H31: NB EX RF FO OM | I31: — | J31: OFF EDU HEA RET IND HOS | L31: 5.1 | M31: 1 | P31: 4.41
A32: S-0027 | B32: 4.4 | C32: Kitchens | D32: 4 Toilets, kitchens and fittings | E32: Toilets, bathrooms and kitchens | F32: One | G32: ROUND(IF(USE=RES, GIFA / r.m2_per_dwelling, IF(USE=STU, GIFA / r.m2_per_bed / r.beds_per_kitchen, STOREYS * r.tea_points_per_floor)), 0) | H32: NB EX RF FO OM | I32: NB EX | J32: ALL | L32: 4.2 | M32: 1 | P32: 4.3, 4.3-NR, 4.3-RES, 4.42
A33: S-0028 | B33: 4.5 | C33: Fixed joinery | D33: 4 Toilets, kitchens and fittings | E33: Fittings and furniture | F33: One | G33: GIFA | H33: NB EX RF FO OM | I33: — | J33: ALL | L33: 4.1 | M33: 1 | P33: 4.1
A34: S-0029 | B34: 4.6 | C34: Signage | D34: 4 Toilets, kitchens and fittings | E34: Fittings and furniture | F34: One | G34: IF(USE=IND, IF(PT=NB EX, OFFICES, GIFA), GIFA) | H34: NB EX RF FO OM | I34: NB EX | J34: ALL | L34: 4.4 | M34: 1 | P34: 4.5
A35: S-0030 | B35: 4.7 | C35: AV equipment | D35: 4 Toilets, kitchens and fittings | E35: Fittings and furniture | F35: One | G35: GIFA | H35: NB EX RF FO OM | I35: — | J35: OFF EDU HEA HOS | L35: 5.12 | M35: 1 | P35: 4.22
A36: S-0031 | B36: 4.8 | C36: Loose furniture | D36: 4 Toilets, kitchens and fittings | E36: Fittings and furniture | F36: One | G36: GIFA | H36: NB EX RF FO OM | I36: — | J36: ALL | L36: 4.1 | M36: 1 | P36: 4.6, 4.7, 4.8, 4.9, 4.33
A37: S-0032 | B37: 4.9 | C37: Catering kitchen | D37: 4 Toilets, kitchens and fittings | E37: Specialist equipment | F37: One | G37: GIFA * r.pct_catering | H37: NB EX RF FO OM | I37: — | J37: STU OFF EDU HEA RET IND HOS | L37: 5.2 | M37: 1 | P37: 4.10, 4.11, 4.12, 4.16, 4.34
A38: S-0033 | B38: 4.10 | C38: Laboratory | D38: 4 Toilets, kitchens and fittings | E38: Specialist equipment | F38: One | G38: GIFA * r.pct_lab | H38: NB EX RF FO OM | I38: — | J38: EDU HEA IND | L38: 4.3 | M38: 1 | P38: 4.20, 4.21, 4.36
A39: S-0034 | B39: 4.11 | C39: Clinical | D39: 4 Toilets, kitchens and fittings | E39: Specialist equipment | F39: One | G39: GIFA * r.pct_clinical | H39: NB EX RF FO OM | I39: — | J39: HEA | L39: 4.3 | M39: 1 | P39: 4.19, 4.37
A40: S-0035 | B40: 4.12 | C40: Retail | D40: 4 Toilets, kitchens and fittings | E40: Specialist equipment | F40: One | G40: IF(USE=RET, GIFA, ENTER) | H40: NB EX RF FO OM | I40: — | J40: RET | L40: 4.3 | M40: 1 | P40: 4.24, 4.25, 4.27, 4.35
A41: S-0036 | B41: 4.13 | C41: Warehouse | D41: 4 Toilets, kitchens and fittings | E41: Specialist equipment | F41: One | G41: IF(USE=IND, GIFA, ENTER) | H41: NB EX RF FO OM | I41: — | J41: IND | L41: 4.3 | M41: 1 | P41: 4.13, 4.14, 4.15, 4.38
... A43: S-0038 | B43: 4.15 | C43: Cleanroom | D43: 4 Toilets, kitchens and fittings | E43: Specialist equipment | F43: One | G43: ENTER | H43: NB EX RF FO OM | I43: — | J43: EDU HEA IND | L43: 5.13 | M43: 1 | P43: 4.44, 6.4
A44: S-0039 | B44: 5.1 | C44: Heating and hot water | D44: 5 Services | E44: Mechanical | F44: One | G44: IF(USE=IND, IF(PT=NB EX, OFFICES + PRODUCTION, GIFA), GIFA) | H44: NB EX RF FO OM | I44: NB EX | J44: ALL | L44: 5.5 | M44: 0.4 | N44: 5.6 | O44: 0.6 | P44: 5.2, 5.2L, 5.5
A45: S-0040 | B45: 5.2 | C45: Water and drainage | D45: 5 Services | E45: Mechanical | F45: One | G45: IF(USE=IND, IF(PT=NB EX, OFFICES + PRODUCTION, GIFA), GIFA) | H45: NB EX RF FO OM | I45: NB EX | J45: ALL | L45: 5.3 | M45: 0.5 | N45: 5.4 | O45: 0.5 | P45: 5.1
A46: S-0041 | B46: 5.3 | C46: Ventilation | D46: 5 Services | E46: Mechanical | F46: One | G46: IF(USE=IND, IF(PT=NB EX, OFFICES + PRODUCTION, GIFA), GIFA) | H46: NB EX RF FO OM | I46: NB EX | J46: ALL | L46: 5.7 | M46: 1 | P46: 5.3
A47: S-0042 | B47: 5.4 | C47: Cooling | D47: 5 Services | E47: Mechanical | F47: One | G47: GIFA | H47: NB EX RF FO OM | I47: — | J47: ALL | L47: 5.6 | M47: 1 | P47: 5.4
A48: S-0043 | B48: 5.5 | C48: Controls and BMS | D48: 5 Services | E48: Mechanical | F48: One | G48: GIFA | H48: NB EX RF FO OM | I48: — | J48: ALL | L48: 5.12 | M48: 1 | P48: 5.14
A49: S-0044 | B49: 5.6 | C49: Electricity supply upgrade | D49: 5 Services | E49: Electrical | F49: One | G49: 1 | H49: NB EX RF FO EW OM | I49: — | J49: ALL | L49: 8.7 | M49: 1 | P49: 5.13
A50: S-0045 | B50: 5.7 | C50: Power | D50: 5 Services | E50: Electrical | F50: One | G50: IF(USE=IND, IF(PT=NB EX, OFFICES + PRODUCTION, GIFA), GIFA) | H50: NB EX RF FO OM | I50: NB EX | J50: ALL | L50: 5.8 | M50: 1 | P50: 5.7, 5.7a, 5.8, 5.8a, 5.8b
A51: S-0046 | B51: 5.8 | C51: Lighting | D51: 5 Services | E51: Electrical | F51: One | G51: GIFA | H51: NB EX RF FO OM | I51: NB EX | J51: ALL | L51: 5.8 | M51: 1 | P51: 5.8c, 5.10
A52: S-0047 | B52: 5.9 | C52: Emergency lighting | D52: 5 Services | E52: Electrical | F52: One | G52: GIFA | H52: NB EX RF FO OM | I52: NB EX | J52: ALL | L52: 5.8 | M52: 1 | P52: 5.9b
A53: S-0048 | B53: 5.10 | C53: Standby power | D53: 5 Services | E53: Electrical | F53: Several | G53: 1 | H53: NB EX RF FO OM | I53: — | J53: OFF EDU HEA RET IND HOS | K53: PT=NB & USE=HEA → tick | L53: 5.8 | M53: 1 | P53: 5.25, 5.26
A54: S-0049 | B54: 5.11 | C54: Fire alarm | D54: 5 Services | E54: Fire safety | F54: One | G54: GIFA | H54: NB EX RF FO OM | I54: NB EX | J54: ALL | L54: 5.12 | M54: 1 | P54: 5.9a
A55: S-0050 | B55: 5.12 | C55: Sprinklers | D55: 5 Services | E55: Fire safety | F55: One | G55: GIFA | H55: NB EX RF FO OM | I55: — | J55: ALL | K55: PT=NB & USE=RES STU & STOREYS>=4 → tick | L55: 5.11 | M55: 1 | P55: 5.6
A56: S-0051 | B56: 5.13 | C56: Smoke ventilation | D56: 5 Services | E56: Fire safety | F56: One | G56: STOREYS | H56: NB EX RF OM | I56: — | J56: RES STU HEA HOS | K56: PT=NB & STOREYS>=2 → tick | L56: 5.7 | M56: 1 | P56: 5.31
A57: S-0052 | B57: 5.14 | C57: Data and IT | D57: 5 Services | E57: Data and security | F57: One | G57: IF(USE=IND, IF(PT=NB EX, OFFICES, GIFA), GIFA) | H57: NB EX RF FO OM | I57: NB | J57: ALL | L57: 5.12 | M57: 1 | P57: 5.16
A58: S-0053 | B58: 5.15 | C58: Security | D58: 5 Services | E58: Data and security | F58: One | G58: GIFA | H58: NB EX RF FO OM | I58: — | J58: ALL | L58: 5.12 | M58: 1 | P58: 5.18
A59: S-0054 | B59: 5.16 | C59: Lifts | D59: 5 Services | E59: Lifts | F59: Several | G59: IF(STOREYS>=2, 1, 0) | H59: NB EX RF FO OM | I59: NB | J59: ALL | K59: STOREYS<2 → untick | L59: 5.10 | M59: 1 | P59: 5.19
A60: S-0055 | B60: 5.17 | C60: Solar PV | D60: 5 Services | E60: Renewables and EV | F60: One | G60: FOOTPRINT * r.kwp_per_m2_roof | H60: NB EX RF FO EW OM | I60: — | J60: ALL | L60: 5.8 | M60: 1 | P60: 5.11
A61: S-0056 | B61: 5.18 | C61: Battery storage | D61: 5 Services | E61: Renewables and EV | F61: One | G61: ENTER | H61: NB EX RF FO EW OM | I61: — | J61: ALL | L61: 5.8 | M61: 1 | P61: 5.12
A62: S-0057 | B62: 5.19 | C62: EV charging | D62: 5 Services | E62: Renewables and EV | F62: One | G62: IF(USE=RES, ROUND(GIFA / r.m2_per_dwelling, 0), MAX(1, ROUND(Q(S-0074) / 5, 0))) | H62: NB EX RF FO EW OM | I62: — | J62: ALL | L62: 5.8 | M62: 1 | P62: 5.15
A63: S-0058 | B63: 5.20 | C63: Compressed air | D63: 5 Services | E63: Specialist services | F63: One | G63: 1 | H63: NB EX RF FO OM | I63: — | J63: EDU IND | L63: 5.13 | M63: 1 | P63: 5.21
A64: S-0059 | B64: 5.21 | C64: Fume extraction | D64: 5 Services | E64: Specialist services | F64: One | G64: 1 | H64: NB EX RF FO OM | I64: — | J64: EDU HEA IND | L64: 5.7 | M64: 1 | P64: 5.24
A65: S-0060 | B65: 5.22 | C65: Process drainage | D65: 5 Services | E65: Specialist services | F65: One | G65: ENTER | H65: NB EX RF FO OM | I65: — | J65: IND | L65: 5.3 | M65: 1 | P65: 5.23
A66: S-0061 | B66: 5.23 | C66: Medical gases | D66: 5 Services | E66: Specialist services | F66: One | G66: ROUND(GIFA / r.m2_per_bed * r.gas_outlets_per_bed, 0) | H66: NB EX RF FO OM | I66: — | J66: HEA | L66: 5.13 | M66: 1 | P66: 4.18, 5.33
A67: S-0062 | B67: 5.24 | C67: Nurse call | D67: 5 Services | E67: Specialist services | F67: One | G67: ROUND(GIFA / r.m2_per_bed, 0) | H67: NB EX RF FO OM | I67: — | J67: RES HEA | L67: 5.12 | M67: 1 | P67: 5.27
A68: S-0063 | B68: 5.25 | C68: Server room cooling | D68: 5 Services | E68: Specialist services | F68: One | G68: 1 | H68: NB EX RF FO OM | I68: — | J68: OFF EDU HEA RET IND HOS | L68: 5.6 | M68: 1 | P68: 5.29
A69: S-0083 | B69: 5.26 | C69: Builder's work in connection | D69: 5 Services | E69: Automatic (not shown) | F69: One | G69: IF(USE=IND, IF(PT=NB EX, OFFICES + PRODUCTION, GIFA), GIFA) | H69: — | I69: — | J69: ALL | K69: AUTO: add when any Group 5 item is selected; never shown | L69: 5.14 | M69: 1 | P69: 5.20
A70: S-0064 | B70: 7.1 | C70: Repairs | D70: 7 Work to existing buildings | E70: — | F70: One | G70: GIFA | H70: EX RF OM | I70: — | J70: ALL | L70: 7.6 | M70: 1 | P70: 7.1, 7.2
A71: S-0065 | B71: 7.2 | C71: Alterations | D71: 7 Work to existing buildings | E71: — | F71: One | G71: GIFA | H71: EX RF OM | I71: — | J71: ALL | L71: 7.1 | M71: 1 | P71: 0.2, 7.6
A72: S-0066 | B72: 7.3 | C72: Damp treatment | D72: 7 Work to existing buildings | E72: — | F72: One | G72: FOOTPRINT | H72: EX RF OM | I72: — | J72: ALL | L72: 7.3 | M72: 1 | P72: 7.3
A73: S-0067 | B73: 8.1 | C73: Site clearance and preparation | D73: 8 External works | E73: Site, access and drainage | F73: One | G73: EXT_AREA | H73: NB EX RF EW DM OM | I73: NB EW | J73: ALL | L73: 8.1 | M73: 1 | P73: 8.1
A74: S-0068 | B74: 8.2 | C74: Surface water drainage | D74: 8 External works | E74: Site, access and drainage | F74: One | G74: EXT_AREA | H74: NB EX RF EW OM | I74: NB EX EW | J74: ALL | L74: 8.6 | M74: 1 | P74: 8.4
A75: S-0069 | B75: 8.3 | C75: Foul drainage | D75: 8 External works | E75: Site, access and drainage | F75: One | G75: IF(USE=IND, IF(PT=NB EX, OFFICES + PRODUCTION, GIFA), GIFA) | H75: NB EX RF OM | I75: NB EX | J75: ALL | L75: 8.6 | M75: 1 | P75: 8.5
A76: S-0070 | B76: 8.4 | C76: External utilities | D76: 8 External works | E76: Site, access and drainage | F76: One | G76: GIFA | H76: NB EX RF OM | I76: NB | J76: ALL | L76: 8.7 | M76: 1 | P76: 8.6
A77: S-0071 | B77: 8.5 | C77: Highways and site access | D77: 8 External works | E77: Site, access and drainage | F77: One | G77: 1 | H77: NB EX EW OM | I77: — | J77: ALL | L77: 8.2 | M77: 1 | P77: 8.14
A78: S-0072 | B78: 8.6 | C78: Retaining walls and earthworks | D78: 8 External works | E78: Site, access and drainage | F78: One | G78: 1 | H78: NB EX EW OM | I78: — | J78: ALL | L78: 8.4 | M78: 1 | P78: 8.15
A79: S-0073 | B79: 8.7 | C79: Roads, paths and paving | D79: 8 External works | E79: Paving and landscaping | F79: One | G79: MAX(0, EXT_AREA * r.pct_hard - Q(S-0074) * r.m2_per_car_space - Q(S-0075)) | H79: NB EX RF EW OM | I79: NB EW | J79: ALL | L79: 8.2 | M79: 1 | P79: 8.2
A80: S-0074 | B80: 8.8 | C80: Car parking | D80: 8 External works | E80: Paving and landscaping | F80: One | G80: ENTER | H80: NB EX RF EW OM | I80: — | J80: ALL | L80: 8.2 | M80: 1 | P80: 8.3
A81: S-0075 | B81: 8.9 | C81: HGV yard | D81: 8 External works | E81: Paving and landscaping | F81: One | G81: ENTER | H81: NB EX EW OM | I81: — | J81: IND | L81: 8.2 | M81: 1 | P81: 8.10
... A87: S-0081 | B87: 8.15 | C87: Cycle storage | D87: 8 External works | E87: Boundaries and fixtures | F87: One | G87: ENTER | H87: NB EX RF EW OM | I87: — | J87: ALL | L87: 8.5 | M87: 1 | P87: 8.11
A89: ▶ options
A90: Rate key | B90: Scope ID | C90: Code | D90: Option (as the app shows it) | E90: Default option | F90: Pricing type | G90: Quantity rule (if different from the item) | H90: Available from intervention level | I90: Pre-ticked at intervention levels | J90: Apply band + location factor | K90: When selected (dependencies) | L90: Source detail
A91: S-0001-01 | B91: S-0001 | C91: 0.1 | D91: Standard | E91: Yes | F91: gifa_rate | H91: 1 | J91: Yes | L91: v4.5 0.1 for Refurbishment and Extension. New Build and External works columns were 0 in v4.5; set to the Refurbishment Std/High values (AI adjustment) so asbestos in a building being demolished is priced
A92: S-0002-01 | B92: S-0002 | C92: 0.2 | D92: Standard | E92: Yes | F92: gifa_rate | H92: 4 | J92: Yes | K92: SUGGEST: S-0001 Asbestos removal · ASSUME (NB): demolished area = new GIFA unless entered | L92: v4.5 0.2 Refurbishment rates applied to every column: demolition cost doesn't depend on what replaces the building. v4.5 0.2 also covered structural alterations, now in Alterations
A93: S-0003-01 | B93: S-0003 | C93: 0.3 | D93: Standard | E93: Yes | F93: gifa_rate | H93: 1 | I93: 1, 2, 3, 4 | J93: Yes | K93: SUGGEST: S-0020 Fire stopping · SUGGEST: S-0047 Emergency lighting · SUGGEST: S-0001 Asbestos removal | L93: v4.5 0.5. No source recorded in v4.5 · Sep 2026: rates from the Lakeside S&F tender returns (see 'Tender check' on '2. Rates')
A94: S-0004-01 | B94: S-0004 | C94: 0.4 | D94: Standard | E94: Yes | F94: gifa_rate | H94: 4 | J94: Yes | L94: v4.5 0.3. No source recorded in v4.5
A95: S-0005-01 | B95: S-0005 | C95: 0.5 | D95: Standard | E95: Yes | F95: gifa_rate | H95: 4 | J95: Yes | L95: v4.5 0.4. No source recorded in v4.5 · Note: Piling is in Foundations
A96: S-0006-01 | B96: S-0006 | C96: 0.6 | D96: Standard | E96: Yes | F96: per_nr | H96: 1 | J96: No | L96: AI estimate: felling and stump removal per tree. Spec level stands in for tree size. Not in v4.5
A97: S-0007-01 | B97: S-0007 | C97: 0.7 | D97: Standard | E97: Yes | F97: footprint_rate | H97: 1 | J97: Yes | L97: Owner's rate, 27 Sept 2026: £100 per m² of building footprint (replaces the Small / Medium / Large bands)
A98: S-0008-01 | B98: S-0008 | C98: 1.1a | D98: Type: Standard | E98: Yes | F98: footprint_rate | H98: 4 | J98: Yes | L98: v4.5 1.1. No source recorded in v4.5
A99: S-0008-04 | B99: S-0008 | C99: 1.1d | D99: Type: Standard | F99: footprint_rate | H99: 4 | J99: Yes | L99: Industrial rate (owner, 12 Oct 2026). Pads £3.02 + casings + perimeter ground beam £3.49 at 29,640 m² (×2.7 for a 4,000 m² unit) + dock foundations £1.13 per m² GIFA × 1.30, rounded up for the smaller spans of a typical unit. Spon's A&B 2024 Retail Distribution Unit cost model (PDF p.221-223: single-storey steel portal-frame warehouse, 12 m to haunch, 29,640 m2, with a 1,680 m2 two-storey office; West Midlands, TPI 144). Converted to this workbook's basis as the Spon's check column does for cost models: x 167/144 TPI x 1.11 inflation / (0.86 x 1.15) location = x 1.30.
A100: S-0008-02 | B100: S-0008 | C100: 1.1b | D100: Type: Piled | F100: footprint_rate | H100: 4 | J100: Yes | L100: v4.5 1.2. No source recorded in v4.5
A101: S-0008-03 | B101: S-0008 | C101: 1.1c | D101: Type: Not sure | F101: footprint_rate | H101: 4 | J101: Yes | K101: RISK: piling may be required | L101: Prices as Standard foundations and raises a piling risk (Dependencies)
A102: S-0008-05 | B102: S-0008 | C102: 1.1e | D102: Type: Not sure | F102: footprint_rate | H102: 4 | J102: Yes | L102: Industrial rate (owner, 12 Oct 2026). Prices as 1.1d, like 1.1c prices as 1.1a. Spon's A&B 2024 Retail Distribution Unit cost model (PDF p.221-223: single-storey steel portal-frame warehouse, 12 m to haunch, 29,640 m2, with a 1,680 m2 two-storey office; West Midlands, TPI 144). Converted to this workbook's basis as the Spon's check column does for cost models: x 167/144 TPI x 1.11 inflation / (0.86 x 1.15) location = x 1.30.
A103: S-0009-01 | B103: S-0009 | C103: 1.2a | D103: Standard | E103: Yes | F103: footprint_rate | H103: 4 | J103: Yes | L103: v4.5 1.3. No source recorded in v4.5
A104: S-0009-02 | B104: S-0009 | C104: 1.2b | D104: Standard | F104: footprint_rate | H104: 4 | J104: Yes | L104: Industrial rate (owner, 12 Oct 2026). Ground slab £61, imported fill £8.75, type 1 £8.10, survey and inspection £0.60 per m² GIFA × 1.30 = £102. Spon's A&B 2024 Retail Distribution Unit cost model (PDF p.221-223: single-storey steel portal-frame warehouse, 12 m to haunch, 29,640 m2, with a 1,680 m2 two-storey office; West Midlands, TPI 144). Converted to this workbook's basis as the Spon's check column does for cost models: x 167/144 TPI x 1.11 inflation / (0.86 x 1.15) location = x 1.30.
A105: S-0010-01 | B105: S-0010 | C105: 1.3 | D105: Standard | E105: Yes | F105: footprint_rate | H105: 4 | J105: Yes | K105: ASSUME: excavation, retaining walls and tanking included · RISK: groundwater and dewatering | L105: v4.5 1.4 (900 / 1,600) plus an AI allowance of £100 / £150 per m² for tanking, which moved here from retired 2.9
A106: S-0011-01 | B106: S-0011 | C106: 2.1a | D106: Standard | E106: Yes | F106: gifa_rate | H106: 4 | J106: Yes | L106: v4.5 2.1. No source recorded in v4.5
A107: S-0011-02 | B107: S-0011 | C107: 2.1b | D107: Standard | F107: gifa_rate | H107: 4 | J107: Yes | L107: Industrial rate (owner, 12 Oct 2026). Portal frame 12 m to haunch with cold-rolled sections £69 + decoration £2 = £70.60 per m² GIFA × 1.30 = £92. Spon's A&B 2024 Retail Distribution Unit cost model (PDF p.221-223: single-storey steel portal-frame warehouse, 12 m to haunch, 29,640 m2, with a 1,680 m2 two-storey office; West Midlands, TPI 144). Converted to this workbook's basis as the Spon's check column does for cost models: x 167/144 TPI x 1.11 inflation / (0.86 x 1.15) location = x 1.30.
A108: S-0012-01 | B108: S-0012 | C108: 2.2 | D108: Standard | E108: Yes | F108: upperfloors_rate | H108: 4 | J108: Yes | L108: v4.5 2.2. No source recorded in v4.5
...
