Workbook

Sheet Instructions
B1: NRM1 ORDER OF COST ESTIMATE TOOL | Estates AI | Version 2.0 | May 2026
B2: RIBA Stage 0–1 Indicative Estimates | Prepared by Nabil Kayali | Base date Q2 2026 | West Midlands default
B4: WHAT'S NEW IN VERSION 2.0
B5: ▸ Mid-point rate architecture — each element now has a single benchmark mid-point (£/m²) with ±spread applied automatically
B6: ▸ Tighter 20-25% spread (Low–High range) replacing the previous wide ranges that were not useful for feasibility reporting
B7: ▸ Three specification levels per project type — Basic, Standard, High Spec — each on a separate tab
B8: ▸ Rates Reference Table tab — all benchmark mid-point rates in one place; update here and all tabs recalculate
B9: ▸ BCIS-traceable structure — rate cells reference a named source column; when a BCIS subscription is obtained, update the Rates Table
B11: SPECIFICATION LEVELS — WHICH TAB TO USE
B12: Level 1 — Basic / Maintenance: Like-for-like replacement, redecoration, basic M&E refresh. No layout change. Functional finish only.
B13: Level 2 — Standard / Cat A–B: Modified layout, new M&E distribution, Cat A or Cat B office/teaching finish. Most university estates projects.
B14: Level 3 — High Spec / Specialist: Flagship, lab, healthcare, or bespoke. Heavy M&E, specialist fit-out, feature finishes. Premium.
... B45: All figures are LOW–HIGH ranges only. No single-point estimates are shown. Rates should be updated against BCIS data before formal use.

Sheet Rates Reference Table
A1: RATES REFERENCE TABLE — Mid-point £/m² GIFA Benchmark Rates | Q2 2026 | UK National Mean | Update this table to refresh all estimate tabs
A2: Source: Sense-checked against RICS/BCIS published ranges Q4 2025–Q2 2026, Cushman & Wakefield UK Fit-Out Guide 2025, RateQS benchmarks Nov 2025. All rates are mid-point estimates at UK national mean. Apply BCIS regional factor in estimate tabs. Update quarterly when BCIS subscription is available.
A4: Grp | B4: Sub | C4: Element / Description | D4: Unit | E4: Rfb Basic | F4: Rfb Standard | G4: Rfb High Spec | H4: New Build Standard | I4: New Build High Spec | J4: Extension Standard | K4: Extension High Spec | L4: External Works Only | M4: Notes / Rate Driver
A5: GROUP 0 — FACILITATING WORKS — Include if demolition, known asbestos, or brownfield site identified in questionnaire
A6: 0 | B6: 0.1 | C6: Toxic/hazardous material removal | D6: Item | E6: 15 | F6: 25 | G6: 40 | H6: 10 | I6: 20 | J6: 10 | K6: 20 | L6: 0 | M6: Asbestos; increase if confirmed present (refurb/demo only)
A7: 0 | B7: 0.2 | C7: Demolition & structural alterations | D7: Item | E7: 20 | F7: 35 | G7: 55 | H7: 15 | I7: 25 | J7: 20 | K7: 35 | L7: 5 | M7: Selective or full demolition; structural openings
A8: 0 | B8: 0.3 | C8: Contaminated land remediation | D8: Item | E8: 5 | F8: 10 | G8: 20 | H8: 10 | I8: 20 | J8: 5 | K8: 15 | L8: 10 | M8: Brownfield/contaminated; specialist quote needed
A9: 0 | B9: 0.4 | C9: Ground stabilisation | D9: Item | E9: 5 | F9: 8 | G9: 15 | H9: 8 | I9: 15 | J9: 5 | K9: 12 | L9: 5 | M9: Underpinning/piling if ground risk identified
A10: GROUP 1 — SUBSTRUCTURE — New build and extension only; always exclude for pure refurb/fit-out
A11: 1 | B11: 1.1 | C11: Standard foundations (strip/pad) | D11: m² | E11: 0 | F11: 0 | G11: 0 | H11: 55 | I11: 80 | J11: 55 | K11: 80 | L11: 0 | M11: New build only; included in Group 7 rate for extensions
A12: 1 | B12: 1.2 | C12: Specialist foundations (piled) | D12: m² | E12: 0 | F12: 0 | G12: 0 | H12: 40 | I12: 60 | J12: 40 | K12: 60 | L12: 0 | M12: Poor ground conditions; trigger from GI report
A13: 1 | B13: 1.3 | C13: Lowest floor construction (slab) | D13: m² | E13: 0 | F13: 0 | G13: 0 | H13: 35 | I13: 55 | J13: 35 | K13: 55 | L13: 0 | M13: Ground bearing or suspended; inc DPM and insulation
A14: 1 | B14: 1.4 | C14: Basement excavation & structure | D14: Item | E14: 0 | F14: 0 | G14: 0 | H14: 80 | I14: 150 | J14: 80 | K14: 150 | L14: 0 | M14: High uncertainty; specialist estimate recommended
A15: GROUP 2 — SUPERSTRUCTURE — Core element for new build; partial inclusion for extension/refurb with structural alterations
A16: 2 | B16: 2.1 | C16: Structural frame | D16: m² | E16: 0 | F16: 20 | G16: 40 | H16: 150 | I16: 220 | J16: 130 | K16: 200 | L16: 0 | M16: Steel/concrete/timber; new build or major extensions only
A17: 2 | B17: 2.2 | C17: Upper floors | D17: m² | E17: 0 | F17: 15 | G17: 30 | H17: 65 | I17: 95 | J17: 65 | K17: 95 | L17: 0 | M17: New build or added floors; inc topping and insulation
A18: 2 | B18: 2.3 | C18: Roof structure & covering | D18: m² | E18: 35 | F18: 55 | G18: 90 | H18: 75 | I18: 120 | J18: 75 | K18: 120 | L18: 0 | M18: New or replacement; inc insulation, waterproofing, rainwater
A19: 2 | B19: 2.4 | C19: Stairs & ramps | D19: Item | E19: 10 | F19: 15 | G19: 25 | H19: 20 | I19: 35 | J19: 20 | K19: 35 | L19: 0 | M19: RC, steel or timber; accessibility ramps
A20: 2 | B20: 2.5 | C20: External walls & facade | D20: m² | E20: 30 | F20: 60 | G20: 110 | H20: 200 | I20: 320 | J20: 180 | K20: 280 | L20: 0 | M20: Masonry/cladding; refurb = overcladding or repair only
A21: 2 | B21: 2.6 | C21: Windows & external doors | D21: m² | E21: 80 | F21: 130 | G21: 200 | H21: 100 | I21: 160 | J21: 90 | K21: 150 | L21: 0 | M21: uPVC (low) to aluminium curtain wall (high)
A22: 2 | B22: 2.7 | C22: Internal walls & partitions | D22: m² | E22: 20 | F22: 35 | G22: 60 | H22: 30 | I22: 50 | J22: 25 | K22: 45 | L22: 0 | M22: Blockwork, drywall or glazed; do not double-count Grp 3
A23: 2 | B23: 2.8 | C23: Internal doors & ironmongery | D23: Nr | E23: 15 | F23: 25 | G23: 40 | H23: 20 | I23: 35 | J23: 18 | K23: 30 | L23: 0 | M23: Fire-rated at upper range; standard at lower
A24: GROUP 3 — INTERNAL FINISHES ★ ALWAYS INCLUDED — NEVER excluded — every project has internal finishes to some level
A25: 3 | B25: 3.1 | C25: Wall finishes | D25: m² | E25: 15 | F25: 35 | G25: 75 | H25: 25 | I25: 55 | J25: 20 | K25: 50 | L25: 0 | M25: Emulsion (low) → specialist tiling/feature panelling (high)
A26: 3 | B26: 3.2 | C26: Floor finishes | D26: m² | E26: 20 | F26: 55 | G26: 130 | H26: 30 | I26: 80 | J26: 25 | K26: 70 | L26: 0 | M26: Vinyl/carpet (low) → stone/raised access floor (high)
A27: 3 | B27: 3.3 | C27: Ceiling finishes | D27: m² | E27: 10 | F27: 30 | G27: 65 | H27: 15 | I27: 45 | J27: 12 | K27: 40 | L27: 0 | M27: Emulsion (low) → bespoke acoustic ceiling system (high)
A28: GROUP 4 — FITTINGS, FURNISHINGS & EQUIPMENT — Include if joinery, kitchens, toilets or specialist fit-out selected in Q2.2
A29: 4 | B29: 4.1 | C29: General fittings & built-in joinery | D29: Item | E29: 10 | F29: 30 | G29: 80 | H29: 15 | I29: 50 | J29: 10 | K29: 40 | L29: 0 | M29: Reception desks, shelving, built-in furniture
A30: 4 | B30: 4.2 | C30: Sanitary fittings & toilet fit-out | D30: Nr | E30: 8 | F30: 18 | G30: 35 | H30: 10 | I30: 22 | J30: 8 | K30: 18 | L30: 0 | M30: WC packs; uplift for accessible/changing facilities
A31: 4 | B31: 4.3 | C31: Kitchen / break-out area | D31: Item | E31: 5 | F31: 15 | G31: 35 | H31: 8 | I31: 20 | J31: 5 | K31: 15 | L31: 0 | M31: Fitted units, worktops, appliances
A32: 4 | B32: 4.4 | C32: Specialist equipment (lab/AV/med) | D32: Item | E32: 0 | F32: 10 | G32: 80 | H32: 5 | I32: 60 | J32: 0 | K32: 40 | L32: 0 | M32: Laboratory, medical, AV; confirm with specialist
A33: GROUP 5 — MECHANICAL & ELECTRICAL SERVICES ★ KEY ELEMENT — Always price separately — never bundle into superstructure rate
A34: 5 | B34: 5.1 | C34: Sanitary plumbing (1st & 2nd fix) | D34: m² | E34: 15 | F34: 35 | G34: 65 | H34: 25 | I34: 50 | J34: 20 | K34: 45 | L34: 0 | M34: HWS, cold water, drainage connections
A35: 5 | B35: 5.2 | C35: Heating & hot water (LTHW/heat pump) | D35: m² | E35: 25 | F35: 50 | G35: 90 | H35: 35 | I35: 70 | J35: 30 | K35: 65 | L35: 0 | M35: LTHW system or heat pump; include buffer vessel
A36: 5 | B36: 5.3 | C36: Ventilation & air handling | D36: m² | E36: 20 | F36: 45 | G36: 90 | H36: 30 | I36: 70 | J36: 25 | K36: 60 | L36: 0 | M36: MVHR/AHU; uplift for lab/healthcare extract (+50-100%)
A37: 5 | B37: 5.4 | C37: Air conditioning & cooling | D37: m² | E37: 0 | F37: 30 | G37: 70 | H37: 15 | I37: 55 | J37: 10 | K37: 45 | L37: 0 | M37: VRF/splits; omit if not in scope
A38: 5 | B38: 5.5 | C38: Gas installation | D38: Item | E38: 5 | F38: 10 | G38: 15 | H38: 8 | I38: 15 | J38: 5 | K38: 10 | L38: 0 | M38: Omit if all-electric; confirm with utility
A39: 5 | B39: 5.6 | C39: Sprinkler / fire suppression | D39: m² | E39: 0 | F39: 15 | G39: 30 | H39: 10 | I39: 25 | J39: 5 | K39: 20 | L39: 0 | M39: >18m height or insurer requirement
A40: 5 | B40: 5.7 | C40: Electrical distribution & switchgear | D40: m² | E40: 15 | F40: 30 | G40: 55 | H40: 20 | I40: 45 | J40: 15 | K40: 40 | L40: 0 | M40: LV panels, distribution boards, earthing, containment
A41: 5 | B41: 5.8 | C41: Electrical wiring (1st & 2nd fix) | D41: m² | E41: 20 | F41: 40 | G41: 75 | H41: 30 | I41: 60 | J41: 25 | K41: 55 | L41: 0 | M41: All power and lighting circuits; inc containment
A42: 5 | B42: 5.9 | C42: Emergency lighting & fire alarm | D42: m² | E42: 10 | F42: 20 | G42: 35 | H42: 12 | I42: 25 | J42: 10 | K42: 22 | L42: 0 | M42: L2 minimum; upgrade for multi-zone/complex layouts
A43: 5 | B43: 5.10 | C43: External lighting | D43: Item | E43: 0 | F43: 5 | G43: 10 | H43: 5 | I43: 12 | J43: 3 | K43: 8 | L43: 10 | M43: Column/wall-mounted perimeter lighting
A44: 5 | B44: 5.11 | C44: Solar PV / renewables | D44: kWp | E44: 0 | F44: 800 | G44: 1200 | H44: 800 | I44: 1200 | J44: 800 | K44: 1200 | L44: 0 | M44: £/kWp installed; coordinate structural loading + electrical
A45: 5 | B45: 5.12 | C45: EV charging points | D45: Nr | E45: 0 | F45: 1500 | G45: 2500 | H45: 1500 | I45: 2500 | J45: 1500 | K45: 2500 | L45: 2000 | M45: Per charge point inc groundworks; 7kW fast charger
... A50: 5 | B50: 5.17 | C50: Builder's work in connection (BWIC) | D50: m² | E50: 5 | F50: 12 | G50: 22 | H50: 8 | I50: 18 | J50: 6 | K50: 15 | L50: 0 | M50: Penetrations, plinths, ducts, concrete bases for plant
A51: GROUP 6 — PREFABRICATED / MODULAR (if applicable) — Exclude if not applicable; specialist contractor quote always required
A52: 6 | B52: 6.1 | C52: Prefabricated / modular units | D52: Item | E52: 0 | F52: 0 | G52: 200 | H52: 0 | I52: 150 | J52: 0 | K52: 100 | L52: 0 | M52: Factory-built modular; specialist quote required
A53: 6 | B53: 6.2 | C53: Pre-engineered systems (mezzanine) | D53: Item | E53: 0 | F53: 50 | G53: 100 | H53: 0 | I53: 80 | J53: 0 | K53: 60 | L53: 0 | M53: Mezzanine floors, demountable partitions
A54: GROUP 7 — WORK TO EXISTING BUILDINGS — Refurbishment and extension only; +15-25% rate uplift for pre-1900 or listed buildings
A55: 7 | B55: 7.1 | C55: Structural repairs | D55: Item | E55: 10 | F55: 25 | G55: 55 | H55: 0 | I55: 0 | J55: 15 | K55: 35 | L55: 0 | M55: Crack stitching, bearing repairs; increase for poor condition
A56: 7 | B56: 7.2 | C56: Fabric / envelope repairs | D56: Item | E56: 10 | F56: 20 | G56: 45 | H56: 0 | I56: 0 | J56: 12 | K56: 28 | L56: 0 | M56: Repointing, waterproofing, weathertight works
A57: 7 | B57: 7.3 | C57: Damp proof course treatment | D57: Item | E57: 5 | F57: 10 | G57: 20 | H57: 0 | I57: 0 | J57: 5 | K57: 15 | L57: 0 | M57: Chemical DPC; increase for severe rising damp
A58: 7 | B58: 7.4 | C58: M&E overhaul / life-expired services | D58: Item | E58: 0 | F58: 30 | G58: 80 | H58: 0 | I58: 0 | J58: 20 | K58: 55 | L58: 0 | M58: Replacement of end-of-life mechanical & electrical plant
A59: 7 | B59: 7.5 | C59: Making good after structural works | D59: Item | E59: 5 | F59: 10 | G59: 20 | H59: 0 | I59: 0 | J59: 5 | K59: 12 | L59: 0 | M59: Patch plaster, redecoration after structural alterations
A60: GROUP 8 — EXTERNAL WORKS — Always include; External Works tab uses these as primary cost driver
A61: 8 | B61: 8.1 | C61: Site preparation & clearance | D61: Item | E61: 3 | F61: 8 | G61: 15 | H61: 8 | I61: 18 | J61: 5 | K61: 12 | L61: 10 | M61: Strip topsoil, vegetation, temp fencing and hoarding
A62: 8 | B62: 8.2 | C62: Roads, paths & hard paving | D62: m² | E62: 0 | F62: 10 | G62: 20 | H62: 15 | I62: 35 | J62: 10 | K62: 25 | L62: 35 | M62: Macadam/block paving; inc edging and drainage channels
A63: 8 | B63: 8.3 | C63: Car parking (line-marked bays) | D63: Nr | E63: 0 | F63: 5 | G63: 10 | H63: 5 | I63: 12 | J63: 3 | K63: 8 | L63: 20 | M63: Surfacing, line markings, disabled bays
A64: 8 | B64: 8.4 | C64: Surface water drainage | D64: Item | E64: 3 | F64: 8 | G64: 15 | H64: 10 | I64: 20 | J64: 5 | K64: 15 | L64: 25 | M64: Gullies, pipes, SuDS if required by planning
A65: 8 | B65: 8.5 | C65: Foul drainage connections | D65: Item | E65: 3 | F65: 6 | G65: 12 | H65: 8 | I65: 15 | J65: 5 | K65: 10 | L65: 15 | M65: Connection to existing drain or new manhole
A66: 8 | B66: 8.6 | C66: External utility services | D66: Item | E66: 3 | F66: 8 | G66: 15 | H66: 10 | I66: 20 | J66: 5 | K66: 15 | L66: 20 | M66: Gas/water/electric diversions; early check with DNO
A67: 8 | B67: 8.7 | C67: Soft landscaping | D67: m² | E67: 0 | F67: 3 | G67: 8 | H67: 5 | I67: 12 | J67: 3 | K67: 10 | L67: 15 | M67: Planting, seeding, topsoil reinstatement
A68: 8 | B68: 8.8 | C68: Boundary enclosures (fences/gates) | D68: Item | E68: 0 | F68: 3 | G68: 8 | H68: 3 | I68: 10 | J68: 2 | K68: 8 | L68: 12 | M68: Security fencing, gates, boundary walls, railings
A69: 8 | B69: 8.9 | C69: External lighting | D69: Item | E69: 0 | F69: 2 | G69: 5 | H69: 3 | I69: 8 | J69: 2 | K69: 6 | L69: 10 | M69: Column or wall-mounted lighting (see also 5.10)
A71: UPDATE LOG: Version 2.0 — May 2026 — Rates sense-checked against: BCIS Q4 2025 index (+5% from Q4 2024); RICS new build £1,800–£2,500/m² national (standard-good spec); Cushman & Wakefield Cat B office £800–£1,300/m² national; RapidQS commercial fit-out £800–£2,500/m²; K2 Space/Fusion office fit-out £500–£1,300/m² national. Next review due: Q4 2026. When BCIS subscription obtained, replace rates above with BCIS elemental benchmarks.

Sheet Rfb – Basic
A1: NRM1 ESTIMATE — REFURB / FIT-OUT — BASIC / MAINTENANCE
A2: Spec level: Like-for-like replacement, redecoration, basic M&E refresh. No layout changes. | RIBA Stage 0–1 indicative only | Base date Q2 2026
A4: Project Type: | B4: Refurb / Fit-Out | D4: Spec Level: | E4: Basic / Maintenance | G4: Region: | H4: West Midlands
A5: GIFA (m²) ▼ update: | B5: 500 | D5: BCIS Location Factor ▼: | E5: 0.94 | G5: Spread ±% ▼: | H5: 0.22
A7: Grp | B7: Sub | C7: Element / Description | D7: Unit | E7: Mid-Point £/m² | F7: Low £/m² | G7: High £/m² | H7: Total LOW (£) | I7: Total HIGH (£) | J7: Notes / Rate Driver
A8: GROUP 0 — FACILITATING WORKS
A9: 0 | B9: 0.1 | C9: Toxic/hazardous material removal | D9: Item | E9: =IFERROR('Rates Reference Table'!E6*$E$5,0) -> 14.1 | F9: =IFERROR(E9*(1-$H$5/2),0) -> 12.549 | G9: =IFERROR(E9*(1+$H$5/2),0) -> 15.651 | H9: =IFERROR(F9*$B$5,0) -> 6274.5 | I9: =IFERROR(G9*$B$5,0) -> 7825.5 | J9: Asbestos; increase if confirmed present (refurb/demo only)
A10: 0 | B10: 0.2 | C10: Demolition & structural alterations | D10: Item | E10: =IFERROR('Rates Reference Table'!E7*$E$5,0) -> 18.8 | F10: =IFERROR(E10*(1-$H$5/2),0) -> 16.732 | G10: =IFERROR(E10*(1+$H$5/2),0) -> 20.868 | H10: =IFERROR(F10*$B$5,0) -> 8366 | I10: =IFERROR(G10*$B$5,0) -> 10434 | J10: Selective or full demolition; structural openings
A11: 0 | B11: 0.3 | C11: Contaminated land remediation | D11: Item | E11: =IFERROR('Rates Reference Table'!E8*$E$5,0) -> 4.7 | F11: =IFERROR(E11*(1-$H$5/2),0) -> 4.183 | G11: =IFERROR(E11*(1+$H$5/2),0) -> 5.217 | H11: =IFERROR(F11*$B$5,0) -> 2091.5 | I11: =IFERROR(G11*$B$5,0) -> 2608.5 | J11: Brownfield/contaminated; specialist quote needed
A12: 0 | B12: 0.4 | C12: Ground stabilisation | D12: Item | E12: =IFERROR('Rates Reference Table'!E9*$E$5,0) -> 4.7 | F12: =IFERROR(E12*(1-$H$5/2),0) -> 4.183 | G12: =IFERROR(E12*(1+$H$5/2),0) -> 5.217 | H12: =IFERROR(F12*$B$5,0) -> 2091.5 | I12: =IFERROR(G12*$B$5,0) -> 2608.5 | J12: Underpinning/piling if ground risk identified
A13: GROUP 1 — SUBSTRUCTURE
A14: 1 | B14: 1.1 | C14: Standard foundations (strip/pad) | D14: m² | E14: EXCLUDED | F14: EXCLUDED | G14: EXCLUDED | H14: 0 | I14: 0 | J14: New build only; included in Group 7 rate for extensions
A15: 1 | B15: 1.2 | C15: Specialist foundations (piled) | D15: m² | E15: EXCLUDED | F15: EXCLUDED | G15: EXCLUDED | H15: 0 | I15: 0 | J15: Poor ground conditions; trigger from GI report
A16: 1 | B16: 1.3 | C16: Lowest floor construction (slab) | D16: m² | E16: EXCLUDED | F16: EXCLUDED | G16: EXCLUDED | H16: 0 | I16: 0 | J16: Ground bearing or suspended; inc DPM and insulation
A17: 1 | B17: 1.4 | C17: Basement excavation & structure | D17: Item | E17: EXCLUDED | F17: EXCLUDED | G17: EXCLUDED | H17: 0 | I17: 0 | J17: High uncertainty; specialist estimate recommended
A18: GROUP 2 — SUPERSTRUCTURE
A19: 2 | B19: 2.1 | C19: Structural frame | D19: m² | E19: =IFERROR('Rates Reference Table'!E16*$E$5,0) -> 0 | F19: =IFERROR(E19*(1-$H$5/2),0) -> 0 | G19: =IFERROR(E19*(1+$H$5/2),0) -> 0 | H19: =IFERROR(F19*$B$5,0) -> 0 | I19: =IFERROR(G19*$B$5,0) -> 0 | J19: Steel/concrete/timber; new build or major extensions only
A20: 2 | B20: 2.2 | C20: Upper floors | D20: m² | E20: =IFERROR('Rates Reference Table'!E17*$E$5,0) -> 0 | F20: =IFERROR(E20*(1-$H$5/2),0) -> 0 | G20: =IFERROR(E20*(1+$H$5/2),0) -> 0 | H20: =IFERROR(F20*$B$5,0) -> 0 | I20: =IFERROR(G20*$B$5,0) -> 0 | J20: New build or added floors; inc topping and insulation
A21: 2 | B21: 2.3 | C21: Roof structure & covering | D21: m² | E21: =IFERROR('Rates Reference Table'!E18*$E$5,0) -> 32.9 | F21: =IFERROR(E21*(1-$H$5/2),0) -> 29.281 | G21: =IFERROR(E21*(1+$H$5/2),0) -> 36.519 | H21: =IFERROR(F21*$B$5,0) -> 14640.5 | I21: =IFERROR(G21*$B$5,0) -> 18259.5 | J21: New or replacement; inc insulation, waterproofing, rainwater
A22: 2 | B22: 2.4 | C22: Stairs & ramps | D22: Item | E22: =IFERROR('Rates Reference Table'!E19*$E$5,0) -> 9.4 | F22: =IFERROR(E22*(1-$H$5/2),0) -> 8.366 | G22: =IFERROR(E22*(1+$H$5/2),0) -> 10.434 | H22: =IFERROR(F22*$B$5,0) -> 4183 | I22: =IFERROR(G22*$B$5,0) -> 5217 | J22: RC, steel or timber; accessibility ramps
A23: 2 | B23: 2.5 | C23: External walls & facade | D23: m² | E23: =IFERROR('Rates Reference Table'!E20*$E$5,0) -> 28.2 | F23: =IFERROR(E23*(1-$H$5/2),0) -> 25.098 | G23: =IFERROR(E23*(1+$H$5/2),0) -> 31.302 | H23: =IFERROR(F23*$B$5,0) -> 12549 | I23: =IFERROR(G23*$B$5,0) -> 15651 | J23: Masonry/cladding; refurb = overcladding or repair only
A24: 2 | B24: 2.6 | C24: Windows & external doors | D24: m² | E24: =IFERROR('Rates Reference Table'!E21*$E$5,0) -> 75.2 | F24: =IFERROR(E24*(1-$H$5/2),0) -> 66.928 | G24: =IFERROR(E24*(1+$H$5/2),0) -> 83.472 | H24: =IFERROR(F24*$B$5,0) -> 33464 | I24: =IFERROR(G24*$B$5,0) -> 41736 | J24: uPVC (low) to aluminium curtain wall (high)
A25: 2 | B25: 2.7 | C25: Internal walls & partitions | D25: m² | E25: =IFERROR('Rates Reference Table'!E22*$E$5,0) -> 18.8 | F25: =IFERROR(E25*(1-$H$5/2),0) -> 16.732 | G25: =IFERROR(E25*(1+$H$5/2),0) -> 20.868 | H25: =IFERROR(F25*$B$5,0) -> 8366 | I25: =IFERROR(G25*$B$5,0) -> 10434 | J25: Blockwork, drywall or glazed; do not double-count Grp 3
A26: 2 | B26: 2.8 | C26: Internal doors & ironmongery | D26: Nr | E26: =IFERROR('Rates Reference Table'!E23*$E$5,0) -> 14.1 | F26: =IFERROR(E26*(1-$H$5/2),0) -> 12.549 | G26: =IFERROR(E26*(1+$H$5/2),0) -> 15.651 | H26: =IFERROR(F26*$B$5,0) -> 6274.5 | I26: =IFERROR(G26*$B$5,0) -> 7825.5 | J26: Fire-rated at upper range; standard at lower
A27: GROUP 3 — INTERNAL FINISHES ★ ALWAYS INCLUDED
A28: 3 | B28: 3.1 | C28: Wall finishes | D28: m² | E28: =IFERROR('Rates Reference Table'!E25*$E$5,0) -> 14.1 | F28: =IFERROR(E28*(1-$H$5/2),0) -> 12.549 | G28: =IFERROR(E28*(1+$H$5/2),0) -> 15.651 | H28: =IFERROR(F28*$B$5,0) -> 6274.5 | I28: =IFERROR(G28*$B$5,0) -> 7825.5 | J28: Emulsion (low) → specialist tiling/feature panelling (high)
A29: 3 | B29: 3.2 | C29: Floor finishes | D29: m² | E29: =IFERROR('Rates Reference Table'!E26*$E$5,0) -> 18.8 | F29: =IFERROR(E29*(1-$H$5/2),0) -> 16.732 | G29: =IFERROR(E29*(1+$H$5/2),0) -> 20.868 | H29: =IFERROR(F29*$B$5,0) -> 8366 | I29: =IFERROR(G29*$B$5,0) -> 10434 | J29: Vinyl/carpet (low) → stone/raised access floor (high)
A30: 3 | B30: 3.3 | C30: Ceiling finishes | D30: m² | E30: =IFERROR('Rates Reference Table'!E27*$E$5,0) -> 9.4 | F30: =IFERROR(E30*(1-$H$5/2),0) -> 8.366 | G30: =IFERROR(E30*(1+$H$5/2),0) -> 10.434 | H30: =IFERROR(F30*$B$5,0) -> 4183 | I30: =IFERROR(G30*$B$5,0) -> 5217 | J30: Emulsion (low) → bespoke acoustic ceiling system (high)
A31: GROUP 4 — FITTINGS, FURNISHINGS & EQUIPMENT
A32: 4 | B32: 4.1 | C32: General fittings & built-in joinery | D32: Item | E32: =IFERROR('Rates Reference Table'!E29*$E$5,0) -> 9.4 | F32: =IFERROR(E32*(1-$H$5/2),0) -> 8.366 | G32: =IFERROR(E32*(1+$H$5/2),0) -> 10.434 | H32: =IFERROR(F32*$B$5,0) -> 4183 | I32: =IFERROR(G32*$B$5,0) -> 5217 | J32: Reception desks, shelving, built-in furniture
A33: 4 | B33: 4.2 | C33: Sanitary fittings & toilet fit-out | D33: Nr | E33: =IFERROR('Rates Reference Table'!E30*$E$5,0) -> 7.52 | F33: =IFERROR(E33*(1-$H$5/2),0) -> 6.6928 | G33: =IFERROR(E33*(1+$H$5/2),0) -> 8.3472 | H33: =IFERROR(F33*$B$5,0) -> 3346.4 | I33: =IFERROR(G33*$B$5,0) -> 4173.6 | J33: WC packs; uplift for accessible/changing facilities
A34: 4 | B34: 4.3 | C34: Kitchen / break-out area | D34: Item | E34: =IFERROR('Rates Reference Table'!E31*$E$5,0) -> 4.7 | F34: =IFERROR(E34*(1-$H$5/2),0) -> 4.183 | G34: =IFERROR(E34*(1+$H$5/2),0) -> 5.217 | H34: =IFERROR(F34*$B$5,0) -> 2091.5 | I34: =IFERROR(G34*$B$5,0) -> 2608.5 | J34: Fitted units, worktops, appliances
A35: 4 | B35: 4.4 | C35: Specialist equipment (lab/AV/med) | D35: Item | E35: =IFERROR('Rates Reference Table'!E32*$E$5,0) -> 0 | F35: =IFERROR(E35*(1-$H$5/2),0) -> 0 | G35: =IFERROR(E35*(1+$H$5/2),0) -> 0 | H35: =IFERROR(F35*$B$5,0) -> 0 | I35: =IFERROR(G35*$B$5,0) -> 0 | J35: Laboratory, medical, AV; confirm with specialist
A36: GROUP 5 — MECHANICAL & ELECTRICAL SERVICES ★ KEY ELEMENT
A37: 5 | B37: 5.1 | C37: Sanitary plumbing (1st & 2nd fix) | D37: m² | E37: =IFERROR('Rates Reference Table'!E34*$E$5,0) -> 14.1 | F37: =IFERROR(E37*(1-$H$5/2),0) -> 12.549 | G37: =IFERROR(E37*(1+$H$5/2),0) -> 15.651 | H37: =IFERROR(F37*$B$5,0) -> 6274.5 | I37: =IFERROR(G37*$B$5,0) -> 7825.5 | J37: HWS, cold water, drainage connections
A38: 5 | B38: 5.2 | C38: Heating & hot water (LTHW/heat pump) | D38: m² | E38: =IFERROR('Rates Reference Table'!E35*$E$5,0) -> 23.5 | F38: =IFERROR(E38*(1-$H$5/2),0) -> 20.915 | G38: =IFERROR(E38*(1+$H$5/2),0) -> 26.085 | H38: =IFERROR(F38*$B$5,0) -> 10457.5 | I38: =IFERROR(G38*$B$5,0) -> 13042.5 | J38: LTHW system or heat pump; include buffer vessel
A39: 5 | B39: 5.3 | C39: Ventilation & air handling | D39: m² | E39: =IFERROR('Rates Reference Table'!E36*$E$5,0) -> 18.8 | F39: =IFERROR(E39*(1-$H$5/2),0) -> 16.732 | G39: =IFERROR(E39*(1+$H$5/2),0) -> 20.868 | H39: =IFERROR(F39*$B$5,0) -> 8366 | I39: =IFERROR(G39*$B$5,0) -> 10434 | J39: MVHR/AHU; uplift for lab/healthcare extract (+50-100%)
A40: 5 | B40: 5.4 | C40: Air conditioning & cooling | D40: m² | E40: =IFERROR('Rates Reference Table'!E37*$E$5,0) -> 0 | F40: =IFERROR(E40*(1-$H$5/2),0) -> 0 | G40: =IFERROR(E40*(1+$H$5/2),0) -> 0 | H40: =IFERROR(F40*$B$5,0) -> 0 | I40: =IFERROR(G40*$B$5,0) -> 0 | J40: VRF/splits; omit if not in scope
A41: 5 | B41: 5.5 | C41: Gas installation | D41: Item | E41: =IFERROR('Rates Reference Table'!E38*$E$5,0) -> 4.7 | F41: =IFERROR(E41*(1-$H$5/2),0) -> 4.183 | G41: =IFERROR(E41*(1+$H$5/2),0) -> 5.217 | H41: =IFERROR(F41*$B$5,0) -> 2091.5 | I41: =IFERROR(G41*$B$5,0) -> 2608.5 | J41: Omit if all-electric; confirm with utility
A42: 5 | B42: 5.6 | C42: Sprinkler / fire suppression | D42: m² | E42: =IFERROR('Rates Reference Table'!E39*$E$5,0) -> 0 | F42: =IFERROR(E42*(1-$H$5/2),0) -> 0 | G42: =IFERROR(E42*(1+$H$5/2),0) -> 0 | H42: =IFERROR(F42*$B$5,0) -> 0 | I42: =IFERROR(G42*$B$5,0) -> 0 | J42: >18m height or insurer requirement
A43: 5 | B43: 5.7 | C43: Electrical distribution & switchgear | D43: m² | E43: =IFERROR('Rates Reference Table'!E40*$E$5,0) -> 14.1 | F43: =IFERROR(E43*(1-$H$5/2),0) -> 12.549 | G43: =IFERROR(E43*(1+$H$5/2),0) -> 15.651 | H43: =IFERROR(F43*$B$5,0) -> 6274.5 | I43: =IFERROR(G43*$B$5,0) -> 7825.5 | J43: LV panels, distribution boards, earthing, containment
A44: 5 | B44: 5.8 | C44: Electrical wiring (1st & 2nd fix) | D44: m² | E44: =IFERROR('Rates Reference Table'!E41*$E$5,0) -> 18.8 | F44: =IFERROR(E44*(1-$H$5/2),0) -> 16.732 | G44: =IFERROR(E44*(1+$H$5/2),0) -> 20.868 | H44: =IFERROR(F44*$B$5,0) -> 8366 | I44: =IFERROR(G44*$B$5,0) -> 10434 | J44: All power and lighting circuits; inc containment
A45: 5 | B45: 5.9 | C45: Emergency lighting & fire alarm | D45: m² | E45: =IFERROR('Rates Reference Table'!E42*$E$5,0) -> 9.4 | F45: =IFERROR(E45*(1-$H$5/2),0) -> 8.366 | G45: =IFERROR(E45*(1+$H$5/2),0) -> 10.434 | H45: =IFERROR(F45*$B$5,0) -> 4183 | I45: =IFERROR(G45*$B$5,0) -> 5217 | J45: L2 minimum; upgrade for multi-zone/complex layouts
A46: 5 | B46: 5.10 | C46: External lighting | D46: Item | E46: =IFERROR('Rates Reference Table'!E43*$E$5,0) -> 0 | F46: =IFERROR(E46*(1-$H$5/2),0) -> 0 | G46: =IFERROR(E46*(1+$H$5/2),0) -> 0 | H46: =IFERROR(F46*$B$5,0) -> 0 | I46: =IFERROR(G46*$B$5,0) -> 0 | J46: Column/wall-mounted perimeter lighting
A47: 5 | B47: 5.11 | C47: Solar PV / renewables | D47: kWp | E47: =IFERROR('Rates Reference Table'!E44*$E$5,0) -> 0 | F47: =IFERROR(E47*(1-$H$5/2),0) -> 0 | G47: =IFERROR(E47*(1+$H$5/2),0) -> 0 | H47: =IFERROR(F47*$B$5,0) -> 0 | I47: =IFERROR(G47*$B$5,0) -> 0 | J47: £/kWp installed; coordinate structural loading + electrical
A48: 5 | B48: 5.12 | C48: EV charging points | D48: Nr | E48: =IFERROR('Rates Reference Table'!E45*$E$5,0) -> 0 | F48: =IFERROR(E48*(1-$H$5/2),0) -> 0 | G48: =IFERROR(E48*(1+$H$5/2),0) -> 0 | H48: =IFERROR(F48*$B$5,0) -> 0 | I48: =IFERROR(G48*$B$5,0) -> 0 | J48: Per charge point inc groundworks; 7kW fast charger
... A53: 5 | B53: 5.17 | C53: Builder's work in connection (BWIC) | D53: m² | E53: =IFERROR('Rates Reference Table'!E50*$E$5,0) -> 4.7 | F53: =IFERROR(E53*(1-$H$5/2),0) -> 4.183 | G53: =IFERROR(E53*(1+$H$5/2),0) -> 5.217 | H53: =IFERROR(F53*$B$5,0) -> 2091.5 | I53: =IFERROR(G53*$B$5,0) -> 2608.5 | J53: Penetrations, plinths, ducts, concrete bases for plant
A54: GROUP 6 — PREFABRICATED / MODULAR (if applicable)
A55: 6 | B55: 6.1 | C55: Prefabricated / modular units | D55: Item | E55: EXCLUDED | F55: EXCLUDED | G55: EXCLUDED | H55: 0 | I55: 0 | J55: Factory-built modular; specialist quote required
A56: 6 | B56: 6.2 | C56: Pre-engineered systems (mezzanine) | D56: Item | E56: EXCLUDED | F56: EXCLUDED | G56: EXCLUDED | H56: 0 | I56: 0 | J56: Mezzanine floors, demountable partitions
A57: GROUP 7 — WORK TO EXISTING BUILDINGS
A58: 7 | B58: 7.1 | C58: Structural repairs | D58: Item | E58: =IFERROR('Rates Reference Table'!E55*$E$5,0) -> 9.4 | F58: =IFERROR(E58*(1-$H$5/2),0) -> 8.366 | G58: =IFERROR(E58*(1+$H$5/2),0) -> 10.434 | H58: =IFERROR(F58*$B$5,0) -> 4183 | I58: =IFERROR(G58*$B$5,0) -> 5217 | J58: Crack stitching, bearing repairs; increase for poor condition
A59: 7 | B59: 7.2 | C59: Fabric / envelope repairs | D59: Item | E59: =IFERROR('Rates Reference Table'!E56*$E$5,0) -> 9.4 | F59: =IFERROR(E59*(1-$H$5/2),0) -> 8.366 | G59: =IFERROR(E59*(1+$H$5/2),0) -> 10.434 | H59: =IFERROR(F59*$B$5,0) -> 4183 | I59: =IFERROR(G59*$B$5,0) -> 5217 | J59: Repointing, waterproofing, weathertight works
A60: 7 | B60: 7.3 | C60: Damp proof course treatment | D60: Item | E60: =IFERROR('Rates Reference Table'!E57*$E$5,0) -> 4.7 | F60: =IFERROR(E60*(1-$H$5/2),0) -> 4.183 | G60: =IFERROR(E60*(1+$H$5/2),0) -> 5.217 | H60: =IFERROR(F60*$B$5,0) -> 2091.5 | I60: =IFERROR(G60*$B$5,0) -> 2608.5 | J60: Chemical DPC; increase for severe rising damp
A61: 7 | B61: 7.4 | C61: M&E overhaul / life-expired services | D61: Item | E61: =IFERROR('Rates Reference Table'!E58*$E$5,0) -> 0 | F61: =IFERROR(E61*(1-$H$5/2),0) -> 0 | G61: =IFERROR(E61*(1+$H$5/2),0) -> 0 | H61: =IFERROR(F61*$B$5,0) -> 0 | I61: =IFERROR(G61*$B$5,0) -> 0 | J61: Replacement of end-of-life mechanical & electrical plant
A62: 7 | B62: 7.5 | C62: Making good after structural works | D62: Item | E62: =IFERROR('Rates Reference Table'!E59*$E$5,0) -> 4.7 | F62: =IFERROR(E62*(1-$H$5/2),0) -> 4.183 | G62: =IFERROR(E62*(1+$H$5/2),0) -> 5.217 | H62: =IFERROR(F62*$B$5,0) -> 2091.5 | I62: =IFERROR(G62*$B$5,0) -> 2608.5 | J62: Patch plaster, redecoration after structural alterations
A63: GROUP 8 — EXTERNAL WORKS
A64: 8 | B64: 8.1 | C64: Site preparation & clearance | D64: Item | E64: =IFERROR('Rates Reference Table'!E61*$E$5,0) -> 2.82 | F64: =IFERROR(E64*(1-$H$5/2),0) -> 2.5098 | G64: =IFERROR(E64*(1+$H$5/2),0) -> 3.1302 | H64: =IFERROR(F64*$B$5,0) -> 1254.9 | I64: =IFERROR(G64*$B$5,0) -> 1565.1 | J64: Strip topsoil, vegetation, temp fencing and hoarding
A65: 8 | B65: 8.2 | C65: Roads, paths & hard paving | D65: m² | E65: =IFERROR('Rates Reference Table'!E62*$E$5,0) -> 0 | F65: =IFERROR(E65*(1-$H$5/2),0) -> 0 | G65: =IFERROR(E65*(1+$H$5/2),0) -> 0 | H65: =IFERROR(F65*$B$5,0) -> 0 | I65: =IFERROR(G65*$B$5,0) -> 0 | J65: Macadam/block paving; inc edging and drainage channels
A66: 8 | B66: 8.3 | C66: Car parking (line-marked bays) | D66: Nr | E66: =IFERROR('Rates Reference Table'!E63*$E$5,0) -> 0 | F66: =IFERROR(E66*(1-$H$5/2),0) -> 0 | G66: =IFERROR(E66*(1+$H$5/2),0) -> 0 | H66: =IFERROR(F66*$B$5,0) -> 0 | I66: =IFERROR(G66*$B$5,0) -> 0 | J66: Surfacing, line markings, disabled bays
A67: 8 | B67: 8.4 | C67: Surface water drainage | D67: Item | E67: =IFERROR('Rates Reference Table'!E64*$E$5,0) -> 2.82 | F67: =IFERROR(E67*(1-$H$5/2),0) -> 2.5098 | G67: =IFERROR(E67*(1+$H$5/2),0) -> 3.1302 | H67: =IFERROR(F67*$B$5,0) -> 1254.9 | I67: =IFERROR(G67*$B$5,0) -> 1565.1 | J67: Gullies, pipes, SuDS if required by planning
A68: 8 | B68: 8.5 | C68: Foul drainage connections | D68: Item | E68: =IFERROR('Rates Reference Table'!E65*$E$5,0) -> 2.82 | F68: =IFERROR(E68*(1-$H$5/2),0) -> 2.5098 | G68: =IFERROR(E68*(1+$H$5/2),0) -> 3.1302 | H68: =IFERROR(F68*$B$5,0) -> 1254.9 | I68: =IFERROR(G68*$B$5,0) -> 1565.1 | J68: Connection to existing drain or new manhole
A69: 8 | B69: 8.6 | C69: External utility services | D69: Item | E69: =IFERROR('Rates Reference Table'!E66*$E$5,0) -> 2.82 | F69: =IFERROR(E69*(1-$H$5/2),0) -> 2.5098 | G69: =IFERROR(E69*(1+$H$5/2),0) -> 3.1302 | H69: =IFERROR(F69*$B$5,0) -> 1254.9 | I69: =IFERROR(G69*$B$5,0) -> 1565.1 | J69: Gas/water/electric diversions; early check with DNO
A70: 8 | B70: 8.7 | C70: Soft landscaping | D70: m² | E70: =IFERROR('Rates Reference Table'!E67*$E$5,0) -> 0 | F70: =IFERROR(E70*(1-$H$5/2),0) -> 0 | G70: =IFERROR(E70*(1+$H$5/2),0) -> 0 | H70: =IFERROR(F70*$B$5,0) -> 0 | I70: =IFERROR(G70*$B$5,0) -> 0 | J70: Planting, seeding, topsoil reinstatement
A71: 8 | B71: 8.8 | C71: Boundary enclosures (fences/gates) | D71: Item | E71: =IFERROR('Rates Reference Table'!E68*$E$5,0) -> 0 | F71: =IFERROR(E71*(1-$H$5/2),0) -> 0 | G71: =IFERROR(E71*(1+$H$5/2),0) -> 0 | H71: =IFERROR(F71*$B$5,0) -> 0 | I71: =IFERROR(G71*$B$5,0) -> 0 | J71: Security fencing, gates, boundary walls, railings
A72: 8 | B72: 8.9 | C72: External lighting | D72: Item | E72: =IFERROR('Rates Reference Table'!E69*$E$5,0) -> 0 | F72: =IFERROR(E72*(1-$H$5/2),0) -> 0 | G72: =IFERROR(E72*(1+$H$5/2),0) -> 0 | H72: =IFERROR(F72*$B$5,0) -> 0 | I72: =IFERROR(G72*$B$5,0) -> 0 | J72: Column or wall-mounted lighting (see also 5.10)
A73: WORKS COST SUBTOTAL (Groups 0–8) | H73: =SUMPRODUCT((H8:H72>0)*H8:H72) -> 218770.9 | I73: =SUMPRODUCT((I8:I72>0)*I8:I72) -> 272849.1
A75: ADDITIONS TO WORKS COST — Adjust % using signal rules in Notes column
A76: Code | D76: Description | E76: Applied To | F76: Low % | G76: High % | H76: Total LOW (£) | I76: Total HIGH (£) | J76: Signal Rules / Notes
A77: A | D77: Contractor's Preliminaries | E77: Works Cost | F77: 0.08 | G77: 0.1 | H77: =IFERROR(F77*H73,0) -> 17501.672 | I77: =IFERROR(G77*I73,0) -> 27284.91 | J77: 8%=clean/vacant/short prog | +0.5% per: 6-18mo prog, partial occ, restricted access | cap 10%
A78: B | D78: Contractor's Overheads & Profit | E78: Works Cost | F78: 0.08 | G78: 0.12 | H78: =IFERROR(F78*H73,0) -> 17501.672 | I78: =IFERROR(G78*I73,0) -> 32741.892 | J78: >£5M→8-9% | £1-5M→9-10% | <£1M→10-12% | Lower end = cost priority; upper = D&B/speed
A79: CONSTRUCTION COST SUBTOTAL (Works + Prelims + OH&P) | H79: =H73+H77+H78 -> 253774.24 | I79: =I73+I77+I78 -> 332875.9
A80: C | D80: Professional Fees | E80: Construction Cost | F80: 0.05 | G80: 0.15 | H80: =IFERROR(F80*H79,0) -> 12688.712 | I80: =IFERROR(G80*I79,0) -> 49931.385 | J80: Stage 0-1→12-15% | Stage 2→10-13% | Stage 3→7-10% | Stage 4→5-7% | +1-2% M&E/struct/BREEAM
A81: D | D81: Dev & Project Costs | E81: Construction Cost | F81: 0.02 | G81: 0.04 | H81: =IFERROR(F81*H79,0) -> 5075.4849 | I81: =IFERROR(G81*I79,0) -> 13315.036 | J81: Full planning→3-4% | LBC also→4% | Permitted dev→2% | +0.5% if no surveys yet
A82: E | D82: Risk Allowance | E82: Works Cost | F82: 0.05 | G82: 0.1 | H82: =IFERROR(F82*H73,0) -> 10938.545 | I82: =IFERROR(G82*I73,0) -> 27284.91 | J82: Baseline 5% | +2% no surveys | +1.5% asbestos/contamination | +1% structural concern | +1% hard deadline | cap 10%
A83: H | D83: Client Contingency [FIXED 5%] | E83: Works Cost | F83: 0.05 | G83: 0.05 | H83: =IFERROR(0.05*H73,0) -> 10938.545 | I83: =IFERROR(0.05*I73,0) -> 13642.455 | J83: FIXED at 5% — held by client, not released to contractor. Do not adjust.
A84: F | D84: Inflation Allowance | E84: Works Cost | F84: 0.02 | G84: 0.12 | H84: =IFERROR(F84*H73,0) -> 4375.418 | I84: =IFERROR(G84*I73,0) -> 32741.892 | J84: Component 1: tender delay (0-18mo=2-6%) + Component 2: construction mid-point (6-24mo=1-4%) | cap 12%
A85: TOTAL PROJECT COST (excl. VAT) | H85: =H79+H80+H81+H82+H83+H84 -> 297790.95 | I85: =I79+I80+I81+I82+I83+I84 -> 469791.58
A86: G | D86: VAT — reference only, NOT in total | E86: Project Total | F86: 0.2 | G86: 0.2 | H86: =IFERROR(0.2*H85,0) -> 59558.19 | I86: =IFERROR(0.2*I85,0) -> 93958.316 | J86: Recoverability must be confirmed with client Finance team. New build may attract zero-rating.
A88: Implied blended Works Cost rate — cross-check against BCIS benchmarks: | E88: =IFERROR(H73/$B$5,0) -> 437.5418 | G88: =IFERROR(I73/$B$5,0) -> 545.6982
A90: ⚠ DISCLAIMER: Indicative only — RIBA Stage 0–1 without measured quantities. Rates from Rates Reference Table, cross-referenced Q2 2026 market data. Must be reviewed by a Chartered QS before use in any business case or budget approval. LOW–HIGH range = mid-point ± 11% (default spread 22%). Update GIFA, BCIS factor and Spread as required.

Sheet Rfb – Standard
A1: NRM1 ESTIMATE — REFURB / FIT-OUT — STANDARD / CAT A–B
A2: Spec level: Modified layout, new M&E distribution, Cat A/B office or teaching space finish. | RIBA Stage 0–1 indicative only | Base date Q2 2026
A4: Project Type: | B4: Refurb / Fit-Out | D4: Spec Level: | E4: Standard / Cat A–B | G4: Region: | H4: West Midlands
A5: GIFA (m²) ▼ update: | B5: 500 | D5: BCIS Location Factor ▼: | E5: 0.94 | G5: Spread ±% ▼: | H5: 0.22
A7: Grp | B7: Sub | C7: Element / Description | D7: Unit | E7: Mid-Point £/m² | F7: Low £/m² | G7: High £/m² | H7: Total LOW (£) | I7: Total HIGH (£) | J7: Notes / Rate Driver
A8: GROUP 0 — FACILITATING WORKS
A9: 0 | B9: 0.1 | C9: Toxic/hazardous material removal | D9: Item | E9: =IFERROR('Rates Reference Table'!F6*$E$5,0) -> 23.5 | F9: =IFERROR(E9*(1-$H$5/2),0) -> 20.915 | G9: =IFERROR(E9*(1+$H$5/2),0) -> 26.085 | H9: =IFERROR(F9*$B$5,0) -> 10457.5 | I9: =IFERROR(G9*$B$5,0) -> 13042.5 | J9: Asbestos; increase if confirmed present (refurb/demo only)
A10: 0 | B10: 0.2 | C10: Demolition & structural alterations | D10: Item | E10: =IFERROR('Rates Reference Table'!F7*$E$5,0) -> 32.9 | F10: =IFERROR(E10*(1-$H$5/2),0) -> 29.281 | G10: =IFERROR(E10*(1+$H$5/2),0) -> 36.519 | H10: =IFERROR(F10*$B$5,0) -> 14640.5 | I10: =IFERROR(G10*$B$5,0) -> 18259.5 | J10: Selective or full demolition; structural openings
A11: 0 | B11: 0.3 | C11: Contaminated land remediation | D11: Item | E11: =IFERROR('Rates Reference Table'!F8*$E$5,0) -> 9.4 | F11: =IFERROR(E11*(1-$H$5/2),0) -> 8.366 | G11: =IFERROR(E11*(1+$H$5/2),0) -> 10.434 | H11: =IFERROR(F11*$B$5,0) -> 4183 | I11: =IFERROR(G11*$B$5,0) -> 5217 | J11: Brownfield/contaminated; specialist quote needed
A12: 0 | B12: 0.4 | C12: Ground stabilisation | D12: Item | E12: =IFERROR('Rates Reference Table'!F9*$E$5,0) -> 7.52 | F12: =IFERROR(E12*(1-$H$5/2),0) -> 6.6928 | G12: =IFERROR(E12*(1+$H$5/2),0) -> 8.3472 | H12: =IFERROR(F12*$B$5,0) -> 3346.4 | I12: =IFERROR(G12*$B$5,0) -> 4173.6 | J12: Underpinning/piling if ground risk identified
A13: GROUP 1 — SUBSTRUCTURE
A14: 1 | B14: 1.1 | C14: Standard foundations (strip/pad) | D14: m² | E14: EXCLUDED | F14: EXCLUDED | G14: EXCLUDED | H14: 0 | I14: 0 | J14: New build only; included in Group 7 rate for extensions
A15: 1 | B15: 1.2 | C15: Specialist foundations (piled) | D15: m² | E15: EXCLUDED | F15: EXCLUDED | G15: EXCLUDED | H15: 0 | I15: 0 | J15: Poor ground conditions; trigger from GI report
A16: 1 | B16: 1.3 | C16: Lowest floor construction (slab) | D16: m² | E16: EXCLUDED | F16: EXCLUDED | G16: EXCLUDED | H16: 0 | I16: 0 | J16: Ground bearing or suspended; inc DPM and insulation
A17: 1 | B17: 1.4 | C17: Basement excavation & structure | D17: Item | E17: EXCLUDED | F17: EXCLUDED | G17: EXCLUDED | H17: 0 | I17: 0 | J17: High uncertainty; specialist estimate recommended
A18: GROUP 2 — SUPERSTRUCTURE
A19: 2 | B19: 2.1 | C19: Structural frame | D19: m² | E19: =IFERROR('Rates Reference Table'!F16*$E$5,0) -> 18.8 | F19: =IFERROR(E19*(1-$H$5/2),0) -> 16.732 | G19: =IFERROR(E19*(1+$H$5/2),0) -> 20.868 | H19: =IFERROR(F19*$B$5,0) -> 8366 | I19: =IFERROR(G19*$B$5,0) -> 10434 | J19: Steel/concrete/timber; new build or major extensions only
A20: 2 | B20: 2.2 | C20: Upper floors | D20: m² | E20: =IFERROR('Rates Reference Table'!F17*$E$5,0) -> 14.1 | F20: =IFERROR(E20*(1-$H$5/2),0) -> 12.549 | G20: =IFERROR(E20*(1+$H$5/2),0) -> 15.651 | H20: =IFERROR(F20*$B$5,0) -> 6274.5 | I20: =IFERROR(G20*$B$5,0) -> 7825.5 | J20: New build or added floors; inc topping and insulation
A21: 2 | B21: 2.3 | C21: Roof structure & covering | D21: m² | E21: =IFERROR('Rates Reference Table'!F18*$E$5,0) -> 51.7 | F21: =IFERROR(E21*(1-$H$5/2),0) -> 46.013 | G21: =IFERROR(E21*(1+$H$5/2),0) -> 57.387 | H21: =IFERROR(F21*$B$5,0) -> 23006.5 | I21: =IFERROR(G21*$B$5,0) -> 28693.5 | J21: New or replacement; inc insulation, waterproofing, rainwater
A22: 2 | B22: 2.4 | C22: Stairs & ramps | D22: Item | E22: =IFERROR('Rates Reference Table'!F19*$E$5,0) -> 14.1 | F22: =IFERROR(E22*(1-$H$5/2),0) -> 12.549 | G22: =IFERROR(E22*(1+$H$5/2),0) -> 15.651 | H22: =IFERROR(F22*$B$5,0) -> 6274.5 | I22: =IFERROR(G22*$B$5,0) -> 7825.5 | J22: RC, steel or timber; accessibility ramps
A23: 2 | B23: 2.5 | C23: External walls & facade | D23: m² | E23: =IFERROR('Rates Reference Table'!F20*$E$5,0) -> 56.4 | F23: =IFERROR(E23*(1-$H$5/2),0) -> 50.196 | G23: =IFERROR(E23*(1+$H$5/2),0) -> 62.604 | H23: =IFERROR(F23*$B$5,0) -> 25098 | I23: =IFERROR(G23*$B$5,0) -> 31302 | J23: Masonry/cladding; refurb = overcladding or repair only
A24: 2 | B24: 2.6 | C24: Windows & external doors | D24: m² | E24: =IFERROR('Rates Reference Table'!F21*$E$5,0) -> 122.2 | F24: =IFERROR(E24*(1-$H$5/2),0) -> 108.758 | G24: =IFERROR(E24*(1+$H$5/2),0) -> 135.642 | H24: =IFERROR(F24*$B$5,0) -> 54379 | I24: =IFERROR(G24*$B$5,0) -> 67821 | J24: uPVC (low) to aluminium curtain wall (high)
A25: 2 | B25: 2.7 | C25: Internal walls & partitions | D25: m² | E25: =IFERROR('Rates Reference Table'!F22*$E$5,0) -> 32.9 | F25: =IFERROR(E25*(1-$H$5/2),0) -> 29.281 | G25: =IFERROR(E25*(1+$H$5/2),0) -> 36.519 | H25: =IFERROR(F25*$B$5,0) -> 14640.5 | I25: =IFERROR(G25*$B$5,0) -> 18259.5 | J25: Blockwork, drywall or glazed; do not double-count Grp 3
A26: 2 | B26: 2.8 | C26: Internal doors & ironmongery | D26: Nr | E26: =IFERROR('Rates Reference Table'!F23*$E$5,0) -> 23.5 | F26: =IFERROR(E26*(1-$H$5/2),0) -> 20.915 | G26: =IFERROR(E26*(1+$H$5/2),0) -> 26.085 | H26: =IFERROR(F26*$B$5,0) -> 10457.5 | I26: =IFERROR(G26*$B$5,0) -> 13042.5 | J26: Fire-rated at upper range; standard at lower
A27: GROUP 3 — INTERNAL FINISHES ★ ALWAYS INCLUDED
A28: 3 | B28: 3.1 | C28: Wall finishes | D28: m² | E28: =IFERROR('Rates Reference Table'!F25*$E$5,0) -> 32.9 | F28: =IFERROR(E28*(1-$H$5/2),0) -> 29.281 | G28: =IFERROR(E28*(1+$H$5/2),0) -> 36.519 | H28: =IFERROR(F28*$B$5,0) -> 14640.5 | I28: =IFERROR(G28*$B$5,0) -> 18259.5 | J28: Emulsion (low) → specialist tiling/feature panelling (high)
A29: 3 | B29: 3.2 | C29: Floor finishes | D29: m² | E29: =IFERROR('Rates Reference Table'!F26*$E$5,0) -> 51.7 | F29: =IFERROR(E29*(1-$H$5/2),0) -> 46.013 | G29: =IFERROR(E29*(1+$H$5/2),0) -> 57.387 | H29: =IFERROR(F29*$B$5,0) -> 23006.5 | I29: =IFERROR(G29*$B$5,0) -> 28693.5 | J29: Vinyl/carpet (low) → stone/raised access floor (high)
A30: 3 | B30: 3.3 | C30: Ceiling finishes | D30: m² | E30: =IFERROR('Rates Reference Table'!F27*$E$5,0) -> 28.2 | F30: =IFERROR(E30*(1-$H$5/2),0) -> 25.098 | G30: =IFERROR(E30*(1+$H$5/2),0) -> 31.302 | H30: =IFERROR(F30*$B$5,0) -> 12549 | I30: =IFERROR(G30*$B$5,0) -> 15651 | J30: Emulsion (low) → bespoke acoustic ceiling system (high)
A31: GROUP 4 — FITTINGS, FURNISHINGS & EQUIPMENT
A32: 4 | B32: 4.1 | C32: General fittings & built-in joinery | D32: Item | E32: =IFERROR('Rates Reference Table'!F29*$E$5,0) -> 28.2 | F32: =IFERROR(E32*(1-$H$5/2),0) -> 25.098 | G32: =IFERROR(E32*(1+$H$5/2),0) -> 31.302 | H32: =IFERROR(F32*$B$5,0) -> 12549 | I32: =IFERROR(G32*$B$5,0) -> 15651 | J32: Reception desks, shelving, built-in furniture
A33: 4 | B33: 4.2 | C33: Sanitary fittings & toilet fit-out | D33: Nr | E33: =IFERROR('Rates Reference Table'!F30*$E$5,0) -> 16.92 | F33: =IFERROR(E33*(1-$H$5/2),0) -> 15.0588 | G33: =IFERROR(E33*(1+$H$5/2),0) -> 18.7812 | H33: =IFERROR(F33*$B$5,0) -> 7529.4 | I33: =IFERROR(G33*$B$5,0) -> 9390.6 | J33: WC packs; uplift for accessible/changing facilities
A34: 4 | B34: 4.3 | C34: Kitchen / break-out area | D34: Item | E34: =IFERROR('Rates Reference Table'!F31*$E$5,0) -> 14.1 | F34: =IFERROR(E34*(1-$H$5/2),0) -> 12.549 | G34: =IFERROR(E34*(1+$H$5/2),0) -> 15.651 | H34: =IFERROR(F34*$B$5,0) -> 6274.5 | I34: =IFERROR(G34*$B$5,0) -> 7825.5 | J34: Fitted units, worktops, appliances
A35: 4 | B35: 4.4 | C35: Specialist equipment (lab/AV/med) | D35: Item | E35: =IFERROR('Rates Reference Table'!F32*$E$5,0) -> 9.4 | F35: =IFERROR(E35*(1-$H$5/2),0) -> 8.366 | G35: =IFERROR(E35*(1+$H$5/2),0) -> 10.434 | H35: =IFERROR(F35*$B$5,0) -> 4183 | I35: =IFERROR(G35*$B$5,0) -> 5217 | J35: Laboratory, medical, AV; confirm with specialist
A36: GROUP 5 — MECHANICAL & ELECTRICAL SERVICES ★ KEY ELEMENT
A37: 5 | B37: 5.1 | C37: Sanitary plumbing (1st & 2nd fix) | D37: m² | E37: =IFERROR('Rates Reference Table'!F34*$E$5,0) -> 32.9 | F37: =IFERROR(E37*(1-$H$5/2),0) -> 29.281 | G37: =IFERROR(E37*(1+$H$5/2),0) -> 36.519 | H37: =IFERROR(F37*$B$5,0) -> 14640.5 | I37: =IFERROR(G37*$B$5,0) -> 18259.5 | J37: HWS, cold water, drainage connections
A38: 5 | B38: 5.2 | C38: Heating & hot water (LTHW/heat pump) | D38: m² | E38: =IFERROR('Rates Reference Table'!F35*$E$5,0) -> 47 | F38: =IFERROR(E38*(1-$H$5/2),0) -> 41.83 | G38: =IFERROR(E38*(1+$H$5/2),0) -> 52.17 | H38: =IFERROR(F38*$B$5,0) -> 20915 | I38: =IFERROR(G38*$B$5,0) -> 26085 | J38: LTHW system or heat pump; include buffer vessel
A39: 5 | B39: 5.3 | C39: Ventilation & air handling | D39: m² | E39: =IFERROR('Rates Reference Table'!F36*$E$5,0) -> 42.3 | F39: =IFERROR(E39*(1-$H$5/2),0) -> 37.647 | G39: =IFERROR(E39*(1+$H$5/2),0) -> 46.953 | H39: =IFERROR(F39*$B$5,0) -> 18823.5 | I39: =IFERROR(G39*$B$5,0) -> 23476.5 | J39: MVHR/AHU; uplift for lab/healthcare extract (+50-100%)
A40: 5 | B40: 5.4 | C40: Air conditioning & cooling | D40: m² | E40: =IFERROR('Rates Reference Table'!F37*$E$5,0) -> 28.2 | F40: =IFERROR(E40*(1-$H$5/2),0) -> 25.098 | G40: =IFERROR(E40*(1+$H$5/2),0) -> 31.302 | H40: =IFERROR(F40*$B$5,0) -> 12549 | I40: =IFERROR(G40*$B$5,0) -> 15651 | J40: VRF/splits; omit if not in scope
A41: 5 | B41: 5.5 | C41: Gas installation | D41: Item | E41: =IFERROR('Rates Reference Table'!F38*$E$5,0) -> 9.4 | F41: =IFERROR(E41*(1-$H$5/2),0) -> 8.366 | G41: =IFERROR(E41*(1+$H$5/2),0) -> 10.434 | H41: =IFERROR(F41*$B$5,0) -> 4183 | I41: =IFERROR(G41*$B$5,0) -> 5217 | J41: Omit if all-electric; confirm with utility
A42: 5 | B42: 5.6 | C42: Sprinkler / fire suppression | D42: m² | E42: =IFERROR('Rates Reference Table'!F39*$E$5,0) -> 14.1 | F42: =IFERROR(E42*(1-$H$5/2),0) -> 12.549 | G42: =IFERROR(E42*(1+$H$5/2),0) -> 15.651 | H42: =IFERROR(F42*$B$5,0) -> 6274.5 | I42: =IFERROR(G42*$B$5,0) -> 7825.5 | J42: >18m height or insurer requirement
A43: 5 | B43: 5.7 | C43: Electrical distribution & switchgear | D43: m² | E43: =IFERROR('Rates Reference Table'!F40*$E$5,0) -> 28.2 | F43: =IFERROR(E43*(1-$H$5/2),0) -> 25.098 | G43: =IFERROR(E43*(1+$H$5/2),0) -> 31.302 | H43: =IFERROR(F43*$B$5,0) -> 12549 | I43: =IFERROR(G43*$B$5,0) -> 15651 | J43: LV panels, distribution boards, earthing, containment
A44: 5 | B44: 5.8 | C44: Electrical wiring (1st & 2nd fix) | D44: m² | E44: =IFERROR('Rates Reference Table'!F41*$E$5,0) -> 37.6 | F44: =IFERROR(E44*(1-$H$5/2),0) -> 33.464 | G44: =IFERROR(E44*(1+$H$5/2),0) -> 41.736 | H44: =IFERROR(F44*$B$5,0) -> 16732 | I44: =IFERROR(G44*$B$5,0) -> 20868 | J44: All power and lighting circuits; inc containment
A45: 5 | B45: 5.9 | C45: Emergency lighting & fire alarm | D45: m² | E45: =IFERROR('Rates Reference Table'!F42*$E$5,0) -> 18.8 | F45: =IFERROR(E45*(1-$H$5/2),0) -> 16.732 | G45: =IFERROR(E45*(1+$H$5/2),0) -> 20.868 | H45: =IFERROR(F45*$B$5,0) -> 8366 | I45: =IFERROR(G45*$B$5,0) -> 10434 | J45: L2 minimum; upgrade for multi-zone/complex layouts
A46: 5 | B46: 5.10 | C46: External lighting | D46: Item | E46: =IFERROR('Rates Reference Table'!F43*$E$5,0) -> 4.7 | F46: =IFERROR(E46*(1-$H$5/2),0) -> 4.183 | G46: =IFERROR(E46*(1+$H$5/2),0) -> 5.217 | H46: =IFERROR(F46*$B$5,0) -> 2091.5 | I46: =IFERROR(G46*$B$5,0) -> 2608.5 | J46: Column/wall-mounted perimeter lighting
A47: 5 | B47: 5.11 | C47: Solar PV / renewables | D47: kWp | E47: =IFERROR('Rates Reference Table'!F44*$E$5,0) -> 752 | F47: =IFERROR(E47*(1-$H$5/2),0) -> 669.28 | G47: =IFERROR(E47*(1+$H$5/2),0) -> 834.72 | H47: =IFERROR(F47*$B$5,0) -> 334640 | I47: =IFERROR(G47*$B$5,0) -> 417360 | J47: £/kWp installed; coordinate structural loading + electrical
A48: 5 | B48: 5.12 | C48: EV charging points | D48: Nr | E48: =IFERROR('Rates Reference Table'!F45*$E$5,0) -> 1410 | F48: =IFERROR(E48*(1-$H$5/2),0) -> 1254.9 | G48: =IFERROR(E48*(1+$H$5/2),0) -> 1565.1 | H48: =IFERROR(F48*$B$5,0) -> 627450 | I48: =IFERROR(G48*$B$5,0) -> 782550 | J48: Per charge point inc groundworks; 7kW fast charger
... A53: 5 | B53: 5.17 | C53: Builder's work in connection (BWIC) | D53: m² | E53: =IFERROR('Rates Reference Table'!F50*$E$5,0) -> 11.28 | F53: =IFERROR(E53*(1-$H$5/2),0) -> 10.0392 | G53: =IFERROR(E53*(1+$H$5/2),0) -> 12.5208 | H53: =IFERROR(F53*$B$5,0) -> 5019.6 | I53: =IFERROR(G53*$B$5,0) -> 6260.4 | J53: Penetrations, plinths, ducts, concrete bases for plant
A54: GROUP 6 — PREFABRICATED / MODULAR (if applicable)
A55: 6 | B55: 6.1 | C55: Prefabricated / modular units | D55: Item | E55: EXCLUDED | F55: EXCLUDED | G55: EXCLUDED | H55: 0 | I55: 0 | J55: Factory-built modular; specialist quote required
A56: 6 | B56: 6.2 | C56: Pre-engineered systems (mezzanine) | D56: Item | E56: EXCLUDED | F56: EXCLUDED | G56: EXCLUDED | H56: 0 | I56: 0 | J56: Mezzanine floors, demountable partitions
A57: GROUP 7 — WORK TO EXISTING BUILDINGS
A58: 7 | B58: 7.1 | C58: Structural repairs | D58: Item | E58: =IFERROR('Rates Reference Table'!F55*$E$5,0) -> 23.5 | F58: =IFERROR(E58*(1-$H$5/2),0) -> 20.915 | G58: =IFERROR(E58*(1+$H$5/2),0) -> 26.085 | H58: =IFERROR(F58*$B$5,0) -> 10457.5 | I58: =IFERROR(G58*$B$5,0) -> 13042.5 | J58: Crack stitching, bearing repairs; increase for poor condition
A59: 7 | B59: 7.2 | C59: Fabric / envelope repairs | D59: Item | E59: =IFERROR('Rates Reference Table'!F56*$E$5,0) -> 18.8 | F59: =IFERROR(E59*(1-$H$5/2),0) -> 16.732 | G59: =IFERROR(E59*(1+$H$5/2),0) -> 20.868 | H59: =IFERROR(F59*$B$5,0) -> 8366 | I59: =IFERROR(G59*$B$5,0) -> 10434 | J59: Repointing, waterproofing, weathertight works
A60: 7 | B60: 7.3 | C60: Damp proof course treatment | D60: Item | E60: =IFERROR('Rates Reference Table'!F57*$E$5,0) -> 9.4 | F60: =IFERROR(E60*(1-$H$5/2),0) -> 8.366 | G60: =IFERROR(E60*(1+$H$5/2),0) -> 10.434 | H60: =IFERROR(F60*$B$5,0) -> 4183 | I60: =IFERROR(G60*$B$5,0) -> 5217 | J60: Chemical DPC; increase for severe rising damp
A61: 7 | B61: 7.4 | C61: M&E overhaul / life-expired services | D61: Item | E61: =IFERROR('Rates Reference Table'!F58*$E$5,0) -> 28.2 | F61: =IFERROR(E61*(1-$H$5/2),0) -> 25.098 | G61: =IFERROR(E61*(1+$H$5/2),0) -> 31.302 | H61: =IFERROR(F61*$B$5,0) -> 12549 | I61: =IFERROR(G61*$B$5,0) -> 15651 | J61: Replacement of end-of-life mechanical & electrical plant
A62: 7 | B62: 7.5 | C62: Making good after structural works | D62: Item | E62: =IFERROR('Rates Reference Table'!F59*$E$5,0) -> 9.4 | F62: =IFERROR(E62*(1-$H$5/2),0) -> 8.366 | G62: =IFERROR(E62*(1+$H$5/2),0) -> 10.434 | H62: =IFERROR(F62*$B$5,0) -> 4183 | I62: =IFERROR(G62*$B$5,0) -> 5217 | J62: Patch plaster, redecoration after structural alterations
A63: GROUP 8 — EXTERNAL WORKS
A64: 8 | B64: 8.1 | C64: Site preparation & clearance | D64: Item | E64: =IFERROR('Rates Reference Table'!F61*$E$5,0) -> 7.52 | F64: =IFERROR(E64*(1-$H$5/2),0) -> 6.6928 | G64: =IFERROR(E64*(1+$H$5/2),0) -> 8.3472 | H64: =IFERROR(F64*$B$5,0) -> 3346.4 | I64: =IFERROR(G64*$B$5,0) -> 4173.6 | J64: Strip topsoil, vegetation, temp fencing and hoarding
A65: 8 | B65: 8.2 | C65: Roads, paths & hard paving | D65: m² | E65: =IFERROR('Rates Reference Table'!F62*$E$5,0) -> 9.4 | F65: =IFERROR(E65*(1-$H$5/2),0) -> 8.366 | G65: =IFERROR(E65*(1+$H$5/2),0) -> 10.434 | H65: =IFERROR(F65*$B$5,0) -> 4183 | I65: =IFERROR(G65*$B$5,0) -> 5217 | J65: Macadam/block paving; inc edging and drainage channels
A66: 8 | B66: 8.3 | C66: Car parking (line-marked bays) | D66: Nr | E66: =IFERROR('Rates Reference Table'!F63*$E$5,0) -> 4.7 | F66: =IFERROR(E66*(1-$H$5/2),0) -> 4.183 | G66: =IFERROR(E66*(1+$H$5/2),0) -> 5.217 | H66: =IFERROR(F66*$B$5,0) -> 2091.5 | I66: =IFERROR(G66*$B$5,0) -> 2608.5 | J66: Surfacing, line markings, disabled bays
A67: 8 | B67: 8.4 | C67: Surface water drainage | D67: Item | E67: =IFERROR('Rates Reference Table'!F64*$E$5,0) -> 7.52 | F67: =IFERROR(E67*(1-$H$5/2),0) -> 6.6928 | G67: =IFERROR(E67*(1+$H$5/2),0) -> 8.3472 | H67: =IFERROR(F67*$B$5,0) -> 3346.4 | I67: =IFERROR(G67*$B$5,0) -> 4173.6 | J67: Gullies, pipes, SuDS if required by planning
A68: 8 | B68: 8.5 | C68: Foul drainage connections | D68: Item | E68: =IFERROR('Rates Reference Table'!F65*$E$5,0) -> 5.64 | F68: =IFERROR(E68*(1-$H$5/2),0) -> 5.0196 | G68: =IFERROR(E68*(1+$H$5/2),0) -> 6.2604 | H68: =IFERROR(F68*$B$5,0) -> 2509.8 | I68: =IFERROR(G68*$B$5,0) -> 3130.2 | J68: Connection to existing drain or new manhole
A69: 8 | B69: 8.6 | C69: External utility services | D69: Item | E69: =IFERROR('Rates Reference Table'!F66*$E$5,0) -> 7.52 | F69: =IFERROR(E69*(1-$H$5/2),0) -> 6.6928 | G69: =IFERROR(E69*(1+$H$5/2),0) -> 8.3472 | H69: =IFERROR(F69*$B$5,0) -> 3346.4 | I69: =IFERROR(G69*$B$5,0) -> 4173.6 | J69: Gas/water/electric diversions; early check with DNO
A70: 8 | B70: 8.7 | C70: Soft landscaping | D70: m² | E70: =IFERROR('Rates Reference Table'!F67*$E$5,0) -> 2.82 | F70: =IFERROR(E70*(1-$H$5/2),0) -> 2.5098 | G70: =IFERROR(E70*(1+$H$5/2),0) -> 3.1302 | H70: =IFERROR(F70*$B$5,0) -> 1254.9 | I70: =IFERROR(G70*$B$5,0) -> 1565.1 | J70: Planting, seeding, topsoil reinstatement
A71: 8 | B71: 8.8 | C71: Boundary enclosures (fences/gates) | D71: Item | E71: =IFERROR('Rates Reference Table'!F68*$E$5,0) -> 2.82 | F71: =IFERROR(E71*(1-$H$5/2),0) -> 2.5098 | G71: =IFERROR(E71*(1+$H$5/2),0) -> 3.1302 | H71: =IFERROR(F71*$B$5,0) -> 1254.9 | I71: =IFERROR(G71*$B$5,0) -> 1565.1 | J71: Security fencing, gates, boundary walls, railings
A72: 8 | B72: 8.9 | C72: External lighting | D72: Item | E72: =IFERROR('Rates Reference Table'!F69*$E$5,0) -> 1.88 | F72: =IFERROR(E72*(1-$H$5/2),0) -> 1.6732 | G72: =IFERROR(E72*(1+$H$5/2),0) -> 2.0868 | H72: =IFERROR(F72*$B$5,0) -> 836.6 | I72: =IFERROR(G72*$B$5,0) -> 1043.4 | J72: Column or wall-mounted lighting (see also 5.10)
A73: WORKS COST SUBTOTAL (Groups 0–8) | H73: =SUMPRODUCT((H8:H72>0)*H8:H72) -> 1459448.7 | I73: =SUMPRODUCT((I8:I72>0)*I8:I72) -> 1820211.3
A75: ADDITIONS TO WORKS COST — Adjust % using signal rules in Notes column
A76: Code | D76: Description | E76: Applied To | F76: Low % | G76: High % | H76: Total LOW (£) | I76: Total HIGH (£) | J76: Signal Rules / Notes
A77: A | D77: Contractor's Preliminaries | E77: Works Cost | F77: 0.08 | G77: 0.1 | H77: =IFERROR(F77*H73,0) -> 116755.9 | I77: =IFERROR(G77*I73,0) -> 182021.13 | J77: 8%=clean/vacant/short prog | +0.5% per: 6-18mo prog, partial occ, restricted access | cap 10%
A78: B | D78: Contractor's Overheads & Profit | E78: Works Cost | F78: 0.08 | G78: 0.12 | H78: =IFERROR(F78*H73,0) -> 116755.9 | I78: =IFERROR(G78*I73,0) -> 218425.36 | J78: >£5M→8-9% | £1-5M→9-10% | <£1M→10-12% | Lower end = cost priority; upper = D&B/speed
A79: CONSTRUCTION COST SUBTOTAL (Works + Prelims + OH&P) | H79: =H73+H77+H78 -> 1692960.5 | I79: =I73+I77+I78 -> 2220657.8
A80: C | D80: Professional Fees | E80: Construction Cost | F80: 0.05 | G80: 0.15 | H80: =IFERROR(F80*H79,0) -> 84648.025 | I80: =IFERROR(G80*I79,0) -> 333098.67 | J80: Stage 0-1→12-15% | Stage 2→10-13% | Stage 3→7-10% | Stage 4→5-7% | +1-2% M&E/struct/BREEAM
A81: D | D81: Dev & Project Costs | E81: Construction Cost | F81: 0.02 | G81: 0.04 | H81: =IFERROR(F81*H79,0) -> 33859.21 | I81: =IFERROR(G81*I79,0) -> 88826.311 | J81: Full planning→3-4% | LBC also→4% | Permitted dev→2% | +0.5% if no surveys yet
A82: E | D82: Risk Allowance | E82: Works Cost | F82: 0.05 | G82: 0.1 | H82: =IFERROR(F82*H73,0) -> 72972.435 | I82: =IFERROR(G82*I73,0) -> 182021.13 | J82: Baseline 5% | +2% no surveys | +1.5% asbestos/contamination | +1% structural concern | +1% hard deadline | cap 10%
A83: H | D83: Client Contingency [FIXED 5%] | E83: Works Cost | F83: 0.05 | G83: 0.05 | H83: =IFERROR(0.05*H73,0) -> 72972.435 | I83: =IFERROR(0.05*I73,0) -> 91010.565 | J83: FIXED at 5% — held by client, not released to contractor. Do not adjust.
A84: F | D84: Inflation Allowance | E84: Works Cost | F84: 0.02 | G84: 0.12 | H84: =IFERROR(F84*H73,0) -> 29188.974 | I84: =IFERROR(G84*I73,0) -> 218425.36 | J84: Component 1: tender delay (0-18mo=2-6%) + Component 2: construction mid-point (6-24mo=1-4%) | cap 12%
A85: TOTAL PROJECT COST (excl. VAT) | H85: =H79+H80+H81+H82+H83+H84 -> 1986601.6 | I85: =I79+I80+I81+I82+I83+I84 -> 3134039.8
A86: G | D86: VAT — reference only, NOT in total | E86: Project Total | F86: 0.2 | G86: 0.2 | H86: =IFERROR(0.2*H85,0) -> 397320.31 | I86: =IFERROR(0.2*I85,0) -> 626807.96 | J86: Recoverability must be confirmed with client Finance team. New build may attract zero-rating.
A88: Implied blended Works Cost rate — cross-check against BCIS benchmarks: | E88: =IFERROR(H73/$B$5,0) -> 2918.8974 | G88: =IFERROR(I73/$B$5,0) -> 3640.4226
A90: ⚠ DISCLAIMER: Indicative only — RIBA Stage 0–1 without measured quantities. Rates from Rates Reference Table, cross-referenced Q2 2026 market data. Must be reviewed by a Chartered QS before use in any business case or budget approval. LOW–HIGH range = mid-point ± 11% (default spread 22%). Update GIFA, BCIS factor and Spread as required.

Sheet Rfb – High Spec
A1: NRM1 ESTIMATE — REFURB / FIT-OUT — HIGH SPEC / SPECIALIST
A2: Spec level: Flagship, lab, healthcare or bespoke. Heavy M&E, specialist fit-out, feature finishes. | RIBA Stage 0–1 indicative only | Base date Q2 2026
A4: Project Type: | B4: Refurb / Fit-Out | D4: Spec Level: | E4: High Spec / Specialist | G4: Region: | H4: West Midlands
A5: GIFA (m²) ▼ update: | B5: 500 | D5: BCIS Location Factor ▼: | E5: 0.94 | G5: Spread ±% ▼: | H5: 0.22
A7: Grp | B7: Sub | C7: Element / Description | D7: Unit | E7: Mid-Point £/m² | F7: Low £/m² | G7: High £/m² | H7: Total LOW (£) | I7: Total HIGH (£) | J7: Notes / Rate Driver
A8: GROUP 0 — FACILITATING WORKS
A9: 0 | B9: 0.1 | C9: Toxic/hazardous material removal | D9: Item | E9: =IFERROR('Rates Reference Table'!G6*$E$5,0) -> 37.6 | F9: =IFERROR(E9*(1-$H$5/2),0) -> 33.464 | G9: =IFERROR(E9*(1+$H$5/2),0) -> 41.736 | H9: =IFERROR(F9*$B$5,0) -> 16732 | I9: =IFERROR(G9*$B$5,0) -> 20868 | J9: Asbestos; increase if confirmed present (refurb/demo only)
A10: 0 | B10: 0.2 | C10: Demolition & structural alterations | D10: Item | E10: =IFERROR('Rates Reference Table'!G7*$E$5,0) -> 51.7 | F10: =IFERROR(E10*(1-$H$5/2),0) -> 46.013 | G10: =IFERROR(E10*(1+$H$5/2),0) -> 57.387 | H10: =IFERROR(F10*$B$5,0) -> 23006.5 | I10: =IFERROR(G10*$B$5,0) -> 28693.5 | J10: Selective or full demolition; structural openings
A11: 0 | B11: 0.3 | C11: Contaminated land remediation | D11: Item | E11: =IFERROR('Rates Reference Table'!G8*$E$5,0) -> 18.8 | F11: =IFERROR(E11*(1-$H$5/2),0) -> 16.732 | G11: =IFERROR(E11*(1+$H$5/2),0) -> 20.868 | H11: =IFERROR(F11*$B$5,0) -> 8366 | I11: =IFERROR(G11*$B$5,0) -> 10434 | J11: Brownfield/contaminated; specialist quote needed
A12: 0 | B12: 0.4 | C12: Ground stabilisation | D12: Item | E12: =IFERROR('Rates Reference Table'!G9*$E$5,0) -> 14.1 | F12: =IFERROR(E12*(1-$H$5/2),0) -> 12.549 | G12: =IFERROR(E12*(1+$H$5/2),0) -> 15.651 | H12: =IFERROR(F12*$B$5,0) -> 6274.5 | I12: =IFERROR(G12*$B$5,0) -> 7825.5 | J12: Underpinning/piling if ground risk identified
A13: GROUP 1 — SUBSTRUCTURE
A14: 1 | B14: 1.1 | C14: Standard foundations (strip/pad) | D14: m² | E14: EXCLUDED | F14: EXCLUDED | G14: EXCLUDED | H14: 0 | I14: 0 | J14: New build only; included in Group 7 rate for extensions
A15: 1 | B15: 1.2 | C15: Specialist foundations (piled) | D15: m² | E15: EXCLUDED | F15: EXCLUDED | G15: EXCLUDED | H15: 0 | I15: 0 | J15: Poor ground conditions; trigger from GI report
A16: 1 | B16: 1.3 | C16: Lowest floor construction (slab) | D16: m² | E16: EXCLUDED | F16: EXCLUDED | G16: EXCLUDED | H16: 0 | I16: 0 | J16: Ground bearing or suspended; inc DPM and insulation
A17: 1 | B17: 1.4 | C17: Basement excavation & structure | D17: Item | E17: EXCLUDED | F17: EXCLUDED | G17: EXCLUDED | H17: 0 | I17: 0 | J17: High uncertainty; specialist estimate recommended
A18: GROUP 2 — SUPERSTRUCTURE
A19: 2 | B19: 2.1 | C19: Structural frame | D19: m² | E19: =IFERROR('Rates Reference Table'!G16*$E$5,0) -> 37.6 | F19: =IFERROR(E19*(1-$H$5/2),0) -> 33.464 | G19: =IFERROR(E19*(1+$H$5/2),0) -> 41.736 | H19: =IFERROR(F19*$B$5,0) -> 16732 | I19: =IFERROR(G19*$B$5,0) -> 20868 | J19: Steel/concrete/timber; new build or major extensions only
A20: 2 | B20: 2.2 | C20: Upper floors | D20: m² | E20: =IFERROR('Rates Reference Table'!G17*$E$5,0) -> 28.2 | F20: =IFERROR(E20*(1-$H$5/2),0) -> 25.098 | G20: =IFERROR(E20*(1+$H$5/2),0) -> 31.302 | H20: =IFERROR(F20*$B$5,0) -> 12549 | I20: =IFERROR(G20*$B$5,0) -> 15651 | J20: New build or added floors; inc topping and insulation
A21: 2 | B21: 2.3 | C21: Roof structure & covering | D21: m² | E21: =IFERROR('Rates Reference Table'!G18*$E$5,0) -> 84.6 | F21: =IFERROR(E21*(1-$H$5/2),0) -> 75.294 | G21: =IFERROR(E21*(1+$H$5/2),0) -> 93.906 | H21: =IFERROR(F21*$B$5,0) -> 37647 | I21: =IFERROR(G21*$B$5,0) -> 46953 | J21: New or replacement; inc insulation, waterproofing, rainwater
A22: 2 | B22: 2.4 | C22: Stairs & ramps | D22: Item | E22: =IFERROR('Rates Reference Table'!G19*$E$5,0) -> 23.5 | F22: =IFERROR(E22*(1-$H$5/2),0) -> 20.915 | G22: =IFERROR(E22*(1+$H$5/2),0) -> 26.085 | H22: =IFERROR(F22*$B$5,0) -> 10457.5 | I22: =IFERROR(G22*$B$5,0) -> 13042.5 | J22: RC, steel or timber; accessibility ramps
A23: 2 | B23: 2.5 | C23: External walls & facade | D23: m² | E23: =IFERROR('Rates Reference Table'!G20*$E$5,0) -> 103.4 | F23: =IFERROR(E23*(1-$H$5/2),0) -> 92.026 | G23: =IFERROR(E23*(1+$H$5/2),0) -> 114.774 | H23: =IFERROR(F23*$B$5,0) -> 46013 | I23: =IFERROR(G23*$B$5,0) -> 57387 | J23: Masonry/cladding; refurb = overcladding or repair only
A24: 2 | B24: 2.6 | C24: Windows & external doors | D24: m² | E24: =IFERROR('Rates Reference Table'!G21*$E$5,0) -> 188 | F24: =IFERROR(E24*(1-$H$5/2),0) -> 167.32 | G24: =IFERROR(E24*(1+$H$5/2),0) -> 208.68 | H24: =IFERROR(F24*$B$5,0) -> 83660 | I24: =IFERROR(G24*$B$5,0) -> 104340 | J24: uPVC (low) to aluminium curtain wall (high)
A25: 2 | B25: 2.7 | C25: Internal walls & partitions | D25: m² | E25: =IFERROR('Rates Reference Table'!G22*$E$5,0) -> 56.4 | F25: =IFERROR(E25*(1-$H$5/2),0) -> 50.196 | G25: =IFERROR(E25*(1+$H$5/2),0) -> 62.604 | H25: =IFERROR(F25*$B$5,0) -> 25098 | I25: =IFERROR(G25*$B$5,0) -> 31302 | J25: Blockwork, drywall or glazed; do not double-count Grp 3
A26: 2 | B26: 2.8 | C26: Internal doors & ironmongery | D26: Nr | E26: =IFERROR('Rates Reference Table'!G23*$E$5,0) -> 37.6 | F26: =IFERROR(E26*(1-$H$5/2),0) -> 33.464 | G26: =IFERROR(E26*(1+$H$5/2),0) -> 41.736 | H26: =IFERROR(F26*$B$5,0) -> 16732 | I26: =IFERROR(G26*$B$5,0) -> 20868 | J26: Fire-rated at upper range; standard at lower
A27: GROUP 3 — INTERNAL FINISHES ★ ALWAYS INCLUDED
A28: 3 | B28: 3.1 | C28: Wall finishes | D28: m² | E28: =IFERROR('Rates Reference Table'!G25*$E$5,0) -> 70.5 | F28: =IFERROR(E28*(1-$H$5/2),0) -> 62.745 | G28: =IFERROR(E28*(1+$H$5/2),0) -> 78.255 | H28: =IFERROR(F28*$B$5,0) -> 31372.5 | I28: =IFERROR(G28*$B$5,0) -> 39127.5 | J28: Emulsion (low) → specialist tiling/feature panelling (high)
A29: 3 | B29: 3.2 | C29: Floor finishes | D29: m² | E29: =IFERROR('Rates Reference Table'!G26*$E$5,0) -> 122.2 | F29: =IFERROR(E29*(1-$H$5/2),0) -> 108.758 | G29: =IFERROR(E29*(1+$H$5/2),0) -> 135.642 | H29: =IFERROR(F29*$B$5,0) -> 54379 | I29: =IFERROR(G29*$B$5,0) -> 67821 | J29: Vinyl/carpet (low) → stone/raised access floor (high)
A30: 3 | B30: 3.3 | C30: Ceiling finishes | D30: m² | E30: =IFERROR('Rates Reference Table'!G27*$E$5,0) -> 61.1 | F30: =IFERROR(E30*(1-$H$5/2),0) -> 54.379 | G30: =IFERROR(E30*(1+$H$5/2),0) -> 67.821 | H30: =IFERROR(F30*$B$5,0) -> 27189.5 | I30: =IFERROR(G30*$B$5,0) -> 33910.5 | J30: Emulsion (low) → bespoke acoustic ceiling system (high)
A31: GROUP 4 — FITTINGS, FURNISHINGS & EQUIPMENT
A32: 4 | B32: 4.1 | C32: General fittings & built-in joinery | D32: Item | E32: =IFERROR('Rates Reference Table'!G29*$E$5,0) -> 75.2 | F32: =IFERROR(E32*(1-$H$5/2),0) -> 66.928 | G32: =IFERROR(E32*(1+$H$5/2),0) -> 83.472 | H32: =IFERROR(F32*$B$5,0) -> 33464 | I32: =IFERROR(G32*$B$5,0) -> 41736 | J32: Reception desks, shelving, built-in furniture
A33: 4 | B33: 4.2 | C33: Sanitary fittings & toilet fit-out | D33: Nr | E33: =IFERROR('Rates Reference Table'!G30*$E$5,0) -> 32.9 | F33: =IFERROR(E33*(1-$H$5/2),0) -> 29.281 | G33: =IFERROR(E33*(1+$H$5/2),0) -> 36.519 | H33: =IFERROR(F33*$B$5,0) -> 14640.5 | I33: =IFERROR(G33*$B$5,0) -> 18259.5 | J33: WC packs; uplift for accessible/changing facilities
A34: 4 | B34: 4.3 | C34: Kitchen / break-out area | D34: Item | E34: =IFERROR('Rates Reference Table'!G31*$E$5,0) -> 32.9 | F34: =IFERROR(E34*(1-$H$5/2),0) -> 29.281 | G34: =IFERROR(E34*(1+$H$5/2),0) -> 36.519 | H34: =IFERROR(F34*$B$5,0) -> 14640.5 | I34: =IFERROR(G34*$B$5,0) -> 18259.5 | J34: Fitted units, worktops, appliances
A35: 4 | B35: 4.4 | C35: Specialist equipment (lab/AV/med) | D35: Item | E35: =IFERROR('Rates Reference Table'!G32*$E$5,0) -> 75.2 | F35: =IFERROR(E35*(1-$H$5/2),0) -> 66.928 | G35: =IFERROR(E35*(1+$H$5/2),0) -> 83.472 | H35: =IFERROR(F35*$B$5,0) -> 33464 | I35: =IFERROR(G35*$B$5,0) -> 41736 | J35: Laboratory, medical, AV; confirm with specialist
A36: GROUP 5 — MECHANICAL & ELECTRICAL SERVICES ★ KEY ELEMENT
A37: 5 | B37: 5.1 | C37: Sanitary plumbing (1st & 2nd fix) | D37: m² | E37: =IFERROR('Rates Reference Table'!G34*$E$5,0) -> 61.1 | F37: =IFERROR(E37*(1-$H$5/2),0) -> 54.379 | G37: =IFERROR(E37*(1+$H$5/2),0) -> 67.821 | H37: =IFERROR(F37*$B$5,0) -> 27189.5 | I37: =IFERROR(G37*$B$5,0) -> 33910.5 | J37: HWS, cold water, drainage connections
A38: 5 | B38: 5.2 | C38: Heating & hot water (LTHW/heat pump) | D38: m² | E38: =IFERROR('Rates Reference Table'!G35*$E$5,0) -> 84.6 | F38: =IFERROR(E38*(1-$H$5/2),0) -> 75.294 | G38: =IFERROR(E38*(1+$H$5/2),0) -> 93.906 | H38: =IFERROR(F38*$B$5,0) -> 37647 | I38: =IFERROR(G38*$B$5,0) -> 46953 | J38: LTHW system or heat pump; include buffer vessel
A39: 5 | B39: 5.3 | C39: Ventilation & air handling | D39: m² | E39: =IFERROR('Rates Reference Table'!G36*$E$5,0) -> 84.6 | F39: =IFERROR(E39*(1-$H$5/2),0) -> 75.294 | G39: =IFERROR(E39*(1+$H$5/2),0) -> 93.906 | H39: =IFERROR(F39*$B$5,0) -> 37647 | I39: =IFERROR(G39*$B$5,0) -> 46953 | J39: MVHR/AHU; uplift for lab/healthcare extract (+50-100%)
A40: 5 | B40: 5.4 | C40: Air conditioning & cooling | D40: m² | E40: =IFERROR('Rates Reference Table'!G37*$E$5,0) -> 65.8 | F40: =IFERROR(E40*(1-$H$5/2),0) -> 58.562 | G40: =IFERROR(E40*(1+$H$5/2),0) -> 73.038 | H40: =IFERROR(F40*$B$5,0) -> 29281 | I40: =IFERROR(G40*$B$5,0) -> 36519 | J40: VRF/splits; omit if not in scope
A41: 5 | B41: 5.5 | C41: Gas installation | D41: Item | E41: =IFERROR('Rates Reference Table'!G38*$E$5,0) -> 14.1 | F41: =IFERROR(E41*(1-$H$5/2),0) -> 12.549 | G41: =IFERROR(E41*(1+$H$5/2),0) -> 15.651 | H41: =IFERROR(F41*$B$5,0) -> 6274.5 | I41: =IFERROR(G41*$B$5,0) -> 7825.5 | J41: Omit if all-electric; confirm with utility
A42: 5 | B42: 5.6 | C42: Sprinkler / fire suppression | D42: m² | E42: =IFERROR('Rates Reference Table'!G39*$E$5,0) -> 28.2 | F42: =IFERROR(E42*(1-$H$5/2),0) -> 25.098 | G42: =IFERROR(E42*(1+$H$5/2),0) -> 31.302 | H42: =IFERROR(F42*$B$5,0) -> 12549 | I42: =IFERROR(G42*$B$5,0) -> 15651 | J42: >18m height or insurer requirement
A43: 5 | B43: 5.7 | C43: Electrical distribution & switchgear | D43: m² | E43: =IFERROR('Rates Reference Table'!G40*$E$5,0) -> 51.7 | F43: =IFERROR(E43*(1-$H$5/2),0) -> 46.013 | G43: =IFERROR(E43*(1+$H$5/2),0) -> 57.387 | H43: =IFERROR(F43*$B$5,0) -> 23006.5 | I43: =IFERROR(G43*$B$5,0) -> 28693.5 | J43: LV panels, distribution boards, earthing, containment
A44: 5 | B44: 5.8 | C44: Electrical wiring (1st & 2nd fix) | D44: m² | E44: =IFERROR('Rates Reference Table'!G41*$E$5,0) -> 70.5 | F44: =IFERROR(E44*(1-$H$5/2),0) -> 62.745 | G44: =IFERROR(E44*(1+$H$5/2),0) -> 78.255 | H44: =IFERROR(F44*$B$5,0) -> 31372.5 | I44: =IFERROR(G44*$B$5,0) -> 39127.5 | J44: All power and lighting circuits; inc containment
A45: 5 | B45: 5.9 | C45: Emergency lighting & fire alarm | D45: m² | E45: =IFERROR('Rates Reference Table'!G42*$E$5,0) -> 32.9 | F45: =IFERROR(E45*(1-$H$5/2),0) -> 29.281 | G45: =IFERROR(E45*(1+$H$5/2),0) -> 36.519 | H45: =IFERROR(F45*$B$5,0) -> 14640.5 | I45: =IFERROR(G45*$B$5,0) -> 18259.5 | J45: L2 minimum; upgrade for multi-zone/complex layouts
A46: 5 | B46: 5.10 | C46: External lighting | D46: Item | E46: =IFERROR('Rates Reference Table'!G43*$E$5,0) -> 9.4 | F46: =IFERROR(E46*(1-$H$5/2),0) -> 8.366 | G46: =IFERROR(E46*(1+$H$5/2),0) -> 10.434 | H46: =IFERROR(F46*$B$5,0) -> 4183 | I46: =IFERROR(G46*$B$5,0) -> 5217 | J46: Column/wall-mounted perimeter lighting
A47: 5 | B47: 5.11 | C47: Solar PV / renewables | D47: kWp | E47: =IFERROR('Rates Reference Table'!G44*$E$5,0) -> 1128 | F47: =IFERROR(E47*(1-$H$5/2),0) -> 1003.92 | G47: =IFERROR(E47*(1+$H$5/2),0) -> 1252.08 | H47: =IFERROR(F47*$B$5,0) -> 501960 | I47: =IFERROR(G47*$B$5,0) -> 626040 | J47: £/kWp installed; coordinate structural loading + electrical
A48: 5 | B48: 5.12 | C48: EV charging points | D48: Nr | E48: =IFERROR('Rates Reference Table'!G45*$E$5,0) -> 2350 | F48: =IFERROR(E48*(1-$H$5/2),0) -> 2091.5 | G48: =IFERROR(E48*(1+$H$5/2),0) -> 2608.5 | H48: =IFERROR(F48*$B$5,0) -> 1045750 | I48: =IFERROR(G48*$B$5,0) -> 1304250 | J48: Per charge point inc groundworks; 7kW fast charger
... A53: 5 | B53: 5.17 | C53: Builder's work in connection (BWIC) | D53: m² | E53: =IFERROR('Rates Reference Table'!G50*$E$5,0) -> 20.68 | F53: =IFERROR(E53*(1-$H$5/2),0) -> 18.4052 | G53: =IFERROR(E53*(1+$H$5/2),0) -> 22.9548 | H53: =IFERROR(F53*$B$5,0) -> 9202.6 | I53: =IFERROR(G53*$B$5,0) -> 11477.4 | J53: Penetrations, plinths, ducts, concrete bases for plant
A54: GROUP 6 — PREFABRICATED / MODULAR (if applicable)
A55: 6 | B55: 6.1 | C55: Prefabricated / modular units | D55: Item | E55: EXCLUDED | F55: EXCLUDED | G55: EXCLUDED | H55: 0 | I55: 0 | J55: Factory-built modular; specialist quote required
A56: 6 | B56: 6.2 | C56: Pre-engineered systems (mezzanine) | D56: Item | E56: EXCLUDED | F56: EXCLUDED | G56: EXCLUDED | H56: 0 | I56: 0 | J56: Mezzanine floors, demountable partitions
A57: GROUP 7 — WORK TO EXISTING BUILDINGS
A58: 7 | B58: 7.1 | C58: Structural repairs | D58: Item | E58: =IFERROR('Rates Reference Table'!G55*$E$5,0) -> 51.7 | F58: =IFERROR(E58*(1-$H$5/2),0) -> 46.013 | G58: =IFERROR(E58*(1+$H$5/2),0) -> 57.387 | H58: =IFERROR(F58*$B$5,0) -> 23006.5 | I58: =IFERROR(G58*$B$5,0) -> 28693.5 | J58: Crack stitching, bearing repairs; increase for poor condition
A59: 7 | B59: 7.2 | C59: Fabric / envelope repairs | D59: Item | E59: =IFERROR('Rates Reference Table'!G56*$E$5,0) -> 42.3 | F59: =IFERROR(E59*(1-$H$5/2),0) -> 37.647 | G59: =IFERROR(E59*(1+$H$5/2),0) -> 46.953 | H59: =IFERROR(F59*$B$5,0) -> 18823.5 | I59: =IFERROR(G59*$B$5,0) -> 23476.5 | J59: Repointing, waterproofing, weathertight works
A60: 7 | B60: 7.3 | C60: Damp proof course treatment | D60: Item | E60: =IFERROR('Rates Reference Table'!G57*$E$5,0) -> 18.8 | F60: =IFERROR(E60*(1-$H$5/2),0) -> 16.732 | G60: =IFERROR(E60*(1+$H$5/2),0) -> 20.868 | H60: =IFERROR(F60*$B$5,0) -> 8366 | I60: =IFERROR(G60*$B$5,0) -> 10434 | J60: Chemical DPC; increase for severe rising damp
A61: 7 | B61: 7.4 | C61: M&E overhaul / life-expired services | D61: Item | E61: =IFERROR('Rates Reference Table'!G58*$E$5,0) -> 75.2 | F61: =IFERROR(E61*(1-$H$5/2),0) -> 66.928 | G61: =IFERROR(E61*(1+$H$5/2),0) -> 83.472 | H61: =IFERROR(F61*$B$5,0) -> 33464 | I61: =IFERROR(G61*$B$5,0) -> 41736 | J61: Replacement of end-of-life mechanical & electrical plant
A62: 7 | B62: 7.5 | C62: Making good after structural works | D62: Item | E62: =IFERROR('Rates Reference Table'!G59*$E$5,0) -> 18.8 | F62: =IFERROR(E62*(1-$H$5/2),0) -> 16.732 | G62: =IFERROR(E62*(1+$H$5/2),0) -> 20.868 | H62: =IFERROR(F62*$B$5,0) -> 8366 | I62: =IFERROR(G62*$B$5,0) -> 10434 | J62: Patch plaster, redecoration after structural alterations
A63: GROUP 8 — EXTERNAL WORKS
A64: 8 | B64: 8.1 | C64: Site preparation & clearance | D64: Item | E64: =IFERROR('Rates Reference Table'!G61*$E$5,0) -> 14.1 | F64: =IFERROR(E64*(1-$H$5/2),0) -> 12.549 | G64: =IFERROR(E64*(1+$H$5/2),0) -> 15.651 | H64: =IFERROR(F64*$B$5,0) -> 6274.5 | I64: =IFERROR(G64*$B$5,0) -> 7825.5 | J64: Strip topsoil, vegetation, temp fencing and hoarding
A65: 8 | B65: 8.2 | C65: Roads, paths & hard paving | D65: m² | E65: =IFERROR('Rates Reference Table'!G62*$E$5,0) -> 18.8 | F65: =IFERROR(E65*(1-$H$5/2),0) -> 16.732 | G65: =IFERROR(E65*(1+$H$5/2),0) -> 20.868 | H65: =IFERROR(F65*$B$5,0) -> 8366 | I65: =IFERROR(G65*$B$5,0) -> 10434 | J65: Macadam/block paving; inc edging and drainage channels
A66: 8 | B66: 8.3 | C66: Car parking (line-marked bays) | D66: Nr | E66: =IFERROR('Rates Reference Table'!G63*$E$5,0) -> 9.4 | F66: =IFERROR(E66*(1-$H$5/2),0) -> 8.366 | G66: =IFERROR(E66*(1+$H$5/2),0) -> 10.434 | H66: =IFERROR(F66*$B$5,0) -> 4183 | I66: =IFERROR(G66*$B$5,0) -> 5217 | J66: Surfacing, line markings, disabled bays
A67: 8 | B67: 8.4 | C67: Surface water drainage | D67: Item | E67: =IFERROR('Rates Reference Table'!G64*$E$5,0) -> 14.1 | F67: =IFERROR(E67*(1-$H$5/2),0) -> 12.549 | G67: =IFERROR(E67*(1+$H$5/2),0) -> 15.651 | H67: =IFERROR(F67*$B$5,0) -> 6274.5 | I67: =IFERROR(G67*$B$5,0) -> 7825.5 | J67: Gullies, pipes, SuDS if required by planning
A68: 8 | B68: 8.5 | C68: Foul drainage connections | D68: Item | E68: =IFERROR('Rates Reference Table'!G65*$E$5,0) -> 11.28 | F68: =IFERROR(E68*(1-$H$5/2),0) -> 10.0392 | G68: =IFERROR(E68*(1+$H$5/2),0) -> 12.5208 | H68: =IFERROR(F68*$B$5,0) -> 5019.6 | I68: =IFERROR(G68*$B$5,0) -> 6260.4 | J68: Connection to existing drain or new manhole
A69: 8 | B69: 8.6 | C69: External utility services | D69: Item | E69: =IFERROR('Rates Reference Table'!G66*$E$5,0) -> 14.1 | F69: =IFERROR(E69*(1-$H$5/2),0) -> 12.549 | G69: =IFERROR(E69*(1+$H$5/2),0) -> 15.651 | H69: =IFERROR(F69*$B$5,0) -> 6274.5 | I69: =IFERROR(G69*$B$5,0) -> 7825.5 | J69: Gas/water/electric diversions; early check with DNO
A70: 8 | B70: 8.7 | C70: Soft landscaping | D70: m² | E70: =IFERROR('Rates Reference Table'!G67*$E$5,0) -> 7.52 | F70: =IFERROR(E70*(1-$H$5/2),0) -> 6.6928 | G70: =IFERROR(E70*(1+$H$5/2),0) -> 8.3472 | H70: =IFERROR(F70*$B$5,0) -> 3346.4 | I70: =IFERROR(G70*$B$5,0) -> 4173.6 | J70: Planting, seeding, topsoil reinstatement
A71: 8 | B71: 8.8 | C71: Boundary enclosures (fences/gates) | D71: Item | E71: =IFERROR('Rates Reference Table'!G68*$E$5,0) -> 7.52 | F71: =IFERROR(E71*(1-$H$5/2),0) -> 6.6928 | G71: =IFERROR(E71*(1+$H$5/2),0) -> 8.3472 | H71: =IFERROR(F71*$B$5,0) -> 3346.4 | I71: =IFERROR(G71*$B$5,0) -> 4173.6 | J71: Security fencing, gates, boundary walls, railings
A72: 8 | B72: 8.9 | C72: External lighting | D72: Item | E72: =IFERROR('Rates Reference Table'!G69*$E$5,0) -> 4.7 | F72: =IFERROR(E72*(1-$H$5/2),0) -> 4.183 | G72: =IFERROR(E72*(1+$H$5/2),0) -> 5.217 | H72: =IFERROR(F72*$B$5,0) -> 2091.5 | I72: =IFERROR(G72*$B$5,0) -> 2608.5 | J72: Column or wall-mounted lighting (see also 5.10)
A73: WORKS COST SUBTOTAL (Groups 0–8) | H73: =SUMPRODUCT((H8:H72>0)*H8:H72) -> 2528623.5 | I73: =SUMPRODUCT((I8:I72>0)*I8:I72) -> 3153676.5
A75: ADDITIONS TO WORKS COST — Adjust % using signal rules in Notes column
A76: Code | D76: Description | E76: Applied To | F76: Low % | G76: High % | H76: Total LOW (£) | I76: Total HIGH (£) | J76: Signal Rules / Notes
A77: A | D77: Contractor's Preliminaries | E77: Works Cost | F77: 0.08 | G77: 0.1 | H77: =IFERROR(F77*H73,0) -> 202289.88 | I77: =IFERROR(G77*I73,0) -> 315367.65 | J77: 8%=clean/vacant/short prog | +0.5% per: 6-18mo prog, partial occ, restricted access | cap 10%
A78: B | D78: Contractor's Overheads & Profit | E78: Works Cost | F78: 0.08 | G78: 0.12 | H78: =IFERROR(F78*H73,0) -> 202289.88 | I78: =IFERROR(G78*I73,0) -> 378441.18 | J78: >£5M→8-9% | £1-5M→9-10% | <£1M→10-12% | Lower end = cost priority; upper = D&B/speed
A79: CONSTRUCTION COST SUBTOTAL (Works + Prelims + OH&P) | H79: =H73+H77+H78 -> 2933203.3 | I79: =I73+I77+I78 -> 3847485.3
A80: C | D80: Professional Fees | E80: Construction Cost | F80: 0.05 | G80: 0.15 | H80: =IFERROR(F80*H79,0) -> 146660.16 | I80: =IFERROR(G80*I79,0) -> 577122.8 | J80: Stage 0-1→12-15% | Stage 2→10-13% | Stage 3→7-10% | Stage 4→5-7% | +1-2% M&E/struct/BREEAM
A81: D | D81: Dev & Project Costs | E81: Construction Cost | F81: 0.02 | G81: 0.04 | H81: =IFERROR(F81*H79,0) -> 58664.065 | I81: =IFERROR(G81*I79,0) -> 153899.41 | J81: Full planning→3-4% | LBC also→4% | Permitted dev→2% | +0.5% if no surveys yet
A82: E | D82: Risk Allowance | E82: Works Cost | F82: 0.05 | G82: 0.1 | H82: =IFERROR(F82*H73,0) -> 126431.18 | I82: =IFERROR(G82*I73,0) -> 315367.65 | J82: Baseline 5% | +2% no surveys | +1.5% asbestos/contamination | +1% structural concern | +1% hard deadline | cap 10%
A83: H | D83: Client Contingency [FIXED 5%] | E83: Works Cost | F83: 0.05 | G83: 0.05 | H83: =IFERROR(0.05*H73,0) -> 126431.18 | I83: =IFERROR(0.05*I73,0) -> 157683.83 | J83: FIXED at 5% — held by client, not released to contractor. Do not adjust.
A84: F | D84: Inflation Allowance | E84: Works Cost | F84: 0.02 | G84: 0.12 | H84: =IFERROR(F84*H73,0) -> 50572.47 | I84: =IFERROR(G84*I73,0) -> 378441.18 | J84: Component 1: tender delay (0-18mo=2-6%) + Component 2: construction mid-point (6-24mo=1-4%) | cap 12%
A85: TOTAL PROJECT COST (excl. VAT) | H85: =H79+H80+H81+H82+H83+H84 -> 3441962.3 | I85: =I79+I80+I81+I82+I83+I84 -> 5430000.2
A86: G | D86: VAT — reference only, NOT in total | E86: Project Total | F86: 0.2 | G86: 0.2 | H86: =IFERROR(0.2*H85,0) -> 688392.46 | I86: =IFERROR(0.2*I85,0) -> 1086000 | J86: Recoverability must be confirmed with client Finance team. New build may attract zero-rating.
A88: Implied blended Works Cost rate — cross-check against BCIS benchmarks: | E88: =IFERROR(H73/$B$5,0) -> 5057.247 | G88: =IFERROR(I73/$B$5,0) -> 6307.353
A90: ⚠ DISCLAIMER: Indicative only — RIBA Stage 0–1 without measured quantities. Rates from Rates Reference Table, cross-referenced Q2 2026 market data. Must be reviewed by a Chartered QS before use in any business case or budget approval. LOW–HIGH range = mid-point ± 11% (default spread 22%). Update GIFA, BCIS factor and Spread as required.

Sheet NB – Standard
A1: NRM1 ESTIMATE — NEW BUILD — STANDARD
A2: Spec level: Standard commercial/education new build. Conventional construction, standard M&E. | RIBA Stage 0–1 indicative only | Base date Q2 2026
A4: Project Type: | B4: New Build | D4: Spec Level: | E4: Standard | G4: Region: | H4: West Midlands
A5: GIFA (m²) ▼ update: | B5: 500 | D5: BCIS Location Factor ▼: | E5: 0.94 | G5: Spread ±% ▼: | H5: 0.22
A7: Grp | B7: Sub | C7: Element / Description | D7: Unit | E7: Mid-Point £/m² | F7: Low £/m² | G7: High £/m² | H7: Total LOW (£) | I7: Total HIGH (£) | J7: Notes / Rate Driver
A8: GROUP 0 — FACILITATING WORKS
A9: 0 | B9: 0.1 | C9: Toxic/hazardous material removal | D9: Item | E9: =IFERROR('Rates Reference Table'!H6*$E$5,0) -> 9.4 | F9: =IFERROR(E9*(1-$H$5/2),0) -> 8.366 | G9: =IFERROR(E9*(1+$H$5/2),0) -> 10.434 | H9: =IFERROR(F9*$B$5,0) -> 4183 | I9: =IFERROR(G9*$B$5,0) -> 5217 | J9: Asbestos; increase if confirmed present (refurb/demo only)
A10: 0 | B10: 0.2 | C10: Demolition & structural alterations | D10: Item | E10: =IFERROR('Rates Reference Table'!H7*$E$5,0) -> 14.1 | F10: =IFERROR(E10*(1-$H$5/2),0) -> 12.549 | G10: =IFERROR(E10*(1+$H$5/2),0) -> 15.651 | H10: =IFERROR(F10*$B$5,0) -> 6274.5 | I10: =IFERROR(G10*$B$5,0) -> 7825.5 | J10: Selective or full demolition; structural openings
A11: 0 | B11: 0.3 | C11: Contaminated land remediation | D11: Item | E11: =IFERROR('Rates Reference Table'!H8*$E$5,0) -> 9.4 | F11: =IFERROR(E11*(1-$H$5/2),0) -> 8.366 | G11: =IFERROR(E11*(1+$H$5/2),0) -> 10.434 | H11: =IFERROR(F11*$B$5,0) -> 4183 | I11: =IFERROR(G11*$B$5,0) -> 5217 | J11: Brownfield/contaminated; specialist quote needed
A12: 0 | B12: 0.4 | C12: Ground stabilisation | D12: Item | E12: =IFERROR('Rates Reference Table'!H9*$E$5,0) -> 7.52 | F12: =IFERROR(E12*(1-$H$5/2),0) -> 6.6928 | G12: =IFERROR(E12*(1+$H$5/2),0) -> 8.3472 | H12: =IFERROR(F12*$B$5,0) -> 3346.4 | I12: =IFERROR(G12*$B$5,0) -> 4173.6 | J12: Underpinning/piling if ground risk identified
A13: GROUP 1 — SUBSTRUCTURE
A14: 1 | B14: 1.1 | C14: Standard foundations (strip/pad) | D14: m² | E14: =IFERROR('Rates Reference Table'!H11*$E$5,0) -> 51.7 | F14: =IFERROR(E14*(1-$H$5/2),0) -> 46.013 | G14: =IFERROR(E14*(1+$H$5/2),0) -> 57.387 | H14: =IFERROR(F14*$B$5,0) -> 23006.5 | I14: =IFERROR(G14*$B$5,0) -> 28693.5 | J14: New build only; included in Group 7 rate for extensions
A15: 1 | B15: 1.2 | C15: Specialist foundations (piled) | D15: m² | E15: =IFERROR('Rates Reference Table'!H12*$E$5,0) -> 37.6 | F15: =IFERROR(E15*(1-$H$5/2),0) -> 33.464 | G15: =IFERROR(E15*(1+$H$5/2),0) -> 41.736 | H15: =IFERROR(F15*$B$5,0) -> 16732 | I15: =IFERROR(G15*$B$5,0) -> 20868 | J15: Poor ground conditions; trigger from GI report
A16: 1 | B16: 1.3 | C16: Lowest floor construction (slab) | D16: m² | E16: =IFERROR('Rates Reference Table'!H13*$E$5,0) -> 32.9 | F16: =IFERROR(E16*(1-$H$5/2),0) -> 29.281 | G16: =IFERROR(E16*(1+$H$5/2),0) -> 36.519 | H16: =IFERROR(F16*$B$5,0) -> 14640.5 | I16: =IFERROR(G16*$B$5,0) -> 18259.5 | J16: Ground bearing or suspended; inc DPM and insulation
A17: 1 | B17: 1.4 | C17: Basement excavation & structure | D17: Item | E17: =IFERROR('Rates Reference Table'!H14*$E$5,0) -> 75.2 | F17: =IFERROR(E17*(1-$H$5/2),0) -> 66.928 | G17: =IFERROR(E17*(1+$H$5/2),0) -> 83.472 | H17: =IFERROR(F17*$B$5,0) -> 33464 | I17: =IFERROR(G17*$B$5,0) -> 41736 | J17: High uncertainty; specialist estimate recommended
A18: GROUP 2 — SUPERSTRUCTURE
A19: 2 | B19: 2.1 | C19: Structural frame | D19: m² | E19: =IFERROR('Rates Reference Table'!H16*$E$5,0) -> 141 | F19: =IFERROR(E19*(1-$H$5/2),0) -> 125.49 | G19: =IFERROR(E19*(1+$H$5/2),0) -> 156.51 | H19: =IFERROR(F19*$B$5,0) -> 62745 | I19: =IFERROR(G19*$B$5,0) -> 78255 | J19: Steel/concrete/timber; new build or major extensions only
A20: 2 | B20: 2.2 | C20: Upper floors | D20: m² | E20: =IFERROR('Rates Reference Table'!H17*$E$5,0) -> 61.1 | F20: =IFERROR(E20*(1-$H$5/2),0) -> 54.379 | G20: =IFERROR(E20*(1+$H$5/2),0) -> 67.821 | H20: =IFERROR(F20*$B$5,0) -> 27189.5 | I20: =IFERROR(G20*$B$5,0) -> 33910.5 | J20: New build or added floors; inc topping and insulation
A21: 2 | B21: 2.3 | C21: Roof structure & covering | D21: m² | E21: =IFERROR('Rates Reference Table'!H18*$E$5,0) -> 70.5 | F21: =IFERROR(E21*(1-$H$5/2),0) -> 62.745 | G21: =IFERROR(E21*(1+$H$5/2),0) -> 78.255 | H21: =IFERROR(F21*$B$5,0) -> 31372.5 | I21: =IFERROR(G21*$B$5,0) -> 39127.5 | J21: New or replacement; inc insulation, waterproofing, rainwater
A22: 2 | B22: 2.4 | C22: Stairs & ramps | D22: Item | E22: =IFERROR('Rates Reference Table'!H19*$E$5,0) -> 18.8 | F22: =IFERROR(E22*(1-$H$5/2),0) -> 16.732 | G22: =IFERROR(E22*(1+$H$5/2),0) -> 20.868 | H22: =IFERROR(F22*$B$5,0) -> 8366 | I22: =IFERROR(G22*$B$5,0) -> 10434 | J22: RC, steel or timber; accessibility ramps
A23: 2 | B23: 2.5 | C23: External walls & facade | D23: m² | E23: =IFERROR('Rates Reference Table'!H20*$E$5,0) -> 188 | F23: =IFERROR(E23*(1-$H$5/2),0) -> 167.32 | G23: =IFERROR(E23*(1+$H$5/2),0) -> 208.68 | H23: =IFERROR(F23*$B$5,0) -> 83660 | I23: =IFERROR(G23*$B$5,0) -> 104340 | J23: Masonry/cladding; refurb = overcladding or repair only
A24: 2 | B24: 2.6 | C24: Windows & external doors | D24: m² | E24: =IFERROR('Rates Reference Table'!H21*$E$5,0) -> 94 | F24: =IFERROR(E24*(1-$H$5/2),0) -> 83.66 | G24: =IFERROR(E24*(1+$H$5/2),0) -> 104.34 | H24: =IFERROR(F24*$B$5,0) -> 41830 | I24: =IFERROR(G24*$B$5,0) -> 52170 | J24: uPVC (low) to aluminium curtain wall (high)
A25: 2 | B25: 2.7 | C25: Internal walls & partitions | D25: m² | E25: =IFERROR('Rates Reference Table'!H22*$E$5,0) -> 28.2 | F25: =IFERROR(E25*(1-$H$5/2),0) -> 25.098 | G25: =IFERROR(E25*(1+$H$5/2),0) -> 31.302 | H25: =IFERROR(F25*$B$5,0) -> 12549 | I25: =IFERROR(G25*$B$5,0) -> 15651 | J25: Blockwork, drywall or glazed; do not double-count Grp 3
A26: 2 | B26: 2.8 | C26: Internal doors & ironmongery | D26: Nr | E26: =IFERROR('Rates Reference Table'!H23*$E$5,0) -> 18.8 | F26: =IFERROR(E26*(1-$H$5/2),0) -> 16.732 | G26: =IFERROR(E26*(1+$H$5/2),0) -> 20.868 | H26: =IFERROR(F26*$B$5,0) -> 8366 | I26: =IFERROR(G26*$B$5,0) -> 10434 | J26: Fire-rated at upper range; standard at lower
A27: GROUP 3 — INTERNAL FINISHES ★ ALWAYS INCLUDED
A28: 3 | B28: 3.1 | C28: Wall finishes | D28: m² | E28: =IFERROR('Rates Reference Table'!H25*$E$5,0) -> 23.5 | F28: =IFERROR(E28*(1-$H$5/2),0) -> 20.915 | G28: =IFERROR(E28*(1+$H$5/2),0) -> 26.085 | H28: =IFERROR(F28*$B$5,0) -> 10457.5 | I28: =IFERROR(G28*$B$5,0) -> 13042.5 | J28: Emulsion (low) → specialist tiling/feature panelling (high)
A29: 3 | B29: 3.2 | C29: Floor finishes | D29: m² | E29: =IFERROR('Rates Reference Table'!H26*$E$5,0) -> 28.2 | F29: =IFERROR(E29*(1-$H$5/2),0) -> 25.098 | G29: =IFERROR(E29*(1+$H$5/2),0) -> 31.302 | H29: =IFERROR(F29*$B$5,0) -> 12549 | I29: =IFERROR(G29*$B$5,0) -> 15651 | J29: Vinyl/carpet (low) → stone/raised access floor (high)
A30: 3 | B30: 3.3 | C30: Ceiling finishes | D30: m² | E30: =IFERROR('Rates Reference Table'!H27*$E$5,0) -> 14.1 | F30: =IFERROR(E30*(1-$H$5/2),0) -> 12.549 | G30: =IFERROR(E30*(1+$H$5/2),0) -> 15.651 | H30: =IFERROR(F30*$B$5,0) -> 6274.5 | I30: =IFERROR(G30*$B$5,0) -> 7825.5 | J30: Emulsion (low) → bespoke acoustic ceiling system (high)
A31: GROUP 4 — FITTINGS, FURNISHINGS & EQUIPMENT
A32: 4 | B32: 4.1 | C32: General fittings & built-in joinery | D32: Item | E32: =IFERROR('Rates Reference Table'!H29*$E$5,0) -> 14.1 | F32: =IFERROR(E32*(1-$H$5/2),0) -> 12.549 | G32: =IFERROR(E32*(1+$H$5/2),0) -> 15.651 | H32: =IFERROR(F32*$B$5,0) -> 6274.5 | I32: =IFERROR(G32*$B$5,0) -> 7825.5 | J32: Reception desks, shelving, built-in furniture
A33: 4 | B33: 4.2 | C33: Sanitary fittings & toilet fit-out | D33: Nr | E33: =IFERROR('Rates Reference Table'!H30*$E$5,0) -> 9.4 | F33: =IFERROR(E33*(1-$H$5/2),0) -> 8.366 | G33: =IFERROR(E33*(1+$H$5/2),0) -> 10.434 | H33: =IFERROR(F33*$B$5,0) -> 4183 | I33: =IFERROR(G33*$B$5,0) -> 5217 | J33: WC packs; uplift for accessible/changing facilities
A34: 4 | B34: 4.3 | C34: Kitchen / break-out area | D34: Item | E34: =IFERROR('Rates Reference Table'!H31*$E$5,0) -> 7.52 | F34: =IFERROR(E34*(1-$H$5/2),0) -> 6.6928 | G34: =IFERROR(E34*(1+$H$5/2),0) -> 8.3472 | H34: =IFERROR(F34*$B$5,0) -> 3346.4 | I34: =IFERROR(G34*$B$5,0) -> 4173.6 | J34: Fitted units, worktops, appliances
A35: 4 | B35: 4.4 | C35: Specialist equipment (lab/AV/med) | D35: Item | E35: =IFERROR('Rates Reference Table'!H32*$E$5,0) -> 4.7 | F35: =IFERROR(E35*(1-$H$5/2),0) -> 4.183 | G35: =IFERROR(E35*(1+$H$5/2),0) -> 5.217 | H35: =IFERROR(F35*$B$5,0) -> 2091.5 | I35: =IFERROR(G35*$B$5,0) -> 2608.5 | J35: Laboratory, medical, AV; confirm with specialist
A36: GROUP 5 — MECHANICAL & ELECTRICAL SERVICES ★ KEY ELEMENT
A37: 5 | B37: 5.1 | C37: Sanitary plumbing (1st & 2nd fix) | D37: m² | E37: =IFERROR('Rates Reference Table'!H34*$E$5,0) -> 23.5 | F37: =IFERROR(E37*(1-$H$5/2),0) -> 20.915 | G37: =IFERROR(E37*(1+$H$5/2),0) -> 26.085 | H37: =IFERROR(F37*$B$5,0) -> 10457.5 | I37: =IFERROR(G37*$B$5,0) -> 13042.5 | J37: HWS, cold water, drainage connections
A38: 5 | B38: 5.2 | C38: Heating & hot water (LTHW/heat pump) | D38: m² | E38: =IFERROR('Rates Reference Table'!H35*$E$5,0) -> 32.9 | F38: =IFERROR(E38*(1-$H$5/2),0) -> 29.281 | G38: =IFERROR(E38*(1+$H$5/2),0) -> 36.519 | H38: =IFERROR(F38*$B$5,0) -> 14640.5 | I38: =IFERROR(G38*$B$5,0) -> 18259.5 | J38: LTHW system or heat pump; include buffer vessel
A39: 5 | B39: 5.3 | C39: Ventilation & air handling | D39: m² | E39: =IFERROR('Rates Reference Table'!H36*$E$5,0) -> 28.2 | F39: =IFERROR(E39*(1-$H$5/2),0) -> 25.098 | G39: =IFERROR(E39*(1+$H$5/2),0) -> 31.302 | H39: =IFERROR(F39*$B$5,0) -> 12549 | I39: =IFERROR(G39*$B$5,0) -> 15651 | J39: MVHR/AHU; uplift for lab/healthcare extract (+50-100%)
A40: 5 | B40: 5.4 | C40: Air conditioning & cooling | D40: m² | E40: =IFERROR('Rates Reference Table'!H37*$E$5,0) -> 14.1 | F40: =IFERROR(E40*(1-$H$5/2),0) -> 12.549 | G40: =IFERROR(E40*(1+$H$5/2),0) -> 15.651 | H40: =IFERROR(F40*$B$5,0) -> 6274.5 | I40: =IFERROR(G40*$B$5,0) -> 7825.5 | J40: VRF/splits; omit if not in scope
A41: 5 | B41: 5.5 | C41: Gas installation | D41: Item | E41: =IFERROR('Rates Reference Table'!H38*$E$5,0) -> 7.52 | F41: =IFERROR(E41*(1-$H$5/2),0) -> 6.6928 | G41: =IFERROR(E41*(1+$H$5/2),0) -> 8.3472 | H41: =IFERROR(F41*$B$5,0) -> 3346.4 | I41: =IFERROR(G41*$B$5,0) -> 4173.6 | J41: Omit if all-electric; confirm with utility
A42: 5 | B42: 5.6 | C42: Sprinkler / fire suppression | D42: m² | E42: =IFERROR('Rates Reference Table'!H39*$E$5,0) -> 9.4 | F42: =IFERROR(E42*(1-$H$5/2),0) -> 8.366 | G42: =IFERROR(E42*(1+$H$5/2),0) -> 10.434 | H42: =IFERROR(F42*$B$5,0) -> 4183 | I42: =IFERROR(G42*$B$5,0) -> 5217 | J42: >18m height or insurer requirement
A43: 5 | B43: 5.7 | C43: Electrical distribution & switchgear | D43: m² | E43: =IFERROR('Rates Reference Table'!H40*$E$5,0) -> 18.8 | F43: =IFERROR(E43*(1-$H$5/2),0) -> 16.732 | G43: =IFERROR(E43*(1+$H$5/2),0) -> 20.868 | H43: =IFERROR(F43*$B$5,0) -> 8366 | I43: =IFERROR(G43*$B$5,0) -> 10434 | J43: LV panels, distribution boards, earthing, containment
A44: 5 | B44: 5.8 | C44: Electrical wiring (1st & 2nd fix) | D44: m² | E44: =IFERROR('Rates Reference Table'!H41*$E$5,0) -> 28.2 | F44: =IFERROR(E44*(1-$H$5/2),0) -> 25.098 | G44: =IFERROR(E44*(1+$H$5/2),0) -> 31.302 | H44: =IFERROR(F44*$B$5,0) -> 12549 | I44: =IFERROR(G44*$B$5,0) -> 15651 | J44: All power and lighting circuits; inc containment
A45: 5 | B45: 5.9 | C45: Emergency lighting & fire alarm | D45: m² | E45: =IFERROR('Rates Reference Table'!H42*$E$5,0) -> 11.28 | F45: =IFERROR(E45*(1-$H$5/2),0) -> 10.0392 | G45: =IFERROR(E45*(1+$H$5/2),0) -> 12.5208 | H45: =IFERROR(F45*$B$5,0) -> 5019.6 | I45: =IFERROR(G45*$B$5,0) -> 6260.4 | J45: L2 minimum; upgrade for multi-zone/complex layouts
A46: 5 | B46: 5.10 | C46: External lighting | D46: Item | E46: =IFERROR('Rates Reference Table'!H43*$E$5,0) -> 4.7 | F46: =IFERROR(E46*(1-$H$5/2),0) -> 4.183 | G46: =IFERROR(E46*(1+$H$5/2),0) -> 5.217 | H46: =IFERROR(F46*$B$5,0) -> 2091.5 | I46: =IFERROR(G46*$B$5,0) -> 2608.5 | J46: Column/wall-mounted perimeter lighting
A47: 5 | B47: 5.11 | C47: Solar PV / renewables | D47: kWp | E47: =IFERROR('Rates Reference Table'!H44*$E$5,0) -> 752 | F47: =IFERROR(E47*(1-$H$5/2),0) -> 669.28 | G47: =IFERROR(E47*(1+$H$5/2),0) -> 834.72 | H47: =IFERROR(F47*$B$5,0) -> 334640 | I47: =IFERROR(G47*$B$5,0) -> 417360 | J47: £/kWp installed; coordinate structural loading + electrical
A48: 5 | B48: 5.12 | C48: EV charging points | D48: Nr | E48: =IFERROR('Rates Reference Table'!H45*$E$5,0) -> 1410 | F48: =IFERROR(E48*(1-$H$5/2),0) -> 1254.9 | G48: =IFERROR(E48*(1+$H$5/2),0) -> 1565.1 | H48: =IFERROR(F48*$B$5,0) -> 627450 | I48: =IFERROR(G48*$B$5,0) -> 782550 | J48: Per charge point inc groundworks; 7kW fast charger
... A53: 5 | B53: 5.17 | C53: Builder's work in connection (BWIC) | D53: m² | E53: =IFERROR('Rates Reference Table'!H50*$E$5,0) -> 7.52 | F53: =IFERROR(E53*(1-$H$5/2),0) -> 6.6928 | G53: =IFERROR(E53*(1+$H$5/2),0) -> 8.3472 | H53: =IFERROR(F53*$B$5,0) -> 3346.4 | I53: =IFERROR(G53*$B$5,0) -> 4173.6 | J53: Penetrations, plinths, ducts, concrete bases for plant
A54: GROUP 6 — PREFABRICATED / MODULAR (if applicable)
A55: 6 | B55: 6.1 | C55: Prefabricated / modular units | D55: Item | E55: =IFERROR('Rates Reference Table'!H52*$E$5,0) -> 0 | F55: =IFERROR(E55*(1-$H$5/2),0) -> 0 | G55: =IFERROR(E55*(1+$H$5/2),0) -> 0 | H55: =IFERROR(F55*$B$5,0) -> 0 | I55: =IFERROR(G55*$B$5,0) -> 0 | J55: Factory-built modular; specialist quote required
A56: 6 | B56: 6.2 | C56: Pre-engineered systems (mezzanine) | D56: Item | E56: =IFERROR('Rates Reference Table'!H53*$E$5,0) -> 0 | F56: =IFERROR(E56*(1-$H$5/2),0) -> 0 | G56: =IFERROR(E56*(1+$H$5/2),0) -> 0 | H56: =IFERROR(F56*$B$5,0) -> 0 | I56: =IFERROR(G56*$B$5,0) -> 0 | J56: Mezzanine floors, demountable partitions
A57: GROUP 7 — WORK TO EXISTING BUILDINGS
A58: 7 | B58: 7.1 | C58: Structural repairs | D58: Item | E58: EXCLUDED | F58: EXCLUDED | G58: EXCLUDED | H58: 0 | I58: 0 | J58: Crack stitching, bearing repairs; increase for poor condition
A59: 7 | B59: 7.2 | C59: Fabric / envelope repairs | D59: Item | E59: EXCLUDED | F59: EXCLUDED | G59: EXCLUDED | H59: 0 | I59: 0 | J59: Repointing, waterproofing, weathertight works
A60: 7 | B60: 7.3 | C60: Damp proof course treatment | D60: Item | E60: EXCLUDED | F60: EXCLUDED | G60: EXCLUDED | H60: 0 | I60: 0 | J60: Chemical DPC; increase for severe rising damp
A61: 7 | B61: 7.4 | C61: M&E overhaul / life-expired services | D61: Item | E61: EXCLUDED | F61: EXCLUDED | G61: EXCLUDED | H61: 0 | I61: 0 | J61: Replacement of end-of-life mechanical & electrical plant
A62: 7 | B62: 7.5 | C62: Making good after structural works | D62: Item | E62: EXCLUDED | F62: EXCLUDED | G62: EXCLUDED | H62: 0 | I62: 0 | J62: Patch plaster, redecoration after structural alterations
A63: GROUP 8 — EXTERNAL WORKS
A64: 8 | B64: 8.1 | C64: Site preparation & clearance | D64: Item | E64: =IFERROR('Rates Reference Table'!H61*$E$5,0) -> 7.52 | F64: =IFERROR(E64*(1-$H$5/2),0) -> 6.6928 | G64: =IFERROR(E64*(1+$H$5/2),0) -> 8.3472 | H64: =IFERROR(F64*$B$5,0) -> 3346.4 | I64: =IFERROR(G64*$B$5,0) -> 4173.6 | J64: Strip topsoil, vegetation, temp fencing and hoarding
A65: 8 | B65: 8.2 | C65: Roads, paths & hard paving | D65: m² | E65: =IFERROR('Rates Reference Table'!H62*$E$5,0) -> 14.1 | F65: =IFERROR(E65*(1-$H$5/2),0) -> 12.549 | G65: =IFERROR(E65*(1+$H$5/2),0) -> 15.651 | H65: =IFERROR(F65*$B$5,0) -> 6274.5 | I65: =IFERROR(G65*$B$5,0) -> 7825.5 | J65: Macadam/block paving; inc edging and drainage channels
A66: 8 | B66: 8.3 | C66: Car parking (line-marked bays) | D66: Nr | E66: =IFERROR('Rates Reference Table'!H63*$E$5,0) -> 4.7 | F66: =IFERROR(E66*(1-$H$5/2),0) -> 4.183 | G66: =IFERROR(E66*(1+$H$5/2),0) -> 5.217 | H66: =IFERROR(F66*$B$5,0) -> 2091.5 | I66: =IFERROR(G66*$B$5,0) -> 2608.5 | J66: Surfacing, line markings, disabled bays
A67: 8 | B67: 8.4 | C67: Surface water drainage | D67: Item | E67: =IFERROR('Rates Reference Table'!H64*$E$5,0) -> 9.4 | F67: =IFERROR(E67*(1-$H$5/2),0) -> 8.366 | G67: =IFERROR(E67*(1+$H$5/2),0) -> 10.434 | H67: =IFERROR(F67*$B$5,0) -> 4183 | I67: =IFERROR(G67*$B$5,0) -> 5217 | J67: Gullies, pipes, SuDS if required by planning
A68: 8 | B68: 8.5 | C68: Foul drainage connections | D68: Item | E68: =IFERROR('Rates Reference Table'!H65*$E$5,0) -> 7.52 | F68: =IFERROR(E68*(1-$H$5/2),0) -> 6.6928 | G68: =IFERROR(E68*(1+$H$5/2),0) -> 8.3472 | H68: =IFERROR(F68*$B$5,0) -> 3346.4 | I68: =IFERROR(G68*$B$5,0) -> 4173.6 | J68: Connection to existing drain or new manhole
A69: 8 | B69: 8.6 | C69: External utility services | D69: Item | E69: =IFERROR('Rates Reference Table'!H66*$E$5,0) -> 9.4 | F69: =IFERROR(E69*(1-$H$5/2),0) -> 8.366 | G69: =IFERROR(E69*(1+$H$5/2),0) -> 10.434 | H69: =IFERROR(F69*$B$5,0) -> 4183 | I69: =IFERROR(G69*$B$5,0) -> 5217 | J69: Gas/water/electric diversions; early check with DNO
A70: 8 | B70: 8.7 | C70: Soft landscaping | D70: m² | E70: =IFERROR('Rates Reference Table'!H67*$E$5,0) -> 4.7 | F70: =IFERROR(E70*(1-$H$5/2),0) -> 4.183 | G70: =IFERROR(E70*(1+$H$5/2),0) -> 5.217 | H70: =IFERROR(F70*$B$5,0) -> 2091.5 | I70: =IFERROR(G70*$B$5,0) -> 2608.5 | J70: Planting, seeding, topsoil reinstatement
A71: 8 | B71: 8.8 | C71: Boundary enclosures (fences/gates) | D71: Item | E71: =IFERROR('Rates Reference Table'!H68*$E$5,0) -> 2.82 | F71: =IFERROR(E71*(1-$H$5/2),0) -> 2.5098 | G71: =IFERROR(E71*(1+$H$5/2),0) -> 3.1302 | H71: =IFERROR(F71*$B$5,0) -> 1254.9 | I71: =IFERROR(G71*$B$5,0) -> 1565.1 | J71: Security fencing, gates, boundary walls, railings
A72: 8 | B72: 8.9 | C72: External lighting | D72: Item | E72: =IFERROR('Rates Reference Table'!H69*$E$5,0) -> 2.82 | F72: =IFERROR(E72*(1-$H$5/2),0) -> 2.5098 | G72: =IFERROR(E72*(1+$H$5/2),0) -> 3.1302 | H72: =IFERROR(F72*$B$5,0) -> 1254.9 | I72: =IFERROR(G72*$B$5,0) -> 1565.1 | J72: Column or wall-mounted lighting (see also 5.10)
A73: WORKS COST SUBTOTAL (Groups 0–8) | H73: =SUMPRODUCT((H8:H72>0)*H8:H72) -> 1534742.7 | I73: =SUMPRODUCT((I8:I72>0)*I8:I72) -> 1914117.3
A75: ADDITIONS TO WORKS COST — Adjust % using signal rules in Notes column
A76: Code | D76: Description | E76: Applied To | F76: Low % | G76: High % | H76: Total LOW (£) | I76: Total HIGH (£) | J76: Signal Rules / Notes
A77: A | D77: Contractor's Preliminaries | E77: Works Cost | F77: 0.08 | G77: 0.1 | H77: =IFERROR(F77*H73,0) -> 122779.42 | I77: =IFERROR(G77*I73,0) -> 191411.73 | J77: 8%=clean/vacant/short prog | +0.5% per: 6-18mo prog, partial occ, restricted access | cap 10%
A78: B | D78: Contractor's Overheads & Profit | E78: Works Cost | F78: 0.08 | G78: 0.12 | H78: =IFERROR(F78*H73,0) -> 122779.42 | I78: =IFERROR(G78*I73,0) -> 229694.08 | J78: >£5M→8-9% | £1-5M→9-10% | <£1M→10-12% | Lower end = cost priority; upper = D&B/speed
A79: CONSTRUCTION COST SUBTOTAL (Works + Prelims + OH&P) | H79: =H73+H77+H78 -> 1780301.5 | I79: =I73+I77+I78 -> 2335223.1
A80: C | D80: Professional Fees | E80: Construction Cost | F80: 0.05 | G80: 0.15 | H80: =IFERROR(F80*H79,0) -> 89015.077 | I80: =IFERROR(G80*I79,0) -> 350283.47 | J80: Stage 0-1→12-15% | Stage 2→10-13% | Stage 3→7-10% | Stage 4→5-7% | +1-2% M&E/struct/BREEAM
A81: D | D81: Dev & Project Costs | E81: Construction Cost | F81: 0.02 | G81: 0.04 | H81: =IFERROR(F81*H79,0) -> 35606.031 | I81: =IFERROR(G81*I79,0) -> 93408.924 | J81: Full planning→3-4% | LBC also→4% | Permitted dev→2% | +0.5% if no surveys yet
A82: E | D82: Risk Allowance | E82: Works Cost | F82: 0.05 | G82: 0.1 | H82: =IFERROR(F82*H73,0) -> 76737.135 | I82: =IFERROR(G82*I73,0) -> 191411.73 | J82: Baseline 5% | +2% no surveys | +1.5% asbestos/contamination | +1% structural concern | +1% hard deadline | cap 10%
A83: H | D83: Client Contingency [FIXED 5%] | E83: Works Cost | F83: 0.05 | G83: 0.05 | H83: =IFERROR(0.05*H73,0) -> 76737.135 | I83: =IFERROR(0.05*I73,0) -> 95705.865 | J83: FIXED at 5% — held by client, not released to contractor. Do not adjust.
A84: F | D84: Inflation Allowance | E84: Works Cost | F84: 0.02 | G84: 0.12 | H84: =IFERROR(F84*H73,0) -> 30694.854 | I84: =IFERROR(G84*I73,0) -> 229694.08 | J84: Component 1: tender delay (0-18mo=2-6%) + Component 2: construction mid-point (6-24mo=1-4%) | cap 12%
A85: TOTAL PROJECT COST (excl. VAT) | H85: =H79+H80+H81+H82+H83+H84 -> 2089091.8 | I85: =I79+I80+I81+I82+I83+I84 -> 3295727.2
A86: G | D86: VAT — reference only, NOT in total | E86: Project Total | F86: 0.2 | G86: 0.2 | H86: =IFERROR(0.2*H85,0) -> 417818.35 | I86: =IFERROR(0.2*I85,0) -> 659145.43 | J86: Recoverability must be confirmed with client Finance team. New build may attract zero-rating.
A88: Implied blended Works Cost rate — cross-check against BCIS benchmarks: | E88: =IFERROR(H73/$B$5,0) -> 3069.4854 | G88: =IFERROR(I73/$B$5,0) -> 3828.2346
A90: ⚠ DISCLAIMER: Indicative only — RIBA Stage 0–1 without measured quantities. Rates from Rates Reference Table, cross-referenced Q2 2026 market data. Must be reviewed by a Chartered QS before use in any business case or budget approval. LOW–HIGH range = mid-point ± 11% (default spread 22%). Update GIFA, BCIS factor and Spread as required.

Sheet NB – High Spec
A1: NRM1 ESTIMATE — NEW BUILD — HIGH SPEC / SPECIALIST
A2: Spec level: High specification new build — lab, healthcare, flagship or technically complex. | RIBA Stage 0–1 indicative only | Base date Q2 2026
A4: Project Type: | B4: New Build | D4: Spec Level: | E4: High Spec / Specialist | G4: Region: | H4: West Midlands
A5: GIFA (m²) ▼ update: | B5: 500 | D5: BCIS Location Factor ▼: | E5: 0.94 | G5: Spread ±% ▼: | H5: 0.22
A7: Grp | B7: Sub | C7: Element / Description | D7: Unit | E7: Mid-Point £/m² | F7: Low £/m² | G7: High £/m² | H7: Total LOW (£) | I7: Total HIGH (£) | J7: Notes / Rate Driver
A8: GROUP 0 — FACILITATING WORKS
A9: 0 | B9: 0.1 | C9: Toxic/hazardous material removal | D9: Item | E9: =IFERROR('Rates Reference Table'!I6*$E$5,0) -> 18.8 | F9: =IFERROR(E9*(1-$H$5/2),0) -> 16.732 | G9: =IFERROR(E9*(1+$H$5/2),0) -> 20.868 | H9: =IFERROR(F9*$B$5,0) -> 8366 | I9: =IFERROR(G9*$B$5,0) -> 10434 | J9: Asbestos; increase if confirmed present (refurb/demo only)
A10: 0 | B10: 0.2 | C10: Demolition & structural alterations | D10: Item | E10: =IFERROR('Rates Reference Table'!I7*$E$5,0) -> 23.5 | F10: =IFERROR(E10*(1-$H$5/2),0) -> 20.915 | G10: =IFERROR(E10*(1+$H$5/2),0) -> 26.085 | H10: =IFERROR(F10*$B$5,0) -> 10457.5 | I10: =IFERROR(G10*$B$5,0) -> 13042.5 | J10: Selective or full demolition; structural openings
A11: 0 | B11: 0.3 | C11: Contaminated land remediation | D11: Item | E11: =IFERROR('Rates Reference Table'!I8*$E$5,0) -> 18.8 | F11: =IFERROR(E11*(1-$H$5/2),0) -> 16.732 | G11: =IFERROR(E11*(1+$H$5/2),0) -> 20.868 | H11: =IFERROR(F11*$B$5,0) -> 8366 | I11: =IFERROR(G11*$B$5,0) -> 10434 | J11: Brownfield/contaminated; specialist quote needed
A12: 0 | B12: 0.4 | C12: Ground stabilisation | D12: Item | E12: =IFERROR('Rates Reference Table'!I9*$E$5,0) -> 14.1 | F12: =IFERROR(E12*(1-$H$5/2),0) -> 12.549 | G12: =IFERROR(E12*(1+$H$5/2),0) -> 15.651 | H12: =IFERROR(F12*$B$5,0) -> 6274.5 | I12: =IFERROR(G12*$B$5,0) -> 7825.5 | J12: Underpinning/piling if ground risk identified
A13: GROUP 1 — SUBSTRUCTURE
A14: 1 | B14: 1.1 | C14: Standard foundations (strip/pad) | D14: m² | E14: =IFERROR('Rates Reference Table'!I11*$E$5,0) -> 75.2 | F14: =IFERROR(E14*(1-$H$5/2),0) -> 66.928 | G14: =IFERROR(E14*(1+$H$5/2),0) -> 83.472 | H14: =IFERROR(F14*$B$5,0) -> 33464 | I14: =IFERROR(G14*$B$5,0) -> 41736 | J14: New build only; included in Group 7 rate for extensions
A15: 1 | B15: 1.2 | C15: Specialist foundations (piled) | D15: m² | E15: =IFERROR('Rates Reference Table'!I12*$E$5,0) -> 56.4 | F15: =IFERROR(E15*(1-$H$5/2),0) -> 50.196 | G15: =IFERROR(E15*(1+$H$5/2),0) -> 62.604 | H15: =IFERROR(F15*$B$5,0) -> 25098 | I15: =IFERROR(G15*$B$5,0) -> 31302 | J15: Poor ground conditions; trigger from GI report
A16: 1 | B16: 1.3 | C16: Lowest floor construction (slab) | D16: m² | E16: =IFERROR('Rates Reference Table'!I13*$E$5,0) -> 51.7 | F16: =IFERROR(E16*(1-$H$5/2),0) -> 46.013 | G16: =IFERROR(E16*(1+$H$5/2),0) -> 57.387 | H16: =IFERROR(F16*$B$5,0) -> 23006.5 | I16: =IFERROR(G16*$B$5,0) -> 28693.5 | J16: Ground bearing or suspended; inc DPM and insulation
A17: 1 | B17: 1.4 | C17: Basement excavation & structure | D17: Item | E17: =IFERROR('Rates Reference Table'!I14*$E$5,0) -> 141 | F17: =IFERROR(E17*(1-$H$5/2),0) -> 125.49 | G17: =IFERROR(E17*(1+$H$5/2),0) -> 156.51 | H17: =IFERROR(F17*$B$5,0) -> 62745 | I17: =IFERROR(G17*$B$5,0) -> 78255 | J17: High uncertainty; specialist estimate recommended
A18: GROUP 2 — SUPERSTRUCTURE
A19: 2 | B19: 2.1 | C19: Structural frame | D19: m² | E19: =IFERROR('Rates Reference Table'!I16*$E$5,0) -> 206.8 | F19: =IFERROR(E19*(1-$H$5/2),0) -> 184.052 | G19: =IFERROR(E19*(1+$H$5/2),0) -> 229.548 | H19: =IFERROR(F19*$B$5,0) -> 92026 | I19: =IFERROR(G19*$B$5,0) -> 114774 | J19: Steel/concrete/timber; new build or major extensions only
A20: 2 | B20: 2.2 | C20: Upper floors | D20: m² | E20: =IFERROR('Rates Reference Table'!I17*$E$5,0) -> 89.3 | F20: =IFERROR(E20*(1-$H$5/2),0) -> 79.477 | G20: =IFERROR(E20*(1+$H$5/2),0) -> 99.123 | H20: =IFERROR(F20*$B$5,0) -> 39738.5 | I20: =IFERROR(G20*$B$5,0) -> 49561.5 | J20: New build or added floors; inc topping and insulation
A21: 2 | B21: 2.3 | C21: Roof structure & covering | D21: m² | E21: =IFERROR('Rates Reference Table'!I18*$E$5,0) -> 112.8 | F21: =IFERROR(E21*(1-$H$5/2),0) -> 100.392 | G21: =IFERROR(E21*(1+$H$5/2),0) -> 125.208 | H21: =IFERROR(F21*$B$5,0) -> 50196 | I21: =IFERROR(G21*$B$5,0) -> 62604 | J21: New or replacement; inc insulation, waterproofing, rainwater
A22: 2 | B22: 2.4 | C22: Stairs & ramps | D22: Item | E22: =IFERROR('Rates Reference Table'!I19*$E$5,0) -> 32.9 | F22: =IFERROR(E22*(1-$H$5/2),0) -> 29.281 | G22: =IFERROR(E22*(1+$H$5/2),0) -> 36.519 | H22: =IFERROR(F22*$B$5,0) -> 14640.5 | I22: =IFERROR(G22*$B$5,0) -> 18259.5 | J22: RC, steel or timber; accessibility ramps
A23: 2 | B23: 2.5 | C23: External walls & facade | D23: m² | E23: =IFERROR('Rates Reference Table'!I20*$E$5,0) -> 300.8 | F23: =IFERROR(E23*(1-$H$5/2),0) -> 267.712 | G23: =IFERROR(E23*(1+$H$5/2),0) -> 333.888 | H23: =IFERROR(F23*$B$5,0) -> 133856 | I23: =IFERROR(G23*$B$5,0) -> 166944 | J23: Masonry/cladding; refurb = overcladding or repair only
A24: 2 | B24: 2.6 | C24: Windows & external doors | D24: m² | E24: =IFERROR('Rates Reference Table'!I21*$E$5,0) -> 150.4 | F24: =IFERROR(E24*(1-$H$5/2),0) -> 133.856 | G24: =IFERROR(E24*(1+$H$5/2),0) -> 166.944 | H24: =IFERROR(F24*$B$5,0) -> 66928 | I24: =IFERROR(G24*$B$5,0) -> 83472 | J24: uPVC (low) to aluminium curtain wall (high)
A25: 2 | B25: 2.7 | C25: Internal walls & partitions | D25: m² | E25: =IFERROR('Rates Reference Table'!I22*$E$5,0) -> 47 | F25: =IFERROR(E25*(1-$H$5/2),0) -> 41.83 | G25: =IFERROR(E25*(1+$H$5/2),0) -> 52.17 | H25: =IFERROR(F25*$B$5,0) -> 20915 | I25: =IFERROR(G25*$B$5,0) -> 26085 | J25: Blockwork, drywall or glazed; do not double-count Grp 3
A26: 2 | B26: 2.8 | C26: Internal doors & ironmongery | D26: Nr | E26: =IFERROR('Rates Reference Table'!I23*$E$5,0) -> 32.9 | F26: =IFERROR(E26*(1-$H$5/2),0) -> 29.281 | G26: =IFERROR(E26*(1+$H$5/2),0) -> 36.519 | H26: =IFERROR(F26*$B$5,0) -> 14640.5 | I26: =IFERROR(G26*$B$5,0) -> 18259.5 | J26: Fire-rated at upper range; standard at lower
A27: GROUP 3 — INTERNAL FINISHES ★ ALWAYS INCLUDED
A28: 3 | B28: 3.1 | C28: Wall finishes | D28: m² | E28: =IFERROR('Rates Reference Table'!I25*$E$5,0) -> 51.7 | F28: =IFERROR(E28*(1-$H$5/2),0) -> 46.013 | G28: =IFERROR(E28*(1+$H$5/2),0) -> 57.387 | H28: =IFERROR(F28*$B$5,0) -> 23006.5 | I28: =IFERROR(G28*$B$5,0) -> 28693.5 | J28: Emulsion (low) → specialist tiling/feature panelling (high)
A29: 3 | B29: 3.2 | C29: Floor finishes | D29: m² | E29: =IFERROR('Rates Reference Table'!I26*$E$5,0) -> 75.2 | F29: =IFERROR(E29*(1-$H$5/2),0) -> 66.928 | G29: =IFERROR(E29*(1+$H$5/2),0) -> 83.472 | H29: =IFERROR(F29*$B$5,0) -> 33464 | I29: =IFERROR(G29*$B$5,0) -> 41736 | J29: Vinyl/carpet (low) → stone/raised access floor (high)
A30: 3 | B30: 3.3 | C30: Ceiling finishes | D30: m² | E30: =IFERROR('Rates Reference Table'!I27*$E$5,0) -> 42.3 | F30: =IFERROR(E30*(1-$H$5/2),0) -> 37.647 | G30: =IFERROR(E30*(1+$H$5/2),0) -> 46.953 | H30: =IFERROR(F30*$B$5,0) -> 18823.5 | I30: =IFERROR(G30*$B$5,0) -> 23476.5 | J30: Emulsion (low) → bespoke acoustic ceiling system (high)
A31: GROUP 4 — FITTINGS, FURNISHINGS & EQUIPMENT
A32: 4 | B32: 4.1 | C32: General fittings & built-in joinery | D32: Item | E32: =IFERROR('Rates Reference Table'!I29*$E$5,0) -> 47 | F32: =IFERROR(E32*(1-$H$5/2),0) -> 41.83 | G32: =IFERROR(E32*(1+$H$5/2),0) -> 52.17 | H32: =IFERROR(F32*$B$5,0) -> 20915 | I32: =IFERROR(G32*$B$5,0) -> 26085 | J32: Reception desks, shelving, built-in furniture
A33: 4 | B33: 4.2 | C33: Sanitary fittings & toilet fit-out | D33: Nr | E33: =IFERROR('Rates Reference Table'!I30*$E$5,0) -> 20.68 | F33: =IFERROR(E33*(1-$H$5/2),0) -> 18.4052 | G33: =IFERROR(E33*(1+$H$5/2),0) -> 22.9548 | H33: =IFERROR(F33*$B$5,0) -> 9202.6 | I33: =IFERROR(G33*$B$5,0) -> 11477.4 | J33: WC packs; uplift for accessible/changing facilities
A34: 4 | B34: 4.3 | C34: Kitchen / break-out area | D34: Item | E34: =IFERROR('Rates Reference Table'!I31*$E$5,0) -> 18.8 | F34: =IFERROR(E34*(1-$H$5/2),0) -> 16.732 | G34: =IFERROR(E34*(1+$H$5/2),0) -> 20.868 | H34: =IFERROR(F34*$B$5,0) -> 8366 | I34: =IFERROR(G34*$B$5,0) -> 10434 | J34: Fitted units, worktops, appliances
A35: 4 | B35: 4.4 | C35: Specialist equipment (lab/AV/med) | D35: Item | E35: =IFERROR('Rates Reference Table'!I32*$E$5,0) -> 56.4 | F35: =IFERROR(E35*(1-$H$5/2),0) -> 50.196 | G35: =IFERROR(E35*(1+$H$5/2),0) -> 62.604 | H35: =IFERROR(F35*$B$5,0) -> 25098 | I35: =IFERROR(G35*$B$5,0) -> 31302 | J35: Laboratory, medical, AV; confirm with specialist
A36: GROUP 5 — MECHANICAL & ELECTRICAL SERVICES ★ KEY ELEMENT
A37: 5 | B37: 5.1 | C37: Sanitary plumbing (1st & 2nd fix) | D37: m² | E37: =IFERROR('Rates Reference Table'!I34*$E$5,0) -> 47 | F37: =IFERROR(E37*(1-$H$5/2),0) -> 41.83 | G37: =IFERROR(E37*(1+$H$5/2),0) -> 52.17 | H37: =IFERROR(F37*$B$5,0) -> 20915 | I37: =IFERROR(G37*$B$5,0) -> 26085 | J37: HWS, cold water, drainage connections
A38: 5 | B38: 5.2 | C38: Heating & hot water (LTHW/heat pump) | D38: m² | E38: =IFERROR('Rates Reference Table'!I35*$E$5,0) -> 65.8 | F38: =IFERROR(E38*(1-$H$5/2),0) -> 58.562 | G38: =IFERROR(E38*(1+$H$5/2),0) -> 73.038 | H38: =IFERROR(F38*$B$5,0) -> 29281 | I38: =IFERROR(G38*$B$5,0) -> 36519 | J38: LTHW system or heat pump; include buffer vessel
A39: 5 | B39: 5.3 | C39: Ventilation & air handling | D39: m² | E39: =IFERROR('Rates Reference Table'!I36*$E$5,0) -> 65.8 | F39: =IFERROR(E39*(1-$H$5/2),0) -> 58.562 | G39: =IFERROR(E39*(1+$H$5/2),0) -> 73.038 | H39: =IFERROR(F39*$B$5,0) -> 29281 | I39: =IFERROR(G39*$B$5,0) -> 36519 | J39: MVHR/AHU; uplift for lab/healthcare extract (+50-100%)
A40: 5 | B40: 5.4 | C40: Air conditioning & cooling | D40: m² | E40: =IFERROR('Rates Reference Table'!I37*$E$5,0) -> 51.7 | F40: =IFERROR(E40*(1-$H$5/2),0) -> 46.013 | G40: =IFERROR(E40*(1+$H$5/2),0) -> 57.387 | H40: =IFERROR(F40*$B$5,0) -> 23006.5 | I40: =IFERROR(G40*$B$5,0) -> 28693.5 | J40: VRF/splits; omit if not in scope
A41: 5 | B41: 5.5 | C41: Gas installation | D41: Item | E41: =IFERROR('Rates Reference Table'!I38*$E$5,0) -> 14.1 | F41: =IFERROR(E41*(1-$H$5/2),0) -> 12.549 | G41: =IFERROR(E41*(1+$H$5/2),0) -> 15.651 | H41: =IFERROR(F41*$B$5,0) -> 6274.5 | I41: =IFERROR(G41*$B$5,0) -> 7825.5 | J41: Omit if all-electric; confirm with utility
A42: 5 | B42: 5.6 | C42: Sprinkler / fire suppression | D42: m² | E42: =IFERROR('Rates Reference Table'!I39*$E$5,0) -> 23.5 | F42: =IFERROR(E42*(1-$H$5/2),0) -> 20.915 | G42: =IFERROR(E42*(1+$H$5/2),0) -> 26.085 | H42: =IFERROR(F42*$B$5,0) -> 10457.5 | I42: =IFERROR(G42*$B$5,0) -> 13042.5 | J42: >18m height or insurer requirement
A43: 5 | B43: 5.7 | C43: Electrical distribution & switchgear | D43: m² | E43: =IFERROR('Rates Reference Table'!I40*$E$5,0) -> 42.3 | F43: =IFERROR(E43*(1-$H$5/2),0) -> 37.647 | G43: =IFERROR(E43*(1+$H$5/2),0) -> 46.953 | H43: =IFERROR(F43*$B$5,0) -> 18823.5 | I43: =IFERROR(G43*$B$5,0) -> 23476.5 | J43: LV panels, distribution boards, earthing, containment
A44: 5 | B44: 5.8 | C44: Electrical wiring (1st & 2nd fix) | D44: m² | E44: =IFERROR('Rates Reference Table'!I41*$E$5,0) -> 56.4 | F44: =IFERROR(E44*(1-$H$5/2),0) -> 50.196 | G44: =IFERROR(E44*(1+$H$5/2),0) -> 62.604 | H44: =IFERROR(F44*$B$5,0) -> 25098 | I44: =IFERROR(G44*$B$5,0) -> 31302 | J44: All power and lighting circuits; inc containment
A45: 5 | B45: 5.9 | C45: Emergency lighting & fire alarm | D45: m² | E45: =IFERROR('Rates Reference Table'!I42*$E$5,0) -> 23.5 | F45: =IFERROR(E45*(1-$H$5/2),0) -> 20.915 | G45: =IFERROR(E45*(1+$H$5/2),0) -> 26.085 | H45: =IFERROR(F45*$B$5,0) -> 10457.5 | I45: =IFERROR(G45*$B$5,0) -> 13042.5 | J45: L2 minimum; upgrade for multi-zone/complex layouts
A46: 5 | B46: 5.10 | C46: External lighting | D46: Item | E46: =IFERROR('Rates Reference Table'!I43*$E$5,0) -> 11.28 | F46: =IFERROR(E46*(1-$H$5/2),0) -> 10.0392 | G46: =IFERROR(E46*(1+$H$5/2),0) -> 12.5208 | H46: =IFERROR(F46*$B$5,0) -> 5019.6 | I46: =IFERROR(G46*$B$5,0) -> 6260.4 | J46: Column/wall-mounted perimeter lighting
A47: 5 | B47: 5.11 | C47: Solar PV / renewables | D47: kWp | E47: =IFERROR('Rates Reference Table'!I44*$E$5,0) -> 1128 | F47: =IFERROR(E47*(1-$H$5/2),0) -> 1003.92 | G47: =IFERROR(E47*(1+$H$5/2),0) -> 1252.08 | H47: =IFERROR(F47*$B$5,0) -> 501960 | I47: =IFERROR(G47*$B$5,0) -> 626040 | J47: £/kWp installed; coordinate structural loading + electrical
A48: 5 | B48: 5.12 | C48: EV charging points | D48: Nr | E48: =IFERROR('Rates Reference Table'!I45*$E$5,0) -> 2350 | F48: =IFERROR(E48*(1-$H$5/2),0) -> 2091.5 | G48: =IFERROR(E48*(1+$H$5/2),0) -> 2608.5 | H48: =IFERROR(F48*$B$5,0) -> 1045750 | I48: =IFERROR(G48*$B$5,0) -> 1304250 | J48: Per charge point inc groundworks; 7kW fast charger
... A53: 5 | B53: 5.17 | C53: Builder's work in connection (BWIC) | D53: m² | E53: =IFERROR('Rates Reference Table'!I50*$E$5,0) -> 16.92 | F53: =IFERROR(E53*(1-$H$5/2),0) -> 15.0588 | G53: =IFERROR(E53*(1+$H$5/2),0) -> 18.7812 | H53: =IFERROR(F53*$B$5,0) -> 7529.4 | I53: =IFERROR(G53*$B$5,0) -> 9390.6 | J53: Penetrations, plinths, ducts, concrete bases for plant
A54: GROUP 6 — PREFABRICATED / MODULAR (if applicable)
A55: 6 | B55: 6.1 | C55: Prefabricated / modular units | D55: Item | E55: =IFERROR('Rates Reference Table'!I52*$E$5,0) -> 141 | F55: =IFERROR(E55*(1-$H$5/2),0) -> 125.49 | G55: =IFERROR(E55*(1+$H$5/2),0) -> 156.51 | H55: =IFERROR(F55*$B$5,0) -> 62745 | I55: =IFERROR(G55*$B$5,0) -> 78255 | J55: Factory-built modular; specialist quote required
A56: 6 | B56: 6.2 | C56: Pre-engineered systems (mezzanine) | D56: Item | E56: =IFERROR('Rates Reference Table'!I53*$E$5,0) -> 75.2 | F56: =IFERROR(E56*(1-$H$5/2),0) -> 66.928 | G56: =IFERROR(E56*(1+$H$5/2),0) -> 83.472 | H56: =IFERROR(F56*$B$5,0) -> 33464 | I56: =IFERROR(G56*$B$5,0) -> 41736 | J56: Mezzanine floors, demountable partitions
A57: GROUP 7 — WORK TO EXISTING BUILDINGS
A58: 7 | B58: 7.1 | C58: Structural repairs | D58: Item | E58: EXCLUDED | F58: EXCLUDED | G58: EXCLUDED | H58: 0 | I58: 0 | J58: Crack stitching, bearing repairs; increase for poor condition
A59: 7 | B59: 7.2 | C59: Fabric / envelope repairs | D59: Item | E59: EXCLUDED | F59: EXCLUDED | G59: EXCLUDED | H59: 0 | I59: 0 | J59: Repointing, waterproofing, weathertight works
A60: 7 | B60: 7.3 | C60: Damp proof course treatment | D60: Item | E60: EXCLUDED | F60: EXCLUDED | G60: EXCLUDED | H60: 0 | I60: 0 | J60: Chemical DPC; increase for severe rising damp
A61: 7 | B61: 7.4 | C61: M&E overhaul / life-expired services | D61: Item | E61: EXCLUDED | F61: EXCLUDED | G61: EXCLUDED | H61: 0 | I61: 0 | J61: Replacement of end-of-life mechanical & electrical plant
A62: 7 | B62: 7.5 | C62: Making good after structural works | D62: Item | E62: EXCLUDED | F62: EXCLUDED | G62: EXCLUDED | H62: 0 | I62: 0 | J62: Patch plaster, redecoration after structural alterations
A63: GROUP 8 — EXTERNAL WORKS
A64: 8 | B64: 8.1 | C64: Site preparation & clearance | D64: Item | E64: =IFERROR('Rates Reference Table'!I61*$E$5,0) -> 16.92 | F64: =IFERROR(E64*(1-$H$5/2),0) -> 15.0588 | G64: =IFERROR(E64*(1+$H$5/2),0) -> 18.7812 | H64: =IFERROR(F64*$B$5,0) -> 7529.4 | I64: =IFERROR(G64*$B$5,0) -> 9390.6 | J64: Strip topsoil, vegetation, temp fencing and hoarding
A65: 8 | B65: 8.2 | C65: Roads, paths & hard paving | D65: m² | E65: =IFERROR('Rates Reference Table'!I62*$E$5,0) -> 32.9 | F65: =IFERROR(E65*(1-$H$5/2),0) -> 29.281 | G65: =IFERROR(E65*(1+$H$5/2),0) -> 36.519 | H65: =IFERROR(F65*$B$5,0) -> 14640.5 | I65: =IFERROR(G65*$B$5,0) -> 18259.5 | J65: Macadam/block paving; inc edging and drainage channels
A66: 8 | B66: 8.3 | C66: Car parking (line-marked bays) | D66: Nr | E66: =IFERROR('Rates Reference Table'!I63*$E$5,0) -> 11.28 | F66: =IFERROR(E66*(1-$H$5/2),0) -> 10.0392 | G66: =IFERROR(E66*(1+$H$5/2),0) -> 12.5208 | H66: =IFERROR(F66*$B$5,0) -> 5019.6 | I66: =IFERROR(G66*$B$5,0) -> 6260.4 | J66: Surfacing, line markings, disabled bays
A67: 8 | B67: 8.4 | C67: Surface water drainage | D67: Item | E67: =IFERROR('Rates Reference Table'!I64*$E$5,0) -> 18.8 | F67: =IFERROR(E67*(1-$H$5/2),0) -> 16.732 | G67: =IFERROR(E67*(1+$H$5/2),0) -> 20.868 | H67: =IFERROR(F67*$B$5,0) -> 8366 | I67: =IFERROR(G67*$B$5,0) -> 10434 | J67: Gullies, pipes, SuDS if required by planning
A68: 8 | B68: 8.5 | C68: Foul drainage connections | D68: Item | E68: =IFERROR('Rates Reference Table'!I65*$E$5,0) -> 14.1 | F68: =IFERROR(E68*(1-$H$5/2),0) -> 12.549 | G68: =IFERROR(E68*(1+$H$5/2),0) -> 15.651 | H68: =IFERROR(F68*$B$5,0) -> 6274.5 | I68: =IFERROR(G68*$B$5,0) -> 7825.5 | J68: Connection to existing drain or new manhole
A69: 8 | B69: 8.6 | C69: External utility services | D69: Item | E69: =IFERROR('Rates Reference Table'!I66*$E$5,0) -> 18.8 | F69: =IFERROR(E69*(1-$H$5/2),0) -> 16.732 | G69: =IFERROR(E69*(1+$H$5/2),0) -> 20.868 | H69: =IFERROR(F69*$B$5,0) -> 8366 | I69: =IFERROR(G69*$B$5,0) -> 10434 | J69: Gas/water/electric diversions; early check with DNO
A70: 8 | B70: 8.7 | C70: Soft landscaping | D70: m² | E70: =IFERROR('Rates Reference Table'!I67*$E$5,0) -> 11.28 | F70: =IFERROR(E70*(1-$H$5/2),0) -> 10.0392 | G70: =IFERROR(E70*(1+$H$5/2),0) -> 12.5208 | H70: =IFERROR(F70*$B$5,0) -> 5019.6 | I70: =IFERROR(G70*$B$5,0) -> 6260.4 | J70: Planting, seeding, topsoil reinstatement
A71: 8 | B71: 8.8 | C71: Boundary enclosures (fences/gates) | D71: Item | E71: =IFERROR('Rates Reference Table'!I68*$E$5,0) -> 9.4 | F71: =IFERROR(E71*(1-$H$5/2),0) -> 8.366 | G71: =IFERROR(E71*(1+$H$5/2),0) -> 10.434 | H71: =IFERROR(F71*$B$5,0) -> 4183 | I71: =IFERROR(G71*$B$5,0) -> 5217 | J71: Security fencing, gates, boundary walls, railings
A72: 8 | B72: 8.9 | C72: External lighting | D72: Item | E72: =IFERROR('Rates Reference Table'!I69*$E$5,0) -> 7.52 | F72: =IFERROR(E72*(1-$H$5/2),0) -> 6.6928 | G72: =IFERROR(E72*(1+$H$5/2),0) -> 8.3472 | H72: =IFERROR(F72*$B$5,0) -> 3346.4 | I72: =IFERROR(G72*$B$5,0) -> 4173.6 | J72: Column or wall-mounted lighting (see also 5.10)
A73: WORKS COST SUBTOTAL (Groups 0–8) | H73: =SUMPRODUCT((H8:H72>0)*H8:H72) -> 2719786.6 | I73: =SUMPRODUCT((I8:I72>0)*I8:I72) -> 3392093.4
A75: ADDITIONS TO WORKS COST — Adjust % using signal rules in Notes column
A76: Code | D76: Description | E76: Applied To | F76: Low % | G76: High % | H76: Total LOW (£) | I76: Total HIGH (£) | J76: Signal Rules / Notes
A77: A | D77: Contractor's Preliminaries | E77: Works Cost | F77: 0.08 | G77: 0.1 | H77: =IFERROR(F77*H73,0) -> 217582.93 | I77: =IFERROR(G77*I73,0) -> 339209.34 | J77: 8%=clean/vacant/short prog | +0.5% per: 6-18mo prog, partial occ, restricted access | cap 10%
A78: B | D78: Contractor's Overheads & Profit | E78: Works Cost | F78: 0.08 | G78: 0.12 | H78: =IFERROR(F78*H73,0) -> 217582.93 | I78: =IFERROR(G78*I73,0) -> 407051.21 | J78: >£5M→8-9% | £1-5M→9-10% | <£1M→10-12% | Lower end = cost priority; upper = D&B/speed
A79: CONSTRUCTION COST SUBTOTAL (Works + Prelims + OH&P) | H79: =H73+H77+H78 -> 3154952.5 | I79: =I73+I77+I78 -> 4138353.9
A80: C | D80: Professional Fees | E80: Construction Cost | F80: 0.05 | G80: 0.15 | H80: =IFERROR(F80*H79,0) -> 157747.62 | I80: =IFERROR(G80*I79,0) -> 620753.09 | J80: Stage 0-1→12-15% | Stage 2→10-13% | Stage 3→7-10% | Stage 4→5-7% | +1-2% M&E/struct/BREEAM
A81: D | D81: Dev & Project Costs | E81: Construction Cost | F81: 0.02 | G81: 0.04 | H81: =IFERROR(F81*H79,0) -> 63099.049 | I81: =IFERROR(G81*I79,0) -> 165534.16 | J81: Full planning→3-4% | LBC also→4% | Permitted dev→2% | +0.5% if no surveys yet
A82: E | D82: Risk Allowance | E82: Works Cost | F82: 0.05 | G82: 0.1 | H82: =IFERROR(F82*H73,0) -> 135989.33 | I82: =IFERROR(G82*I73,0) -> 339209.34 | J82: Baseline 5% | +2% no surveys | +1.5% asbestos/contamination | +1% structural concern | +1% hard deadline | cap 10%
A83: H | D83: Client Contingency [FIXED 5%] | E83: Works Cost | F83: 0.05 | G83: 0.05 | H83: =IFERROR(0.05*H73,0) -> 135989.33 | I83: =IFERROR(0.05*I73,0) -> 169604.67 | J83: FIXED at 5% — held by client, not released to contractor. Do not adjust.
A84: F | D84: Inflation Allowance | E84: Works Cost | F84: 0.02 | G84: 0.12 | H84: =IFERROR(F84*H73,0) -> 54395.732 | I84: =IFERROR(G84*I73,0) -> 407051.21 | J84: Component 1: tender delay (0-18mo=2-6%) + Component 2: construction mid-point (6-24mo=1-4%) | cap 12%
A85: TOTAL PROJECT COST (excl. VAT) | H85: =H79+H80+H81+H82+H83+H84 -> 3702173.5 | I85: =I79+I80+I81+I82+I83+I84 -> 5840506.4
A86: G | D86: VAT — reference only, NOT in total | E86: Project Total | F86: 0.2 | G86: 0.2 | H86: =IFERROR(0.2*H85,0) -> 740434.7 | I86: =IFERROR(0.2*I85,0) -> 1168101.3 | J86: Recoverability must be confirmed with client Finance team. New build may attract zero-rating.
A88: Implied blended Works Cost rate — cross-check against BCIS benchmarks: | E88: =IFERROR(H73/$B$5,0) -> 5439.5732 | G88: =IFERROR(I73/$B$5,0) -> 6784.1868
A90: ⚠ DISCLAIMER: Indicative only — RIBA Stage 0–1 without measured quantities. Rates from Rates Reference Table, cross-referenced Q2 2026 market data. Must be reviewed by a Chartered QS before use in any business case or budget approval. LOW–HIGH range = mid-point ± 11% (default spread 22%). Update GIFA, BCIS factor and Spread as required.

Sheet Extension – Std
A1: NRM1 ESTIMATE — EXTENSION — STANDARD
A2: Spec level: Standard extension to existing building, matching existing spec and construction. | RIBA Stage 0–1 indicative only | Base date Q2 2026
A4: Project Type: | B4: Extension | D4: Spec Level: | E4: Standard | G4: Region: | H4: West Midlands
A5: GIFA (m²) ▼ update: | B5: 250 | D5: BCIS Location Factor ▼: | E5: 0.94 | G5: Spread ±% ▼: | H5: 0.22
A7: Grp | B7: Sub | C7: Element / Description | D7: Unit | E7: Mid-Point £/m² | F7: Low £/m² | G7: High £/m² | H7: Total LOW (£) | I7: Total HIGH (£) | J7: Notes / Rate Driver
A8: GROUP 0 — FACILITATING WORKS
A9: 0 | B9: 0.1 | C9: Toxic/hazardous material removal | D9: Item | E9: =IFERROR('Rates Reference Table'!J6*$E$5,0) -> 9.4 | F9: =IFERROR(E9*(1-$H$5/2),0) -> 8.366 | G9: =IFERROR(E9*(1+$H$5/2),0) -> 10.434 | H9: =IFERROR(F9*$B$5,0) -> 2091.5 | I9: =IFERROR(G9*$B$5,0) -> 2608.5 | J9: Asbestos; increase if confirmed present (refurb/demo only)
A10: 0 | B10: 0.2 | C10: Demolition & structural alterations | D10: Item | E10: =IFERROR('Rates Reference Table'!J7*$E$5,0) -> 18.8 | F10: =IFERROR(E10*(1-$H$5/2),0) -> 16.732 | G10: =IFERROR(E10*(1+$H$5/2),0) -> 20.868 | H10: =IFERROR(F10*$B$5,0) -> 4183 | I10: =IFERROR(G10*$B$5,0) -> 5217 | J10: Selective or full demolition; structural openings
A11: 0 | B11: 0.3 | C11: Contaminated land remediation | D11: Item | E11: =IFERROR('Rates Reference Table'!J8*$E$5,0) -> 4.7 | F11: =IFERROR(E11*(1-$H$5/2),0) -> 4.183 | G11: =IFERROR(E11*(1+$H$5/2),0) -> 5.217 | H11: =IFERROR(F11*$B$5,0) -> 1045.75 | I11: =IFERROR(G11*$B$5,0) -> 1304.25 | J11: Brownfield/contaminated; specialist quote needed
A12: 0 | B12: 0.4 | C12: Ground stabilisation | D12: Item | E12: =IFERROR('Rates Reference Table'!J9*$E$5,0) -> 4.7 | F12: =IFERROR(E12*(1-$H$5/2),0) -> 4.183 | G12: =IFERROR(E12*(1+$H$5/2),0) -> 5.217 | H12: =IFERROR(F12*$B$5,0) -> 1045.75 | I12: =IFERROR(G12*$B$5,0) -> 1304.25 | J12: Underpinning/piling if ground risk identified
A13: GROUP 1 — SUBSTRUCTURE
A14: 1 | B14: 1.1 | C14: Standard foundations (strip/pad) | D14: m² | E14: =IFERROR('Rates Reference Table'!J11*$E$5,0) -> 51.7 | F14: =IFERROR(E14*(1-$H$5/2),0) -> 46.013 | G14: =IFERROR(E14*(1+$H$5/2),0) -> 57.387 | H14: =IFERROR(F14*$B$5,0) -> 11503.25 | I14: =IFERROR(G14*$B$5,0) -> 14346.75 | J14: New build only; included in Group 7 rate for extensions
A15: 1 | B15: 1.2 | C15: Specialist foundations (piled) | D15: m² | E15: =IFERROR('Rates Reference Table'!J12*$E$5,0) -> 37.6 | F15: =IFERROR(E15*(1-$H$5/2),0) -> 33.464 | G15: =IFERROR(E15*(1+$H$5/2),0) -> 41.736 | H15: =IFERROR(F15*$B$5,0) -> 8366 | I15: =IFERROR(G15*$B$5,0) -> 10434 | J15: Poor ground conditions; trigger from GI report
A16: 1 | B16: 1.3 | C16: Lowest floor construction (slab) | D16: m² | E16: =IFERROR('Rates Reference Table'!J13*$E$5,0) -> 32.9 | F16: =IFERROR(E16*(1-$H$5/2),0) -> 29.281 | G16: =IFERROR(E16*(1+$H$5/2),0) -> 36.519 | H16: =IFERROR(F16*$B$5,0) -> 7320.25 | I16: =IFERROR(G16*$B$5,0) -> 9129.75 | J16: Ground bearing or suspended; inc DPM and insulation
A17: 1 | B17: 1.4 | C17: Basement excavation & structure | D17: Item | E17: =IFERROR('Rates Reference Table'!J14*$E$5,0) -> 75.2 | F17: =IFERROR(E17*(1-$H$5/2),0) -> 66.928 | G17: =IFERROR(E17*(1+$H$5/2),0) -> 83.472 | H17: =IFERROR(F17*$B$5,0) -> 16732 | I17: =IFERROR(G17*$B$5,0) -> 20868 | J17: High uncertainty; specialist estimate recommended
A18: GROUP 2 — SUPERSTRUCTURE
A19: 2 | B19: 2.1 | C19: Structural frame | D19: m² | E19: =IFERROR('Rates Reference Table'!J16*$E$5,0) -> 122.2 | F19: =IFERROR(E19*(1-$H$5/2),0) -> 108.758 | G19: =IFERROR(E19*(1+$H$5/2),0) -> 135.642 | H19: =IFERROR(F19*$B$5,0) -> 27189.5 | I19: =IFERROR(G19*$B$5,0) -> 33910.5 | J19: Steel/concrete/timber; new build or major extensions only
A20: 2 | B20: 2.2 | C20: Upper floors | D20: m² | E20: =IFERROR('Rates Reference Table'!J17*$E$5,0) -> 61.1 | F20: =IFERROR(E20*(1-$H$5/2),0) -> 54.379 | G20: =IFERROR(E20*(1+$H$5/2),0) -> 67.821 | H20: =IFERROR(F20*$B$5,0) -> 13594.75 | I20: =IFERROR(G20*$B$5,0) -> 16955.25 | J20: New build or added floors; inc topping and insulation
A21: 2 | B21: 2.3 | C21: Roof structure & covering | D21: m² | E21: =IFERROR('Rates Reference Table'!J18*$E$5,0) -> 70.5 | F21: =IFERROR(E21*(1-$H$5/2),0) -> 62.745 | G21: =IFERROR(E21*(1+$H$5/2),0) -> 78.255 | H21: =IFERROR(F21*$B$5,0) -> 15686.25 | I21: =IFERROR(G21*$B$5,0) -> 19563.75 | J21: New or replacement; inc insulation, waterproofing, rainwater
A22: 2 | B22: 2.4 | C22: Stairs & ramps | D22: Item | E22: =IFERROR('Rates Reference Table'!J19*$E$5,0) -> 18.8 | F22: =IFERROR(E22*(1-$H$5/2),0) -> 16.732 | G22: =IFERROR(E22*(1+$H$5/2),0) -> 20.868 | H22: =IFERROR(F22*$B$5,0) -> 4183 | I22: =IFERROR(G22*$B$5,0) -> 5217 | J22: RC, steel or timber; accessibility ramps
A23: 2 | B23: 2.5 | C23: External walls & facade | D23: m² | E23: =IFERROR('Rates Reference Table'!J20*$E$5,0) -> 169.2 | F23: =IFERROR(E23*(1-$H$5/2),0) -> 150.588 | G23: =IFERROR(E23*(1+$H$5/2),0) -> 187.812 | H23: =IFERROR(F23*$B$5,0) -> 37647 | I23: =IFERROR(G23*$B$5,0) -> 46953 | J23: Masonry/cladding; refurb = overcladding or repair only
A24: 2 | B24: 2.6 | C24: Windows & external doors | D24: m² | E24: =IFERROR('Rates Reference Table'!J21*$E$5,0) -> 84.6 | F24: =IFERROR(E24*(1-$H$5/2),0) -> 75.294 | G24: =IFERROR(E24*(1+$H$5/2),0) -> 93.906 | H24: =IFERROR(F24*$B$5,0) -> 18823.5 | I24: =IFERROR(G24*$B$5,0) -> 23476.5 | J24: uPVC (low) to aluminium curtain wall (high)
A25: 2 | B25: 2.7 | C25: Internal walls & partitions | D25: m² | E25: =IFERROR('Rates Reference Table'!J22*$E$5,0) -> 23.5 | F25: =IFERROR(E25*(1-$H$5/2),0) -> 20.915 | G25: =IFERROR(E25*(1+$H$5/2),0) -> 26.085 | H25: =IFERROR(F25*$B$5,0) -> 5228.75 | I25: =IFERROR(G25*$B$5,0) -> 6521.25 | J25: Blockwork, drywall or glazed; do not double-count Grp 3
A26: 2 | B26: 2.8 | C26: Internal doors & ironmongery | D26: Nr | E26: =IFERROR('Rates Reference Table'!J23*$E$5,0) -> 16.92 | F26: =IFERROR(E26*(1-$H$5/2),0) -> 15.0588 | G26: =IFERROR(E26*(1+$H$5/2),0) -> 18.7812 | H26: =IFERROR(F26*$B$5,0) -> 3764.7 | I26: =IFERROR(G26*$B$5,0) -> 4695.3 | J26: Fire-rated at upper range; standard at lower
A27: GROUP 3 — INTERNAL FINISHES ★ ALWAYS INCLUDED
A28: 3 | B28: 3.1 | C28: Wall finishes | D28: m² | E28: =IFERROR('Rates Reference Table'!J25*$E$5,0) -> 18.8 | F28: =IFERROR(E28*(1-$H$5/2),0) -> 16.732 | G28: =IFERROR(E28*(1+$H$5/2),0) -> 20.868 | H28: =IFERROR(F28*$B$5,0) -> 4183 | I28: =IFERROR(G28*$B$5,0) -> 5217 | J28: Emulsion (low) → specialist tiling/feature panelling (high)
A29: 3 | B29: 3.2 | C29: Floor finishes | D29: m² | E29: =IFERROR('Rates Reference Table'!J26*$E$5,0) -> 23.5 | F29: =IFERROR(E29*(1-$H$5/2),0) -> 20.915 | G29: =IFERROR(E29*(1+$H$5/2),0) -> 26.085 | H29: =IFERROR(F29*$B$5,0) -> 5228.75 | I29: =IFERROR(G29*$B$5,0) -> 6521.25 | J29: Vinyl/carpet (low) → stone/raised access floor (high)
A30: 3 | B30: 3.3 | C30: Ceiling finishes | D30: m² | E30: =IFERROR('Rates Reference Table'!J27*$E$5,0) -> 11.28 | F30: =IFERROR(E30*(1-$H$5/2),0) -> 10.0392 | G30: =IFERROR(E30*(1+$H$5/2),0) -> 12.5208 | H30: =IFERROR(F30*$B$5,0) -> 2509.8 | I30: =IFERROR(G30*$B$5,0) -> 3130.2 | J30: Emulsion (low) → bespoke acoustic ceiling system (high)
A31: GROUP 4 — FITTINGS, FURNISHINGS & EQUIPMENT
A32: 4 | B32: 4.1 | C32: General fittings & built-in joinery | D32: Item | E32: =IFERROR('Rates Reference Table'!J29*$E$5,0) -> 9.4 | F32: =IFERROR(E32*(1-$H$5/2),0) -> 8.366 | G32: =IFERROR(E32*(1+$H$5/2),0) -> 10.434 | H32: =IFERROR(F32*$B$5,0) -> 2091.5 | I32: =IFERROR(G32*$B$5,0) -> 2608.5 | J32: Reception desks, shelving, built-in furniture
A33: 4 | B33: 4.2 | C33: Sanitary fittings & toilet fit-out | D33: Nr | E33: =IFERROR('Rates Reference Table'!J30*$E$5,0) -> 7.52 | F33: =IFERROR(E33*(1-$H$5/2),0) -> 6.6928 | G33: =IFERROR(E33*(1+$H$5/2),0) -> 8.3472 | H33: =IFERROR(F33*$B$5,0) -> 1673.2 | I33: =IFERROR(G33*$B$5,0) -> 2086.8 | J33: WC packs; uplift for accessible/changing facilities
A34: 4 | B34: 4.3 | C34: Kitchen / break-out area | D34: Item | E34: =IFERROR('Rates Reference Table'!J31*$E$5,0) -> 4.7 | F34: =IFERROR(E34*(1-$H$5/2),0) -> 4.183 | G34: =IFERROR(E34*(1+$H$5/2),0) -> 5.217 | H34: =IFERROR(F34*$B$5,0) -> 1045.75 | I34: =IFERROR(G34*$B$5,0) -> 1304.25 | J34: Fitted units, worktops, appliances
A35: 4 | B35: 4.4 | C35: Specialist equipment (lab/AV/med) | D35: Item | E35: =IFERROR('Rates Reference Table'!J32*$E$5,0) -> 0 | F35: =IFERROR(E35*(1-$H$5/2),0) -> 0 | G35: =IFERROR(E35*(1+$H$5/2),0) -> 0 | H35: =IFERROR(F35*$B$5,0) -> 0 | I35: =IFERROR(G35*$B$5,0) -> 0 | J35: Laboratory, medical, AV; confirm with specialist
A36: GROUP 5 — MECHANICAL & ELECTRICAL SERVICES ★ KEY ELEMENT
A37: 5 | B37: 5.1 | C37: Sanitary plumbing (1st & 2nd fix) | D37: m² | E37: =IFERROR('Rates Reference Table'!J34*$E$5,0) -> 18.8 | F37: =IFERROR(E37*(1-$H$5/2),0) -> 16.732 | G37: =IFERROR(E37*(1+$H$5/2),0) -> 20.868 | H37: =IFERROR(F37*$B$5,0) -> 4183 | I37: =IFERROR(G37*$B$5,0) -> 5217 | J37: HWS, cold water, drainage connections
A38: 5 | B38: 5.2 | C38: Heating & hot water (LTHW/heat pump) | D38: m² | E38: =IFERROR('Rates Reference Table'!J35*$E$5,0) -> 28.2 | F38: =IFERROR(E38*(1-$H$5/2),0) -> 25.098 | G38: =IFERROR(E38*(1+$H$5/2),0) -> 31.302 | H38: =IFERROR(F38*$B$5,0) -> 6274.5 | I38: =IFERROR(G38*$B$5,0) -> 7825.5 | J38: LTHW system or heat pump; include buffer vessel
A39: 5 | B39: 5.3 | C39: Ventilation & air handling | D39: m² | E39: =IFERROR('Rates Reference Table'!J36*$E$5,0) -> 23.5 | F39: =IFERROR(E39*(1-$H$5/2),0) -> 20.915 | G39: =IFERROR(E39*(1+$H$5/2),0) -> 26.085 | H39: =IFERROR(F39*$B$5,0) -> 5228.75 | I39: =IFERROR(G39*$B$5,0) -> 6521.25 | J39: MVHR/AHU; uplift for lab/healthcare extract (+50-100%)
A40: 5 | B40: 5.4 | C40: Air conditioning & cooling | D40: m² | E40: =IFERROR('Rates Reference Table'!J37*$E$5,0) -> 9.4 | F40: =IFERROR(E40*(1-$H$5/2),0) -> 8.366 | G40: =IFERROR(E40*(1+$H$5/2),0) -> 10.434 | H40: =IFERROR(F40*$B$5,0) -> 2091.5 | I40: =IFERROR(G40*$B$5,0) -> 2608.5 | J40: VRF/splits; omit if not in scope
A41: 5 | B41: 5.5 | C41: Gas installation | D41: Item | E41: =IFERROR('Rates Reference Table'!J38*$E$5,0) -> 4.7 | F41: =IFERROR(E41*(1-$H$5/2),0) -> 4.183 | G41: =IFERROR(E41*(1+$H$5/2),0) -> 5.217 | H41: =IFERROR(F41*$B$5,0) -> 1045.75 | I41: =IFERROR(G41*$B$5,0) -> 1304.25 | J41: Omit if all-electric; confirm with utility
A42: 5 | B42: 5.6 | C42: Sprinkler / fire suppression | D42: m² | E42: =IFERROR('Rates Reference Table'!J39*$E$5,0) -> 4.7 | F42: =IFERROR(E42*(1-$H$5/2),0) -> 4.183 | G42: =IFERROR(E42*(1+$H$5/2),0) -> 5.217 | H42: =IFERROR(F42*$B$5,0) -> 1045.75 | I42: =IFERROR(G42*$B$5,0) -> 1304.25 | J42: >18m height or insurer requirement
A43: 5 | B43: 5.7 | C43: Electrical distribution & switchgear | D43: m² | E43: =IFERROR('Rates Reference Table'!J40*$E$5,0) -> 14.1 | F43: =IFERROR(E43*(1-$H$5/2),0) -> 12.549 | G43: =IFERROR(E43*(1+$H$5/2),0) -> 15.651 | H43: =IFERROR(F43*$B$5,0) -> 3137.25 | I43: =IFERROR(G43*$B$5,0) -> 3912.75 | J43: LV panels, distribution boards, earthing, containment
A44: 5 | B44: 5.8 | C44: Electrical wiring (1st & 2nd fix) | D44: m² | E44: =IFERROR('Rates Reference Table'!J41*$E$5,0) -> 23.5 | F44: =IFERROR(E44*(1-$H$5/2),0) -> 20.915 | G44: =IFERROR(E44*(1+$H$5/2),0) -> 26.085 | H44: =IFERROR(F44*$B$5,0) -> 5228.75 | I44: =IFERROR(G44*$B$5,0) -> 6521.25 | J44: All power and lighting circuits; inc containment
A45: 5 | B45: 5.9 | C45: Emergency lighting & fire alarm | D45: m² | E45: =IFERROR('Rates Reference Table'!J42*$E$5,0) -> 9.4 | F45: =IFERROR(E45*(1-$H$5/2),0) -> 8.366 | G45: =IFERROR(E45*(1+$H$5/2),0) -> 10.434 | H45: =IFERROR(F45*$B$5,0) -> 2091.5 | I45: =IFERROR(G45*$B$5,0) -> 2608.5 | J45: L2 minimum; upgrade for multi-zone/complex layouts
A46: 5 | B46: 5.10 | C46: External lighting | D46: Item | E46: =IFERROR('Rates Reference Table'!J43*$E$5,0) -> 2.82 | F46: =IFERROR(E46*(1-$H$5/2),0) -> 2.5098 | G46: =IFERROR(E46*(1+$H$5/2),0) -> 3.1302 | H46: =IFERROR(F46*$B$5,0) -> 627.45 | I46: =IFERROR(G46*$B$5,0) -> 782.55 | J46: Column/wall-mounted perimeter lighting
A47: 5 | B47: 5.11 | C47: Solar PV / renewables | D47: kWp | E47: =IFERROR('Rates Reference Table'!J44*$E$5,0) -> 752 | F47: =IFERROR(E47*(1-$H$5/2),0) -> 669.28 | G47: =IFERROR(E47*(1+$H$5/2),0) -> 834.72 | H47: =IFERROR(F47*$B$5,0) -> 167320 | I47: =IFERROR(G47*$B$5,0) -> 208680 | J47: £/kWp installed; coordinate structural loading + electrical
A48: 5 | B48: 5.12 | C48: EV charging points | D48: Nr | E48: =IFERROR('Rates Reference Table'!J45*$E$5,0) -> 1410 | F48: =IFERROR(E48*(1-$H$5/2),0) -> 1254.9 | G48: =IFERROR(E48*(1+$H$5/2),0) -> 1565.1 | H48: =IFERROR(F48*$B$5,0) -> 313725 | I48: =IFERROR(G48*$B$5,0) -> 391275 | J48: Per charge point inc groundworks; 7kW fast charger
... A53: 5 | B53: 5.17 | C53: Builder's work in connection (BWIC) | D53: m² | E53: =IFERROR('Rates Reference Table'!J50*$E$5,0) -> 5.64 | F53: =IFERROR(E53*(1-$H$5/2),0) -> 5.0196 | G53: =IFERROR(E53*(1+$H$5/2),0) -> 6.2604 | H53: =IFERROR(F53*$B$5,0) -> 1254.9 | I53: =IFERROR(G53*$B$5,0) -> 1565.1 | J53: Penetrations, plinths, ducts, concrete bases for plant
A54: GROUP 6 — PREFABRICATED / MODULAR (if applicable)
A55: 6 | B55: 6.1 | C55: Prefabricated / modular units | D55: Item | E55: EXCLUDED | F55: EXCLUDED | G55: EXCLUDED | H55: 0 | I55: 0 | J55: Factory-built modular; specialist quote required
A56: 6 | B56: 6.2 | C56: Pre-engineered systems (mezzanine) | D56: Item | E56: EXCLUDED | F56: EXCLUDED | G56: EXCLUDED | H56: 0 | I56: 0 | J56: Mezzanine floors, demountable partitions
A57: GROUP 7 — WORK TO EXISTING BUILDINGS
A58: 7 | B58: 7.1 | C58: Structural repairs | D58: Item | E58: =IFERROR('Rates Reference Table'!J55*$E$5,0) -> 14.1 | F58: =IFERROR(E58*(1-$H$5/2),0) -> 12.549 | G58: =IFERROR(E58*(1+$H$5/2),0) -> 15.651 | H58: =IFERROR(F58*$B$5,0) -> 3137.25 | I58: =IFERROR(G58*$B$5,0) -> 3912.75 | J58: Crack stitching, bearing repairs; increase for poor condition
A59: 7 | B59: 7.2 | C59: Fabric / envelope repairs | D59: Item | E59: =IFERROR('Rates Reference Table'!J56*$E$5,0) -> 11.28 | F59: =IFERROR(E59*(1-$H$5/2),0) -> 10.0392 | G59: =IFERROR(E59*(1+$H$5/2),0) -> 12.5208 | H59: =IFERROR(F59*$B$5,0) -> 2509.8 | I59: =IFERROR(G59*$B$5,0) -> 3130.2 | J59: Repointing, waterproofing, weathertight works
A60: 7 | B60: 7.3 | C60: Damp proof course treatment | D60: Item | E60: =IFERROR('Rates Reference Table'!J57*$E$5,0) -> 4.7 | F60: =IFERROR(E60*(1-$H$5/2),0) -> 4.183 | G60: =IFERROR(E60*(1+$H$5/2),0) -> 5.217 | H60: =IFERROR(F60*$B$5,0) -> 1045.75 | I60: =IFERROR(G60*$B$5,0) -> 1304.25 | J60: Chemical DPC; increase for severe rising damp
A61: 7 | B61: 7.4 | C61: M&E overhaul / life-expired services | D61: Item | E61: =IFERROR('Rates Reference Table'!J58*$E$5,0) -> 18.8 | F61: =IFERROR(E61*(1-$H$5/2),0) -> 16.732 | G61: =IFERROR(E61*(1+$H$5/2),0) -> 20.868 | H61: =IFERROR(F61*$B$5,0) -> 4183 | I61: =IFERROR(G61*$B$5,0) -> 5217 | J61: Replacement of end-of-life mechanical & electrical plant
A62: 7 | B62: 7.5 | C62: Making good after structural works | D62: Item | E62: =IFERROR('Rates Reference Table'!J59*$E$5,0) -> 4.7 | F62: =IFERROR(E62*(1-$H$5/2),0) -> 4.183 | G62: =IFERROR(E62*(1+$H$5/2),0) -> 5.217 | H62: =IFERROR(F62*$B$5,0) -> 1045.75 | I62: =IFERROR(G62*$B$5,0) -> 1304.25 | J62: Patch plaster, redecoration after structural alterations
A63: GROUP 8 — EXTERNAL WORKS
A64: 8 | B64: 8.1 | C64: Site preparation & clearance | D64: Item | E64: =IFERROR('Rates Reference Table'!J61*$E$5,0) -> 4.7 | F64: =IFERROR(E64*(1-$H$5/2),0) -> 4.183 | G64: =IFERROR(E64*(1+$H$5/2),0) -> 5.217 | H64: =IFERROR(F64*$B$5,0) -> 1045.75 | I64: =IFERROR(G64*$B$5,0) -> 1304.25 | J64: Strip topsoil, vegetation, temp fencing and hoarding
A65: 8 | B65: 8.2 | C65: Roads, paths & hard paving | D65: m² | E65: =IFERROR('Rates Reference Table'!J62*$E$5,0) -> 9.4 | F65: =IFERROR(E65*(1-$H$5/2),0) -> 8.366 | G65: =IFERROR(E65*(1+$H$5/2),0) -> 10.434 | H65: =IFERROR(F65*$B$5,0) -> 2091.5 | I65: =IFERROR(G65*$B$5,0) -> 2608.5 | J65: Macadam/block paving; inc edging and drainage channels
A66: 8 | B66: 8.3 | C66: Car parking (line-marked bays) | D66: Nr | E66: =IFERROR('Rates Reference Table'!J63*$E$5,0) -> 2.82 | F66: =IFERROR(E66*(1-$H$5/2),0) -> 2.5098 | G66: =IFERROR(E66*(1+$H$5/2),0) -> 3.1302 | H66: =IFERROR(F66*$B$5,0) -> 627.45 | I66: =IFERROR(G66*$B$5,0) -> 782.55 | J66: Surfacing, line markings, disabled bays
A67: 8 | B67: 8.4 | C67: Surface water drainage | D67: Item | E67: =IFERROR('Rates Reference Table'!J64*$E$5,0) -> 4.7 | F67: =IFERROR(E67*(1-$H$5/2),0) -> 4.183 | G67: =IFERROR(E67*(1+$H$5/2),0) -> 5.217 | H67: =IFERROR(F67*$B$5,0) -> 1045.75 | I67: =IFERROR(G67*$B$5,0) -> 1304.25 | J67: Gullies, pipes, SuDS if required by planning
A68: 8 | B68: 8.5 | C68: Foul drainage connections | D68: Item | E68: =IFERROR('Rates Reference Table'!J65*$E$5,0) -> 4.7 | F68: =IFERROR(E68*(1-$H$5/2),0) -> 4.183 | G68: =IFERROR(E68*(1+$H$5/2),0) -> 5.217 | H68: =IFERROR(F68*$B$5,0) -> 1045.75 | I68: =IFERROR(G68*$B$5,0) -> 1304.25 | J68: Connection to existing drain or new manhole
A69: 8 | B69: 8.6 | C69: External utility services | D69: Item | E69: =IFERROR('Rates Reference Table'!J66*$E$5,0) -> 4.7 | F69: =IFERROR(E69*(1-$H$5/2),0) -> 4.183 | G69: =IFERROR(E69*(1+$H$5/2),0) -> 5.217 | H69: =IFERROR(F69*$B$5,0) -> 1045.75 | I69: =IFERROR(G69*$B$5,0) -> 1304.25 | J69: Gas/water/electric diversions; early check with DNO
A70: 8 | B70: 8.7 | C70: Soft landscaping | D70: m² | E70: =IFERROR('Rates Reference Table'!J67*$E$5,0) -> 2.82 | F70: =IFERROR(E70*(1-$H$5/2),0) -> 2.5098 | G70: =IFERROR(E70*(1+$H$5/2),0) -> 3.1302 | H70: =IFERROR(F70*$B$5,0) -> 627.45 | I70: =IFERROR(G70*$B$5,0) -> 782.55 | J70: Planting, seeding, topsoil reinstatement
A71: 8 | B71: 8.8 | C71: Boundary enclosures (fences/gates) | D71: Item | E71: =IFERROR('Rates Reference Table'!J68*$E$5,0) -> 1.88 | F71: =IFERROR(E71*(1-$H$5/2),0) -> 1.6732 | G71: =IFERROR(E71*(1+$H$5/2),0) -> 2.0868 | H71: =IFERROR(F71*$B$5,0) -> 418.3 | I71: =IFERROR(G71*$B$5,0) -> 521.7 | J71: Security fencing, gates, boundary walls, railings
A72: 8 | B72: 8.9 | C72: External lighting | D72: Item | E72: =IFERROR('Rates Reference Table'!J69*$E$5,0) -> 1.88 | F72: =IFERROR(E72*(1-$H$5/2),0) -> 1.6732 | G72: =IFERROR(E72*(1+$H$5/2),0) -> 2.0868 | H72: =IFERROR(F72*$B$5,0) -> 418.3 | I72: =IFERROR(G72*$B$5,0) -> 521.7 | J72: Column or wall-mounted lighting (see also 5.10)
A73: WORKS COST SUBTOTAL (Groups 0–8) | H73: =SUMPRODUCT((H8:H72>0)*H8:H72) -> 742482.5 | I73: =SUMPRODUCT((I8:I72>0)*I8:I72) -> 926017.5
A75: ADDITIONS TO WORKS COST — Adjust % using signal rules in Notes column
A76: Code | D76: Description | E76: Applied To | F76: Low % | G76: High % | H76: Total LOW (£) | I76: Total HIGH (£) | J76: Signal Rules / Notes
A77: A | D77: Contractor's Preliminaries | E77: Works Cost | F77: 0.08 | G77: 0.1 | H77: =IFERROR(F77*H73,0) -> 59398.6 | I77: =IFERROR(G77*I73,0) -> 92601.75 | J77: 8%=clean/vacant/short prog | +0.5% per: 6-18mo prog, partial occ, restricted access | cap 10%
A78: B | D78: Contractor's Overheads & Profit | E78: Works Cost | F78: 0.08 | G78: 0.12 | H78: =IFERROR(F78*H73,0) -> 59398.6 | I78: =IFERROR(G78*I73,0) -> 111122.1 | J78: >£5M→8-9% | £1-5M→9-10% | <£1M→10-12% | Lower end = cost priority; upper = D&B/speed
A79: CONSTRUCTION COST SUBTOTAL (Works + Prelims + OH&P) | H79: =H73+H77+H78 -> 861279.7 | I79: =I73+I77+I78 -> 1129741.4
A80: C | D80: Professional Fees | E80: Construction Cost | F80: 0.05 | G80: 0.15 | H80: =IFERROR(F80*H79,0) -> 43063.985 | I80: =IFERROR(G80*I79,0) -> 169461.2 | J80: Stage 0-1→12-15% | Stage 2→10-13% | Stage 3→7-10% | Stage 4→5-7% | +1-2% M&E/struct/BREEAM
A81: D | D81: Dev & Project Costs | E81: Construction Cost | F81: 0.02 | G81: 0.04 | H81: =IFERROR(F81*H79,0) -> 17225.594 | I81: =IFERROR(G81*I79,0) -> 45189.654 | J81: Full planning→3-4% | LBC also→4% | Permitted dev→2% | +0.5% if no surveys yet
A82: E | D82: Risk Allowance | E82: Works Cost | F82: 0.05 | G82: 0.1 | H82: =IFERROR(F82*H73,0) -> 37124.125 | I82: =IFERROR(G82*I73,0) -> 92601.75 | J82: Baseline 5% | +2% no surveys | +1.5% asbestos/contamination | +1% structural concern | +1% hard deadline | cap 10%
A83: H | D83: Client Contingency [FIXED 5%] | E83: Works Cost | F83: 0.05 | G83: 0.05 | H83: =IFERROR(0.05*H73,0) -> 37124.125 | I83: =IFERROR(0.05*I73,0) -> 46300.875 | J83: FIXED at 5% — held by client, not released to contractor. Do not adjust.
A84: F | D84: Inflation Allowance | E84: Works Cost | F84: 0.02 | G84: 0.12 | H84: =IFERROR(F84*H73,0) -> 14849.65 | I84: =IFERROR(G84*I73,0) -> 111122.1 | J84: Component 1: tender delay (0-18mo=2-6%) + Component 2: construction mid-point (6-24mo=1-4%) | cap 12%
A85: TOTAL PROJECT COST (excl. VAT) | H85: =H79+H80+H81+H82+H83+H84 -> 1010667.2 | I85: =I79+I80+I81+I82+I83+I84 -> 1594416.9
A86: G | D86: VAT — reference only, NOT in total | E86: Project Total | F86: 0.2 | G86: 0.2 | H86: =IFERROR(0.2*H85,0) -> 202133.44 | I86: =IFERROR(0.2*I85,0) -> 318883.39 | J86: Recoverability must be confirmed with client Finance team. New build may attract zero-rating.
A88: Implied blended Works Cost rate — cross-check against BCIS benchmarks: | E88: =IFERROR(H73/$B$5,0) -> 2969.93 | G88: =IFERROR(I73/$B$5,0) -> 3704.07
A90: ⚠ DISCLAIMER: Indicative only — RIBA Stage 0–1 without measured quantities. Rates from Rates Reference Table, cross-referenced Q2 2026 market data. Must be reviewed by a Chartered QS before use in any business case or budget approval. LOW–HIGH range = mid-point ± 11% (default spread 22%). Update GIFA, BCIS factor and Spread as required.

Sheet Extension – High
A1: NRM1 ESTIMATE — EXTENSION — HIGH SPEC
A2: Spec level: High-spec or technically complex extension (lab, glazed atrium, bespoke facade). | RIBA Stage 0–1 indicative only | Base date Q2 2026
A4: Project Type: | B4: Extension | D4: Spec Level: | E4: High Spec | G4: Region: | H4: West Midlands
A5: GIFA (m²) ▼ update: | B5: 250 | D5: BCIS Location Factor ▼: | E5: 0.94 | G5: Spread ±% ▼: | H5: 0.22
A7: Grp | B7: Sub | C7: Element / Description | D7: Unit | E7: Mid-Point £/m² | F7: Low £/m² | G7: High £/m² | H7: Total LOW (£) | I7: Total HIGH (£) | J7: Notes / Rate Driver
A8: GROUP 0 — FACILITATING WORKS
A9: 0 | B9: 0.1 | C9: Toxic/hazardous material removal | D9: Item | E9: =IFERROR('Rates Reference Table'!K6*$E$5,0) -> 18.8 | F9: =IFERROR(E9*(1-$H$5/2),0) -> 16.732 | G9: =IFERROR(E9*(1+$H$5/2),0) -> 20.868 | H9: =IFERROR(F9*$B$5,0) -> 4183 | I9: =IFERROR(G9*$B$5,0) -> 5217 | J9: Asbestos; increase if confirmed present (refurb/demo only)
A10: 0 | B10: 0.2 | C10: Demolition & structural alterations | D10: Item | E10: =IFERROR('Rates Reference Table'!K7*$E$5,0) -> 32.9 | F10: =IFERROR(E10*(1-$H$5/2),0) -> 29.281 | G10: =IFERROR(E10*(1+$H$5/2),0) -> 36.519 | H10: =IFERROR(F10*$B$5,0) -> 7320.25 | I10: =IFERROR(G10*$B$5,0) -> 9129.75 | J10: Selective or full demolition; structural openings
A11: 0 | B11: 0.3 | C11: Contaminated land remediation | D11: Item | E11: =IFERROR('Rates Reference Table'!K8*$E$5,0) -> 14.1 | F11: =IFERROR(E11*(1-$H$5/2),0) -> 12.549 | G11: =IFERROR(E11*(1+$H$5/2),0) -> 15.651 | H11: =IFERROR(F11*$B$5,0) -> 3137.25 | I11: =IFERROR(G11*$B$5,0) -> 3912.75 | J11: Brownfield/contaminated; specialist quote needed
A12: 0 | B12: 0.4 | C12: Ground stabilisation | D12: Item | E12: =IFERROR('Rates Reference Table'!K9*$E$5,0) -> 11.28 | F12: =IFERROR(E12*(1-$H$5/2),0) -> 10.0392 | G12: =IFERROR(E12*(1+$H$5/2),0) -> 12.5208 | H12: =IFERROR(F12*$B$5,0) -> 2509.8 | I12: =IFERROR(G12*$B$5,0) -> 3130.2 | J12: Underpinning/piling if ground risk identified
A13: GROUP 1 — SUBSTRUCTURE
A14: 1 | B14: 1.1 | C14: Standard foundations (strip/pad) | D14: m² | E14: =IFERROR('Rates Reference Table'!K11*$E$5,0) -> 75.2 | F14: =IFERROR(E14*(1-$H$5/2),0) -> 66.928 | G14: =IFERROR(E14*(1+$H$5/2),0) -> 83.472 | H14: =IFERROR(F14*$B$5,0) -> 16732 | I14: =IFERROR(G14*$B$5,0) -> 20868 | J14: New build only; included in Group 7 rate for extensions
A15: 1 | B15: 1.2 | C15: Specialist foundations (piled) | D15: m² | E15: =IFERROR('Rates Reference Table'!K12*$E$5,0) -> 56.4 | F15: =IFERROR(E15*(1-$H$5/2),0) -> 50.196 | G15: =IFERROR(E15*(1+$H$5/2),0) -> 62.604 | H15: =IFERROR(F15*$B$5,0) -> 12549 | I15: =IFERROR(G15*$B$5,0) -> 15651 | J15: Poor ground conditions; trigger from GI report
A16: 1 | B16: 1.3 | C16: Lowest floor construction (slab) | D16: m² | E16: =IFERROR('Rates Reference Table'!K13*$E$5,0) -> 51.7 | F16: =IFERROR(E16*(1-$H$5/2),0) -> 46.013 | G16: =IFERROR(E16*(1+$H$5/2),0) -> 57.387 | H16: =IFERROR(F16*$B$5,0) -> 11503.25 | I16: =IFERROR(G16*$B$5,0) -> 14346.75 | J16: Ground bearing or suspended; inc DPM and insulation
A17: 1 | B17: 1.4 | C17: Basement excavation & structure | D17: Item | E17: =IFERROR('Rates Reference Table'!K14*$E$5,0) -> 141 | F17: =IFERROR(E17*(1-$H$5/2),0) -> 125.49 | G17: =IFERROR(E17*(1+$H$5/2),0) -> 156.51 | H17: =IFERROR(F17*$B$5,0) -> 31372.5 | I17: =IFERROR(G17*$B$5,0) -> 39127.5 | J17: High uncertainty; specialist estimate recommended
A18: GROUP 2 — SUPERSTRUCTURE
A19: 2 | B19: 2.1 | C19: Structural frame | D19: m² | E19: =IFERROR('Rates Reference Table'!K16*$E$5,0) -> 188 | F19: =IFERROR(E19*(1-$H$5/2),0) -> 167.32 | G19: =IFERROR(E19*(1+$H$5/2),0) -> 208.68 | H19: =IFERROR(F19*$B$5,0) -> 41830 | I19: =IFERROR(G19*$B$5,0) -> 52170 | J19: Steel/concrete/timber; new build or major extensions only
A20: 2 | B20: 2.2 | C20: Upper floors | D20: m² | E20: =IFERROR('Rates Reference Table'!K17*$E$5,0) -> 89.3 | F20: =IFERROR(E20*(1-$H$5/2),0) -> 79.477 | G20: =IFERROR(E20*(1+$H$5/2),0) -> 99.123 | H20: =IFERROR(F20*$B$5,0) -> 19869.25 | I20: =IFERROR(G20*$B$5,0) -> 24780.75 | J20: New build or added floors; inc topping and insulation
A21: 2 | B21: 2.3 | C21: Roof structure & covering | D21: m² | E21: =IFERROR('Rates Reference Table'!K18*$E$5,0) -> 112.8 | F21: =IFERROR(E21*(1-$H$5/2),0) -> 100.392 | G21: =IFERROR(E21*(1+$H$5/2),0) -> 125.208 | H21: =IFERROR(F21*$B$5,0) -> 25098 | I21: =IFERROR(G21*$B$5,0) -> 31302 | J21: New or replacement; inc insulation, waterproofing, rainwater
A22: 2 | B22: 2.4 | C22: Stairs & ramps | D22: Item | E22: =IFERROR('Rates Reference Table'!K19*$E$5,0) -> 32.9 | F22: =IFERROR(E22*(1-$H$5/2),0) -> 29.281 | G22: =IFERROR(E22*(1+$H$5/2),0) -> 36.519 | H22: =IFERROR(F22*$B$5,0) -> 7320.25 | I22: =IFERROR(G22*$B$5,0) -> 9129.75 | J22: RC, steel or timber; accessibility ramps
A23: 2 | B23: 2.5 | C23: External walls & facade | D23: m² | E23: =IFERROR('Rates Reference Table'!K20*$E$5,0) -> 263.2 | F23: =IFERROR(E23*(1-$H$5/2),0) -> 234.248 | G23: =IFERROR(E23*(1+$H$5/2),0) -> 292.152 | H23: =IFERROR(F23*$B$5,0) -> 58562 | I23: =IFERROR(G23*$B$5,0) -> 73038 | J23: Masonry/cladding; refurb = overcladding or repair only
A24: 2 | B24: 2.6 | C24: Windows & external doors | D24: m² | E24: =IFERROR('Rates Reference Table'!K21*$E$5,0) -> 141 | F24: =IFERROR(E24*(1-$H$5/2),0) -> 125.49 | G24: =IFERROR(E24*(1+$H$5/2),0) -> 156.51 | H24: =IFERROR(F24*$B$5,0) -> 31372.5 | I24: =IFERROR(G24*$B$5,0) -> 39127.5 | J24: uPVC (low) to aluminium curtain wall (high)
A25: 2 | B25: 2.7 | C25: Internal walls & partitions | D25: m² | E25: =IFERROR('Rates Reference Table'!K22*$E$5,0) -> 42.3 | F25: =IFERROR(E25*(1-$H$5/2),0) -> 37.647 | G25: =IFERROR(E25*(1+$H$5/2),0) -> 46.953 | H25: =IFERROR(F25*$B$5,0) -> 9411.75 | I25: =IFERROR(G25*$B$5,0) -> 11738.25 | J25: Blockwork, drywall or glazed; do not double-count Grp 3
A26: 2 | B26: 2.8 | C26: Internal doors & ironmongery | D26: Nr | E26: =IFERROR('Rates Reference Table'!K23*$E$5,0) -> 28.2 | F26: =IFERROR(E26*(1-$H$5/2),0) -> 25.098 | G26: =IFERROR(E26*(1+$H$5/2),0) -> 31.302 | H26: =IFERROR(F26*$B$5,0) -> 6274.5 | I26: =IFERROR(G26*$B$5,0) -> 7825.5 | J26: Fire-rated at upper range; standard at lower
A27: GROUP 3 — INTERNAL FINISHES ★ ALWAYS INCLUDED
A28: 3 | B28: 3.1 | C28: Wall finishes | D28: m² | E28: =IFERROR('Rates Reference Table'!K25*$E$5,0) -> 47 | F28: =IFERROR(E28*(1-$H$5/2),0) -> 41.83 | G28: =IFERROR(E28*(1+$H$5/2),0) -> 52.17 | H28: =IFERROR(F28*$B$5,0) -> 10457.5 | I28: =IFERROR(G28*$B$5,0) -> 13042.5 | J28: Emulsion (low) → specialist tiling/feature panelling (high)
A29: 3 | B29: 3.2 | C29: Floor finishes | D29: m² | E29: =IFERROR('Rates Reference Table'!K26*$E$5,0) -> 65.8 | F29: =IFERROR(E29*(1-$H$5/2),0) -> 58.562 | G29: =IFERROR(E29*(1+$H$5/2),0) -> 73.038 | H29: =IFERROR(F29*$B$5,0) -> 14640.5 | I29: =IFERROR(G29*$B$5,0) -> 18259.5 | J29: Vinyl/carpet (low) → stone/raised access floor (high)
A30: 3 | B30: 3.3 | C30: Ceiling finishes | D30: m² | E30: =IFERROR('Rates Reference Table'!K27*$E$5,0) -> 37.6 | F30: =IFERROR(E30*(1-$H$5/2),0) -> 33.464 | G30: =IFERROR(E30*(1+$H$5/2),0) -> 41.736 | H30: =IFERROR(F30*$B$5,0) -> 8366 | I30: =IFERROR(G30*$B$5,0) -> 10434 | J30: Emulsion (low) → bespoke acoustic ceiling system (high)
A31: GROUP 4 — FITTINGS, FURNISHINGS & EQUIPMENT
A32: 4 | B32: 4.1 | C32: General fittings & built-in joinery | D32: Item | E32: =IFERROR('Rates Reference Table'!K29*$E$5,0) -> 37.6 | F32: =IFERROR(E32*(1-$H$5/2),0) -> 33.464 | G32: =IFERROR(E32*(1+$H$5/2),0) -> 41.736 | H32: =IFERROR(F32*$B$5,0) -> 8366 | I32: =IFERROR(G32*$B$5,0) -> 10434 | J32: Reception desks, shelving, built-in furniture
A33: 4 | B33: 4.2 | C33: Sanitary fittings & toilet fit-out | D33: Nr | E33: =IFERROR('Rates Reference Table'!K30*$E$5,0) -> 16.92 | F33: =IFERROR(E33*(1-$H$5/2),0) -> 15.0588 | G33: =IFERROR(E33*(1+$H$5/2),0) -> 18.7812 | H33: =IFERROR(F33*$B$5,0) -> 3764.7 | I33: =IFERROR(G33*$B$5,0) -> 4695.3 | J33: WC packs; uplift for accessible/changing facilities
A34: 4 | B34: 4.3 | C34: Kitchen / break-out area | D34: Item | E34: =IFERROR('Rates Reference Table'!K31*$E$5,0) -> 14.1 | F34: =IFERROR(E34*(1-$H$5/2),0) -> 12.549 | G34: =IFERROR(E34*(1+$H$5/2),0) -> 15.651 | H34: =IFERROR(F34*$B$5,0) -> 3137.25 | I34: =IFERROR(G34*$B$5,0) -> 3912.75 | J34: Fitted units, worktops, appliances
A35: 4 | B35: 4.4 | C35: Specialist equipment (lab/AV/med) | D35: Item | E35: =IFERROR('Rates Reference Table'!K32*$E$5,0) -> 37.6 | F35: =IFERROR(E35*(1-$H$5/2),0) -> 33.464 | G35: =IFERROR(E35*(1+$H$5/2),0) -> 41.736 | H35: =IFERROR(F35*$B$5,0) -> 8366 | I35: =IFERROR(G35*$B$5,0) -> 10434 | J35: Laboratory, medical, AV; confirm with specialist
A36: GROUP 5 — MECHANICAL & ELECTRICAL SERVICES ★ KEY ELEMENT
A37: 5 | B37: 5.1 | C37: Sanitary plumbing (1st & 2nd fix) | D37: m² | E37: =IFERROR('Rates Reference Table'!K34*$E$5,0) -> 42.3 | F37: =IFERROR(E37*(1-$H$5/2),0) -> 37.647 | G37: =IFERROR(E37*(1+$H$5/2),0) -> 46.953 | H37: =IFERROR(F37*$B$5,0) -> 9411.75 | I37: =IFERROR(G37*$B$5,0) -> 11738.25 | J37: HWS, cold water, drainage connections
A38: 5 | B38: 5.2 | C38: Heating & hot water (LTHW/heat pump) | D38: m² | E38: =IFERROR('Rates Reference Table'!K35*$E$5,0) -> 61.1 | F38: =IFERROR(E38*(1-$H$5/2),0) -> 54.379 | G38: =IFERROR(E38*(1+$H$5/2),0) -> 67.821 | H38: =IFERROR(F38*$B$5,0) -> 13594.75 | I38: =IFERROR(G38*$B$5,0) -> 16955.25 | J38: LTHW system or heat pump; include buffer vessel
A39: 5 | B39: 5.3 | C39: Ventilation & air handling | D39: m² | E39: =IFERROR('Rates Reference Table'!K36*$E$5,0) -> 56.4 | F39: =IFERROR(E39*(1-$H$5/2),0) -> 50.196 | G39: =IFERROR(E39*(1+$H$5/2),0) -> 62.604 | H39: =IFERROR(F39*$B$5,0) -> 12549 | I39: =IFERROR(G39*$B$5,0) -> 15651 | J39: MVHR/AHU; uplift for lab/healthcare extract (+50-100%)
A40: 5 | B40: 5.4 | C40: Air conditioning & cooling | D40: m² | E40: =IFERROR('Rates Reference Table'!K37*$E$5,0) -> 42.3 | F40: =IFERROR(E40*(1-$H$5/2),0) -> 37.647 | G40: =IFERROR(E40*(1+$H$5/2),0) -> 46.953 | H40: =IFERROR(F40*$B$5,0) -> 9411.75 | I40: =IFERROR(G40*$B$5,0) -> 11738.25 | J40: VRF/splits; omit if not in scope
A41: 5 | B41: 5.5 | C41: Gas installation | D41: Item | E41: =IFERROR('Rates Reference Table'!K38*$E$5,0) -> 9.4 | F41: =IFERROR(E41*(1-$H$5/2),0) -> 8.366 | G41: =IFERROR(E41*(1+$H$5/2),0) -> 10.434 | H41: =IFERROR(F41*$B$5,0) -> 2091.5 | I41: =IFERROR(G41*$B$5,0) -> 2608.5 | J41: Omit if all-electric; confirm with utility
A42: 5 | B42: 5.6 | C42: Sprinkler / fire suppression | D42: m² | E42: =IFERROR('Rates Reference Table'!K39*$E$5,0) -> 18.8 | F42: =IFERROR(E42*(1-$H$5/2),0) -> 16.732 | G42: =IFERROR(E42*(1+$H$5/2),0) -> 20.868 | H42: =IFERROR(F42*$B$5,0) -> 4183 | I42: =IFERROR(G42*$B$5,0) -> 5217 | J42: >18m height or insurer requirement
A43: 5 | B43: 5.7 | C43: Electrical distribution & switchgear | D43: m² | E43: =IFERROR('Rates Reference Table'!K40*$E$5,0) -> 37.6 | F43: =IFERROR(E43*(1-$H$5/2),0) -> 33.464 | G43: =IFERROR(E43*(1+$H$5/2),0) -> 41.736 | H43: =IFERROR(F43*$B$5,0) -> 8366 | I43: =IFERROR(G43*$B$5,0) -> 10434 | J43: LV panels, distribution boards, earthing, containment
A44: 5 | B44: 5.8 | C44: Electrical wiring (1st & 2nd fix) | D44: m² | E44: =IFERROR('Rates Reference Table'!K41*$E$5,0) -> 51.7 | F44: =IFERROR(E44*(1-$H$5/2),0) -> 46.013 | G44: =IFERROR(E44*(1+$H$5/2),0) -> 57.387 | H44: =IFERROR(F44*$B$5,0) -> 11503.25 | I44: =IFERROR(G44*$B$5,0) -> 14346.75 | J44: All power and lighting circuits; inc containment
A45: 5 | B45: 5.9 | C45: Emergency lighting & fire alarm | D45: m² | E45: =IFERROR('Rates Reference Table'!K42*$E$5,0) -> 20.68 | F45: =IFERROR(E45*(1-$H$5/2),0) -> 18.4052 | G45: =IFERROR(E45*(1+$H$5/2),0) -> 22.9548 | H45: =IFERROR(F45*$B$5,0) -> 4601.3 | I45: =IFERROR(G45*$B$5,0) -> 5738.7 | J45: L2 minimum; upgrade for multi-zone/complex layouts
A46: 5 | B46: 5.10 | C46: External lighting | D46: Item | E46: =IFERROR('Rates Reference Table'!K43*$E$5,0) -> 7.52 | F46: =IFERROR(E46*(1-$H$5/2),0) -> 6.6928 | G46: =IFERROR(E46*(1+$H$5/2),0) -> 8.3472 | H46: =IFERROR(F46*$B$5,0) -> 1673.2 | I46: =IFERROR(G46*$B$5,0) -> 2086.8 | J46: Column/wall-mounted perimeter lighting
A47: 5 | B47: 5.11 | C47: Solar PV / renewables | D47: kWp | E47: =IFERROR('Rates Reference Table'!K44*$E$5,0) -> 1128 | F47: =IFERROR(E47*(1-$H$5/2),0) -> 1003.92 | G47: =IFERROR(E47*(1+$H$5/2),0) -> 1252.08 | H47: =IFERROR(F47*$B$5,0) -> 250980 | I47: =IFERROR(G47*$B$5,0) -> 313020 | J47: £/kWp installed; coordinate structural loading + electrical
A48: 5 | B48: 5.12 | C48: EV charging points | D48: Nr | E48: =IFERROR('Rates Reference Table'!K45*$E$5,0) -> 2350 | F48: =IFERROR(E48*(1-$H$5/2),0) -> 2091.5 | G48: =IFERROR(E48*(1+$H$5/2),0) -> 2608.5 | H48: =IFERROR(F48*$B$5,0) -> 522875 | I48: =IFERROR(G48*$B$5,0) -> 652125 | J48: Per charge point inc groundworks; 7kW fast charger
... A53: 5 | B53: 5.17 | C53: Builder's work in connection (BWIC) | D53: m² | E53: =IFERROR('Rates Reference Table'!K50*$E$5,0) -> 14.1 | F53: =IFERROR(E53*(1-$H$5/2),0) -> 12.549 | G53: =IFERROR(E53*(1+$H$5/2),0) -> 15.651 | H53: =IFERROR(F53*$B$5,0) -> 3137.25 | I53: =IFERROR(G53*$B$5,0) -> 3912.75 | J53: Penetrations, plinths, ducts, concrete bases for plant
A54: GROUP 6 — PREFABRICATED / MODULAR (if applicable)
A55: 6 | B55: 6.1 | C55: Prefabricated / modular units | D55: Item | E55: EXCLUDED | F55: EXCLUDED | G55: EXCLUDED | H55: 0 | I55: 0 | J55: Factory-built modular; specialist quote required
A56: 6 | B56: 6.2 | C56: Pre-engineered systems (mezzanine) | D56: Item | E56: EXCLUDED | F56: EXCLUDED | G56: EXCLUDED | H56: 0 | I56: 0 | J56: Mezzanine floors, demountable partitions
A57: GROUP 7 — WORK TO EXISTING BUILDINGS
A58: 7 | B58: 7.1 | C58: Structural repairs | D58: Item | E58: =IFERROR('Rates Reference Table'!K55*$E$5,0) -> 32.9 | F58: =IFERROR(E58*(1-$H$5/2),0) -> 29.281 | G58: =IFERROR(E58*(1+$H$5/2),0) -> 36.519 | H58: =IFERROR(F58*$B$5,0) -> 7320.25 | I58: =IFERROR(G58*$B$5,0) -> 9129.75 | J58: Crack stitching, bearing repairs; increase for poor condition
A59: 7 | B59: 7.2 | C59: Fabric / envelope repairs | D59: Item | E59: =IFERROR('Rates Reference Table'!K56*$E$5,0) -> 26.32 | F59: =IFERROR(E59*(1-$H$5/2),0) -> 23.4248 | G59: =IFERROR(E59*(1+$H$5/2),0) -> 29.2152 | H59: =IFERROR(F59*$B$5,0) -> 5856.2 | I59: =IFERROR(G59*$B$5,0) -> 7303.8 | J59: Repointing, waterproofing, weathertight works
A60: 7 | B60: 7.3 | C60: Damp proof course treatment | D60: Item | E60: =IFERROR('Rates Reference Table'!K57*$E$5,0) -> 14.1 | F60: =IFERROR(E60*(1-$H$5/2),0) -> 12.549 | G60: =IFERROR(E60*(1+$H$5/2),0) -> 15.651 | H60: =IFERROR(F60*$B$5,0) -> 3137.25 | I60: =IFERROR(G60*$B$5,0) -> 3912.75 | J60: Chemical DPC; increase for severe rising damp
A61: 7 | B61: 7.4 | C61: M&E overhaul / life-expired services | D61: Item | E61: =IFERROR('Rates Reference Table'!K58*$E$5,0) -> 51.7 | F61: =IFERROR(E61*(1-$H$5/2),0) -> 46.013 | G61: =IFERROR(E61*(1+$H$5/2),0) -> 57.387 | H61: =IFERROR(F61*$B$5,0) -> 11503.25 | I61: =IFERROR(G61*$B$5,0) -> 14346.75 | J61: Replacement of end-of-life mechanical & electrical plant
A62: 7 | B62: 7.5 | C62: Making good after structural works | D62: Item | E62: =IFERROR('Rates Reference Table'!K59*$E$5,0) -> 11.28 | F62: =IFERROR(E62*(1-$H$5/2),0) -> 10.0392 | G62: =IFERROR(E62*(1+$H$5/2),0) -> 12.5208 | H62: =IFERROR(F62*$B$5,0) -> 2509.8 | I62: =IFERROR(G62*$B$5,0) -> 3130.2 | J62: Patch plaster, redecoration after structural alterations
A63: GROUP 8 — EXTERNAL WORKS
A64: 8 | B64: 8.1 | C64: Site preparation & clearance | D64: Item | E64: =IFERROR('Rates Reference Table'!K61*$E$5,0) -> 11.28 | F64: =IFERROR(E64*(1-$H$5/2),0) -> 10.0392 | G64: =IFERROR(E64*(1+$H$5/2),0) -> 12.5208 | H64: =IFERROR(F64*$B$5,0) -> 2509.8 | I64: =IFERROR(G64*$B$5,0) -> 3130.2 | J64: Strip topsoil, vegetation, temp fencing and hoarding
A65: 8 | B65: 8.2 | C65: Roads, paths & hard paving | D65: m² | E65: =IFERROR('Rates Reference Table'!K62*$E$5,0) -> 23.5 | F65: =IFERROR(E65*(1-$H$5/2),0) -> 20.915 | G65: =IFERROR(E65*(1+$H$5/2),0) -> 26.085 | H65: =IFERROR(F65*$B$5,0) -> 5228.75 | I65: =IFERROR(G65*$B$5,0) -> 6521.25 | J65: Macadam/block paving; inc edging and drainage channels
A66: 8 | B66: 8.3 | C66: Car parking (line-marked bays) | D66: Nr | E66: =IFERROR('Rates Reference Table'!K63*$E$5,0) -> 7.52 | F66: =IFERROR(E66*(1-$H$5/2),0) -> 6.6928 | G66: =IFERROR(E66*(1+$H$5/2),0) -> 8.3472 | H66: =IFERROR(F66*$B$5,0) -> 1673.2 | I66: =IFERROR(G66*$B$5,0) -> 2086.8 | J66: Surfacing, line markings, disabled bays
A67: 8 | B67: 8.4 | C67: Surface water drainage | D67: Item | E67: =IFERROR('Rates Reference Table'!K64*$E$5,0) -> 14.1 | F67: =IFERROR(E67*(1-$H$5/2),0) -> 12.549 | G67: =IFERROR(E67*(1+$H$5/2),0) -> 15.651 | H67: =IFERROR(F67*$B$5,0) -> 3137.25 | I67: =IFERROR(G67*$B$5,0) -> 3912.75 | J67: Gullies, pipes, SuDS if required by planning
A68: 8 | B68: 8.5 | C68: Foul drainage connections | D68: Item | E68: =IFERROR('Rates Reference Table'!K65*$E$5,0) -> 9.4 | F68: =IFERROR(E68*(1-$H$5/2),0) -> 8.366 | G68: =IFERROR(E68*(1+$H$5/2),0) -> 10.434 | H68: =IFERROR(F68*$B$5,0) -> 2091.5 | I68: =IFERROR(G68*$B$5,0) -> 2608.5 | J68: Connection to existing drain or new manhole
A69: 8 | B69: 8.6 | C69: External utility services | D69: Item | E69: =IFERROR('Rates Reference Table'!K66*$E$5,0) -> 14.1 | F69: =IFERROR(E69*(1-$H$5/2),0) -> 12.549 | G69: =IFERROR(E69*(1+$H$5/2),0) -> 15.651 | H69: =IFERROR(F69*$B$5,0) -> 3137.25 | I69: =IFERROR(G69*$B$5,0) -> 3912.75 | J69: Gas/water/electric diversions; early check with DNO
A70: 8 | B70: 8.7 | C70: Soft landscaping | D70: m² | E70: =IFERROR('Rates Reference Table'!K67*$E$5,0) -> 9.4 | F70: =IFERROR(E70*(1-$H$5/2),0) -> 8.366 | G70: =IFERROR(E70*(1+$H$5/2),0) -> 10.434 | H70: =IFERROR(F70*$B$5,0) -> 2091.5 | I70: =IFERROR(G70*$B$5,0) -> 2608.5 | J70: Planting, seeding, topsoil reinstatement
A71: 8 | B71: 8.8 | C71: Boundary enclosures (fences/gates) | D71: Item | E71: =IFERROR('Rates Reference Table'!K68*$E$5,0) -> 7.52 | F71: =IFERROR(E71*(1-$H$5/2),0) -> 6.6928 | G71: =IFERROR(E71*(1+$H$5/2),0) -> 8.3472 | H71: =IFERROR(F71*$B$5,0) -> 1673.2 | I71: =IFERROR(G71*$B$5,0) -> 2086.8 | J71: Security fencing, gates, boundary walls, railings
A72: 8 | B72: 8.9 | C72: External lighting | D72: Item | E72: =IFERROR('Rates Reference Table'!K69*$E$5,0) -> 5.64 | F72: =IFERROR(E72*(1-$H$5/2),0) -> 5.0196 | G72: =IFERROR(E72*(1+$H$5/2),0) -> 6.2604 | H72: =IFERROR(F72*$B$5,0) -> 1254.9 | I72: =IFERROR(G72*$B$5,0) -> 1565.1 | J72: Column or wall-mounted lighting (see also 5.10)
A73: WORKS COST SUBTOTAL (Groups 0–8) | H73: =SUMPRODUCT((H8:H72>0)*H8:H72) -> 1286063.4 | I73: =SUMPRODUCT((I8:I72>0)*I8:I72) -> 1603966.6
A75: ADDITIONS TO WORKS COST — Adjust % using signal rules in Notes column
A76: Code | D76: Description | E76: Applied To | F76: Low % | G76: High % | H76: Total LOW (£) | I76: Total HIGH (£) | J76: Signal Rules / Notes
A77: A | D77: Contractor's Preliminaries | E77: Works Cost | F77: 0.08 | G77: 0.1 | H77: =IFERROR(F77*H73,0) -> 102885.07 | I77: =IFERROR(G77*I73,0) -> 160396.67 | J77: 8%=clean/vacant/short prog | +0.5% per: 6-18mo prog, partial occ, restricted access | cap 10%
A78: B | D78: Contractor's Overheads & Profit | E78: Works Cost | F78: 0.08 | G78: 0.12 | H78: =IFERROR(F78*H73,0) -> 102885.07 | I78: =IFERROR(G78*I73,0) -> 192476 | J78: >£5M→8-9% | £1-5M→9-10% | <£1M→10-12% | Lower end = cost priority; upper = D&B/speed
A79: CONSTRUCTION COST SUBTOTAL (Works + Prelims + OH&P) | H79: =H73+H77+H78 -> 1491833.5 | I79: =I73+I77+I78 -> 1956839.3
A80: C | D80: Professional Fees | E80: Construction Cost | F80: 0.05 | G80: 0.15 | H80: =IFERROR(F80*H79,0) -> 74591.674 | I80: =IFERROR(G80*I79,0) -> 293525.9 | J80: Stage 0-1→12-15% | Stage 2→10-13% | Stage 3→7-10% | Stage 4→5-7% | +1-2% M&E/struct/BREEAM
A81: D | D81: Dev & Project Costs | E81: Construction Cost | F81: 0.02 | G81: 0.04 | H81: =IFERROR(F81*H79,0) -> 29836.67 | I81: =IFERROR(G81*I79,0) -> 78273.573 | J81: Full planning→3-4% | LBC also→4% | Permitted dev→2% | +0.5% if no surveys yet
A82: E | D82: Risk Allowance | E82: Works Cost | F82: 0.05 | G82: 0.1 | H82: =IFERROR(F82*H73,0) -> 64303.168 | I82: =IFERROR(G82*I73,0) -> 160396.67 | J82: Baseline 5% | +2% no surveys | +1.5% asbestos/contamination | +1% structural concern | +1% hard deadline | cap 10%
A83: H | D83: Client Contingency [FIXED 5%] | E83: Works Cost | F83: 0.05 | G83: 0.05 | H83: =IFERROR(0.05*H73,0) -> 64303.168 | I83: =IFERROR(0.05*I73,0) -> 80198.333 | J83: FIXED at 5% — held by client, not released to contractor. Do not adjust.
A84: F | D84: Inflation Allowance | E84: Works Cost | F84: 0.02 | G84: 0.12 | H84: =IFERROR(F84*H73,0) -> 25721.267 | I84: =IFERROR(G84*I73,0) -> 192476 | J84: Component 1: tender delay (0-18mo=2-6%) + Component 2: construction mid-point (6-24mo=1-4%) | cap 12%
A85: TOTAL PROJECT COST (excl. VAT) | H85: =H79+H80+H81+H82+H83+H84 -> 1750589.4 | I85: =I79+I80+I81+I82+I83+I84 -> 2761709.8
A86: G | D86: VAT — reference only, NOT in total | E86: Project Total | F86: 0.2 | G86: 0.2 | H86: =IFERROR(0.2*H85,0) -> 350117.89 | I86: =IFERROR(0.2*I85,0) -> 552341.96 | J86: Recoverability must be confirmed with client Finance team. New build may attract zero-rating.
A88: Implied blended Works Cost rate — cross-check against BCIS benchmarks: | E88: =IFERROR(H73/$B$5,0) -> 5144.2534 | G88: =IFERROR(I73/$B$5,0) -> 6415.8666
A90: ⚠ DISCLAIMER: Indicative only — RIBA Stage 0–1 without measured quantities. Rates from Rates Reference Table, cross-referenced Q2 2026 market data. Must be reviewed by a Chartered QS before use in any business case or budget approval. LOW–HIGH range = mid-point ± 11% (default spread 22%). Update GIFA, BCIS factor and Spread as required.

Sheet External Works
A1: NRM1 ESTIMATE — EXTERNAL WORKS — SITE WORKS
A2: Spec level: Site-only works: roads, parking, drainage, landscaping, utilities, lighting. | RIBA Stage 0–1 indicative only | Base date Q2 2026
A4: Project Type: | B4: External Works | D4: Spec Level: | E4: Site Works | G4: Region: | H4: West Midlands
A5: GIFA (m²) ▼ update: | B5: 1000 | D5: BCIS Location Factor ▼: | E5: 0.94 | G5: Spread ±% ▼: | H5: 0.22
A7: Grp | B7: Sub | C7: Element / Description | D7: Unit | E7: Mid-Point £/m² | F7: Low £/m² | G7: High £/m² | H7: Total LOW (£) | I7: Total HIGH (£) | J7: Notes / Rate Driver
A8: GROUP 0 — FACILITATING WORKS
A9: 0 | B9: 0.1 | C9: Toxic/hazardous material removal | D9: Item | E9: =IFERROR('Rates Reference Table'!L6*$E$5,0) -> 0 | F9: =IFERROR(E9*(1-$H$5/2),0) -> 0 | G9: =IFERROR(E9*(1+$H$5/2),0) -> 0 | H9: =IFERROR(F9*$B$5,0) -> 0 | I9: =IFERROR(G9*$B$5,0) -> 0 | J9: Asbestos; increase if confirmed present (refurb/demo only)
A10: 0 | B10: 0.2 | C10: Demolition & structural alterations | D10: Item | E10: =IFERROR('Rates Reference Table'!L7*$E$5,0) -> 4.7 | F10: =IFERROR(E10*(1-$H$5/2),0) -> 4.183 | G10: =IFERROR(E10*(1+$H$5/2),0) -> 5.217 | H10: =IFERROR(F10*$B$5,0) -> 4183 | I10: =IFERROR(G10*$B$5,0) -> 5217 | J10: Selective or full demolition; structural openings
A11: 0 | B11: 0.3 | C11: Contaminated land remediation | D11: Item | E11: =IFERROR('Rates Reference Table'!L8*$E$5,0) -> 9.4 | F11: =IFERROR(E11*(1-$H$5/2),0) -> 8.366 | G11: =IFERROR(E11*(1+$H$5/2),0) -> 10.434 | H11: =IFERROR(F11*$B$5,0) -> 8366 | I11: =IFERROR(G11*$B$5,0) -> 10434 | J11: Brownfield/contaminated; specialist quote needed
A12: 0 | B12: 0.4 | C12: Ground stabilisation | D12: Item | E12: =IFERROR('Rates Reference Table'!L9*$E$5,0) -> 4.7 | F12: =IFERROR(E12*(1-$H$5/2),0) -> 4.183 | G12: =IFERROR(E12*(1+$H$5/2),0) -> 5.217 | H12: =IFERROR(F12*$B$5,0) -> 4183 | I12: =IFERROR(G12*$B$5,0) -> 5217 | J12: Underpinning/piling if ground risk identified
A13: GROUP 1 — SUBSTRUCTURE
A14: 1 | B14: 1.1 | C14: Standard foundations (strip/pad) | D14: m² | E14: EXCLUDED | F14: EXCLUDED | G14: EXCLUDED | H14: 0 | I14: 0 | J14: New build only; included in Group 7 rate for extensions
A15: 1 | B15: 1.2 | C15: Specialist foundations (piled) | D15: m² | E15: EXCLUDED | F15: EXCLUDED | G15: EXCLUDED | H15: 0 | I15: 0 | J15: Poor ground conditions; trigger from GI report
A16: 1 | B16: 1.3 | C16: Lowest floor construction (slab) | D16: m² | E16: EXCLUDED | F16: EXCLUDED | G16: EXCLUDED | H16: 0 | I16: 0 | J16: Ground bearing or suspended; inc DPM and insulation
A17: 1 | B17: 1.4 | C17: Basement excavation & structure | D17: Item | E17: EXCLUDED | F17: EXCLUDED | G17: EXCLUDED | H17: 0 | I17: 0 | J17: High uncertainty; specialist estimate recommended
A18: GROUP 2 — SUPERSTRUCTURE
A19: 2 | B19: 2.1 | C19: Structural frame | D19: m² | E19: EXCLUDED | F19: EXCLUDED | G19: EXCLUDED | H19: 0 | I19: 0 | J19: Steel/concrete/timber; new build or major extensions only
A20: 2 | B20: 2.2 | C20: Upper floors | D20: m² | E20: EXCLUDED | F20: EXCLUDED | G20: EXCLUDED | H20: 0 | I20: 0 | J20: New build or added floors; inc topping and insulation
A21: 2 | B21: 2.3 | C21: Roof structure & covering | D21: m² | E21: EXCLUDED | F21: EXCLUDED | G21: EXCLUDED | H21: 0 | I21: 0 | J21: New or replacement; inc insulation, waterproofing, rainwater
A22: 2 | B22: 2.4 | C22: Stairs & ramps | D22: Item | E22: EXCLUDED | F22: EXCLUDED | G22: EXCLUDED | H22: 0 | I22: 0 | J22: RC, steel or timber; accessibility ramps
A23: 2 | B23: 2.5 | C23: External walls & facade | D23: m² | E23: EXCLUDED | F23: EXCLUDED | G23: EXCLUDED | H23: 0 | I23: 0 | J23: Masonry/cladding; refurb = overcladding or repair only
A24: 2 | B24: 2.6 | C24: Windows & external doors | D24: m² | E24: EXCLUDED | F24: EXCLUDED | G24: EXCLUDED | H24: 0 | I24: 0 | J24: uPVC (low) to aluminium curtain wall (high)
A25: 2 | B25: 2.7 | C25: Internal walls & partitions | D25: m² | E25: EXCLUDED | F25: EXCLUDED | G25: EXCLUDED | H25: 0 | I25: 0 | J25: Blockwork, drywall or glazed; do not double-count Grp 3
A26: 2 | B26: 2.8 | C26: Internal doors & ironmongery | D26: Nr | E26: EXCLUDED | F26: EXCLUDED | G26: EXCLUDED | H26: 0 | I26: 0 | J26: Fire-rated at upper range; standard at lower
A27: GROUP 3 — INTERNAL FINISHES ★ ALWAYS INCLUDED
A28: 3 | B28: 3.1 | C28: Wall finishes | D28: m² | E28: EXCLUDED | F28: EXCLUDED | G28: EXCLUDED | H28: 0 | I28: 0 | J28: Emulsion (low) → specialist tiling/feature panelling (high)
A29: 3 | B29: 3.2 | C29: Floor finishes | D29: m² | E29: EXCLUDED | F29: EXCLUDED | G29: EXCLUDED | H29: 0 | I29: 0 | J29: Vinyl/carpet (low) → stone/raised access floor (high)
A30: 3 | B30: 3.3 | C30: Ceiling finishes | D30: m² | E30: EXCLUDED | F30: EXCLUDED | G30: EXCLUDED | H30: 0 | I30: 0 | J30: Emulsion (low) → bespoke acoustic ceiling system (high)
A31: GROUP 4 — FITTINGS, FURNISHINGS & EQUIPMENT
A32: 4 | B32: 4.1 | C32: General fittings & built-in joinery | D32: Item | E32: EXCLUDED | F32: EXCLUDED | G32: EXCLUDED | H32: 0 | I32: 0 | J32: Reception desks, shelving, built-in furniture
A33: 4 | B33: 4.2 | C33: Sanitary fittings & toilet fit-out | D33: Nr | E33: EXCLUDED | F33: EXCLUDED | G33: EXCLUDED | H33: 0 | I33: 0 | J33: WC packs; uplift for accessible/changing facilities
A34: 4 | B34: 4.3 | C34: Kitchen / break-out area | D34: Item | E34: EXCLUDED | F34: EXCLUDED | G34: EXCLUDED | H34: 0 | I34: 0 | J34: Fitted units, worktops, appliances
A35: 4 | B35: 4.4 | C35: Specialist equipment (lab/AV/med) | D35: Item | E35: EXCLUDED | F35: EXCLUDED | G35: EXCLUDED | H35: 0 | I35: 0 | J35: Laboratory, medical, AV; confirm with specialist
A36: GROUP 5 — MECHANICAL & ELECTRICAL SERVICES ★ KEY ELEMENT
A37: 5 | B37: 5.1 | C37: Sanitary plumbing (1st & 2nd fix) | D37: m² | E37: EXCLUDED | F37: EXCLUDED | G37: EXCLUDED | H37: 0 | I37: 0 | J37: HWS, cold water, drainage connections
A38: 5 | B38: 5.2 | C38: Heating & hot water (LTHW/heat pump) | D38: m² | E38: EXCLUDED | F38: EXCLUDED | G38: EXCLUDED | H38: 0 | I38: 0 | J38: LTHW system or heat pump; include buffer vessel
A39: 5 | B39: 5.3 | C39: Ventilation & air handling | D39: m² | E39: EXCLUDED | F39: EXCLUDED | G39: EXCLUDED | H39: 0 | I39: 0 | J39: MVHR/AHU; uplift for lab/healthcare extract (+50-100%)
A40: 5 | B40: 5.4 | C40: Air conditioning & cooling | D40: m² | E40: EXCLUDED | F40: EXCLUDED | G40: EXCLUDED | H40: 0 | I40: 0 | J40: VRF/splits; omit if not in scope
A41: 5 | B41: 5.5 | C41: Gas installation | D41: Item | E41: EXCLUDED | F41: EXCLUDED | G41: EXCLUDED | H41: 0 | I41: 0 | J41: Omit if all-electric; confirm with utility
A42: 5 | B42: 5.6 | C42: Sprinkler / fire suppression | D42: m² | E42: EXCLUDED | F42: EXCLUDED | G42: EXCLUDED | H42: 0 | I42: 0 | J42: >18m height or insurer requirement
A43: 5 | B43: 5.7 | C43: Electrical distribution & switchgear | D43: m² | E43: EXCLUDED | F43: EXCLUDED | G43: EXCLUDED | H43: 0 | I43: 0 | J43: LV panels, distribution boards, earthing, containment
A44: 5 | B44: 5.8 | C44: Electrical wiring (1st & 2nd fix) | D44: m² | E44: EXCLUDED | F44: EXCLUDED | G44: EXCLUDED | H44: 0 | I44: 0 | J44: All power and lighting circuits; inc containment
A45: 5 | B45: 5.9 | C45: Emergency lighting & fire alarm | D45: m² | E45: EXCLUDED | F45: EXCLUDED | G45: EXCLUDED | H45: 0 | I45: 0 | J45: L2 minimum; upgrade for multi-zone/complex layouts
A46: 5 | B46: 5.10 | C46: External lighting | D46: Item | E46: EXCLUDED | F46: EXCLUDED | G46: EXCLUDED | H46: 0 | I46: 0 | J46: Column/wall-mounted perimeter lighting
A47: 5 | B47: 5.11 | C47: Solar PV / renewables | D47: kWp | E47: EXCLUDED | F47: EXCLUDED | G47: EXCLUDED | H47: 0 | I47: 0 | J47: £/kWp installed; coordinate structural loading + electrical
A48: 5 | B48: 5.12 | C48: EV charging points | D48: Nr | E48: EXCLUDED | F48: EXCLUDED | G48: EXCLUDED | H48: 0 | I48: 0 | J48: Per charge point inc groundworks; 7kW fast charger
... A53: 5 | B53: 5.17 | C53: Builder's work in connection (BWIC) | D53: m² | E53: EXCLUDED | F53: EXCLUDED | G53: EXCLUDED | H53: 0 | I53: 0 | J53: Penetrations, plinths, ducts, concrete bases for plant
A54: GROUP 6 — PREFABRICATED / MODULAR (if applicable)
A55: 6 | B55: 6.1 | C55: Prefabricated / modular units | D55: Item | E55: EXCLUDED | F55: EXCLUDED | G55: EXCLUDED | H55: 0 | I55: 0 | J55: Factory-built modular; specialist quote required
A56: 6 | B56: 6.2 | C56: Pre-engineered systems (mezzanine) | D56: Item | E56: EXCLUDED | F56: EXCLUDED | G56: EXCLUDED | H56: 0 | I56: 0 | J56: Mezzanine floors, demountable partitions
A57: GROUP 7 — WORK TO EXISTING BUILDINGS
A58: 7 | B58: 7.1 | C58: Structural repairs | D58: Item | E58: EXCLUDED | F58: EXCLUDED | G58: EXCLUDED | H58: 0 | I58: 0 | J58: Crack stitching, bearing repairs; increase for poor condition
A59: 7 | B59: 7.2 | C59: Fabric / envelope repairs | D59: Item | E59: EXCLUDED | F59: EXCLUDED | G59: EXCLUDED | H59: 0 | I59: 0 | J59: Repointing, waterproofing, weathertight works
A60: 7 | B60: 7.3 | C60: Damp proof course treatment | D60: Item | E60: EXCLUDED | F60: EXCLUDED | G60: EXCLUDED | H60: 0 | I60: 0 | J60: Chemical DPC; increase for severe rising damp
A61: 7 | B61: 7.4 | C61: M&E overhaul / life-expired services | D61: Item | E61: EXCLUDED | F61: EXCLUDED | G61: EXCLUDED | H61: 0 | I61: 0 | J61: Replacement of end-of-life mechanical & electrical plant
A62: 7 | B62: 7.5 | C62: Making good after structural works | D62: Item | E62: EXCLUDED | F62: EXCLUDED | G62: EXCLUDED | H62: 0 | I62: 0 | J62: Patch plaster, redecoration after structural alterations
A63: GROUP 8 — EXTERNAL WORKS
A64: 8 | B64: 8.1 | C64: Site preparation & clearance | D64: Item | E64: =IFERROR('Rates Reference Table'!L61*$E$5,0) -> 9.4 | F64: =IFERROR(E64*(1-$H$5/2),0) -> 8.366 | G64: =IFERROR(E64*(1+$H$5/2),0) -> 10.434 | H64: =IFERROR(F64*$B$5,0) -> 8366 | I64: =IFERROR(G64*$B$5,0) -> 10434 | J64: Strip topsoil, vegetation, temp fencing and hoarding
A65: 8 | B65: 8.2 | C65: Roads, paths & hard paving | D65: m² | E65: =IFERROR('Rates Reference Table'!L62*$E$5,0) -> 32.9 | F65: =IFERROR(E65*(1-$H$5/2),0) -> 29.281 | G65: =IFERROR(E65*(1+$H$5/2),0) -> 36.519 | H65: =IFERROR(F65*$B$5,0) -> 29281 | I65: =IFERROR(G65*$B$5,0) -> 36519 | J65: Macadam/block paving; inc edging and drainage channels
A66: 8 | B66: 8.3 | C66: Car parking (line-marked bays) | D66: Nr | E66: =IFERROR('Rates Reference Table'!L63*$E$5,0) -> 18.8 | F66: =IFERROR(E66*(1-$H$5/2),0) -> 16.732 | G66: =IFERROR(E66*(1+$H$5/2),0) -> 20.868 | H66: =IFERROR(F66*$B$5,0) -> 16732 | I66: =IFERROR(G66*$B$5,0) -> 20868 | J66: Surfacing, line markings, disabled bays
A67: 8 | B67: 8.4 | C67: Surface water drainage | D67: Item | E67: =IFERROR('Rates Reference Table'!L64*$E$5,0) -> 23.5 | F67: =IFERROR(E67*(1-$H$5/2),0) -> 20.915 | G67: =IFERROR(E67*(1+$H$5/2),0) -> 26.085 | H67: =IFERROR(F67*$B$5,0) -> 20915 | I67: =IFERROR(G67*$B$5,0) -> 26085 | J67: Gullies, pipes, SuDS if required by planning
A68: 8 | B68: 8.5 | C68: Foul drainage connections | D68: Item | E68: =IFERROR('Rates Reference Table'!L65*$E$5,0) -> 14.1 | F68: =IFERROR(E68*(1-$H$5/2),0) -> 12.549 | G68: =IFERROR(E68*(1+$H$5/2),0) -> 15.651 | H68: =IFERROR(F68*$B$5,0) -> 12549 | I68: =IFERROR(G68*$B$5,0) -> 15651 | J68: Connection to existing drain or new manhole
A69: 8 | B69: 8.6 | C69: External utility services | D69: Item | E69: =IFERROR('Rates Reference Table'!L66*$E$5,0) -> 18.8 | F69: =IFERROR(E69*(1-$H$5/2),0) -> 16.732 | G69: =IFERROR(E69*(1+$H$5/2),0) -> 20.868 | H69: =IFERROR(F69*$B$5,0) -> 16732 | I69: =IFERROR(G69*$B$5,0) -> 20868 | J69: Gas/water/electric diversions; early check with DNO
A70: 8 | B70: 8.7 | C70: Soft landscaping | D70: m² | E70: =IFERROR('Rates Reference Table'!L67*$E$5,0) -> 14.1 | F70: =IFERROR(E70*(1-$H$5/2),0) -> 12.549 | G70: =IFERROR(E70*(1+$H$5/2),0) -> 15.651 | H70: =IFERROR(F70*$B$5,0) -> 12549 | I70: =IFERROR(G70*$B$5,0) -> 15651 | J70: Planting, seeding, topsoil reinstatement
A71: 8 | B71: 8.8 | C71: Boundary enclosures (fences/gates) | D71: Item | E71: =IFERROR('Rates Reference Table'!L68*$E$5,0) -> 11.28 | F71: =IFERROR(E71*(1-$H$5/2),0) -> 10.0392 | G71: =IFERROR(E71*(1+$H$5/2),0) -> 12.5208 | H71: =IFERROR(F71*$B$5,0) -> 10039.2 | I71: =IFERROR(G71*$B$5,0) -> 12520.8 | J71: Security fencing, gates, boundary walls, railings
A72: 8 | B72: 8.9 | C72: External lighting | D72: Item | E72: =IFERROR('Rates Reference Table'!L69*$E$5,0) -> 9.4 | F72: =IFERROR(E72*(1-$H$5/2),0) -> 8.366 | G72: =IFERROR(E72*(1+$H$5/2),0) -> 10.434 | H72: =IFERROR(F72*$B$5,0) -> 8366 | I72: =IFERROR(G72*$B$5,0) -> 10434 | J72: Column or wall-mounted lighting (see also 5.10)
A73: WORKS COST SUBTOTAL (Groups 0–8) | H73: =SUMPRODUCT((H8:H72>0)*H8:H72) -> 152261.2 | I73: =SUMPRODUCT((I8:I72>0)*I8:I72) -> 189898.8
A75: ADDITIONS TO WORKS COST — Adjust % using signal rules in Notes column
A76: Code | D76: Description | E76: Applied To | F76: Low % | G76: High % | H76: Total LOW (£) | I76: Total HIGH (£) | J76: Signal Rules / Notes
A77: A | D77: Contractor's Preliminaries | E77: Works Cost | F77: 0.08 | G77: 0.1 | H77: =IFERROR(F77*H73,0) -> 12180.896 | I77: =IFERROR(G77*I73,0) -> 18989.88 | J77: 8%=clean/vacant/short prog | +0.5% per: 6-18mo prog, partial occ, restricted access | cap 10%
A78: B | D78: Contractor's Overheads & Profit | E78: Works Cost | F78: 0.08 | G78: 0.12 | H78: =IFERROR(F78*H73,0) -> 12180.896 | I78: =IFERROR(G78*I73,0) -> 22787.856 | J78: >£5M→8-9% | £1-5M→9-10% | <£1M→10-12% | Lower end = cost priority; upper = D&B/speed
A79: CONSTRUCTION COST SUBTOTAL (Works + Prelims + OH&P) | H79: =H73+H77+H78 -> 176622.99 | I79: =I73+I77+I78 -> 231676.54
A80: C | D80: Professional Fees | E80: Construction Cost | F80: 0.05 | G80: 0.15 | H80: =IFERROR(F80*H79,0) -> 8831.1496 | I80: =IFERROR(G80*I79,0) -> 34751.48 | J80: Stage 0-1→12-15% | Stage 2→10-13% | Stage 3→7-10% | Stage 4→5-7% | +1-2% M&E/struct/BREEAM
A81: D | D81: Dev & Project Costs | E81: Construction Cost | F81: 0.02 | G81: 0.04 | H81: =IFERROR(F81*H79,0) -> 3532.4598 | I81: =IFERROR(G81*I79,0) -> 9267.0614 | J81: Full planning→3-4% | LBC also→4% | Permitted dev→2% | +0.5% if no surveys yet
A82: E | D82: Risk Allowance | E82: Works Cost | F82: 0.05 | G82: 0.1 | H82: =IFERROR(F82*H73,0) -> 7613.06 | I82: =IFERROR(G82*I73,0) -> 18989.88 | J82: Baseline 5% | +2% no surveys | +1.5% asbestos/contamination | +1% structural concern | +1% hard deadline | cap 10%
A83: H | D83: Client Contingency [FIXED 5%] | E83: Works Cost | F83: 0.05 | G83: 0.05 | H83: =IFERROR(0.05*H73,0) -> 7613.06 | I83: =IFERROR(0.05*I73,0) -> 9494.94 | J83: FIXED at 5% — held by client, not released to contractor. Do not adjust.
A84: F | D84: Inflation Allowance | E84: Works Cost | F84: 0.02 | G84: 0.12 | H84: =IFERROR(F84*H73,0) -> 3045.224 | I84: =IFERROR(G84*I73,0) -> 22787.856 | J84: Component 1: tender delay (0-18mo=2-6%) + Component 2: construction mid-point (6-24mo=1-4%) | cap 12%
A85: TOTAL PROJECT COST (excl. VAT) | H85: =H79+H80+H81+H82+H83+H84 -> 207257.95 | I85: =I79+I80+I81+I82+I83+I84 -> 326967.75
A86: G | D86: VAT — reference only, NOT in total | E86: Project Total | F86: 0.2 | G86: 0.2 | H86: =IFERROR(0.2*H85,0) -> 41451.589 | I86: =IFERROR(0.2*I85,0) -> 65393.551 | J86: Recoverability must be confirmed with client Finance team. New build may attract zero-rating.
A88: Implied blended Works Cost rate — cross-check against BCIS benchmarks: | E88: =IFERROR(H73/$B$5,0) -> 152.2612 | G88: =IFERROR(I73/$B$5,0) -> 189.8988
A90: ⚠ DISCLAIMER: Indicative only — RIBA Stage 0–1 without measured quantities. Rates from Rates Reference Table, cross-referenced Q2 2026 market data. Must be reviewed by a Chartered QS before use in any business case or budget approval. LOW–HIGH range = mid-point ± 11% (default spread 22%). Update GIFA, BCIS factor and Spread as required.

Sheet BCIS Factors
A1: BCIS REGIONAL LOCATION FACTORS — Q2 2026 Indicative
A2: Region | B2: Low Factor | C2: High Factor | D2: Notes
A3: Inner London | B3: 1.2 | C3: 1.3 | D3: Central London boroughs; highest UK cost premium
A4: Outer London | B4: 1.1 | C4: 1.2 | D4: Greater London boroughs
A5: South East | B5: 1.05 | C5: 1.12 | D5: Kent, Surrey, Berkshire, Hampshire, Sussex, Oxfordshire
A6: East of England | B6: 1 | C6: 1.05 | D6: Essex, Hertfordshire, Cambridgeshire, Norfolk, Suffolk
A7: West Midlands | B7: 0.92 | C7: 0.97 | D7: Birmingham, Coventry, Warwickshire ★ DEFAULT for this tool
A8: East Midlands | B8: 0.91 | C8: 0.96 | D8: Leicestershire, Nottinghamshire, Derbyshire
A9: Yorkshire & Humberside | B9: 0.88 | C9: 0.93 | D9: Leeds, Sheffield, Hull, York
A10: North West | B10: 0.9 | C10: 0.95 | D10: Manchester, Liverpool, Cheshire, Lancashire
A11: North East | B11: 0.87 | C11: 0.92 | D11: Newcastle, Sunderland, Teesside
A12: Wales | B12: 0.87 | C12: 0.93 | D12: All Welsh regions; Cardiff at upper end
A13: Scotland | B13: 0.93 | C13: 1 | D13: Edinburgh and central belt; Highlands higher
A14: Northern Ireland | B14: 0.82 | C14: 0.88 | D14: Belfast and Northern Ireland — lowest UK factor
A17: USE MID-POINT: For a single-factor estimate use the average of Low and High factors shown. Example: West Midlands = (0.92+0.97)/2 = 0.945 → enter 0.94 in the estimate tab. Source: BCIS Location Factors; broadly stable year-on-year. Update if BCIS publishes revised regional indices.
