Workbook

Sheet 1. Instructions
A1: NRM1 COST ESTIMATE TOOL — v5.4 (September 2026)
B2: Single source of truth for the scope of works and its prices, in three sheets. Prepared by Projento.
A4: THE THREE SHEETS
A5: 2. Scope and Rates | B5: Every scope item, its options and prices, where each price came from, and when the item shows and is ticked. The only place rates live.
A6: 3. Settings | B6: Everything else the app reads: workbook version, building uses, project types (with their rate columns), spec levels, intervention levels, location factors, benchmarks, inputs, quantity ratios, factors, percentage rules, retired codes.
A7: 1. Instructions | B7: This guide, the price-source key, the self-checks and the update log.
A9: HOW THE APP USES THIS WORKBOOK — it is the app's brain
A10: Runtime source | B10: The app loads this file at runtime (from GitHub, cached about 10 minutes, as with v4.5). Every item, option, rule, list, rate and percentage comes from here; the code holds none.
A11: To change a number | B11: Edit it here in Excel, save (Excel recalculates the formula cells), check the self-checks below read 0, bump the version on '3. Settings', and push to GitHub. New estimates use it within about 10 minutes.
A12: Live, no code change | B12: Rates and factors; price sources; new options and building-use rates; new items; quantity rules and ratios; Shown on / Pre-ticked on lists; conditions using the existing names; BCIS mapping; percentages, location factors, benchmarks; new project types or building uses added to their tables on '3. Settings'.
A13: Needs a code change | B13: A new column; a new pricing type; a new input name or function in quantity rules; a new kind of 'When selected' effect; renamed ▶ markers or column headers.
A14: Safety net | B14: If the file won't load, a header is missing or a self-check isn't 0, the app keeps the last good version and warns the admin. Every report records the workbook version it was priced with.
A15: Save with Excel | B15: Save from Excel or LibreOffice. Tools that don't recalculate (e.g. scripts) can leave formula cells empty, and the app will then reject the file.
A17: CODES USED ON '2. SCOPE AND RATES'
A18: Project types | B18: NB New Build · EX Extension · RF Refurbishment · FO Fit-out · EW External works only · DM Demolition only · OM Other or mixed. Several codes are separated by spaces, e.g. 'NB EX RF'. '—' means none.
A19: Building uses | B19: RES Residential · STU Student · OFF Commercial offices · EDU Education · HEA Healthcare · RET Retail · IND Industrial / warehouse · HOS Hospitality / leisure · MIX Mixed use · OTH Other · ALL any building use.
A20: Other conditions | B20: Tests joined by '&' (and), then '→ tick' or '→ untick'. Each test is a name from the inputs table, an operator (= <> < > <= >=) and a value; '=' followed by several codes means any of them. E.g. 'PT=NB & USE=RES STU & STOREYS>=4 → tick'. 'AUTO' = added by the app, never shown.
A21: Options: pick | B21: On Item rows. One = the user picks one option (drop-down). Several = the user can tick more than one option, each with its own quantity (e.g. standard + accessible toilets; passenger + goods lifts).
A22: When selected | B22: RISK: adds a risk · ASSUME: adds an assumption · RATE: changes another item's rate · SUGGEST: ticks another item (by Scope ID). Separate several with ' · '.
A23: Rate key vs Scope ID | B23: Scope ID (S-0039) = the item, e.g. Heating and hot water. Rate key (S-0039-02) = one priced line of that item, e.g. heat pump, full system. Saved projects store the rate key.
A24: Factor (× base row) | B24: Filled only on rows priced as a multiple of another row: rate = base row's rate × factor. Blank = the rate is typed in.
A26: QUANTITY RULES (column 'Quantity rule')
A27: What it is | B27: How the app estimates the quantity when the user hasn't entered one. The user's own quantity always replaces it. On Option rows, blank = same rule as the Item row.
A28: Names | B28: GIFA · STOREYS · FOOTPRINT · UPPER · EXT_AREA · DEMOLISHED · PT · USE · AGE · LEVEL — defined, with defaults, in the inputs table on '3. Settings'.
A29: Ratios | B29: r.name reads the quantity_ratios table on '3. Settings': the row for the project's building use, else the ALL row. E.g. r.m2_per_bed is 25 for student, 70 for healthcare.
A30: Functions | B30: IF(test, then, else) · ROUND(x, 0) · MAX(a, b) · SQRT(x) · Q(S-0000) = the quantity of another item · + − * / and = <> < > <= >=.
A31: Keywords | B31: ENTER = no reliable estimate; the item isn't priced until the user enters a quantity. 1 = one item or one size band.
A32: Examples | B32: Toilets: ROUND(GIFA / r.m2_per_person / r.persons_per_wc, 0). Solar PV: FOOTPRINT * r.kwp_per_m2_roof. Lifts: IF(STOREYS>=2, 1, 0).
A34: HOW TO CHANGE THINGS
A35: Change a rate | B35: Edit the rate cell on its row. Change 'Price source' to say where the new figure came from (e.g. Verified – BCIS) and add the reference in 'Source detail'. Rows with a Factor update themselves when their base row changes.
A36: Add an option | B36: Insert a row under the item. Row type = Option, same Scope ID, next Rate key (e.g. S-0039-16). Fill Option, Unit, Pricing type, rates and Price source. Leave the Item columns blank; they inherit from the Item row.
A37: Add a building-use rate | B37: Same as an option, with 'Rate building use' set to the use's code (e.g. HEA). The app uses the row matching the building use, else the ALL row.
A38: Add a scope item | B38: Insert an Item row in its group with the next unused Scope ID (never reuse one) and Rate key ending -01. Fill every Item column, the rules columns, BCIS element and a price.
A39: Add a project type or building use | B39: Give it a new code in the project_types or building_uses table on '3. Settings', then add the code to 'Shown on' / 'Pre-ticked on' / 'Relevant building uses' where it applies. Also add the code to the matching 'Unknown … codes' check below. No new columns needed.
A40: Retire an item | B40: Don't delete it. Change its rules so it isn't shown, and list its codes against the replacement item ('Replaces old codes') or on the retired_codes table.
A41: Change an estimate | B41: To change a ratio, edit its value on quantity_ratios; to change it for one building use only, add a row with that use's code. To change how an item is estimated, edit its 'Quantity rule'.
A42: Change a BCIS mapping | B42: Edit 'BCIS element' and 'Share' on the Item row. Shares must add up to 100%.
A43: Change a percentage or factor | B43: Edit the value in its table on '3. Settings'.
A44: After any change | B44: Check the self-checks below all show 0, then add a line to the update log.
A46: COLUMNS THE APP READS
A47: Read by the app | B47: Every column on '2. Scope and Rates' except those below, found by header text in row 4. Rows 1–3 are titles only. Every table on '3. Settings', found by its ▶ marker.
A48: Report only | B48: 'Price source': lines marked 'AI estimate – verify' are flagged on the report so the reader knows the rate is unverified.
A49: For people, not the app | B49: 'Factor (× base row)' and 'Base row' (they work out the rate in Excel; the app reads the rate), 'Source detail', 'Notes', and 'Used for' / 'Source' on the ratio tables.
A51: PRICE SOURCE KEY (column 'Price source' on '2. Scope and Rates')
A52: v4.5 – BCIS cited | B52: Carried from v4.5, where the v4.5 note cites BCIS. The citation hasn't been checked against BCIS data. | C52: =COUNTIF('2. Scope and Rates'!AB5:AB1000,A52) -> 3
A53: v4.5 – other source cited | B53: Carried from v4.5, where the v4.5 note cites another source (manufacturer, C&W, BCO, Ofgem …). Not checked. | C53: =COUNTIF('2. Scope and Rates'!AB5:AB1000,A53) -> 25
A54: v4.5 – no source recorded | B54: Carried from v4.5 with no source recorded. Treat as an unverified benchmark. | C54: =COUNTIF('2. Scope and Rates'!AB5:AB1000,A54) -> 35
A55: Derived from v4.5 | B55: Worked out from v4.5 rows; the arithmetic and any assumption are in 'Source detail'. | C55: =COUNTIF('2. Scope and Rates'!AB5:AB1000,A55) -> 31
A56: AI estimate – verify | B56: New number estimated by AI (Claude) for this version. Verify before relying on it. | C56: =COUNTIF('2. Scope and Rates'!AB5:AB1000,A56) -> 47
A57: Verified – BCIS | B57: Use when you have checked a rate against BCIS. Put the BCIS reference and date in 'Source detail'. | C57: =COUNTIF('2. Scope and Rates'!AB5:AB1000,A57) -> 0
A58: Verified – tender | B58: Use when a rate comes from recent tender returns. Put the project and date in 'Source detail'. | C58: =COUNTIF('2. Scope and Rates'!AB5:AB1000,A58) -> 0
A60: SELF-CHECKS (each should be 0)
A61: Duplicate rate keys | C61: =SUMPRODUCT(('2. Scope and Rates'!A5:A1000<>"")*(COUNTIF('2. Scope and Rates'!A5:A1000,'2. Scope and Rates'!A5:A1000)>1)) -> 0
A62: Scope IDs with more than one Item row | C62: =SUMPRODUCT(('2. Scope and Rates'!C5:C1000="Item")*(COUNTIFS('2. Scope and Rates'!B5:B1000,'2. Scope and Rates'!B5:B1000,'2. Scope and Rates'!C5:C1000,"Item")>1)) -> 0
A63: Option rows with no Item row | C63: =SUMPRODUCT(('2. Scope and Rates'!C5:C1000="Option")*(COUNTIFS('2. Scope and Rates'!B5:B1000,'2. Scope and Rates'!B5:B1000,'2. Scope and Rates'!C5:C1000,"Item")=0)) -> 0
A64: Rows with no price source | C64: =SUMPRODUCT(('2. Scope and Rates'!A5:A1000<>"")*('2. Scope and Rates'!AB5:AB1000="")) -> 0
A65: Item rows whose BCIS shares don't total 100% | C65: =SUMPRODUCT(('2. Scope and Rates'!C5:C1000="Item")*(ROUND('2. Scope and Rates'!AJ5:AJ1000+'2. Scope and Rates'!AL5:AL1000,4)<>1)) -> 0
A66: Rows whose option has no ALL building-use row | C66: =SUMPRODUCT(('2. Scope and Rates'!A5:A1000<>"")*(COUNTIFS('2. Scope and Rates'!B5:B1000,'2. Scope and Rates'!B5:B1000,'2. Scope and Rates'!I5:I1000,'2. Scope and Rates'!I5:I1000,'2. Scope and Rates'!J5:J1000,"ALL")=0)) -> 0
A67: Unknown project type codes | C67: =SUMPRODUCT(--(LEN(TRIM(SUBSTITUTE(SUBSTITUTE(SUBSTITUTE(SUBSTITUTE(SUBSTITUTE(SUBSTITUTE(SUBSTITUTE(SUBSTITUTE('2. Scope and Rates'!AD5:AD1000,"NB",""),"EX",""),"RF",""),"FO",""),"EW",""),"DM",""),"OM",""),"—","")))>0))+SUMPRODUCT(--(LEN(TRIM(SUBSTITUTE(SUBSTITUTE(SUBSTITUTE(SUBSTITUTE(SUBSTITUTE(SUBSTITUTE(SUBSTITUTE(SUBSTITUTE('2. Scope and Rates'!AE5:AE1000,"NB",""),"EX",""),"RF",""),"FO",""),"EW",""),"DM",""),"OM",""),"—","")))>0)) -> 0
A68: Unknown building use codes | C68: =SUMPRODUCT(--(LEN(TRIM(SUBSTITUTE(SUBSTITUTE(SUBSTITUTE(SUBSTITUTE(SUBSTITUTE(SUBSTITUTE(SUBSTITUTE(SUBSTITUTE(SUBSTITUTE(SUBSTITUTE(SUBSTITUTE('2. Scope and Rates'!AF5:AF1000,"RES",""),"STU",""),"OFF",""),"EDU",""),"HEA",""),"RET",""),"IND",""),"HOS",""),"MIX",""),"OTH",""),"ALL","")))>0))+SUMPRODUCT(--(LEN(TRIM(SUBSTITUTE(SUBSTITUTE(SUBSTITUTE(SUBSTITUTE(SUBSTITUTE(SUBSTITUTE(SUBSTITUTE(SUBSTITUTE(SUBSTITUTE(SUBSTITUTE(SUBSTITUTE('2. Scope and Rates'!J5:J1000,"RES",""),"STU",""),"OFF",""),"EDU",""),"HEA",""),"RET",""),"IND",""),"HOS",""),"MIX",""),"OTH",""),"ALL","")))>0)) -> 0
A69: Items with no default option | C69: =SUMPRODUCT(('2. Scope and Rates'!C5:C1000="Item")*(COUNTIFS('2. Scope and Rates'!B5:B1000,'2. Scope and Rates'!B5:B1000,'2. Scope and Rates'!K5:K1000,"Yes")=0)) -> 0
A70: 'Pick one' items with more than one default | C70: =SUMPRODUCT(('2. Scope and Rates'!C5:C1000="Item")*('2. Scope and Rates'!H5:H1000="One")*(COUNTIFS('2. Scope and Rates'!B5:B1000,'2. Scope and Rates'!B5:B1000,'2. Scope and Rates'!K5:K1000,"Yes")>1)) -> 0
A71: Item rows with no quantity rule | C71: =SUMPRODUCT(('2. Scope and Rates'!C5:C1000="Item")*('2. Scope and Rates'!N5:N1000="")) -> 0
A72: Ratio keys with no ALL row | C72: =SUMPRODUCT(('3. Settings'!A96:A123<>"")*(COUNTIFS('3. Settings'!A96:A123,'3. Settings'!A96:A123,'3. Settings'!B96:B123,"ALL")=0)) -> 0
A73: Ratios with no value | C73: =SUMPRODUCT(('3. Settings'!A96:A123<>"")*('3. Settings'!C96:C123="")) -> 0
A75: COUNTS
A76: Scope items | C76: =COUNTIF('2. Scope and Rates'!C5:C1000,"Item") -> 83
A77: Option rows | C77: =COUNTIF('2. Scope and Rates'!C5:C1000,"Option") -> 58
A79: CALCULATION SEQUENCE
A80: 1 | B80: Project type + specification level → rate column (project_types); postcode → location factor; inputs worked out (FOOTPRINT, UPPER, EXT_AREA) with their defaults.
A81: 2 | B81: Refurbishment and Fit-out: the user picks the level of intervention; the app never picks it. The level sets the band multiplier ('3. Settings'), greys out options whose 'Available from intervention level' is higher, and ticks the rows that list it in 'Pre-ticked at intervention levels'.
A82: 3 | B82: Other project types: items start ticked per 'Pre-ticked on', 'Relevant building uses' and 'Other conditions'.
A83: 4 | B83: For each selected item: use the row for the chosen option and building use (fall back to ALL). Quantity = the user's figure, else the Quantity rule. Line = rate × quantity × location factor × band multiplier (last two only where 'Apply band + location factor' = Yes); × modular_factor on Groups 1–3 if Modular.
A84: 5 | B84: Apply 'When selected' effects; add the automatic Builder's work line if any Group 5 item is selected; apply percentage rules; total by BCIS element. Lines on BCIS element 12 (biodiversity net gain) print below the construction total.
A86: GOLDEN RULES
B87: Contingency (H) is always 5%; survey uncertainty sits in Risk (E).
B88: Every number lives in this workbook once. The questionnaire and the code hold no rates.
B89: Rate keys and Scope IDs are permanent. Old codes are never deleted.
B90: The app reads this workbook through its v5 loader (sheets by name, columns by header text, Settings tables by ▶ marker). The v4.5 app cannot read it, so publish it only with, or after, that code change.
B91: Question numbers in the percentage rules follow the screen labels: Q2.2 = level of intervention, Q2.3 = scope of works.
A93: UPDATE LOG
A94: v5.4 — 24 Sept 2026 | B94: Regions: South West added (BS, BA, BH, DT, EX, GL, PL, SN, SP, TA, TQ, TR — factors 0.94 / 1.00 / 0.97 are an AI estimate, verify against BCIS); missing areas added (L and CA North West, MK South East, TF West Midlands, HS and ZE Scotland); Shropshire districts SY1–SY13 West Midlands and SY14 North West, the rest of SY stays Wales. Found by the 21-report test run: Bristol, Cotswolds and Liverpool were priced at the West Midlands default.
A95: v5.3 — 23 Sept 2026 | B95: Gaps filled: Solar PV and Battery storage Ext Works rates (= NB Std); External works only pre-ticks (site clearance, surface water drainage, paving, soft landscaping, fences — the app's previous External works preset); ▶ range_widths added on '3. Settings' (illustrative); percentage rule and golden rules updated to Q2.2 = level of intervention, Q2.3 = scope.
A96: v5.2 — 23 Sept 2026 | B96: Brief decisions confirmed: loose furniture moved into the construction total (BCIS 4.1); number of storeys read from the existing question.
A97: v5.2 — Sept 2026 | B97: Ready for Claude Code. Quantity rules written in a coded form the app can run, with named ratios and inputs on '3. Settings'. 'Options: pick' (One / Several) added. Band items default to Medium. Other conditions use the same names. Rate columns per project type and spec level, and benchmark codes, made machine-readable. 'Group 0?' column, redundant notes and old-code references removed.
A98: v5.1 — Sept 2026 | B98: Reduced to three sheets. Scope items, rates, rules, intervention defaults, BCIS mapping, dependencies and old codes merged into '2. Scope and Rates'. All settings tables stacked on '3. Settings'. Drop-down validation and self-checks added.
A99: v5.0 — Sept 2026 | B99: Scope library merged with the v4.5 Master Cost Table. Permanent Scope IDs. Every rate tagged with its source.
A100: v4.5 — June 2026 | B100: Q2.2 trigger column removed from the Master Cost Table (see v4.5 file for earlier logs).

Sheet 2. Scope and Rates
A1: SCOPE AND RATES — every scope item, its options and prices, and when it applies
A2: One row per priced line. The Item row holds the item's details and rules; Option rows below it (same Scope ID) add other options or building-use rates. Rate key and Scope ID are permanent: never change or reuse them. See '1. Instructions' for how to add or change anything.
A3: IDENTITY | D3: ITEM (on Item rows only) | I3: OPTION, QUANTITY AND PRICING | T3: RATES £ (UK mid-point, before location factor) | AB3: WHERE THE PRICE CAME FROM | AD3: WHEN IT SHOWS AND IS TICKED (Item rows; 'When selected' on any row) | AI3: BCIS AND OLD CODES (Item rows)
A4: Rate key | B4: Scope ID | C4: Row type | D4: Group | E4: Section | F4: Item | G4: What's included | H4: Options: pick | I4: Option | J4: Rate building use | K4: Default option | L4: Unit | M4: Pricing type | N4: Quantity rule | O4: Available from intervention level | P4: Pre-ticked at intervention levels | Q4: Apply band + location factor | R4: Factor (× base row) | S4: Base row (rate key) | T4: Rfb Basic | U4: Rfb Std | V4: Rfb High | W4: NB Std | X4: NB High | Y4: Ext Std | Z4: Ext High | AA4: Ext Works | AB4: Price source | AC4: Source detail | AD4: Shown on (project type codes) | AE4: Pre-ticked on (project type codes) | AF4: Relevant building uses (codes) | AG4: Other conditions | AH4: When selected (dependencies) | AI4: BCIS element 1 | AJ4: Share 1 | AK4: BCIS element 2 | AL4: Share 2 | AM4: Replaces old codes | AN4: Notes
A5: S-0001-01 | B5: S-0001 | C5: Item | D5: 0 Facilitating works | E5: — | F5: Asbestos removal | G5: Removal of asbestos and other hazardous materials in the building | H5: One | I5: Standard | J5: ALL | K5: Yes | L5: m² | M5: gifa_rate | N5: IF(PT=NB, DEMOLISHED, GIFA) | O5: 1 | Q5: Yes | T5: 25 | U5: 40 | V5: 90 | W5: 40 | X5: 90 | Y5: 10 | Z5: 20 | AA5: 40 | AB5: Derived from v4.5 | AC5: v4.5 0.1 for Refurbishment and Extension. New Build and External works columns were 0 in v4.5; set to the Refurbishment Std/High values (AI adjustment) so asbestos in a building being demolished is priced | AD5: NB EX RF FO EW DM OM | AE5: — | AF5: ALL | AG5: AGE<2000 & PT=RF FO DM → tick | AI5: 0.1 | AJ5: 1 | AM5: 0.1
A6: S-0002-01 | B6: S-0002 | C6: Item | D6: 0 Facilitating works | E6: — | F6: Demolition of existing building | G6: Whole-building demolition, soft strip and service disconnections | H6: One | I6: Standard | J6: ALL | K6: Yes | L6: m² demolished | M6: gifa_rate | N6: DEMOLISHED | O6: 4 | Q6: Yes | T6: 35 | U6: 60 | V6: 120 | W6: 60 | X6: 120 | Y6: 60 | Z6: 120 | AA6: 60 | AB6: Derived from v4.5 | AC6: v4.5 0.2 Refurbishment rates applied to every column: demolition cost doesn't depend on what replaces the building. v4.5 0.2 also covered structural alterations, now in Alterations | AD6: NB EX EW DM OM | AE6: DM | AF6: ALL | AH6: SUGGEST: S-0001 Asbestos removal · ASSUME (NB): demolished area = new GIFA unless entered | AI6: 0.2 | AJ6: 1 | AM6: 0.2
A7: S-0003-01 | B7: S-0003 | C7: Item | D7: 0 Facilitating works | E7: — | F7: Strip-out | G7: Removal of existing finishes, fittings and redundant services | H7: One | I7: Standard | J7: ALL | K7: Yes | L7: m² | M7: gifa_rate | N7: GIFA | O7: 1 | P7: 1, 2, 3, 4 | Q7: Yes | T7: 15 | U7: 25 | V7: 35 | W7: 0 | X7: 0 | Y7: 0 | Z7: 0 | AA7: 0 | AB7: v4.5 – no source recorded | AC7: v4.5 0.5. No source recorded in v4.5 | AD7: RF FO OM | AE7: — | AF7: ALL | AI7: 0.2 | AJ7: 1 | AM7: 0.5
A8: S-0004-01 | B8: S-0004 | C8: Item | D8: 0 Facilitating works | E8: — | F8: Contaminated land | G8: Remediation of contaminated ground | H8: One | I8: Standard | J8: ALL | K8: Yes | L8: m² | M8: gifa_rate | N8: IF(PT=EW, EXT_AREA, GIFA) | O8: 4 | Q8: Yes | T8: 15 | U8: 35 | V8: 60 | W8: 35 | X8: 60 | Y8: 35 | Z8: 60 | AA8: 30 | AB8: v4.5 – no source recorded | AC8: v4.5 0.3. No source recorded in v4.5 | AD8: NB EX EW DM OM | AE8: — | AF8: ALL | AI8: 0.1 | AJ8: 1 | AM8: 0.3
A9: S-0005-01 | B9: S-0005 | C9: Item | D9: 0 Facilitating works | E9: — | F9: Ground improvement | G9: Ground stabilisation and mine-working treatment (not piling) | H9: One | I9: Standard | J9: ALL | K9: Yes | L9: m² | M9: gifa_rate | N9: FOOTPRINT | O9: 4 | Q9: Yes | T9: 0 | U9: 0 | V9: 0 | W9: 20 | X9: 35 | Y9: 20 | Z9: 35 | AA9: 20 | AB9: v4.5 – no source recorded | AC9: v4.5 0.4. No source recorded in v4.5 | AD9: NB EX EW OM | AE9: — | AF9: ALL | AI9: 0.4 | AJ9: 1 | AM9: 0.4 | AN9: Piling is in Foundations
A10: S-0006-01 | B10: S-0006 | C10: Item | D10: 0 Facilitating works | E10: — | F10: Tree removal | G10: Felling and arboricultural works | H10: One | I10: Standard | J10: ALL | K10: Yes | L10: nr trees | M10: per_nr | N10: ENTER | O10: 1 | Q10: No | T10: 400 | U10: 750 | V10: 1500 | W10: 750 | X10: 1500 | Y10: 750 | Z10: 1500 | AA10: 750 | AB10: AI estimate – verify | AC10: AI estimate: felling and stump removal per tree. Spec level stands in for tree size. Not in v4.5 | AD10: NB EX EW DM OM | AE10: — | AF10: ALL | AI10: 8.1 | AJ10: 1 | AM10: 0.6
A11: S-0007-01 | B11: S-0007 | C11: Item | D11: 0 Facilitating works | E11: — | F11: Service diversions | G11: Diverting existing underground services | H11: One | I11: Size: Small | J11: ALL | L11: band | M11: per_item | N11: 1 | O11: 1 | Q11: No | T11: 15000 | U11: 15000 | V11: 15000 | W11: 15000 | X11: 15000 | Y11: 15000 | Z11: 15000 | AA11: 15000 | AB11: AI estimate – verify | AC11: AI estimate. Large = HV cable or strategic main. Not in v4.5 | AD11: NB EX EW DM OM | AE11: — | AF11: ALL | AI11: 0.5 | AJ11: 1 | AM11: 0.7
A12: S-0007-02 | B12: S-0007 | C12: Option | D12: =D11 -> 0 Facilitating works | E12: =E11 -> — | F12: =F11 -> Service diversions | I12: Size: Medium | J12: ALL | K12: Yes | L12: band | M12: per_item | O12: 1 | Q12: No | T12: 50000 | U12: 50000 | V12: 50000 | W12: 50000 | X12: 50000 | Y12: 50000 | Z12: 50000 | AA12: 50000 | AB12: AI estimate – verify | AC12: AI estimate. Large = HV cable or strategic main. Not in v4.5
A13: S-0007-03 | B13: S-0007 | C13: Option | D13: =D11 -> 0 Facilitating works | E13: =E11 -> — | F13: =F11 -> Service diversions | I13: Size: Large | J13: ALL | L13: band | M13: per_item | O13: 1 | Q13: No | T13: 150000 | U13: 150000 | V13: 150000 | W13: 150000 | X13: 150000 | Y13: 150000 | Z13: 150000 | AA13: 150000 | AB13: AI estimate – verify | AC13: AI estimate. Large = HV cable or strategic main. Not in v4.5
A14: S-0008-01 | B14: S-0008 | C14: Item | D14: 1 Substructure | E14: — | F14: Foundations | G14: Excavation and foundations | H14: One | I14: Type: Standard | J14: ALL | K14: Yes | L14: m² | M14: footprint_rate | N14: FOOTPRINT | O14: 4 | Q14: Yes | T14: 0 | U14: 0 | V14: 0 | W14: 80 | X14: 120 | Y14: 80 | Z14: 120 | AA14: 0 | AB14: v4.5 – no source recorded | AC14: v4.5 1.1. No source recorded in v4.5 | AD14: NB EX OM | AE14: NB EX | AF14: ALL | AI14: 1.1 | AJ14: 1 | AM14: 1.1, 1.2
A15: S-0008-02 | B15: S-0008 | C15: Option | D15: =D14 -> 1 Substructure | E15: =E14 -> — | F15: =F14 -> Foundations | I15: Type: Piled | J15: ALL | L15: m² | M15: footprint_rate | O15: 4 | Q15: Yes | T15: 0 | U15: 0 | V15: 0 | W15: 160 | X15: 220 | Y15: 160 | Z15: 250 | AA15: 0 | AB15: v4.5 – no source recorded | AC15: v4.5 1.2. No source recorded in v4.5
A16: S-0008-03 | B16: S-0008 | C16: Option | D16: =D14 -> 1 Substructure | E16: =E14 -> — | F16: =F14 -> Foundations | I16: Type: Not sure | J16: ALL | L16: m² | M16: footprint_rate | O16: 4 | Q16: Yes | R16: 1 | S16: S-0008-01 | T16: =T14*$R16 -> 0 | U16: =U14*$R16 -> 0 | V16: =V14*$R16 -> 0 | W16: =W14*$R16 -> 80 | X16: =X14*$R16 -> 120 | Y16: =Y14*$R16 -> 80 | Z16: =Z14*$R16 -> 120 | AA16: =AA14*$R16 -> 0 | AB16: Derived from v4.5 | AC16: Prices as Standard foundations and raises a piling risk (Dependencies) | AH16: RISK: piling may be required
A17: S-0009-01 | B17: S-0009 | C17: Item | D17: 1 Substructure | E17: — | F17: Ground floor slab | G17: Excavation, sub-base, DPM, insulation and slab | H17: One | I17: Standard | J17: ALL | K17: Yes | L17: m² | M17: footprint_rate | N17: FOOTPRINT | O17: 4 | Q17: Yes | T17: 0 | U17: 0 | V17: 0 | W17: 90 | X17: 140 | Y17: 90 | Z17: 140 | AA17: 0 | AB17: v4.5 – no source recorded | AC17: v4.5 1.3. No source recorded in v4.5 | AD17: NB EX OM | AE17: NB EX | AF17: ALL | AI17: 1.1 | AJ17: 1 | AM17: 1.3
A18: S-0010-01 | B18: S-0010 | C18: Item | D18: 1 Substructure | E18: — | F18: Basement | G18: Excavation, retaining walls and tanking | H18: One | I18: Standard | J18: ALL | K18: Yes | L18: m² basement | M18: footprint_rate | N18: FOOTPRINT | O18: 4 | Q18: Yes | T18: 0 | U18: 0 | V18: 0 | W18: 1000 | X18: 1750 | Y18: 1000 | Z18: 1750 | AA18: 0 | AB18: Derived from v4.5 | AC18: v4.5 1.4 (900 / 1,600) plus an AI allowance of £100 / £150 per m² for tanking, which moved here from retired 2.9 | AD18: NB EX OM | AE18: — | AF18: ALL | AH18: ASSUME: excavation, retaining walls and tanking included · RISK: groundwater and dewatering | AI18: 1.1 | AJ18: 1 | AM18: 1.4, 2.9, 2.10
A19: S-0011-01 | B19: S-0011 | C19: Item | D19: 2 Superstructure and envelope | E19: Structure | F19: Frame | G19: Structural frame | H19: One | I19: Standard | J19: ALL | K19: Yes | L19: m² | M19: gifa_rate | N19: GIFA | O19: 4 | Q19: Yes | T19: 0 | U19: 20 | V19: 40 | W19: 350 | X19: 550 | Y19: 130 | Z19: 200 | AA19: 0 | AB19: v4.5 – no source recorded | AC19: v4.5 2.1. No source recorded in v4.5 | AD19: NB EX OM | AE19: NB EX | AF19: ALL | AI19: 2.1 | AJ19: 1 | AM19: 2.1
A20: S-0012-01 | B20: S-0012 | C20: Item | D20: 2 Superstructure and envelope | E20: Structure | F20: Upper floors | G20: Upper floor structure, incl. balconies | H20: One | I20: Standard | J20: ALL | K20: Yes | L20: m² | M20: upperfloors_rate | N20: UPPER | O20: 4 | Q20: Yes | T20: 0 | U20: 15 | V20: 30 | W20: 78 | X20: 110 | Y20: 65 | Z20: 95 | AA20: 0 | AB20: v4.5 – no source recorded | AC20: v4.5 2.2. No source recorded in v4.5 | AD20: NB EX OM | AE20: NB EX | AF20: ALL | AG20: STOREYS<2 → untick | AI20: 2.2 | AJ20: 1 | AM20: 2.2
A21: S-0013-01 | B21: S-0013 | C21: Item | D21: 2 Superstructure and envelope | E21: Structure | F21: Stairs and ramps | G21: Stairs, ramps and balustrades | H21: One | I21: Standard | J21: ALL | K21: Yes | L21: m² | M21: gifa_rate | N21: GIFA | O21: 2 | Q21: Yes | T21: 10 | U21: 15 | V21: 25 | W21: 20 | X21: 35 | Y21: 20 | Z21: 35 | AA21: 0 | AB21: v4.5 – no source recorded | AC21: v4.5 2.4. No source recorded in v4.5 | AD21: NB EX RF OM | AE21: NB EX | AF21: ALL | AG21: STOREYS<2 → untick | AI21: 2.4 | AJ21: 1 | AM21: 2.4
A22: S-0014-01 | B22: S-0014 | C22: Item | D22: 2 Superstructure and envelope | E22: Structure | F22: Mezzanine floor | G22: Free-standing mezzanine | H22: One | I22: Standard | J22: ALL | K22: Yes | L22: m² mezzanine | M22: area_rate | N22: ENTER | O22: 4 | Q22: Yes | T22: 180 | U22: 250 | V22: 350 | W22: 250 | X22: 350 | Y22: 250 | Z22: 350 | AA22: 0 | AB22: AI estimate – verify | AC22: AI estimate per m² of mezzanine floor. v4.5 6.2 was priced per m² of whole-building GIFA, so it isn't comparable | AD22: NB EX RF FO OM | AE22: — | AF22: OFF EDU RET IND | AI22: 2.2 | AJ22: 1 | AM22: 2.12, 6.2
A23: S-0015-01 | B23: S-0015 | C23: Item | D23: 2 Superstructure and envelope | E23: Roof and walls | F23: Roof | G23: Structure, covering, insulation, drainage, access and edge protection | H23: One | I23: Standard | J23: ALL | K23: Yes | L23: m² | M23: footprint_rate | N23: FOOTPRINT | O23: 1 | Q23: Yes | T23: 35 | U23: 55 | V23: 90 | W23: 150 | X23: 250 | Y23: 75 | Z23: 120 | AA23: 0 | AB23: v4.5 – no source recorded | AC23: v4.5 2.3. No source recorded in v4.5 | AD23: NB EX RF OM | AE23: NB EX | AF23: ALL | AI23: 2.3 | AJ23: 1 | AM23: 2.3
A24: S-0016-01 | B24: S-0016 | C24: Item | D24: 2 Superstructure and envelope | E24: Roof and walls | F24: External walls | G24: Walls and facade, incl. over-cladding | H24: One | I24: Standard | J24: ALL | K24: Yes | L24: m² | M24: gifa_rate | N24: GIFA | O24: 1 | Q24: Yes | T24: 30 | U24: 60 | V24: 110 | W24: 450 | X24: 650 | Y24: 450 | Z24: 650 | AA24: 0 | AB24: v4.5 – no source recorded | AC24: v4.5 2.5. No source recorded in v4.5 | AD24: NB EX RF OM | AE24: NB EX | AF24: ALL | AI24: 2.5 | AJ24: 1 | AM24: 2.5
A25: S-0017-01 | B25: S-0017 | C25: Item | D25: 2 Superstructure and envelope | E25: Roof and walls | F25: Windows and external doors | G25: Windows, external doors and screens | H25: One | I25: Standard | J25: ALL | K25: Yes | L25: m² | M25: gifa_rate | N25: GIFA | O25: 1 | Q25: Yes | T25: 100 | U25: 150 | V25: 200 | W25: 250 | X25: 350 | Y25: 250 | Z25: 350 | AA25: 0 | AB25: v4.5 – no source recorded | AC25: v4.5 2.6. No source recorded in v4.5 | AD25: NB EX RF OM | AE25: NB EX | AF25: ALL | AI25: 2.6 | AJ25: 1 | AM25: 2.6
A26: S-0018-01 | B26: S-0018 | C26: Item | D26: 2 Superstructure and envelope | E26: Internal walls and doors | F26: Internal walls | G26: Walls and partitions | H26: One | I26: Standard | J26: ALL | K26: Yes | L26: m² | M26: gifa_rate | N26: GIFA | O26: 4 | P26: 4 | Q26: Yes | T26: 50 | U26: 80 | V26: 120 | W26: 80 | X26: 120 | Y26: 80 | Z26: 120 | AA26: 0 | AB26: v4.5 – no source recorded | AC26: v4.5 2.7. No source recorded in v4.5 | AD26: NB EX RF FO OM | AE26: NB EX | AF26: ALL | AI26: 2.7 | AJ26: 1 | AM26: 2.7
A27: S-0019-01 | B27: S-0019 | C27: Item | D27: 2 Superstructure and envelope | E27: Internal walls and doors | F27: Internal doors | G27: Doors and ironmongery, incl. fire doors | H27: One | I27: Standard | J27: ALL | K27: Yes | L27: m² | M27: gifa_rate | N27: GIFA | O27: 1 | P27: 4 | Q27: Yes | T27: 15 | U27: 35 | V27: 60 | W27: 80 | X27: 120 | Y27: 35 | Z27: 60 | AA27: 0 | AB27: v4.5 – no source recorded | AC27: v4.5 2.8. No source recorded in v4.5 | AD27: NB EX RF FO OM | AE27: NB EX | AF27: ALL | AI27: 2.8 | AJ27: 1 | AM27: 2.8
A28: S-0020-01 | B28: S-0020 | C28: Item | D28: 2 Superstructure and envelope | E28: Internal walls and doors | F28: Fire stopping | G28: Fire stopping and compartmentation upgrade | H28: One | I28: Standard | J28: ALL | K28: Yes | L28: m² | M28: gifa_rate | N28: GIFA | O28: 1 | P28: 3, 4 | Q28: Yes | T28: 15 | U28: 30 | V28: 60 | W28: 0 | X28: 0 | Y28: 15 | Z28: 30 | AA28: 0 | AB28: AI estimate – verify | AC28: AI estimate: fire stopping and compartmentation upgrade in an existing building. Not in v4.5 | AD28: EX RF FO OM | AE28: — | AF28: ALL | AI28: 2.7 | AJ28: 1 | AM28: 2.11
A29: S-0021-01 | B29: S-0021 | C29: Item | D29: 3 Internal finishes | E29: — | F29: Wall finishes | G29: Plaster, paint and tiling, incl. tanking in wet areas | H29: One | I29: Standard | J29: ALL | K29: Yes | L29: m² | M29: gifa_rate | N29: GIFA | O29: 1 | P29: 1, 2, 3, 4 | Q29: Yes | T29: 30 | U29: 55 | V29: 140 | W29: 55 | X29: 140 | Y29: 55 | Z29: 120 | AA29: 0 | AB29: v4.5 – no source recorded | AC29: v4.5 3.1. No source recorded in v4.5 | AD29: NB EX RF FO OM | AE29: NB EX | AF29: ALL | AI29: 3.1 | AJ29: 1 | AM29: 2.9, 3.1
A30: S-0022-01 | B30: S-0022 | C30: Item | D30: 3 Internal finishes | E30: — | F30: Floor finishes | G30: Screed and floor coverings, incl. tanking in wet areas | H30: One | I30: Raised access floor: No | J30: ALL | K30: Yes | L30: m² | M30: gifa_rate | N30: GIFA | O30: 1 | P30: 1, 2, 3, 4 | Q30: Yes | T30: 45 | U30: 75 | V30: 200 | W30: 75 | X30: 200 | Y30: 80 | Z30: 140 | AA30: 0 | AB30: v4.5 – no source recorded | AC30: v4.5 3.2. No source recorded in v4.5 | AD30: NB EX RF FO OM | AE30: NB EX | AF30: ALL | AI30: 3.2 | AJ30: 1 | AM30: 2.9, 3.2
A31: S-0022-02 | B31: S-0022 | C31: Option | D31: =D30 -> 3 Internal finishes | E31: =E30 -> — | F31: =F30 -> Floor finishes | I31: Raised access floor: Yes | J31: ALL | L31: m² | M31: gifa_rate | O31: 1 | Q31: Yes | T31: 90 | U31: 120 | V31: 245 | W31: 120 | X31: 245 | Y31: 125 | Z31: 185 | AA31: 0 | AB31: Derived from v4.5 | AC31: v4.5 3.2 plus an AI allowance of £45/m² for raised access floor
A32: S-0023-01 | B32: S-0023 | C32: Item | D32: 3 Internal finishes | E32: — | F32: Ceiling finishes | G32: Plasterboard or suspended ceilings | H32: One | I32: Standard | J32: ALL | K32: Yes | L32: m² | M32: gifa_rate | N32: GIFA | O32: 1 | P32: 1, 2, 3, 4 | Q32: Yes | T32: 30 | U32: 50 | V32: 140 | W32: 50 | X32: 140 | Y32: 50 | Z32: 100 | AA32: 0 | AB32: v4.5 – no source recorded | AC32: v4.5 3.3. No source recorded in v4.5 | AD32: NB EX RF FO OM | AE32: NB EX | AF32: ALL | AI32: 3.3 | AJ32: 1 | AM32: 3.3
A33: S-0024-01 | B33: S-0024 | C33: Item | D33: 4 Toilets, kitchens and fittings | E33: Toilets, bathrooms and kitchens | F33: Toilets | G33: WC pans, basins, cubicles, vanity, dryers and accessories. Pipework is in Water and drainage, tiling in Group 3 | H33: Several | I33: Standard | J33: ALL | K33: Yes | L33: nr | M33: per_nr | N33: ROUND(GIFA / r.m2_per_person / r.persons_per_wc, 0) | O33: 2 | Q33: Yes | T33: 2800 | U33: 4950 | V33: 9400 | W33: 4950 | X33: 9400 | Y33: 4950 | Z33: 9400 | AA33: 0 | AB33: Derived from v4.5 | AC33: Standard WC: v4.5 4.2-COM ware + 4.31-NR cubicle + ½ × 5.30-NR hand dryer + ¼ × 4.32-HOH vanity run (assumption: 1 dryer per 2 WCs, 1 vanity run per 4 WCs) | AD33: NB EX RF FO OM | AE33: NB EX | AF33: OFF EDU HEA RET IND HOS | AI33: 5.1 | AJ33: 0.8 | AK33: 2.7 | AL33: 0.2 | AM33: 4.2-COM, 4.2-HC, 4.2-HP, 4.31-NR, 4.32-HOH, 5.30-NR | AN33: BCIS split is an AI estimate
A34: S-0024-02 | B34: S-0024 | C34: Option | D34: =D33 -> 4 Toilets, kitchens and fittings | E34: =E33 -> Toilets, bathrooms and kitchens | F34: =F33 -> Toilets | I34: Standard | J34: HOS | L34: nr | M34: per_nr | O34: 2 | Q34: Yes | T34: 3600 | U34: 6250 | V34: 11900 | W34: 6250 | X34: 11900 | Y34: 6250 | Z34: 11900 | AA34: 0 | AB34: Derived from v4.5 | AC34: Standard WC: v4.5 4.2-HP ware + 4.31-NR cubicle + ½ × 5.30-NR hand dryer + ¼ × 4.32-HOH vanity run (assumption: 1 dryer per 2 WCs, 1 vanity run per 4 WCs)
A35: S-0024-03 | B35: S-0024 | C35: Option | D35: =D33 -> 4 Toilets, kitchens and fittings | E35: =E33 -> Toilets, bathrooms and kitchens | F35: =F33 -> Toilets | I35: Standard | J35: HEA | L35: nr | M35: per_nr | O35: 2 | Q35: Yes | T35: 4400 | U35: 7250 | V35: 12900 | W35: 7250 | X35: 12900 | Y35: 7250 | Z35: 12900 | AA35: 0 | AB35: Derived from v4.5 | AC35: Standard WC: v4.5 4.2-HC ware + 4.31-NR cubicle + ½ × 5.30-NR hand dryer + ¼ × 4.32-HOH vanity run (assumption: 1 dryer per 2 WCs, 1 vanity run per 4 WCs)
A36: S-0024-04 | B36: S-0024 | C36: Option | D36: =D33 -> 4 Toilets, kitchens and fittings | E36: =E33 -> Toilets, bathrooms and kitchens | F36: =F33 -> Toilets | I36: Accessible | J36: ALL | K36: Yes | L36: nr | M36: per_nr | N36: STOREYS * r.accessible_wc_per_floor | O36: 2 | Q36: Yes | T36: 3500 | U36: 5500 | V36: 9000 | W36: 5500 | X36: 9000 | Y36: 5500 | Z36: 9000 | AA36: 0 | AB36: AI estimate – verify | AC36: AI estimate: Doc M pack, grab rails, alarm and larger cubicle. Not in v4.5
A37: S-0024-05 | B37: S-0024 | C37: Option | D37: =D33 -> 4 Toilets, kitchens and fittings | E37: =E33 -> Toilets, bathrooms and kitchens | F37: =F33 -> Toilets | I37: Changing Places | J37: ALL | L37: nr | M37: per_nr | N37: 1 | O37: 2 | Q37: No | T37: 45000 | U37: 60000 | V37: 80000 | W37: 60000 | X37: 80000 | Y37: 60000 | Z37: 80000 | AA37: 0 | AB37: AI estimate – verify | AC37: AI estimate per Changing Places facility (hoist, adult changing bench, peninsular WC). Not in v4.5
A38: S-0025-01 | B38: S-0025 | C38: Item | D38: 4 Toilets, kitchens and fittings | E38: Toilets, bathrooms and kitchens | F38: Bathrooms and en-suites | G38: Bath or shower, WC, basin and accessories | H38: One | I38: Built in | J38: ALL | K38: Yes | L38: Nr | M38: per_nr | N38: ROUND(IF(USE=STU, GIFA / r.m2_per_bed, IF(USE=HOS, GIFA / r.m2_per_key, GIFA / r.m2_per_dwelling * r.bathrooms_per_dwelling)), 0) | O38: 2 | Q38: Yes | T38: 900 | U38: 2000 | V38: 3500 | W38: 2000 | X38: 3500 | Y38: 2000 | Z38: 3500 | AA38: 0 | AB38: v4.5 – no source recorded | AC38: v4.5 4.2-RES. No source recorded in v4.5 | AD38: NB EX RF FO OM | AE38: NB EX | AF38: RES STU HOS | AI38: 5.1 | AJ38: 1 | AM38: 4.2-HG, 4.2-RES, 6.3
A39: S-0025-02 | B39: S-0025 | C39: Option | D39: =D38 -> 4 Toilets, kitchens and fittings | E39: =E38 -> Toilets, bathrooms and kitchens | F39: =F38 -> Bathrooms and en-suites | I39: Built in | J39: HOS | L39: Nr | M39: per_nr | O39: 2 | Q39: Yes | T39: 3500 | U39: 5500 | V39: 8500 | W39: 5500 | X39: 8500 | Y39: 5500 | Z39: 8500 | AA39: 0 | AB39: v4.5 – no source recorded | AC39: v4.5 4.2-HG. No source recorded in v4.5
A40: S-0025-03 | B40: S-0025 | C40: Option | D40: =D38 -> 4 Toilets, kitchens and fittings | E40: =E38 -> Toilets, bathrooms and kitchens | F40: =F38 -> Bathrooms and en-suites | I40: Pods | J40: ALL | L40: Nr | M40: per_nr | O40: 2 | Q40: Yes | T40: 3200 | U40: 5800 | V40: 10500 | W40: 5800 | X40: 10500 | Y40: 5800 | Z40: 10500 | AA40: 0 | AB40: v4.5 – other source cited | AC40: v4.5 6.3. v4.5 cites: Offsite Solutions Q2 2026 (not verified)
A41: S-0026-01 | B41: S-0026 | C41: Item | D41: 4 Toilets, kitchens and fittings | E41: Toilets, bathrooms and kitchens | F41: Showers | G41: Showers and changing (non-residential) | H41: One | I41: Standard | J41: ALL | K41: Yes | L41: nr | M41: per_nr | N41: ENTER | O41: 2 | Q41: Yes | T41: 1500 | U41: 2500 | V41: 4500 | W41: 2500 | X41: 4500 | Y41: 2500 | Z41: 4500 | AA41: 0 | AB41: AI estimate – verify | AC41: AI estimate per shower: tray, screen, valve and fittings. Not in v4.5 | AD41: NB EX RF FO OM | AE41: — | AF41: OFF EDU HEA RET IND HOS | AI41: 5.1 | AJ41: 1 | AM41: 4.41
A42: S-0027-01 | B42: S-0027 | C42: Item | D42: 4 Toilets, kitchens and fittings | E42: Toilets, bathrooms and kitchens | F42: Kitchens | G42: Domestic kitchens or staff tea points | H42: One | I42: Type: Domestic kitchen | J42: ALL | K42: Yes | L42: Nr | M42: per_nr | N42: ROUND(IF(USE=RES, GIFA / r.m2_per_dwelling, IF(USE=STU, GIFA / r.m2_per_bed / r.beds_per_kitchen, STOREYS * r.tea_points_per_floor)), 0) | O42: 2 | Q42: Yes | T42: 3500 | U42: 6000 | V42: 10000 | W42: 6000 | X42: 10000 | Y42: 6000 | Z42: 10000 | AA42: 0 | AB42: v4.5 – no source recorded | AC42: v4.5 4.3. No source recorded in v4.5 | AD42: NB EX RF FO OM | AE42: NB EX | AF42: ALL | AI42: 4.2 | AJ42: 1 | AM42: 4.3, 4.3-NR, 4.3-RES, 4.42
A43: S-0027-02 | B43: S-0027 | C43: Option | D43: =D42 -> 4 Toilets, kitchens and fittings | E43: =E42 -> Toilets, bathrooms and kitchens | F43: =F42 -> Kitchens | I43: Type: Tea point | J43: ALL | L43: nr | M43: per_nr | O43: 2 | Q43: Yes | T43: 2500 | U43: 4000 | V43: 7000 | W43: 4000 | X43: 7000 | Y43: 4000 | Z43: 7000 | AA43: 0 | AB43: AI estimate – verify | AC43: AI estimate for a staff kitchenette. v4.5 4.3 combined domestic kitchen and break-out
A44: S-0028-01 | B44: S-0028 | C44: Item | D44: 4 Toilets, kitchens and fittings | E44: Fittings and furniture | F44: Fixed joinery | G44: Reception desks, built-in storage and fitted furniture | H44: One | I44: Standard | J44: ALL | K44: Yes | L44: m² | M44: gifa_rate | N44: GIFA | O44: 1 | Q44: Yes | T44: 10 | U44: 45 | V44: 100 | W44: 15 | X44: 50 | Y44: 10 | Z44: 40 | AA44: 0 | AB44: v4.5 – no source recorded | AC44: v4.5 4.1. No source recorded in v4.5 | AD44: NB EX RF FO OM | AE44: — | AF44: ALL | AI44: 4.1 | AJ44: 1 | AM44: 4.1
A45: S-0029-01 | B45: S-0029 | C45: Item | D45: 4 Toilets, kitchens and fittings | E45: Fittings and furniture | F45: Signage | G45: Wayfinding and statutory signs | H45: One | I45: Standard | J45: ALL | K45: Yes | L45: m² | M45: gifa_rate | N45: GIFA | O45: 1 | Q45: Yes | T45: 5 | U45: 10 | V45: 15 | W45: 3 | X45: 10 | Y45: 2 | Z45: 8 | AA45: 5 | AB45: v4.5 – no source recorded | AC45: v4.5 4.5. No source recorded in v4.5 | AD45: NB EX RF FO OM | AE45: NB EX | AF45: ALL | AI45: 4.4 | AJ45: 1 | AM45: 4.5
A46: S-0030-01 | B46: S-0030 | C46: Item | D46: 4 Toilets, kitchens and fittings | E46: Fittings and furniture | F46: AV equipment | G46: Screens, projectors and audio in meeting and teaching rooms | H46: One | I46: Standard | J46: ALL | K46: Yes | L46: m² | M46: gifa_rate | N46: GIFA | O46: 2 | Q46: Yes | T46: 30 | U46: 30 | V46: 82 | W46: 30 | X46: 82 | Y46: 30 | Z46: 82 | AA46: 0 | AB46: Derived from v4.5 | AC46: v4.5 4.22 £/room (v4.5 cites Kinly 2025, not verified) ÷ 200 m² GIFA per AV room (assumption) | AD46: NB EX RF FO OM | AE46: — | AF46: OFF EDU HEA HOS | AI46: 5.12 | AJ46: 1 | AM46: 4.22
A47: S-0031-01 | B47: S-0031 | C47: Item | D47: 4 Toilets, kitchens and fittings | E47: Fittings and furniture | F47: Loose furniture | G47: Desks, chairs, beds and white goods | H47: One | I47: Standard | J47: ALL | K47: Yes | L47: m² | M47: gifa_rate | N47: GIFA | O47: 1 | Q47: No | T47: 55 | U47: 110 | V47: 240 | W47: 110 | X47: 240 | Y47: 110 | Z47: 240 | AA47: 0 | AB47: Derived from v4.5 | AC47: v4.5 4.7 £/workstation (cites BCO Fit-Out Guide 2024, not verified) ÷ 10 m² per workstation (assumption) | AD47: NB EX RF FO OM | AE47: — | AF47: ALL | AI47: 4.1 | AJ47: 1 | AM47: 4.6, 4.7, 4.8, 4.9, 4.33 | AN47: In the construction total (decision 23 Sept 2026)
A48: S-0031-02 | B48: S-0031 | C48: Option | D48: =D47 -> 4 Toilets, kitchens and fittings | E48: =E47 -> Fittings and furniture | F48: =F47 -> Loose furniture | I48: Standard | J48: RES | L48: m² | M48: gifa_rate | O48: 1 | Q48: No | T48: 28 | U48: 50 | V48: 99 | W48: 50 | X48: 99 | Y48: 50 | Z48: 99 | AA48: 0 | AB48: Derived from v4.5 | AC48: v4.5 4.6 furniture + 4.9 white goods per flat (cite BCIS Q1 2026, not verified) ÷ 70 m² per flat (assumption)
A49: S-0031-03 | B49: S-0031 | C49: Option | D49: =D47 -> 4 Toilets, kitchens and fittings | E49: =E47 -> Fittings and furniture | F49: =F47 -> Loose furniture | I49: Standard | J49: STU | L49: m² | M49: gifa_rate | O49: 1 | Q49: No | T49: 48 | U49: 88 | V49: 180 | W49: 88 | X49: 180 | Y49: 88 | Z49: 180 | AA49: 0 | AB49: Derived from v4.5 | AC49: v4.5 4.6 per room (cites BCIS Q1 2026, not verified) ÷ 25 m² GIFA per student bed (assumption)
A50: S-0031-04 | B50: S-0031 | C50: Option | D50: =D47 -> 4 Toilets, kitchens and fittings | E50: =E47 -> Fittings and furniture | F50: =F47 -> Loose furniture | I50: Standard | J50: HOS | L50: m² | M50: gifa_rate | O50: 1 | Q50: No | T50: 62 | U50: 138 | V50: 350 | W50: 138 | X50: 350 | Y50: 138 | Z50: 350 | AA50: 0 | AB50: Derived from v4.5 | AC50: v4.5 4.8 per hotel room (cites C&W 2025, not verified) ÷ 40 m² GIFA per key (assumption)
A51: S-0032-01 | B51: S-0032 | C51: Item | D51: 4 Toilets, kitchens and fittings | E51: Specialist equipment | F51: Catering kitchen | G51: Commercial kitchen equipment, bar and servery counters, extract canopy and grease trap | H51: One | I51: Standard | J51: ALL | K51: Yes | L51: m² kitchen and servery | M51: area_rate | N51: GIFA * r.pct_catering | O51: 3 | Q51: No | T51: 373 | U51: 690 | V51: 1455 | W51: 690 | X51: 1455 | Y51: 690 | Z51: 1455 | AA51: 0 | AB51: Derived from v4.5 | AC51: v4.5 4.10 equipment + 4.11 canopy (per kitchen) ÷ 60 m² typical kitchen (assumption), plus 5.23 grease/drainage per m². Sources cited in v4.5: CEDA 2024, BESA Q2 2026, ACO 2025 (not verified) | AD51: NB EX RF FO OM | AE51: — | AF51: STU OFF EDU HEA RET IND HOS | AH51: ASSUME: extract canopy and grease trap included | AI51: 5.2 | AJ51: 1 | AM51: 4.10, 4.11, 4.12, 4.16, 4.34
A52: S-0033-01 | B52: S-0033 | C52: Item | D52: 4 Toilets, kitchens and fittings | E52: Specialist equipment | F52: Laboratory | G52: Lab benching and fume cupboards | H52: One | I52: Standard | J52: ALL | K52: Yes | L52: m² lab | M52: area_rate | N52: GIFA * r.pct_lab | O52: 1 | Q52: Yes | T52: 310 | U52: 310 | V52: 600 | W52: 310 | X52: 600 | Y52: 310 | Z52: 600 | AA52: 0 | AB52: Derived from v4.5 | AC52: v4.5 4.20 benching per m² + 4.21 fume cupboards ÷ 50 m² lab per cupboard (assumption). v4.5 cites Lab-Interiors / Waldner-Esco Q2 2026 (not verified) | AD52: NB EX RF FO OM | AE52: — | AF52: EDU HEA IND | AH52: SUGGEST: S-0059 Fume extraction | AI52: 4.3 | AJ52: 1 | AM52: 4.20, 4.21, 4.36 | AN52: Fume extraction ductwork and fans are in Fume extraction
A53: S-0034-01 | B53: S-0034 | C53: Item | D53: 4 Toilets, kitchens and fittings | E53: Specialist equipment | F53: Clinical | G53: Clinical fittings and equipment | H53: One | I53: Standard | J53: ALL | K53: Yes | L53: m² clinical | M53: area_rate | N53: GIFA * r.pct_clinical | O53: 1 | Q53: Yes | T53: 65 | U53: 65 | V53: 130 | W53: 65 | X53: 130 | Y53: 65 | Z53: 130 | AA53: 0 | AB53: v4.5 – other source cited | AC53: v4.5 4.19. v4.5 cites: NHS P21+ 2024 (not verified) | AD53: NB EX RF FO OM | AE53: — | AF53: HEA | AH53: SUGGEST: S-0061 Medical gases | AI53: 4.3 | AJ53: 1 | AM53: 4.19, 4.37 | AN53: Medical gas pipework is in Medical gases
A54: S-0035-01 | B54: S-0035 | C54: Item | D54: 4 Toilets, kitchens and fittings | E54: Specialist equipment | F54: Retail | G54: Display units, counters and fitting rooms | H54: One | I54: Standard | J54: ALL | K54: Yes | L54: m² sales area | M54: area_rate | N54: IF(USE=RET, GIFA, ENTER) | O54: 1 | Q54: Yes | T54: 163 | U54: 163 | V54: 305 | W54: 163 | X54: 305 | Y54: 163 | Z54: 305 | AA54: 0 | AB54: Derived from v4.5 | AC54: v4.5 4.24 display per m² + 4.25 tills (1 per 100 m²) + 4.27 EAS (1 per 300 m²), assumptions. Fitting rooms: use Other / specialist | AD54: NB EX RF FO OM | AE54: — | AF54: RET | AI54: 4.3 | AJ54: 1 | AM54: 4.24, 4.25, 4.27, 4.35
A55: S-0036-01 | B55: S-0036 | C55: Item | D55: 4 Toilets, kitchens and fittings | E55: Specialist equipment | F55: Warehouse | G55: Racking, dock levellers and loading doors. Cranes: use Other / specialist scope | H55: One | I55: Standard | J55: ALL | K55: Yes | L55: m² | M55: area_rate | N55: IF(USE=IND, GIFA, ENTER) | O55: 1 | Q55: Yes | T55: 22 | U55: 24 | V55: 51 | W55: 24 | X55: 51 | Y55: 24 | Z55: 51 | AA55: 0 | AB55: Derived from v4.5 | AC55: v4.5 4.13 racking ÷ 2,000 m² + 4.14 dock leveller and 4.15 door per 1,000 m² (assumptions). v4.5 cites SEMA, Thorworld, Hormann (not verified) | AD55: NB EX RF FO OM | AE55: — | AF55: IND | AI55: 4.3 | AJ55: 1 | AM55: 4.13, 4.14, 4.15, 4.38
A56: S-0037-01 | B56: S-0037 | C56: Item | D56: 4 Toilets, kitchens and fittings | E56: Specialist equipment | F56: Sports | G56: Gym equipment and changing lockers. Spectator seating: use Other / specialist scope | H56: One | I56: Standard | J56: ALL | K56: Yes | L56: m² sports area | M56: area_rate | N56: ENTER | O56: 1 | Q56: Yes | T56: 152 | U56: 152 | V56: 352 | W56: 152 | X56: 352 | Y56: 152 | Z56: 352 | AA56: 0 | AB56: Derived from v4.5 | AC56: v4.5 4.28 gym equipment per m² + 20% of area as changing at 4.30 rate (assumption) | AD56: NB EX RF FO OM | AE56: — | AF56: EDU HOS | AI56: 4.3 | AJ56: 1 | AM56: 4.28, 4.30, 4.39
A57: S-0038-01 | B57: S-0038 | C57: Item | D57: 4 Toilets, kitchens and fittings | E57: Specialist equipment | F57: Cleanroom | G57: Cleanroom enclosure and fit-out | H57: One | I57: Standard | J57: ALL | K57: Yes | L57: m² cleanroom | M57: area_rate | N57: ENTER | O57: 4 | Q57: Yes | T57: 380 | U57: 380 | V57: 860 | W57: 380 | X57: 860 | Y57: 380 | Z57: 860 | AA57: 0 | AB57: v4.5 – other source cited | AC57: v4.5 6.4. v4.5 cites: ISO 14644, M+W 2025 (not verified) | AD57: NB EX RF FO OM | AE57: — | AF57: EDU HEA IND | AI57: 5.13 | AJ57: 1 | AM57: 4.44, 6.4
A58: S-0039-01 | B58: S-0039 | C58: Item | D58: 5 Services | E58: Mechanical | F58: Heating and hot water | G58: Heat source, pipework, radiators or underfloor heating, and hot water | H58: One | I58: System: Gas boiler · Scope: Full system | J58: ALL | L58: m² | M58: gifa_rate | N58: GIFA | O58: 3 | P58: 3, 4 | Q58: Yes | T58: 30 | U58: 60 | V58: 105 | W58: 58 | X58: 105 | Y58: 55 | Z58: 100 | AA58: 0 | AB58: Derived from v4.5 | AC58: v4.5 5.2 heating + 5.5 gas installation (no source recorded in v4.5) | AD58: NB EX RF FO OM | AE58: NB EX | AF58: ALL | AI58: 5.5 | AJ58: 0.4 | AK58: 5.6 | AL58: 0.6 | AM58: 5.2, 5.2L, 5.5 | AN58: BCIS split is an AI estimate
A59: S-0039-02 | B59: S-0039 | C59: Option | D59: =D58 -> 5 Services | E59: =E58 -> Mechanical | F59: =F58 -> Heating and hot water | I59: System: Air source heat pump · Scope: Full system | J59: ALL | K59: Yes | L59: m² | M59: gifa_rate | O59: 3 | Q59: Yes | R59: 1.3 | S59: S-0039-01 | T59: =T58*$R59 -> 39 | U59: =U58*$R59 -> 78 | V59: =V58*$R59 -> 136.5 | W59: =W58*$R59 -> 75.4 | X59: =X58*$R59 -> 136.5 | Y59: =Y58*$R59 -> 71.5 | Z59: =Z58*$R59 -> 130 | AA59: =AA58*$R59 -> 0 | AB59: AI estimate – verify | AC59: Gas boiler full system × 1.3 (AI factor for air source heat pump) | AH59: RISK: electrical capacity and DNO check · RATE: Electricity supply upgrade one band up · ASSUME: external plant space included
A60: S-0039-03 | B60: S-0039 | C60: Option | D60: =D58 -> 5 Services | E60: =E58 -> Mechanical | F60: =F58 -> Heating and hot water | I60: System: Ground source heat pump · Scope: Full system | J60: ALL | L60: m² | M60: gifa_rate | O60: 3 | Q60: Yes | R60: 1.8 | S60: S-0039-01 | T60: =T58*$R60 -> 54 | U60: =U58*$R60 -> 108 | V60: =V58*$R60 -> 189 | W60: =W58*$R60 -> 104.4 | X60: =X58*$R60 -> 189 | Y60: =Y58*$R60 -> 99 | Z60: =Z58*$R60 -> 180 | AA60: =AA58*$R60 -> 0 | AB60: AI estimate – verify | AC60: Gas boiler full system × 1.8 (AI factor for ground source heat pump) | AH60: RISK: electrical capacity and DNO check · RATE: Electricity supply upgrade one band up · ASSUME: external plant space included
A61: S-0039-04 | B61: S-0039 | C61: Option | D61: =D58 -> 5 Services | E61: =E58 -> Mechanical | F61: =F58 -> Heating and hot water | I61: System: District heating · Scope: Full system | J61: ALL | L61: m² | M61: gifa_rate | O61: 3 | Q61: Yes | R61: 0.9 | S61: S-0039-01 | T61: =T58*$R61 -> 27 | U61: =U58*$R61 -> 54 | V61: =V58*$R61 -> 94.5 | W61: =W58*$R61 -> 52.2 | X61: =X58*$R61 -> 94.5 | Y61: =Y58*$R61 -> 49.5 | Z61: =Z58*$R61 -> 90 | AA61: =AA58*$R61 -> 0 | AB61: AI estimate – verify | AC61: Gas boiler full system × 0.9 (AI factor for district heating)
A62: S-0039-05 | B62: S-0039 | C62: Option | D62: =D58 -> 5 Services | E62: =E58 -> Mechanical | F62: =F58 -> Heating and hot water | I62: System: Electric · Scope: Full system | J62: ALL | L62: m² | M62: gifa_rate | O62: 3 | Q62: Yes | R62: 0.6 | S62: S-0039-01 | T62: =T58*$R62 -> 18 | U62: =U58*$R62 -> 36 | V62: =V58*$R62 -> 63 | W62: =W58*$R62 -> 34.8 | X62: =X58*$R62 -> 63 | Y62: =Y58*$R62 -> 33 | Z62: =Z58*$R62 -> 60 | AA62: =AA58*$R62 -> 0 | AB62: AI estimate – verify | AC62: Gas boiler full system × 0.6 (AI factor for electric)
A63: S-0039-06 | B63: S-0039 | C63: Option | D63: =D58 -> 5 Services | E63: =E58 -> Mechanical | F63: =F58 -> Heating and hot water | I63: System: Gas boiler · Scope: Plant only | J63: ALL | L63: m² | M63: gifa_rate | O63: 2 | Q63: Yes | R63: 0.35 | S63: S-0039-01 | T63: =T58*$R63 -> 10.5 | U63: =U58*$R63 -> 21 | V63: =V58*$R63 -> 36.75 | W63: =W58*$R63 -> 20.3 | X63: =X58*$R63 -> 36.75 | Y63: =Y58*$R63 -> 19.25 | Z63: =Z58*$R63 -> 35 | AA63: =AA58*$R63 -> 0 | AB63: AI estimate – verify | AC63: Full system × 0.35 (AI share for plant). Replaces v4.5 5.2L (£ per item, domestic scale)
A64: S-0039-07 | B64: S-0039 | C64: Option | D64: =D58 -> 5 Services | E64: =E58 -> Mechanical | F64: =F58 -> Heating and hot water | I64: System: Gas boiler · Scope: Radiators and controls only | J64: ALL | L64: m² | M64: gifa_rate | O64: 2 | P64: 2 | Q64: Yes | R64: 0.3 | S64: S-0039-01 | T64: =T58*$R64 -> 9 | U64: =U58*$R64 -> 18 | V64: =V58*$R64 -> 31.5 | W64: =W58*$R64 -> 17.4 | X64: =X58*$R64 -> 31.5 | Y64: =Y58*$R64 -> 16.5 | Z64: =Z58*$R64 -> 30 | AA64: =AA58*$R64 -> 0 | AB64: AI estimate – verify | AC64: Full system × 0.30 (AI share for emitters, TRVs and controls)
A65: S-0039-08 | B65: S-0039 | C65: Option | D65: =D58 -> 5 Services | E65: =E58 -> Mechanical | F65: =F58 -> Heating and hot water | I65: System: Air source heat pump · Scope: Plant only | J65: ALL | L65: m² | M65: gifa_rate | O65: 2 | Q65: Yes | R65: 0.45 | S65: S-0039-02 | T65: =T59*$R65 -> 17.55 | U65: =U59*$R65 -> 35.1 | V65: =V59*$R65 -> 61.425 | W65: =W59*$R65 -> 33.93 | X65: =X59*$R65 -> 61.425 | Y65: =Y59*$R65 -> 32.175 | Z65: =Z59*$R65 -> 58.5 | AA65: =AA59*$R65 -> 0 | AB65: AI estimate – verify | AC65: Full system × 0.45 (AI share for plant). Replaces v4.5 5.2L (£ per item, domestic scale) | AH65: RISK: electrical capacity and DNO check · RATE: Electricity supply upgrade one band up · ASSUME: external plant space included · RISK: existing radiators may need upsizing
A66: S-0039-09 | B66: S-0039 | C66: Option | D66: =D58 -> 5 Services | E66: =E58 -> Mechanical | F66: =F58 -> Heating and hot water | I66: System: Air source heat pump · Scope: Radiators and controls only | J66: ALL | L66: m² | M66: gifa_rate | O66: 2 | Q66: Yes | R66: 0.3 | S66: S-0039-02 | T66: =T59*$R66 -> 11.7 | U66: =U59*$R66 -> 23.4 | V66: =V59*$R66 -> 40.95 | W66: =W59*$R66 -> 22.62 | X66: =X59*$R66 -> 40.95 | Y66: =Y59*$R66 -> 21.45 | Z66: =Z59*$R66 -> 39 | AA66: =AA59*$R66 -> 0 | AB66: AI estimate – verify | AC66: Full system × 0.30 (AI share for emitters, TRVs and controls) | AH66: RISK: electrical capacity and DNO check · RATE: Electricity supply upgrade one band up · ASSUME: external plant space included
A67: S-0039-10 | B67: S-0039 | C67: Option | D67: =D58 -> 5 Services | E67: =E58 -> Mechanical | F67: =F58 -> Heating and hot water | I67: System: Ground source heat pump · Scope: Plant only | J67: ALL | L67: m² | M67: gifa_rate | O67: 2 | Q67: Yes | R67: 0.45 | S67: S-0039-03 | T67: =T60*$R67 -> 24.3 | U67: =U60*$R67 -> 48.6 | V67: =V60*$R67 -> 85.05 | W67: =W60*$R67 -> 46.98 | X67: =X60*$R67 -> 85.05 | Y67: =Y60*$R67 -> 44.55 | Z67: =Z60*$R67 -> 81 | AA67: =AA60*$R67 -> 0 | AB67: AI estimate – verify | AC67: Full system × 0.45 (AI share for plant). Replaces v4.5 5.2L (£ per item, domestic scale) | AH67: RISK: electrical capacity and DNO check · RATE: Electricity supply upgrade one band up · ASSUME: external plant space included · RISK: existing radiators may need upsizing
A68: S-0039-11 | B68: S-0039 | C68: Option | D68: =D58 -> 5 Services | E68: =E58 -> Mechanical | F68: =F58 -> Heating and hot water | I68: System: Ground source heat pump · Scope: Radiators and controls only | J68: ALL | L68: m² | M68: gifa_rate | O68: 2 | Q68: Yes | R68: 0.3 | S68: S-0039-03 | T68: =T60*$R68 -> 16.2 | U68: =U60*$R68 -> 32.4 | V68: =V60*$R68 -> 56.7 | W68: =W60*$R68 -> 31.32 | X68: =X60*$R68 -> 56.7 | Y68: =Y60*$R68 -> 29.7 | Z68: =Z60*$R68 -> 54 | AA68: =AA60*$R68 -> 0 | AB68: AI estimate – verify | AC68: Full system × 0.30 (AI share for emitters, TRVs and controls) | AH68: RISK: electrical capacity and DNO check · RATE: Electricity supply upgrade one band up · ASSUME: external plant space included
A69: S-0039-12 | B69: S-0039 | C69: Option | D69: =D58 -> 5 Services | E69: =E58 -> Mechanical | F69: =F58 -> Heating and hot water | I69: System: District heating · Scope: Plant only | J69: ALL | L69: m² | M69: gifa_rate | O69: 2 | Q69: Yes | R69: 0.3 | S69: S-0039-04 | T69: =T61*$R69 -> 8.1 | U69: =U61*$R69 -> 16.2 | V69: =V61*$R69 -> 28.35 | W69: =W61*$R69 -> 15.66 | X69: =X61*$R69 -> 28.35 | Y69: =Y61*$R69 -> 14.85 | Z69: =Z61*$R69 -> 27 | AA69: =AA61*$R69 -> 0 | AB69: AI estimate – verify | AC69: Full system × 0.3 (AI share for plant). Replaces v4.5 5.2L (£ per item, domestic scale)
A70: S-0039-13 | B70: S-0039 | C70: Option | D70: =D58 -> 5 Services | E70: =E58 -> Mechanical | F70: =F58 -> Heating and hot water | I70: System: District heating · Scope: Radiators and controls only | J70: ALL | L70: m² | M70: gifa_rate | O70: 2 | Q70: Yes | R70: 0.3 | S70: S-0039-04 | T70: =T61*$R70 -> 8.1 | U70: =U61*$R70 -> 16.2 | V70: =V61*$R70 -> 28.35 | W70: =W61*$R70 -> 15.66 | X70: =X61*$R70 -> 28.35 | Y70: =Y61*$R70 -> 14.85 | Z70: =Z61*$R70 -> 27 | AA70: =AA61*$R70 -> 0 | AB70: AI estimate – verify | AC70: Full system × 0.30 (AI share for emitters, TRVs and controls)
A71: S-0039-14 | B71: S-0039 | C71: Option | D71: =D58 -> 5 Services | E71: =E58 -> Mechanical | F71: =F58 -> Heating and hot water | I71: System: Electric · Scope: Plant only | J71: ALL | L71: m² | M71: gifa_rate | O71: 2 | Q71: Yes | R71: 0.5 | S71: S-0039-05 | T71: =T62*$R71 -> 9 | U71: =U62*$R71 -> 18 | V71: =V62*$R71 -> 31.5 | W71: =W62*$R71 -> 17.4 | X71: =X62*$R71 -> 31.5 | Y71: =Y62*$R71 -> 16.5 | Z71: =Z62*$R71 -> 30 | AA71: =AA62*$R71 -> 0 | AB71: AI estimate – verify | AC71: Full system × 0.5 (AI share for plant). Replaces v4.5 5.2L (£ per item, domestic scale)
A72: S-0039-15 | B72: S-0039 | C72: Option | D72: =D58 -> 5 Services | E72: =E58 -> Mechanical | F72: =F58 -> Heating and hot water | I72: System: Electric · Scope: Radiators and controls only | J72: ALL | L72: m² | M72: gifa_rate | O72: 2 | Q72: Yes | R72: 0.3 | S72: S-0039-05 | T72: =T62*$R72 -> 5.4 | U72: =U62*$R72 -> 10.8 | V72: =V62*$R72 -> 18.9 | W72: =W62*$R72 -> 10.44 | X72: =X62*$R72 -> 18.9 | Y72: =Y62*$R72 -> 9.9 | Z72: =Z62*$R72 -> 18 | AA72: =AA62*$R72 -> 0 | AB72: AI estimate – verify | AC72: Full system × 0.30 (AI share for emitters, TRVs and controls)
A73: S-0040-01 | B73: S-0040 | C73: Item | D73: 5 Services | E73: Mechanical | F73: Water and drainage | G73: Hot and cold water pipework and above-ground drainage | H73: One | I73: Scope: Full installation | J73: ALL | K73: Yes | L73: m² | M73: gifa_rate | N73: GIFA | O73: 2 | P73: 3, 4 | Q73: Yes | T73: 30 | U73: 65 | V73: 110 | W73: 30 | X73: 45 | Y73: 20 | Z73: 45 | AA73: 0 | AB73: v4.5 – no source recorded | AC73: v4.5 5.1. No source recorded in v4.5 | AD73: NB EX RF FO OM | AE73: NB EX | AF73: ALL | AI73: 5.3 | AJ73: 0.5 | AK73: 5.4 | AL73: 0.5 | AM73: 5.1 | AN73: BCIS split is an AI estimate
A74: S-0040-02 | B74: S-0040 | C74: Option | D74: =D73 -> 5 Services | E74: =E73 -> Mechanical | F74: =F73 -> Water and drainage | I74: Scope: Visible fittings only | J74: ALL | L74: m² | M74: gifa_rate | O74: 2 | P74: 2 | Q74: Yes | R74: 0.3 | S74: S-0040-01 | T74: =T73*$R74 -> 9 | U74: =U73*$R74 -> 19.5 | V74: =V73*$R74 -> 33 | W74: =W73*$R74 -> 9 | X74: =X73*$R74 -> 13.5 | Y74: =Y73*$R74 -> 6 | Z74: =Z73*$R74 -> 13.5 | AA74: =AA73*$R74 -> 0 | AB74: AI estimate – verify | AC74: Full installation × 0.30 (AI share for taps and visible fittings)
A75: S-0041-01 | B75: S-0041 | C75: Item | D75: 5 Services | E75: Mechanical | F75: Ventilation | G75: Extract and mechanical ventilation | H75: One | I75: Standard | J75: ALL | K75: Yes | L75: m² | M75: gifa_rate | N75: GIFA | O75: 3 | P75: 3, 4 | Q75: Yes | T75: 20 | U75: 45 | V75: 90 | W75: 40 | X75: 70 | Y75: 25 | Z75: 60 | AA75: 0 | AB75: v4.5 – no source recorded | AC75: v4.5 5.3. No source recorded in v4.5 | AD75: NB EX RF FO OM | AE75: NB EX | AF75: ALL | AI75: 5.7 | AJ75: 1 | AM75: 5.3
A76: S-0042-01 | B76: S-0042 | C76: Item | D76: 5 Services | E76: Mechanical | F76: Cooling | G76: Air conditioning and comfort cooling | H76: One | I76: Standard | J76: ALL | K76: Yes | L76: m² | M76: gifa_rate | N76: GIFA | O76: 3 | Q76: Yes | T76: 30 | U76: 90 | V76: 180 | W76: 150 | X76: 250 | Y76: 10 | Z76: 45 | AA76: 0 | AB76: v4.5 – no source recorded | AC76: v4.5 5.4. No source recorded in v4.5 | AD76: NB EX RF FO OM | AE76: — | AF76: ALL | AI76: 5.6 | AJ76: 1 | AM76: 5.4
A77: S-0043-01 | B77: S-0043 | C77: Item | D77: 5 Services | E77: Mechanical | F77: Controls and BMS | G77: Building management system and controls | H77: One | I77: Standard | J77: ALL | K77: Yes | L77: m² | M77: gifa_rate | N77: GIFA | O77: 3 | Q77: Yes | T77: 8 | U77: 15 | V77: 30 | W77: 12 | X77: 30 | Y77: 5 | Z77: 12 | AA77: 0 | AB77: v4.5 – no source recorded | AC77: v4.5 5.14. No source recorded in v4.5 | AD77: NB EX RF FO OM | AE77: — | AF77: ALL | AI77: 5.12 | AJ77: 1 | AM77: 5.14
A78: S-0044-01 | B78: S-0044 | C78: Item | D78: 5 Services | E78: Electrical | F78: Electricity supply upgrade | G78: New or upgraded supply from the DNO, incl. substation | H78: One | I78: Size: Small | J78: ALL | L78: band | M78: per_item | N78: 1 | O78: 3 | Q78: No | T78: 10000 | U78: 10000 | V78: 10000 | W78: 10000 | X78: 10000 | Y78: 10000 | Z78: 10000 | AA78: 10000 | AB78: v4.5 – other source cited | AC78: v4.5 5.13 Basic lump sum reused as the Small band. v4.5 cites Ofgem/National Grid 2023-26 (not verified) | AD78: NB EX RF FO EW OM | AE78: — | AF78: ALL | AI78: 8.7 | AJ78: 1 | AM78: 5.13
A79: S-0044-02 | B79: S-0044 | C79: Option | D79: =D78 -> 5 Services | E79: =E78 -> Electrical | F79: =F78 -> Electricity supply upgrade | I79: Size: Medium | J79: ALL | K79: Yes | L79: band | M79: per_item | O79: 3 | Q79: No | T79: 40000 | U79: 40000 | V79: 40000 | W79: 40000 | X79: 40000 | Y79: 40000 | Z79: 40000 | AA79: 40000 | AB79: v4.5 – other source cited | AC79: v4.5 5.13 Std lump sum reused as the Medium band. v4.5 cites Ofgem/National Grid 2023-26 (not verified)
A80: S-0044-03 | B80: S-0044 | C80: Option | D80: =D78 -> 5 Services | E80: =E78 -> Electrical | F80: =F78 -> Electricity supply upgrade | I80: Size: Large | J80: ALL | L80: band | M80: per_item | O80: 3 | Q80: No | T80: 250000 | U80: 250000 | V80: 250000 | W80: 250000 | X80: 250000 | Y80: 250000 | Z80: 250000 | AA80: 250000 | AB80: v4.5 – other source cited | AC80: v4.5 5.13 High lump sum reused as the Large band. v4.5 cites Ofgem/National Grid 2023-26 (not verified)
A81: S-0045-01 | B81: S-0045 | C81: Item | D81: 5 Services | E81: Electrical | F81: Power | G81: Switchgear, distribution boards, all wiring (power and lighting circuits) and sockets | H81: One | I81: Scope: Full installation | J81: ALL | K81: Yes | L81: m² | M81: gifa_rate | N81: GIFA | O81: 3 | P81: 3, 4 | Q81: Yes | T81: 80 | U81: 126 | V81: 215 | W81: 109 | X81: 174 | Y81: 48 | Z81: 110 | AA81: 0 | AB81: Derived from v4.5 | AC81: v4.5 5.7 switchgear + 5.7a sub-distribution + 5.8 wiring. 5.7a cites C&W 2025 / BCIS Q1 2026 (not verified) | AD81: NB EX RF FO OM | AE81: NB EX | AF81: ALL | AI81: 5.8 | AJ81: 1 | AM81: 5.7, 5.7a, 5.8, 5.8a, 5.8b
A82: S-0045-02 | B82: S-0045 | C82: Option | D82: =D81 -> 5 Services | E82: =E81 -> Electrical | F82: =F81 -> Power | I82: Scope: Full installation | J82: RES STU | L82: m² | M82: gifa_rate | O82: 3 | P82: 3, 4 | Q82: Yes | T82: 70 | U82: 108 | V82: 185 | W82: 93 | X82: 148 | Y82: 40 | Z82: 95 | AA82: 0 | AB82: Derived from v4.5 | AC82: v4.5 5.7 switchgear + 5.8 wiring (no sub-distribution row for residential in v4.5)
A83: S-0045-03 | B83: S-0045 | C83: Option | D83: =D81 -> 5 Services | E83: =E81 -> Electrical | F83: =F81 -> Power | I83: Scope: Second fix only | J83: ALL | L83: m² | M83: gifa_rate | O83: 2 | P83: 2 | Q83: Yes | T83: 13 | U83: 15 | V83: 30 | W83: 0 | X83: 0 | Y83: 0 | Z83: 0 | AA83: 0 | AB83: v4.5 – other source cited | AC83: v4.5 5.8b. v4.5 cites: C&W 2025, RateQS Nov 2025 (not verified)
A84: S-0046-01 | B84: S-0046 | C84: Item | D84: 5 Services | E84: Electrical | F84: Lighting | G84: Light fittings, controls and external lights on the building (wiring is in Power) | H84: One | I84: Scope: Full installation | J84: ALL | K84: Yes | L84: m² | M84: gifa_rate | N84: GIFA | O84: 2 | P84: 3, 4 | Q84: Yes | T84: 20 | U84: 33 | V84: 52 | W84: 17 | X84: 34 | Y84: 11 | Z84: 23 | AA84: 0 | AB84: Derived from v4.5 | AC84: v4.5 5.8c luminaires and controls (cites C&W Fit-Out Guide 2025, not verified) + 5.10 external lighting on the building | AD84: NB EX RF FO OM | AE84: NB EX | AF84: ALL | AI84: 5.8 | AJ84: 1 | AM84: 5.8c, 5.10
A85: S-0046-02 | B85: S-0046 | C85: Option | D85: =D84 -> 5 Services | E85: =E84 -> Electrical | F85: =F84 -> Lighting | I85: Scope: Replace fittings only | J85: ALL | L85: m² | M85: gifa_rate | O85: 2 | P85: 2 | Q85: Yes | R85: 0.75 | S85: S-0046-01 | T85: =T84*$R85 -> 15 | U85: =U84*$R85 -> 24.75 | V85: =V84*$R85 -> 39 | W85: =W84*$R85 -> 12.75 | X85: =X84*$R85 -> 25.5 | Y85: =Y84*$R85 -> 8.25 | Z85: =Z84*$R85 -> 17.25 | AA85: =AA84*$R85 -> 0 | AB85: AI estimate – verify | AC85: Full installation × 0.75 (AI: like-for-like luminaires, no new controls or layout)
A86: S-0047-01 | B86: S-0047 | C86: Item | D86: 5 Services | E86: Electrical | F86: Emergency lighting | G86: Emergency and exit lighting | H86: One | I86: Standard | J86: ALL | K86: Yes | L86: m² | M86: gifa_rate | N86: GIFA | O86: 3 | P86: 3, 4 | Q86: Yes | T86: 5 | U86: 10 | V86: 18 | W86: 8 | X86: 12 | Y86: 4 | Z86: 8 | AA86: 0 | AB86: v4.5 – BCIS cited | AC86: v4.5 5.9b. v4.5 cites: BCIS Q1 2026 (not verified) | AD86: NB EX RF FO OM | AE86: NB EX | AF86: ALL | AI86: 5.8 | AJ86: 1 | AM86: 5.9b
A87: S-0048-01 | B87: S-0048 | C87: Item | D87: 5 Services | E87: Electrical | F87: Standby power | G87: Generator or UPS | H87: Several | I87: Type: Generator · Size: Small | J87: ALL | L87: band | M87: per_item | N87: 1 | O87: 3 | Q87: No | T87: 25000 | U87: 25000 | V87: 25000 | W87: 25000 | X87: 25000 | Y87: 25000 | Z87: 25000 | AA87: 25000 | AB87: AI estimate – verify | AC87: AI estimate (up to 50 kVA) | AD87: NB EX RF FO OM | AE87: — | AF87: OFF EDU HEA RET IND HOS | AG87: PT=NB & USE=HEA → tick | AI87: 5.8 | AJ87: 1 | AM87: 5.25, 5.26
A88: S-0048-02 | B88: S-0048 | C88: Option | D88: =D87 -> 5 Services | E88: =E87 -> Electrical | F88: =F87 -> Standby power | I88: Type: UPS · Size: Small | J88: ALL | L88: band | M88: per_item | O88: 3 | Q88: No | T88: 17000 | U88: 17000 | V88: 17000 | W88: 17000 | X88: 17000 | Y88: 17000 | Z88: 17000 | AA88: 17000 | AB88: v4.5 – other source cited | AC88: v4.5 5.26 Std (10–20 kVA), cites Eaton 2025 (not verified)
A89: S-0048-03 | B89: S-0048 | C89: Option | D89: =D87 -> 5 Services | E89: =E87 -> Electrical | F89: =F87 -> Standby power | I89: Type: Generator · Size: Medium | J89: ALL | K89: Yes | L89: band | M89: per_item | O89: 3 | Q89: No | T89: 42000 | U89: 42000 | V89: 42000 | W89: 42000 | X89: 42000 | Y89: 42000 | Z89: 42000 | AA89: 42000 | AB89: v4.5 – other source cited | AC89: v4.5 5.25 Std (50–100 kVA), cites FG Wilson 2025 (not verified)
A90: S-0048-04 | B90: S-0048 | C90: Option | D90: =D87 -> 5 Services | E90: =E87 -> Electrical | F90: =F87 -> Standby power | I90: Type: UPS · Size: Medium | J90: ALL | L90: band | M90: per_item | O90: 3 | Q90: No | T90: 30000 | U90: 30000 | V90: 30000 | W90: 30000 | X90: 30000 | Y90: 30000 | Z90: 30000 | AA90: 30000 | AB90: AI estimate – verify | AC90: AI estimate between v4.5 Std and High
A91: S-0048-05 | B91: S-0048 | C91: Option | D91: =D87 -> 5 Services | E91: =E87 -> Electrical | F91: =F87 -> Standby power | I91: Type: Generator · Size: Large | J91: ALL | L91: band | M91: per_item | O91: 3 | Q91: No | T91: 115000 | U91: 115000 | V91: 115000 | W91: 115000 | X91: 115000 | Y91: 115000 | Z91: 115000 | AA91: 115000 | AB91: v4.5 – other source cited | AC91: v4.5 5.25 High (200–400 kVA), cites FG Wilson 2025 (not verified)
A92: S-0048-06 | B92: S-0048 | C92: Option | D92: =D87 -> 5 Services | E92: =E87 -> Electrical | F92: =F87 -> Standby power | I92: Type: UPS · Size: Large | J92: ALL | L92: band | M92: per_item | O92: 3 | Q92: No | T92: 52000 | U92: 52000 | V92: 52000 | W92: 52000 | X92: 52000 | Y92: 52000 | Z92: 52000 | AA92: 52000 | AB92: v4.5 – other source cited | AC92: v4.5 5.26 High (50–100 kVA), cites Eaton 2025 (not verified)
A93: S-0049-01 | B93: S-0049 | C93: Item | D93: 5 Services | E93: Fire safety | F93: Fire alarm | G93: Detection and alarm system | H93: One | I93: Standard | J93: ALL | K93: Yes | L93: m² | M93: gifa_rate | N93: GIFA | O93: 3 | P93: 3, 4 | Q93: Yes | T93: 10 | U93: 18 | V93: 30 | W93: 14 | X93: 20 | Y93: 8 | Z93: 15 | AA93: 0 | AB93: v4.5 – BCIS cited | AC93: v4.5 5.9a. v4.5 cites: BCIS Q1 2026, C&W 2025 (not verified) | AD93: NB EX RF FO OM | AE93: NB EX | AF93: ALL | AI93: 5.12 | AJ93: 1 | AM93: 5.9a
A94: S-0050-01 | B94: S-0050 | C94: Item | D94: 5 Services | E94: Fire safety | F94: Sprinklers | G94: Sprinklers and dry or wet risers | H94: One | I94: Standard | J94: ALL | K94: Yes | L94: m² | M94: gifa_rate | N94: GIFA | O94: 3 | Q94: Yes | T94: 15 | U94: 15 | V94: 30 | W94: 10 | X94: 25 | Y94: 5 | Z94: 20 | AA94: 0 | AB94: Derived from v4.5 | AC94: v4.5 5.6. Refurbishment Basic was 0 in v4.5; set to the Std value so sprinklers are never free | AD94: NB EX RF FO OM | AE94: — | AF94: ALL | AG94: PT=NB & USE=RES STU & STOREYS>=4 → tick | AI94: 5.11 | AJ94: 1 | AM94: 5.6
A95: S-0051-01 | B95: S-0051 | C95: Item | D95: 5 Services | E95: Fire safety | F95: Smoke ventilation | G95: AOVs and smoke shafts to stairs and corridors | H95: One | I95: Standard | J95: ALL | K95: Yes | L95: nr floors | M95: per_nr | N95: STOREYS | O95: 3 | Q95: Yes | T95: 4000 | U95: 6000 | V95: 9000 | W95: 6000 | X95: 9000 | Y95: 6000 | Z95: 9000 | AA95: 0 | AB95: AI estimate – verify | AC95: AI estimate per floor served: AOV, controls and interface. Not in v4.5 | AD95: NB EX RF OM | AE95: — | AF95: RES STU HEA HOS | AG95: PT=NB & STOREYS>=2 → tick | AI95: 5.7 | AJ95: 1 | AM95: 5.31
A96: S-0052-01 | B96: S-0052 | C96: Item | D96: 5 Services | E96: Data and security | F96: Data and IT | G96: Structured cabling, Wi-Fi and comms rooms | H96: One | I96: Standard | J96: ALL | K96: Yes | L96: m² | M96: gifa_rate | N96: GIFA | O96: 2 | Q96: Yes | T96: 8 | U96: 18 | V96: 35 | W96: 15 | X96: 30 | Y96: 8 | Z96: 20 | AA96: 0 | AB96: v4.5 – no source recorded | AC96: v4.5 5.16. No source recorded in v4.5 | AD96: NB EX RF FO OM | AE96: NB | AF96: ALL | AI96: 5.12 | AJ96: 1 | AM96: 5.16
A97: S-0053-01 | B97: S-0053 | C97: Item | D97: 5 Services | E97: Data and security | F97: Security | G97: Access control, CCTV and door entry | H97: One | I97: Standard | J97: ALL | K97: Yes | L97: m² | M97: gifa_rate | N97: GIFA | O97: 3 | Q97: Yes | T97: 5 | U97: 15 | V97: 30 | W97: 8 | X97: 20 | Y97: 5 | Z97: 15 | AA97: 0 | AB97: v4.5 – no source recorded | AC97: v4.5 5.18. No source recorded in v4.5 | AD97: NB EX RF FO OM | AE97: — | AF97: ALL | AI97: 5.12 | AJ97: 1 | AM97: 5.18
A98: S-0054-01 | B98: S-0054 | C98: Item | D98: 5 Services | E98: Lifts | F98: Lifts | G98: Lift installation | H98: Several | I98: Type: Passenger | J98: ALL | K98: Yes | L98: Nr | M98: per_nr | N98: IF(STOREYS>=2, 1, 0) | O98: 3 | Q98: Yes | T98: 25000 | U98: 40000 | V98: 60000 | W98: 40000 | X98: 60000 | Y98: 40000 | Z98: 60000 | AA98: 0 | AB98: v4.5 – no source recorded | AC98: v4.5 5.19. No source recorded in v4.5 | AD98: NB EX RF FO OM | AE98: NB | AF98: ALL | AG98: STOREYS<2 → untick | AI98: 5.10 | AJ98: 1 | AM98: 5.19
A99: S-0054-02 | B99: S-0054 | C99: Option | D99: =D98 -> 5 Services | E99: =E98 -> Lifts | F99: =F98 -> Lifts | I99: Type: Platform | J99: ALL | L99: nr | M99: per_nr | N99: 1 | O99: 3 | Q99: Yes | T99: 15000 | U99: 20000 | V99: 30000 | W99: 20000 | X99: 30000 | Y99: 20000 | Z99: 30000 | AA99: 0 | AB99: AI estimate – verify | AC99: AI estimate per platform lift. v4.5 5.19 combined lifts and platform lifts
A100: S-0054-03 | B100: S-0054 | C100: Option | D100: =D98 -> 5 Services | E100: =E98 -> Lifts | F100: =F98 -> Lifts | I100: Type: Goods or bed | J100: ALL | L100: nr | M100: per_nr | N100: 1 | O100: 3 | Q100: Yes | T100: 50000 | U100: 70000 | V100: 100000 | W100: 70000 | X100: 100000 | Y100: 70000 | Z100: 100000 | AA100: 0 | AB100: AI estimate – verify | AC100: AI estimate per goods or bed lift
...

Sheet 3. Settings
A1: SETTINGS — every other number the app reads
A2: Each table starts at its ▶ marker and ends at the first blank row. To add a row, insert it inside the table (above the blank row). Don't rename markers or headers: the app finds tables by them.
A4: ▶ workbook_info | B4: Version stamped on every report the app produces. Update on every change
A5: Field | B5: Value | C5: Notes
A6: Version | B6: 5.4 | C6: Bump on every published change (5.3, 5.4 …) and add a line to the update log
A7: Date | B7: 2026-09-24
A8: Owner | B8: Projento
A10: ▶ building_uses | B10: Q1.3 options. The Code is what '2. Scope and Rates' uses
A11: Code | B11: Building use (label on screen) | C11: Treated as residential | D11: Notes
A12: RES | B12: Residential | C12: Yes
A13: STU | B13: Student accommodation (PBSA / halls) | C13: Yes
A14: OFF | B14: Commercial offices | C14: No
A15: EDU | B15: Education | C15: No
A16: HEA | B16: Healthcare | C16: No
A17: RET | B17: Retail | C17: No
A18: IND | B18: Industrial / warehouse | C18: No
A19: HOS | B19: Hospitality / leisure | C19: No
A20: MIX | B20: Mixed use | C20: No | D20: Every item listed; nothing hidden under More items
A21: OTH | B21: Other | C21: No | D21: Every item listed; nothing hidden under More items
A22: ALL | B22: (any building use) | D22: Used on '2. Scope and Rates' only: the item or rate applies to every building use
A24: ▶ project_types | B24: Q1.2 options. The rate column read for each specification level. The Code is what '2. Scope and Rates' uses
A25: Code | B25: Project type (label on screen) | C25: Basic column | D25: Standard column | E25: High column | F25: Uses level of intervention | G25: Notes
A26: NB | B26: New Build | C26: NB Std | D26: NB Std | E26: NB High | F26: No | G26: There is no Basic new-build rate, so Basic reads NB Std
A27: EX | B27: Extension | C27: Ext Std | D27: Ext Std | E27: Ext High | F27: No | G27: New-build elements plus tie-in to the existing building
A28: RF | B28: Refurbishment | C28: Rfb Basic | D28: Rfb Std | E28: Rfb High | F28: Yes
A29: FO | B29: Fit-out | C29: Rfb Basic | D29: Rfb Std | E29: Rfb High | F29: Yes
A30: EW | B30: External works only | C30: Ext Works | D30: Ext Works | E30: Ext Works | F30: No | G30: Quantities from the external works area
A31: DM | B31: Demolition only | C31: Rfb Basic | D31: Rfb Std | E31: Rfb High | F31: No
A32: OM | B32: Other or mixed | C32: Per component | D32: Per component | E32: Per component | F32: No | G32: From v4.5: split GIFA by use/type, price each block on its own project type's columns, and sum
A34: ▶ spec_levels | B34: Q2.4 options. The level picks the Basic / Standard / High column on project_types
A35: Level | B35: Description
A36: Basic | B36: Minimum compliance; budget materials; functional finish. Student accommodation, back-of-house, warehouses.
A37: Standard | B37: Good commercial standard; durable mid-range materials. Typical offices, education, general academic space.
A38: High | B38: Flagship/premium; high-end finishes, bespoke joinery, enhanced M&E. Boardrooms, reception, executive, prestige.
A40: ▶ intervention_levels | B40: Level of intervention (Refurbishment and Fit-out only) → band multiplier and design duration (from v4.5)
A41: Level | B41: Name | C41: Band multiplier (m² rates) | D41: Description | E41: Design duration multiplier
A42: 1 | B42: Fabric and finishes only | C42: 0.8 | D42: Decoration, floor/wall finishes, ceilings, fixtures replaced in-place. No M&E work. No walls moved. Lowest cost and shortest programme. | E42: 0.5
A43: 2 | B43: Finishes with minor services | C43: 0.9 | D43: Finishes as above plus light-touch M&E: 2nd fix fixtures, replacement light fittings, sockets and switches. Existing wiring and pipework retained. No new systems. | E43: 0.7
A44: 3 | B44: Full systems replacement | C44: 1 | D44: Complete replacement of heating, plumbing and electrical systems throughout. Same layout, same positions, no structural changes. Building rewired and re-plumbed. Typical full flat or office refurbishment. | E44: 1
A45: 4 | B45: Reconfiguration or full redesign | C45: 1.15 | D45: Layout changes, walls moved or removed, or building stripped to structure and redesigned. Requires architect, structural engineer, building control, possibly planning. Highest cost and longest programme. | E45: 1.3
A47: ▶ location_factors | B47: Regional location factor by postcode area, or by district where an area is split (e.g. SY10). West Midlands is the default. South West added in v5.4 — its factors are an AI estimate, verify against BCIS
A48: Region | B48: Postcode areas | C48: Low | D48: High | E48: Mid (use)
A49: Inner London | B49: EC,WC,E1W,SW1,SE1 | C49: 1.2 | D49: 1.3 | E49: 1.25
A50: Outer London | B50: E,N,NW,SE,SW,W,BR,CR,DA,EN,HA,IG,KT,RM,SM,TW,UB,WD | C50: 1.1 | D50: 1.2 | E50: 1.15
A51: South East | B51: GU,RH,TN,ME,CT,BN,PO,SO,RG,SL,OX,HP,MK | C51: 1.05 | D51: 1.12 | E51: 1.08
A52: East of England | B52: CM,CB,IP,NR,LU,AL,SG,PE,SS,CO | C52: 1 | D52: 1.05 | E52: 1.03
A53: West Midlands ★ DEFAULT | B53: B,CV,WV,WS,DY,ST,WR,HR,TF,SY1,SY2,SY3,SY4,SY5,SY6,SY7,SY8,SY9,SY10,SY11,SY12,SY13 | C53: 0.92 | D53: 0.97 | E53: 0.94
A54: East Midlands | B54: LE,NG,DE,LN,NN | C54: 0.91 | D54: 0.96 | E54: 0.93
A55: Yorkshire & Humberside | B55: LS,BD,HX,HD,HG,YO,HU,S,DN,WF | C55: 0.88 | D55: 0.93 | E55: 0.9
A56: North West | B56: M,SK,WN,WA,BL,OL,PR,BB,LA,FY,CW,CH,L,CA,SY14 | C56: 0.9 | D56: 0.95 | E56: 0.92
A57: North East | B57: NE,SR,DH,TS,DL | C57: 0.87 | D57: 0.92 | E57: 0.88
A58: Wales | B58: CF,SA,NP,LD,SY,LL | C58: 0.87 | D58: 0.93 | E58: 0.89
A59: Scotland | B59: EH,G,FK,KY,DD,PH,AB,IV,KW,PA,KA,ML,TD,DG,HS,ZE | C59: 0.93 | D59: 1 | E59: 0.9
A60: Northern Ireland | B60: BT | C60: 0.82 | D60: 0.88 | E60: 0.85
A61: South West | B61: BS,BA,BH,DT,EX,GL,PL,SN,SP,TA,TQ,TR | C61: 0.94 | D61: 1 | E61: 0.97
A62: ▶ benchmarks | B62: Expected works £/m² by project type and building use (from v4.5, now in codes). Outside the range = review flag
A63: Project type | B63: Building use | C63: Expected low £/m² | D63: Expected high £/m²
A64: RF | B64: OFF | C64: 600 | D64: 1200
A65: RF | B65: RES | C65: 700 | D65: 1500
A66: RF | B66: EDU | C66: 800 | D66: 1800
A67: RF | B67: HOS | C67: 1000 | D67: 2200
A68: RF | B68: HEA | C68: 1500 | D68: 3000
A69: RF | B69: RET | C69: 500 | D69: 1300
A70: RF | B70: IND | C70: 400 | D70: 1100
A71: FO | B71: OFF | C71: 500 | D71: 1200
A72: FO | B72: HOS | C72: 900 | D72: 2000
A73: FO | B73: RET | C73: 500 | D73: 1400
A74: NB | B74: OFF | C74: 1800 | D74: 2800
A75: NB | B75: RES | C75: 1600 | D75: 2600
... A79: NB | B79: IND | C79: 900 | D79: 1800
A81: ▶ inputs | B81: Names used in 'Quantity rule' and 'Other conditions'. Default = what the app uses if the answer is blank
A82: Name | B82: Comes from | C82: Default (quantity rule) | D82: Notes
A83: GIFA | B83: Q1.5 Approximate size (GIFA) | C83: IF(PT=EW, 0, ENTER) | D83: On Refurbishment and Fit-out this is the area of works
A84: STOREYS | B84: Number of storeys (existing question) | C84: 1 | D84: Default used only if the answer is blank
A85: FOOTPRINT | B85: Worked out | C85: GIFA / STOREYS | D85: Ground floor area
A86: UPPER | B86: Worked out | C86: GIFA - FOOTPRINT | D86: Upper floor area
A87: EXT_AREA | B87: External works area, asked on the Group 8 header | C87: IF(PT=EW, ENTER, FOOTPRINT * r.site_ratio) | D87: Must be entered on External works only
A88: DEMOLISHED | B88: Demolition item, 'I know this' | C88: GIFA | D88: Area of building to demolish
A89: PT | B89: Q1.2 Project type | D89: A code from project_types
A90: USE | B90: Q1.3 Building use | D90: A code from building_uses
A91: AGE | B91: Q1.4 Building age | D91: End year of the chosen band (e.g. 1980–1999 → 1999); post-2000 → current year
A92: LEVEL | B92: Level of intervention | D92: 1–4; Refurbishment and Fit-out only
A94: ▶ quantity_ratios | B94: Named ratios used as r.name in quantity rules. The row for the building use is used, else ALL
A95: Key | B95: Building use | C95: Value | D95: Used for | E95: Source
A96: m2_per_person | B96: ALL | C96: 10 | D96: Toilets: people = GIFA ÷ this | E96: AI estimate – verify
A97: m2_per_person | B97: EDU | C97: 5 | D97: Toilets (education) | E97: AI estimate – verify
A98: m2_per_person | B98: HEA | C98: 15 | D98: Toilets (healthcare) | E98: AI estimate – verify
A99: m2_per_person | B99: RET | C99: 7 | D99: Toilets (retail) | E99: AI estimate – verify
A100: m2_per_person | B100: IND | C100: 40 | D100: Toilets (industrial) | E100: AI estimate – verify
A101: m2_per_person | B101: HOS | C101: 5 | D101: Toilets (hospitality) | E101: AI estimate – verify
A102: persons_per_wc | B102: ALL | C102: 20 | D102: Toilets: WCs = people ÷ this (simplified BS 6465-1 / Workplace Regs) | E102: AI estimate – verify
A103: accessible_wc_per_floor | B103: ALL | C103: 1 | D103: Toilets: accessible option | E103: AI estimate – verify
A104: m2_per_dwelling | B104: ALL | C104: 80 | D104: Bathrooms, kitchens, EV charging (residential) | E104: AI estimate – verify
A105: bathrooms_per_dwelling | B105: ALL | C105: 1.2 | D105: Bathrooms (residential) | E105: AI estimate – verify
A106: m2_per_bed | B106: ALL | C106: 25 | D106: Student beds or hospital beds, by building use | E106: AI estimate – verify
A107: m2_per_bed | B107: STU | C107: 25 | D107: Bathrooms and kitchens (student en-suite beds) | E107: AI estimate – verify
... A123: fence_multiplier | B123: ALL | C123: 4 | D123: Fences = this × √ external area (perimeter of a square) | E123: AI estimate – verify
A125: ▶ factors | B125: Multipliers applied to rates
A126: Key | B126: Value | C126: Applies to | D126: When | E126: Source
A127: modular_factor | B127: 1.05 | C127: Groups 1–3 rates | D127: Group 2 construction method = Modular | E127: AI estimate – verify
...
